Workbook

Sheet 00 — دليل الاستخدام
A1: البند | B1: الحكم
A2: ◆ INJAZ-MASTER-MAP — ملفُّ التتبعِ المركزيُّ الواحد · الإصدار 1.0 · خطُّ الأساس 2026-08-06
A3: الغرض | B3: أداةُ التتبعِ والتنفيذِ للحزمةِ النهائية — لا وثيقةً خامسةً سردية
A4: المنهج | B4: التجميعُ النهائيُّ لا التصحيحُ الرجعي: لا تُعدَّل وثيقةٌ قديمةٌ ولا يُعاد إصدارُها — تُقرأ وتُوسَم ويُنقل مضمونُها
A5: الحزمةُ النافذة | B5: أربعُ وثائقَ: INJAZ-CORE-01 · INJAZ-FRD-01 · INJAZ-UX-01 · INJAZ-DELIVERY-01 — وهذا الملفُّ الخامسُ أداةً
A6: ◆ الملفاتُ الحيةُ الثلاثة | B6: NAV-09 و SCR-DES-01 و CMP-03 تبقى مستقلةً بأسمائها ومساراتها وبنيتها — يُفهرسها هذا الملفُّ ولا يبتلعها
A7: قاعدةُ الملفِّ الآلي | B7: لا يُنقل ملفٌّ آليٌّ أو تشغيليٌّ قبل حصرِ الأدواتِ التي تقرؤه وتوفيرِ مسارٍ بديلٍ وتشغيلِ مقارنةٍ تثبت صفرَ فرق
A8: حدُّ القطع | B8: كلُّ ما صدر أو استُلم حتى 2026-08-06 23:59 يدخل خطَّ الأساس المجمَّد
A9: ◆ نفاذُ الحكم | B9: لا يُحدَّد بالتاريخ وحدَه — بل بمرتبةِ الوثيقةِ والإصدارِ وحالةِ الاعتمادِ وقرارِ النسخِ وقرارِ المالك الأحدث
A10: توزيعُ المحتوى | B10: الإنسانُ يقرأ الوثائقَ الأربعَ · والتفصيلُ الذريُّ يُبحَث ويُفرَز في أوراق هذا الملف
A11: التوليدُ من الملف | B11: يجوز توليدُ فصلٍ أو مخرَجٍ لإدارةٍ بعينها من هذا الملف — ولا يصير وثيقةً نافذةً مستقلة
A12: ما بعد القطع | B12: يدخل عبر مسار Change Control الرسميِّ في الورقة 02
A13: قاعدةُ الكود | B13: لا يُغيَّر الكودُ قبل إصدار مصفوفة الفجوات — إلا إصلاحًا حرجًا معتمدًا يمنع سلامةَ التجميعِ نفسِه

Sheet 01 — بيان التجميد وسجل الوثائق
A1: # | B1: الرمز | C1: الملف | D1: مسارُ المصدر | E1: sha256 — البصمةُ الحاكمة | F1: md5_legacy | G1: الحجم (بايت) | H1: آخرُ تعديل | I1: الحالة | J1: الصفةُ الدقيقة | K1: الأداةُ التي تقرؤه | L1: سببُ الإدراج أو الاستبعاد | M1: الوجهةُ في الحزمة | N1: الحكمُ والملاحظة
A2: 1 | B2: CMP-01 | C2: CMP-01 — مقارنة السايدبار بنظام الشاشات.xlsx | D2: /mnt/user-data/outputs/CMP-01 — مقارنة السايدبار بنظام الشاشات.xlsx | E2: aa8cf5fef3c241fb7cd8abd347f7902d7fd6885714f638e94f3c48bec756bb16 | F2: ef847f54 | G2: 116769 | H2: 2026-08-04 11:29 | I2: مرجعُ بيانات | J2: ملفُّ تحليلٍ أو مصفوفة | K2: لا أداة | L2: مُدرَجٌ مرجعًا | M2: INJAZ-MASTER-MAP | N2: مُدرَجٌ مرجعًا
A3: 2 | B3: CMP-02 | C3: CMP-02 — مقارنة شجرتَي الأعطال.xlsx | D3: /mnt/user-data/outputs/CMP-02 — مقارنة شجرتَي الأعطال.xlsx | E3: 02ee94e3cd854d6ca5bf0881a2113fa2cc6c0f49a0081aeec603cdbb9de0768b | F3: e7fb9f2f | G3: 20570 | H3: 2026-08-04 12:37 | I3: مرجعُ بيانات | J3: ملفُّ تحليلٍ أو مصفوفة | K3: لا أداة | L3: مُدرَجٌ مرجعًا | M3: INJAZ-MASTER-MAP | N3: مُدرَجٌ مرجعًا
A4: 3 | B4: CMP-03 | C4: CMP-03 — مقارنة أعمدة الشاشات بالنظام الحي.xlsx | D4: /mnt/user-data/outputs/CMP-03 — مقارنة أعمدة الشاشات بالنظام الحي.xlsx | E4: 17c443fc2fa21e0952890e1062c608fd1f19051c5854b84ab8a31436367c3d7a | F4: 6612feb4 | G4: 183256 | H4: 2026-08-04 14:29 | I4: ملفٌّ حيٌّ — يبقى مستقلًّا | J4: مساحةُ قرارٍ وترحيل | K4: محرّكُ قرارِ الأعمدة | L4: مُدرَجٌ ولا يُدمج — أداةٌ آليةٌ تقرؤه | M4: — | N4: مُدرَجٌ ولا يُدمج — أداةٌ آليةٌ تقرؤه
A5: 4 | B5: D-01 | C5: D-01 — دستور منصة إنجاز.docx | D5: /mnt/user-data/outputs/D-01 — دستور منصة إنجاز.docx | E5: feff594eaa8679611cfd0e419553f9aacbf04097bcb278f6926e048e005879ce | F5: 26d88b9c | G5: 58489 | H5: 2026-08-06 07:02 | I5: نافذةٌ — محرّكٌ عرضي | J5: محرّكٌ يخدم كلَّ الإدارات | K5: لا أداة | L5: مُدرَجٌ — تُحيل إليه وثائقُ الإدارات | M5: — | N5: مُدرَجٌ — تُحيل إليه وثائقُ الإدارات
A6: 5 | B6: D-02 | C6: D-02 — المعمارية الشاملة للمنصة.docx | D6: /mnt/user-data/outputs/D-02 — المعمارية الشاملة للمنصة.docx | E6: 6a916866fc85c583a5d25d1720ce0e6072268873e1d3d45c2b673d6c9b59d923 | F6: 278eb9c3 | G6: 50927 | H6: 2026-08-07 05:32 | I6: نافذةٌ — محرّكٌ عرضي | J6: محرّكٌ يخدم كلَّ الإدارات | K6: لا أداة | L6: مُدرَجٌ — تُحيل إليه وثائقُ الإدارات | M6: — | N6: مُدرَجٌ — تُحيل إليه وثائقُ الإدارات
A7: 6 | B7: DEC-SCR-01 | C7: DEC-SCR-01 — ملف القرارات العالقة على الشاشات والأعمدة.xlsx | D7: /mnt/user-data/outputs/DEC-SCR-01 — ملف القرارات العالقة على الشاشات والأعمدة.xlsx | E7: 1fa84d67f941bc0deeb8dac6fed9724fa0295d9c837160a174512d1ea07eb436 | F7: adf3bcff | G7: 491232 | H7: 2026-08-06 13:05 | I7: مرجعُ بيانات | J7: ملفُّ تحليلٍ أو مصفوفة | K7: لا أداة | L7: مُدرَجٌ مرجعًا | M7: INJAZ-MASTER-MAP | N7: مُدرَجٌ مرجعًا
A8: 7 | B8: DIO-01 | C8: DIO-01 — محرّك التصدير والاستيراد والمشاركة.docx | D8: /mnt/user-data/outputs/DIO-01 — محرّك التصدير والاستيراد والمشاركة.docx | E8: a4b84bf98e4ea2d1ec3cd7cc270e85ae5fa4888fbea4bdb0568bbe490476087f | F8: a084ecae | G8: 64372 | H8: 2026-08-07 05:32 | I8: نافذةٌ — محرّكٌ عرضي | J8: محرّكٌ يخدم كلَّ الإدارات | K8: لا أداة | L8: مُدرَجٌ — تُحيل إليه وثائقُ الإدارات | M8: — | N8: مُدرَجٌ — تُحيل إليه وثائقُ الإدارات
A9: 8 | B9: DIO-MAP-01 | C9: DIO-MAP-01 — مصفوفة قابلية التصدير والاستيراد والمشاركة للشاشات.xlsx | D9: /mnt/user-data/outputs/DIO-MAP-01 — مصفوفة قابلية التصدير والاستيراد والمشاركة للشاشات.xlsx | E9: ca41178308936cba91293977ace48b448d443cbdcbd26c02248d951dee492c56 | F9: 1e80642e | G9: 178742 | H9: 2026-08-06 07:04 | I9: مرجعُ بيانات | J9: ملفُّ تحليلٍ أو مصفوفة | K9: لا أداة | L9: مُدرَجٌ مرجعًا | M9: INJAZ-MASTER-MAP | N9: مُدرَجٌ مرجعًا
A10: 9 | B10: DS-01 | C10: DS-01 — النظام التصميمي ومكتبة المكونات.docx | D10: /mnt/user-data/outputs/DS-01 — النظام التصميمي ومكتبة المكونات.docx | E10: ffa3518d00df0cd25c13bedc37070be9bd2c664272eca3364966e225e3a2fac5 | F10: 028f98aa | G10: 70291 | H10: 2026-08-06 15:50 | I10: نافذةٌ — محرّكٌ عرضي | J10: محرّكٌ يخدم كلَّ الإدارات | K10: لا أداة | L10: مُدرَجٌ — تُحيل إليه وثائقُ الإدارات | M10: — | N10: مُدرَجٌ — تُحيل إليه وثائقُ الإدارات
A11: 10 | B11: DS-MAP-01 | C11: DS-MAP-01 — رموز التصميم والمكونات ومسار الهجرة.xlsx | D11: /mnt/user-data/outputs/DS-MAP-01 — رموز التصميم والمكونات ومسار الهجرة.xlsx | E11: 1b60a8ec2e2757f014d7b384a79904e2c25d19f15af90874c6608200a0c2dda1 | F11: cb36a25a | G11: 63726 | H11: 2026-08-06 15:50 | I11: مرجعُ بيانات | J11: ملفُّ تحليلٍ أو مصفوفة | K11: لا أداة | L11: مُدرَجٌ مرجعًا | M11: INJAZ-MASTER-MAP | N11: مُدرَجٌ مرجعًا
A12: 11 | B12: E-01 | C12: E-01 — محرّك الأحداث المالية والأثر المحاسبي.docx | D12: /mnt/user-data/outputs/E-01 — محرّك الأحداث المالية والأثر المحاسبي.docx | E12: 1033cf84008c9a4d0bcd8a44c3f7b228ab16869657ed5e1ccc3fff9cfc708f01 | F12: dcb322e7 | G12: 30313 | H12: 2026-08-07 05:32 | I12: نافذةٌ — محرّكٌ عرضي | J12: محرّكٌ يخدم كلَّ الإدارات | K12: لا أداة | L12: مُدرَجٌ — تُحيل إليه وثائقُ الإدارات | M12: — | N12: مُدرَجٌ — تُحيل إليه وثائقُ الإدارات
A13: 12 | B13: E-02 | C13: E-02 — محرّك دورة الوحدة والتايم شيت.docx | D13: /mnt/user-data/outputs/E-02 — محرّك دورة الوحدة والتايم شيت.docx | E13: f20289c7dd3cd676b63a92d93fe5a3a4c4782025e649c7f7c31f5b0f23469649 | F13: 47d54524 | G13: 34206 | H13: 2026-08-06 07:02 | I13: نافذةٌ — محرّكٌ عرضي | J13: محرّكٌ يخدم كلَّ الإدارات | K13: لا أداة | L13: مُدرَجٌ — تُحيل إليه وثائقُ الإدارات | M13: — | N13: مُدرَجٌ — تُحيل إليه وثائقُ الإدارات
... A64: 63 | B64: WFM-MAP-01 | C64: WFM-MAP-01 — مصفوفة مهام الإدارات ومسارات العمل والطلبات والإنجازات.xlsx | D64: /mnt/user-data/outputs/WFM-MAP-01 — مصفوفة مهام الإدارات ومسارات العمل والطلبات والإنجازات.xlsx | E64: bdad07394445bf3c8575cffc33955c317305fb7c53a3078d182e21c956fd4545 | F64: 25cecd62 | G64: 281786 | H64: 2026-08-05 13:22 | I64: مرجعُ بيانات | J64: ملفُّ تحليلٍ أو مصفوفة | K64: لا أداة | L64: مُدرَجٌ مرجعًا | M64: INJAZ-MASTER-MAP | N64: مُدرَجٌ مرجعًا

Sheet 02 — مسار التغيير
A1: # | B1: الخطوة | C1: ما يُفعل | D1: من ينفّذها | E1: الشاهدُ المطلوب | F1: لا يُنتقل قبلها
A2: 1 | B2: استلامُ مادةٍ بعد القطع | C2: تُسجَّل في هذه الورقةِ بتاريخها ومصدرِها ومقدّمِها — ولا تُدمج في الحزمة تلقائيًّا | D2: مكتبُ الهندسة | E2: سطرٌ في السجلِّ بمعرّفٍ وتاريخٍ | F2: الفحصِ
A3: 2 | B3: فحصُ المرتبةِ والنفاذ | C3: أالمادةُ أعلى مرتبةً من الحكمِ النافذِ الحالي؟ أمعتمدةٌ أم نافذ؟ | D3: مكتبُ الهندسة | E3: حكمٌ صريحٌ: تنسخ أم تُنسَخ أم تُهمَل | F3: تقديرِ الأثر
A4: 3 | B4: تقديرُ الأثر | C4: أيَّ فصلٍ في أيِّ وثيقةٍ تمسّ؟ وأيَّ ورقةٍ في هذا الملف؟ وأيَّ كودٍ حيّ؟ | D4: مكتبُ الهندسة + المالكُ المختص | E4: مصفوفةُ أثرٍ بثلاثة أعمدة | F4: اعتمادِ المالك
A5: 4 | B5: اعتمادُ المالك | C5: يوقّع الرئيسُ التنفيذيُّ أو نائبُه المختصُّ على الإدماج | D5: الرئيسُ التنفيذيُّ أو نائبُه | E5: اعتمادٌ موثَّقٌ بتاريخه | F5: الإدماج
A6: 5 | B6: الإدماجُ في الحزمة | C6: يُنقل الحكمُ إلى فصله ويُسجَّل في الورقة 03 بمصدرِه وتاريخِه | D6: مكتبُ الهندسة | E6: سطرٌ في سجل الأحكامِ بمرجعه | F6: إصدارِ النسخة
A7: 6 | B7: إصدارُ نسخةٍ جديدة | C7: يُرفع رقمُ الوثيقةِ المتأثرةِ وتُحدَّث بصمتُها في الورقة 01 | D7: مكتبُ الهندسة | E7: بصمةٌ جديدةٌ في بيان التجميد | F7: —
A8: ◆ | B8: الحكم | C8: لا مادةَ تدخل الحزمةَ إلا بالخطوات الستِّ كاملةً — والإدماجُ المباشرُ يُبطل خطَّ الأساس | D8: — | E8: — | F8: —

Sheet 03 — سجل الأحكام النهائية
A1: # | B1: معرّفُ الحكم | C1: نصُّ الحكم | D1: الوثيقةُ الأصلية | E1: القسم | F1: المجالُ أو الإدارة | G1: الحكمُ الأحدثُ الحاكم | H1: canonical_home_document | I1: canonical_home_section | J1: referenced_by_documents | K1: اختبارُ القبول | L1: أمطبَّقٌ في الكود | M1: حالةُ النفاذ
A2: 1 | B2: ORG-001 | C2: منصة إنجاز نشأت نظامًا داخليًا لإدارة شركة إكوبيشن للتشغيل، المتخصصة في تشغيل المعدات والمتحركات في قطاع التعدين والمناجم والمحاجر، وتتحول إلى نواة منصة مؤسسية قابلة للتشغيل بوصفها SaaS متعدد الشركات. | D2: SRC-001 | E2: أولًا | F2: ORG | G2: لا معارض — نافذ بنصّه | H2: INJAZ-CORE-01 | I2: الفصلُ ١ — الدستور | J2: FRD-01 · UX-01 · DELIVERY-01 — تُحيل ولا تعيد الكتابة | K2: اختبارُ وجودٍ وسلوك: بمعطى بيئةٍ مهيَّأةٍ لـ«منصة إنجاز نشأت نظامًا داخليًا لإدارة شركة إكوبيشن ل…» · وعند تنفيذ السيناريو الموصوف · فإن السلوكَ يطابق النصَّ ويُوثَّق الشاهدُ بلقطةٍ أو سجل | L2: غير مقيس — يُملأ عند مراجعة الكود | M2: نافذ
A3: 2 | B3: ORG-002 | C3: القطاعات المخدومة: تشغيل المعدات الثقيلة / التعدين والمحاجر / إدارة المعدات والموردين / المقاولات والخدمات التشغيلية / إدارة المشاريع والمواقع / القوى التشغيلية والمشغلين / الصيانة والمخازن والمشتريات / النقل والترحيل / العقود والاستحقاقات والتسويات / الإدارة المالية والتمويل والملكية / الحوكمة والالتزام والبلاغات. | D3: SRC-001 | E3: أولًا | F3: ORG | G3: لا معارض — نافذ بنصّه | H3: INJAZ-CORE-01 | I3: الفصلُ ١ — الدستور | J3: FRD-01 · UX-01 · DELIVERY-01 — تُحيل ولا تعيد الكتابة | K3: اختبارُ وجودٍ وسلوك: بمعطى بيئةٍ مهيَّأةٍ لـ«تشغيل المعدات الثقيلة / التعدين والمحاجر / إدارة الم…» · وعند تنفيذ السيناريو الموصوف · فإن السلوكَ يطابق النصَّ ويُوثَّق الشاهدُ بلقطةٍ أو سجل | L3: غير مقيس — يُملأ عند مراجعة الكود | M3: نافذ
A4: 3 | B4: ORG-003 | C4: الشريحة المستهدفة تشمل الشركات الصغيرة والمتوسطة والكبيرة معًا؛ ولا يجوز تصميم النظام لفئة واحدة منها. | D4: SRC-001 | E4: أولًا | F4: ORG | G4: لا معارض — نافذ بنصّه | H4: INJAZ-CORE-01 | I4: الفصلُ ١ — الدستور | J4: FRD-01 · UX-01 · DELIVERY-01 — تُحيل ولا تعيد الكتابة | K4: اختبارُ منع: بمعطى محاولةٍ تخالف «الشريحة المستهدفة تشمل الشركات الصغيرة والمتوسطة وال…» · وعند تنفيذها · فإن الخادمَ يرفض برمزٍ وسببٍ ويُسجَّل الرفضُ بالمستخدم والوقت | L4: غير مقيس — يُملأ عند مراجعة الكود | M4: نافذ
A5: 4 | B5: ORG-004 | C5: الجهات التابعة للرئيس التنفيذي مباشرة (تسع): إدارة التشغيل / إدارة المبيعات والعقود / إدارة الموردين / الإدارة المالية والخزينة / إدارة التمويل والملكية / إدارة الأسطول / إدارة الموارد البشرية / إدارة الحوكمة والالتزام / مركز البلاغات. | D5: SRC-001 | E5: تاسعًا | F5: ORG | G5: لا معارض — نافذ بنصّه | H5: INJAZ-CORE-01 | I5: الفصلُ ١ — الدستور | J5: FRD-01 · UX-01 · DELIVERY-01 — تُحيل ولا تعيد الكتابة | K5: اختبارُ وجودٍ وسلوك: بمعطى بيئةٍ مهيَّأةٍ لـ«إدارة التشغيل / إدارة المبيعات والعقود / إدارة المور…» · وعند تنفيذ السيناريو الموصوف · فإن السلوكَ يطابق النصَّ ويُوثَّق الشاهدُ بلقطةٍ أو سجل | L5: غير مقيس — يُملأ عند مراجعة الكود | M5: نافذ
A6: 5 | B6: ORG-005 | C6: الإدارات التشغيلية التابعة لمدير التشغيل (ست): إدارات المواقع وعلى رأس كل موقع مدير موقع / إدارة الصيانة / إدارة القوى التشغيلية / إدارة المشتريات / إدارة المخازن / إدارة النقل والترحيل. | D6: SRC-001 | E6: تاسعًا | F6: ORG | G6: لا معارض — نافذ بنصّه | H6: INJAZ-CORE-01 | I6: الفصلُ ١ — الدستور | J6: FRD-01 · UX-01 · DELIVERY-01 — تُحيل ولا تعيد الكتابة | K6: اختبارُ وجودٍ وسلوك: بمعطى بيئةٍ مهيَّأةٍ لـ«إدارات المواقع وعلى رأس كل موقع مدير موقع / إدارة ال…» · وعند تنفيذ السيناريو الموصوف · فإن السلوكَ يطابق النصَّ ويُوثَّق الشاهدُ بلقطةٍ أو سجل | L6: غير مقيس — يُملأ عند مراجعة الكود | M6: نافذ
A7: 6 | B7: ORG-007 | C7: يجب الحفاظ على التمييز بين ثمانية مفاهيم لا تُخلط: الإدارة التنظيمية / باب التنقل / مجموعة الشاشات / المسمى الوظيفي / التكليف الموقعي / الدور والصلاحية / الشاشة المالكة / شاشة العرض أو زاوية الاطلاع. | D7: SRC-001 | E7: تاسعًا | F7: ORG | G7: لا معارض — نافذ بنصّه | H7: INJAZ-CORE-01 | I7: الفصلُ ١ — الدستور | J7: FRD-01 · UX-01 · DELIVERY-01 — تُحيل ولا تعيد الكتابة | K7: اختبارُ منع: بمعطى محاولةٍ تخالف «الإدارة التنظيمية / باب التنقل / مجموعة الشاشات / ال…» · وعند تنفيذها · فإن الخادمَ يرفض برمزٍ وسببٍ ويُسجَّل الرفضُ بالمستخدم والوقت | L7: غير مقيس — يُملأ عند مراجعة الكود | M7: نافذ
A8: 7 | B8: ORG-008 | C8: الهيكل التنظيمي أعلاه هو نقطة الانطلاق الملزمة، ولا يُعدَّل إلا إذا ظهر قرار أحدث صريح داخل الوثائق. | D8: SRC-001 | E8: تاسعًا | F8: ORG | G8: لا معارض — نافذ بنصّه | H8: INJAZ-CORE-01 | I8: الفصلُ ١ — الدستور | J8: FRD-01 · UX-01 · DELIVERY-01 — تُحيل ولا تعيد الكتابة | K8: اختبارُ منع: بمعطى محاولةٍ تخالف «الهيكل التنظيمي أعلاه هو نقطة الانطلاق الملزمة» · وعند تنفيذها · فإن الخادمَ يرفض برمزٍ وسببٍ ويُسجَّل الرفضُ بالمستخدم والوقت | L8: غير مقيس — يُملأ عند مراجعة الكود | M8: نافذ
A9: 8 | B9: DOC-001 | C9: التوقف عن إضافة وثائق صغيرة متفرقة نهائيًا. | D9: SRC-001 | E9: أولًا | F9: DOC | G9: لا معارض — نافذ بنصّه | H9: INJAZ-CORE-01 | I9: الفصلُ ١ — الدستور | J9: FRD-01 · UX-01 · DELIVERY-01 — تُحيل ولا تعيد الكتابة | K9: اختبارُ وجودٍ وسلوك: بمعطى بيئةٍ مهيَّأةٍ لـ«التوقف عن إضافة وثائق صغيرة متفرقة نهائيًا» · وعند تنفيذ السيناريو الموصوف · فإن السلوكَ يطابق النصَّ ويُوثَّق الشاهدُ بلقطةٍ أو سجل | L9: غير مقيس — يُملأ عند مراجعة الكود | M9: نافذ
A10: 9 | B10: DOC-002 | C10: إعادة بناء المنظومة التوثيقية كأن منصة إنجاز صُممت من البداية وفق آخر ما استقر عليه المشروع. | D10: SRC-001 | E10: أولًا | F10: DOC | G10: لا معارض — نافذ بنصّه | H10: INJAZ-CORE-01 | I10: الفصلُ ١ — الدستور | J10: FRD-01 · UX-01 · DELIVERY-01 — تُحيل ولا تعيد الكتابة | K10: اختبارُ وجودٍ وسلوك: بمعطى بيئةٍ مهيَّأةٍ لـ«إعادة بناء المنظومة التوثيقية كأن منصة إنجاز صُممت م…» · وعند تنفيذ السيناريو الموصوف · فإن السلوكَ يطابق النصَّ ويُوثَّق الشاهدُ بلقطةٍ أو سجل | L10: غير مقيس — يُملأ عند مراجعة الكود | M10: نافذ
A11: 10 | B11: DOC-003 | C11: المهمة ليست تلخيصًا ولا دمجًا ميكانيكيًا ولا إعادة كتابة لآخر نسخة فقط. | D11: SRC-001 | E11: ثانيًا | F11: DOC | G11: لا معارض — نافذ بنصّه | H11: INJAZ-CORE-01 | I11: الفصلُ ١ — الدستور | J11: FRD-01 · UX-01 · DELIVERY-01 — تُحيل ولا تعيد الكتابة | K11: اختبارُ وجودٍ وسلوك: بمعطى بيئةٍ مهيَّأةٍ لـ«المهمة ليست تلخيصًا ولا دمجًا ميكانيكيًا ولا إعادة ك…» · وعند تنفيذ السيناريو الموصوف · فإن السلوكَ يطابق النصَّ ويُوثَّق الشاهدُ بلقطةٍ أو سجل | L11: غير مقيس — يُملأ عند مراجعة الكود | M11: نافذ
A12: 11 | B12: DOC-004 | C12: استخراج كل قاعدة وميزة وشاشة ودورة عمل واعتماد وحارس وقرار من كل وثيقة. | D12: SRC-001 | E12: ثانيًا | F12: DOC | G12: لا معارض — نافذ بنصّه | H12: INJAZ-CORE-01 | I12: الفصلُ ١ — الدستور | J12: FRD-01 · UX-01 · DELIVERY-01 — تُحيل ولا تعيد الكتابة | K12: اختبارُ ظهور: بمعطى مستخدمٍ داخلَ النطاق وآخرَ خارجه لـ«استخراج كل قاعدة وميزة وشاشة ودورة عمل واعتماد وحارس…» · وعند فتح الشاشة · فإن الأولَ يرى نطاقَه والثانيَ لا يُصيَّر له العنصرُ ولا يُرسَل في الاستجابة | L12: غير مقيس — يُملأ عند مراجعة الكود | M12: نافذ
A13: 12 | B13: DOC-005 | C13: معرفة علاقة كل معلومة ببقية المنظومة. | D13: SRC-001 | E13: ثانيًا | F13: DOC | G13: لا معارض — نافذ بنصّه | H13: INJAZ-CORE-01 | I13: الفصلُ ١ — الدستور | J13: FRD-01 · UX-01 · DELIVERY-01 — تُحيل ولا تعيد الكتابة | K13: اختبارُ وجودٍ وسلوك: بمعطى بيئةٍ مهيَّأةٍ لـ«معرفة علاقة كل معلومة ببقية المنظومة» · وعند تنفيذ السيناريو الموصوف · فإن السلوكَ يطابق النصَّ ويُوثَّق الشاهدُ بلقطةٍ أو سجل | L13: غير مقيس — يُملأ عند مراجعة الكود | M13: نافذ
... A5531: 5530 | B5531: GEN-0039 | C5531: ◆ لكل إدارةٍ مساحةُ حوكمةٍ نطاقيةٌ تعرض هيكلَها وأدوارَها وتفويضاتِها وتعارضاتِ واجباتها ومراجعاتِ وصولها — منظرًا على المصادرِ المركزيةِ لا نظامًا مستقلًّا. | D5531: INJAZ-CORE-01 · الفصلُ التاسع — المتطلباتُ العامةُ الملزمةُ لكلِّ شاشة | E5531: §المخاطر والحوكمة | F5531: GEN | G5531: قرار مالك موقَّع — نافذ | H5531: INJAZ-MASTER-MAP | I5531: ورقةُ أحكامٍ غيرِ مصنَّفة | J5531: — | K5531: اختبارُ نطاق: تعرض نطاقَ الإدارةِ وحدَه بحسب الصلاحية | L5531: مطلوب — يُقاس من النظام الحي | M5531: نافذ

Sheet 04 — مصفوفة النسخ والاستبدال
A1: # | B1: الوثيقةُ الأقدم | C1: الحكمُ فيها | D1: الوثيقةُ الأحدث | E1: الحكمُ الناسخ | F1: نوعُ العلاقة | G1: الأساسُ | H1: الحالة
A2: 1 | B2: SCR-DES-01 · الأعمدةُ الحاكمة | C2: تُكتب في كل شاشةٍ على حدة | D2: D-02 النمط AR-03 | E2: تُحقن من طبقةٍ مشتركةٍ واحدة | F2: نسخٌ جزئيّ | G2: المعماريةُ أعلى مرتبةً من ملفِّ التصميم | H2: نافذٌ — والتنفيذُ في MG-2
A3: 2 | B3: E-03 المعيارُ الرابع | C3: الأعمدةُ الحاكمةُ سبعةٌ إلزامية | D3: DS-01 بوابةُ التكافؤ | E3: ثلاثةَ عشرَ عمودًا حاكمًا مصنَّفةً ثلاثةَ أصناف | F3: توسيعٌ لا نسخ | G3: الأحدثُ يفصّل ولا يخالف | H3: نافذان معًا
A4: 3 | B4: E-03 §المعيارُ الخامسُ فقط | C4: طقمُ حالاتٍ موحَّدٌ بسبع | D4: DS-01 المبدأ DS-10 | E4: خمسةُ محاورَ مستقلةٍ يركّبها CM-00 | F4: نسخٌ على مستوى القسم — PARTIAL | G4: النموذجُ القديمُ في قسمٍ بعينِه يخلط محاورَ مختلفة · ◆ وبقيةُ E-03 نافذةٌ كلُّها ولا تُمسّ | H4: القسمُ منسوخٌ — وE-03 يبقى أعلى في ماذا تعرض ومن يرى
A5: 4 | B5: UX-AUD-01 §حالاتُ الشاشة | C5: قائمةٌ واحدةٌ بسبعِ حالات | D5: DS-01 المبدأ DS-10 | E5: خمسةُ محاورَ مستقلة | F5: نسخٌ على مستوى القسم — PARTIAL | G5: محكومٌ في هذه الوثيقة · وبقيةُ UX-AUD-01 نافذة | H5: القسمُ منسوخٌ لا الوثيقة
A6: 5 | B6: DEC-SCR-01 v0.6 | C6: القرارُ على العمودِ بالاسم | D6: DEC-SCR-01 v0.7 | E6: معرّفٌ دلاليٌّ لكل شاشةٍ ولا يُفترض التكافؤ | F6: نسخُ إصدارٍ — VERSION | G6: حادثةُ «الوحدة» أثبتت الخطأ · والإصدارُ الأحدثُ من الوثيقةِ نفسِها | H6: v0.7 نافذٌ و v0.6 تاريخي
A7: 6 | B7: orgmodel v1 §علاقةُ الموقع | C7: إدارةُ الموقعِ تتبع الإداراتِ التشغيليةَ الخمس | D7: orgmodel v2 · L4 الفرعان | E7: مديرو المواقعِ يوازون الإداراتَ التشغيليةَ تحت مدير التشغيل | F7: ◆ نسخٌ كامل للعلاقة | G7: مديرُ الموقعِ ليس موظفًا تحت خمسةِ مدراء | H7: v2 نافذٌ — والأثرُ على parent_org_unit والموافقاتِ والصلاحيات
A8: 7 | B8: DIO-01 v0.9 §المشاركة | C8: ستةُ مستوياتٍ للجميع | D8: DEC-08 التوصية | E8: ثلاثةُ مستوياتٍ للخارجيِّ بلا اعتماد | F8: تخصيصٌ | G8: الاعتمادُ لا يُمنح لمن ليس في الشركة | H8: توصيةٌ تنتظر الاعتماد
A9: 8 | B9: قوائمُ الأفعالِ القديمة | C9: رمزٌ قصيرٌ بلا نطاق | D9: التدقيقُ العالميُّ — الورقة 07 | E9: نمط domain.resource.action | F9: نسخٌ بـalias | G9: أربعةُ رموزٍ تحمل معنيين | H9: ◆ حاجبٌ حتى الإصلاح
A10: 9 | B10: «الرئيس التنفيذي» | C10: المسمّى القياديُّ القديم | D10: قرارُ المالك | E10: الرئيسُ التنفيذيُّ وثلاثةُ نواب | F10: نسخٌ كامل | G10: قرارُ مالكٍ أحدث | H10: نافذٌ — وطُبِّق في 29 وثيقة

Sheet 05 — الإدارات والدورات
A1: الرتبة | B1: الطبقة | C1: الإدارة | D1: التابعُ له | E1: المراحل | F1: المجموعات | G1: ظهورُ الشاشات | H1: الشاشاتُ المملوكة | I1: الأفعال | J1: الفصلُ في FRD | K1: الحكمُ والملاحظة
A2: 1 | B2: L1+L2 | C2: مكتبُ الرئيس التنفيذي والنواب | D2: — | E2: 9 | F2: 18 | G2: 25 | H2: 7 | I2: 10 | J2: — | K2: أعلى الهيكل — الرئيسُ التنفيذيُّ وثلاثةُ نواب
A3: 2 | B3: L3 | C3: إدارة التشغيل | D3: نائبُ العمليات | E3: 9 | F3: 22 | G3: 42 | H3: 8 | I3: 14 | J3: الفصلُ ٤ — إدارة التشغيل | K3: متوازيةٌ — وتحتها فرعان متوازيان: الإداراتُ التشغيليةُ ومديرو المواقع
A4: 3 | B4: L3 | C4: المبيعات والعقود | D4: نائبُ الشؤون المالية والاستثمار | E4: 10 | F4: 26 | G4: 42 | H4: 22 | I4: 27 | J4: الفصلُ ٥ — المبيعات والعقود | K4: متوازيةٌ — تملك العقدَ والتغطيةَ والأسعار
A5: 4 | B5: L3 | C5: إدارة الموردين | D5: نائبُ الشؤون المالية والاستثمار | E5: 11 | F5: 29 | G5: 45 | H5: 18 | I5: 24 | J5: الفصلُ ٦ — إدارة الموردين | K5: متوازيةٌ — تملك عقدَ الموردِ والحصصَ والحاويات
A6: 5 | B6: L3 | C6: إدارة الأسطول | D6: نائبُ الشؤون المالية والاستثمار | E6: 10 | F6: 23 | G6: 37 | H6: 13 | I6: 17 | J6: الفصلُ ٧ — إدارة الأسطول | K6: متوازيةٌ — تملك الأصلَ والوثائقَ والعدّادات
A7: 6 | B7: L3 | C7: المالية والخزينة | D7: نائبُ الشؤون المالية والاستثمار | E7: 11 | F7: 36 | G7: 53 | H7: 28 | I7: 35 | J7: الفصلُ ٨ — المالية والخزينة | K7: متوازيةٌ — تملك الدفاترَ والذممَ والخزينة
A8: 7 | B8: L3 | C8: التمويل والملكية | D8: نائبُ الشؤون المالية والاستثمار | E8: 9 | F8: 21 | G8: 33 | H8: 14 | I8: 18 | J8: الفصلُ ٩ — التمويل والملكية | K8: متوازيةٌ — تملك الملكيةَ وأنماطَ التمويل
A9: 8 | B9: L3 | C9: إدارة المشتريات المركزية | D9: نائبُ الشؤون المالية والاستثمار | E9: ◆ لا دورة | F9: ◆ لا مجموعات | G9: ◆ لا شاشات | H9: ◆ لا شاشات | I9: ◆ لا أفعال | J9: ◆ لا فصلَ بعد | K9: ◆ إدارةٌ مستكملة: الشراءُ الاستراتيجيُّ والاعتماداتُ فوق سقفِ التشغيليةِ والعقودُ الإطارية
A10: 9 | B10: L3 | C10: الموارد البشرية | D10: نائبُ الشؤون الإدارية والحوكمة | E10: 11 | F10: 23 | G10: 34 | H10: 13 | I10: 17 | J10: الفصلُ ١٠ — الموارد البشرية | K10: متوازيةٌ — تملك العلاقةَ الوظيفيةَ والمسيّر
A11: 10 | B11: L3 | C11: شؤونُ العاملين بالمشروعات | D11: نائبُ الشؤون الإدارية والحوكمة | E11: ◆ لا دورة | F11: ◆ لا مجموعات | G11: ◆ لا شاشات | H11: ◆ لا شاشات | I11: ◆ لا أفعال | J11: ◆ لا فصلَ بعد | K11: ◆ وحدةٌ مستكملة: العقودُ المشروعيةُ المؤقتةُ والتعبئةُ والتسريحُ الميداني
A12: 11 | B12: L3 | C12: إدارة المخاطر المؤسسية | D12: ◆ الرئيسُ التنفيذيُّ مباشرةً | E12: 9 | F12: 9 | G12: 18 | H12: 20 | I12: 36 | J12: — | K12: ◆ تتبع الرئيسَ التنفيذيَّ مباشرةً في طبقةٍ موازيةٍ للحوكمةِ والالتزام — فاستقلالُها عمّن تراقبهم شرطُ فاعليتها · وتملك المنهجَ والقياسَ والتحدي والتجميعَ والتصعيدَ لا ملكيةَ مخاطرِ الإدارات
A13: 12 | B13: L3 | C13: الحوكمة والالتزام | D13: ◆ الرئيسُ التنفيذيُّ مباشرةً | E13: 11 | F13: 32 | G13: 41 | H13: 33 | I13: 41 | J13: الفصلُ ١١ — الحوكمة والالتزام | K13: ◆ رقابيةٌ تتبع الرئيسَ مباشرةً — تملك الصلاحياتِ والاستثناءاتِ وسجلَّ التدقيقِ وفصلَ الواجبات · ولا تملك منهجَ المخاطرِ ولا قياسَها
A14: 13 | B14: L3 | C14: مركز البلاغات | D14: نائبُ الشؤون الإدارية والحوكمة | E14: 10 | F14: 15 | G14: 21 | H14: 13 | I14: 19 | J14: الفصلُ ١٢ — مركز البلاغات | K14: ◆ مركزٌ رقابيٌّ وخدميٌّ عابرٌ للإدارات — لا إدارةً مركزيةً بالمعنى نفسِه للمالية
A15: 14 | B15: L4 · الفرعُ الأول | C15: إدارة الصيانة | D15: مديرُ التشغيل | E15: 9 | F15: 19 | G15: 34 | H15: 8 | I15: 14 | J15: الفصلُ ١٣ — إدارة الصيانة | K15: تشغيليةٌ مركزيةٌ — تملك الحكمَ الفنيَّ والجاهزيةَ وشجرةَ الأعطال · ◆ توازي مديري المواقعِ ولا تعلوهم
A16: 15 | B16: L4 · الفرعُ الأول | C16: القوى التشغيلية | D16: مديرُ التشغيل | E16: 10 | F16: 24 | G16: 37 | H16: 11 | I16: 15 | J16: الفصلُ ١٤ — القوى التشغيلية | K16: تشغيليةٌ مركزيةٌ — تملك المشغّلينَ وتأهيلَهم · ◆ توازي مديري المواقع
A17: 16 | B17: L4 · الفرعُ الأول | C17: النقل والترحيل | D17: مديرُ التشغيل | E17: 9 | F17: 14 | G17: 23 | H17: 9 | I17: 13 | J17: الفصلُ ١٥ — النقل والترحيل | K17: تشغيليةٌ مركزيةٌ — تملك أوامرَ الترحيلِ ووسائلَ النقل · ◆ توازي مديري المواقع
A18: 17 | B18: L4 · الفرعُ الأول | C18: إدارة المشتريات التشغيلية | D18: مديرُ التشغيل | E18: 8 | F18: 13 | G18: 23 | H18: 6 | I18: 13 | J18: — | K18: تشغيليةٌ مركزيةٌ — تملك الاحتياجَ التشغيليَّ وأمرَ الشراءِ داخلَ سقفها · ◆ توازي مديري المواقع
A19: 18 | B19: L4 · الفرعُ الأول | C19: إدارة المخازن | D19: مديرُ التشغيل | E19: 8 | F19: 16 | G19: 25 | H19: 11 | I19: 16 | J19: الفصلُ ١٧ — إدارة المخازن | K19: تشغيليةٌ مركزيةٌ — تملك الرصيدَ والتقييمَ والجرد · ◆ توازي مديري المواقع
A20: 19 | B20: L4 · الفرعُ الثاني | C20: إدارة الموقع | D20: مديرُ التشغيل | E20: 11 | F20: 23 | G20: 41 | H20: 11 | I20: 23 | J20: — | K20: ◆ وحدةُ موقعٍ تتبع مديرَ التشغيلِ مباشرةً — وتوازي الإداراتَ التشغيليةَ الخمسَ ولا تتبعها · وأعلى سلطةٍ ميدانيةٍ في موقعها
A21: 20 | B21: — | C21: مساحة عملي | D21: عرضيةٌ لكل الأدوار | E21: 5 | F21: 7 | G21: 13 | H21: 10 | I21: 10 | J21: — | K21: ◆ ليست إدارةً ولا وحدةً — واجهةٌ عرضيةٌ بلا مديرٍ ولا ميزانيةٍ ولا خطِّ تبعية
A22: — | B22: — | C22: الإجمالي | D22: — | E22: 145 | F22: 345 | G22: 553 | H22: 203 | I22: 246 | J22: — | K22: الطبقاتُ الستُّ في الورقة 12

Sheet 06 — سجل الشاشات
A1: # | B1: الإدارةُ المالكة | C1: الملف | D1: اسمُ الشاشة | E1: المرحلة | F1: المجموعة | G1: الأعمدة | H1: أطويلة | I1: الأفعال | J1: العارضون | K1: حقولٌ حساسة | L1: المناظر | M1: الفصلُ في UX
A2: 1 | B2: الإدارة التنفيذية | C2: ceo_approvals.php | D2: اعتمادات الرئيس التنفيذي | E2: ثانيًا: الاعتمادات العليا | F2: صندوق الاعتمادات العليا | G2: 23 | H2: نعم | I2: 1 | J2: 7 | K2: 1 | L2: مطلوبة | M2: الفصلُ ٢ — سجلُّ الشاشات
A3: 2 | B3: الإدارة التنفيذية | C3: ceo_contracts.php | D3: العقود والالتزامات المحجوزة أو المصعَّدة | E3: ثالثًا: العقودُ والالتزاماتُ المحجوزةُ أو المصعَّدةُ للرئيس | F3: توقيع العقود | G3: 30 | H3: نعم | I3: 1 | J3: 4 | K3: 2 | L3: مطلوبة | M3: الفصلُ ٢ — سجلُّ الشاشات
A4: 3 | B4: الإدارة التنفيذية | C4: risk_dept_ceo.php | D4: المخاطر المؤسسية | E4: مخاطرُ الإدارة | F4: مخاطرُ إدارتي | G4: 22 | H4: نعم | I4: 3 | J4: 1 | K4: 1 | L4: مطلوبة | M4: الفصلُ ٢ — سجلُّ الشاشات
A5: 4 | B5: الإدارة التنفيذية | C5: ceo_risk.php | D5: المخاطر والقرارات العليا | E5: خامسًا: المخاطر والحسم | F5: المخاطر والقرارات العليا | G5: 19 | H5: لا | I5: 1 | J5: 1 | K5: 0 | L5: غيرُ لازمة | M5: الفصلُ ٢ — سجلُّ الشاشات
A6: 5 | B6: الإدارة التنفيذية | C6: gov_dept_ceo.php | D6: حوكمة مكتبُ الرئيس التنفيذي والنواب | E6: — | F6: — | G6: 15 | H6: لا | I6: 2 | J6: 1 | K6: 1 | L6: غيرُ لازمة | M6: الفصلُ ٢ — سجلُّ الشاشات
A7: 6 | B7: الإدارة التنفيذية | C7: project_charter.php | D7: قرار فتح مشروع جديد | E7: رابعًا: فتح المشاريع | F7: قرار فتح مشروع | G7: 31 | H7: نعم | I7: 1 | J7: 6 | K7: 3 | L7: مطلوبة | M7: الفصلُ ٢ — سجلُّ الشاشات
A8: 7 | B8: الإدارة التنفيذية | C8: ceo_board.php | D8: لوحة الرئيس التنفيذي | E8: لوحة الإدارة التنفيذية | F8: المؤشرات العليا | G8: 16 | H8: لا | I8: 1 | J8: 0 | K8: 3 | L8: غيرُ لازمة | M8: الفصلُ ٢ — سجلُّ الشاشات
A9: 8 | B9: إدارة التشغيل | C9: unit_assign.php | D9: إسناد المعدات للوحدات | E9: ثانيًا: توزيع الموارد | F9: الإسناد للوحدات | G9: 27 | H9: نعم | I9: 1 | J9: 3 | K9: 1 | L9: مطلوبة | M9: الفصلُ ٢ — سجلُّ الشاشات
A10: 9 | B10: إدارة التشغيل | C10: unit_perf.php | D10: الأداء الشهري للوحدة | E10: رابعًا: متابعة الانحراف | F10: الأداء الشهري | G10: 33 | H10: نعم | I10: 1 | J10: 3 | K10: 3 | L10: مطلوبة | M10: الفصلُ ٢ — سجلُّ الشاشات
A11: 10 | B11: إدارة التشغيل | C11: monthly_close.php | D11: الإقفال الشهري للوحدة | E11: سابعًا: إقفال اليوم | F11: الإقفال | G11: 33 | H11: نعم | I11: 1 | J11: 4 | K11: 3 | L11: مطلوبة | M11: الفصلُ ٢ — سجلُّ الشاشات
A12: 11 | B12: إدارة التشغيل | C12: stops.php | D12: التوقفات وتحديد المتحمل | E12: رابعًا: تسجيل عمل اليوم | F12: التوقفات | G12: 32 | H12: نعم | I12: 2 | J12: 4 | K12: 3 | L12: مطلوبة | M12: الفصلُ ٢ — سجلُّ الشاشات
A13: 12 | B13: إدارة التشغيل | C13: risk_dept_ops.php | D13: المخاطر التشغيلية | E13: مخاطرُ الإدارة | F13: مخاطرُ إدارتي | G13: 22 | H13: نعم | I13: 3 | J13: 1 | K13: 1 | L13: مطلوبة | M13: الفصلُ ٢ — سجلُّ الشاشات
... A256: 255 | B256: مساحة عملي | C256: my_tasks.php | D256: مهامي | E256: لوحة الإدارة التنفيذية | F256: مساحتي الشخصية | G256: 15 | H256: لا | I256: 1 | J256: 15 | K256: 0 | L256: غيرُ لازمة | M256: الفصلُ ٢ — سجلُّ الشاشات

Sheet 07 — سجل الأفعال والتدقيق
A1: # | B1: الرمزُ الحالي | C1: الاسمُ المقترحُ domain.resource.action | D1: الفعل | E1: الإدارة | F1: الشاشة | G1: الفاعل | H1: ما يُكتب | I1: الحدث | J1: المستهلك | K1: الأثر | L1: العكس | M1: ①معنًى | N1: ②alias | O1: ③مالك | P1: ④مصدر | Q1: ⑤معالج | R1: ⑥عكسٌ ماليّ | S1: ⑦دائرية | T1: ⑧الكود | U1: حاجب | V1: حالةُ الربط
A2: 1 | B2: ticket.open | C2: tickets.ticket.create | D2: فتحُ بلاغ | E2: مركز البلاغات | F2: أبلغ عن مشكلة من هذه الشاشة | G2: المستخدم | H2: tickets · ticket_context | I2: TicketOpened | J2: مركزُ البلاغات · الإدارةُ المختصة | K2: تذكرةٌ مصنَّفةٌ موجَّهةٌ آليًّا · ومهلةٌ تبدأ · وسياقُ الشاشة محفوظ | L2: إغلاقٌ إداريٌّ بمرجع | M2: ✔ | N2: ✔ | O2: ✔ | P2: ✔ | Q2: ◐ معلَّقُ الربطِ معلَنٌ | R2: ✔ | S2: ✔ | T2: ◐ يحتاج مقارنةً بالكود الحيّ | U2: لا | V2: معلَّقُ الربطِ — 228 من 242
A3: 2 | B3: ticket.ack | C3: tickets.ticket.receive | D3: استلامُ البلاغ | E3: مركز البلاغات | F3: بلاغات إدارتي | G3: المكلَّف | H3: tickets.state · sla | I3: TicketAcknowledged | J3: مركزُ البلاغات | K3: مهلةُ الاستجابة تتوقف · ومهلةُ الإنجاز تبدأ · والمكلَّفُ مسؤولٌ باسمه | L3: إعادةُ توجيهٍ بسبب | M3: ✔ | N3: ✔ | O3: ✔ | P3: ✔ | Q3: ◐ معلَّقُ الربطِ معلَنٌ | R3: ✔ | S3: ✔ | T3: ◐ يحتاج مقارنةً بالكود الحيّ | U3: لا | V3: معلَّقُ الربطِ — 228 من 242
A4: 3 | B4: ticket.done | C4: tickets.ticket.execute_done | D4: إنجازُ البلاغ | E4: مركز البلاغات | F4: بلاغات إدارتي | G4: المكلَّف | H4: tickets.state · resolution | I4: TicketResolved | J4: المبلِّغُ · المركز | K4: ينتظر تأكيدَ المبلِّغ — ولا يُغلق المكلَّفُ بنفسه | L4: إعادةُ فتحٍ بعدّاد | M4: ✔ | N4: ✔ | O4: ✔ | P4: ✔ | Q4: ◐ معلَّقُ الربطِ معلَنٌ | R4: ✔ | S4: ✔ | T4: ◐ يحتاج مقارنةً بالكود الحيّ | U4: لا | V4: معلَّقُ الربطِ — 228 من 242
A5: 4 | B5: approval.grant | C5: governance.approval.approve | D5: اعتمادٌ في سقفي | E5: الحوكمة والالتزام | F5: صندوق ما ينتظر اعتمادي | G5: المعتمِد | H5: approvals · audit | I5: ApprovalGranted | J5: الحلقةُ التالية | K5: المستندُ ينتقل · والتوقيعُ يُسجَّل بمرجع التفويض | L5: سحبٌ بقرارٍ موثَّق | M5: ✔ | N5: ✔ | O5: ✔ | P5: ✔ | Q5: ◐ معلَّقُ الربطِ معلَنٌ | R5: ✔ | S5: ✔ | T5: ◐ يحتاج مقارنةً بالكود الحيّ | U5: لا | V5: معلَّقُ الربطِ — 228 من 242
A6: 5 | B6: approval.reject | C6: governance.approval.execute_reject | D6: رفضٌ بسببٍ محكوم | E6: الحوكمة والالتزام | F6: صندوق ما ينتظر اعتمادي | G6: المعتمِد | H6: approvals · reasons | I6: ApprovalRejected | J6: المُنشئ · المسار | K6: المستندُ يعود لمُنشئه بسببٍ من قائمةٍ محكومة — ويُقاس السببُ في تحليل الاختناقات | L6: إعادةُ رفعٍ بعد التصحيح | M6: ✔ | N6: ✔ | O6: ✔ | P6: ✔ | Q6: ◐ معلَّقُ الربطِ معلَنٌ | R6: ✔ | S6: ✔ | T6: ◐ يحتاج مقارنةً بالكود الحيّ | U6: لا | V6: معلَّقُ الربطِ — 228 من 242
A7: 6 | B7: approval.return | C7: governance.approval.execute_return | D7: إعادةٌ للتصحيح | E7: الحوكمة والالتزام | F7: صندوق ما ينتظر اعتمادي | G7: المعتمِد | H7: approvals | I7: ApprovalReturned | J7: المُنشئ | K7: المستندُ يعود قابلًا للتعديل · والمهلةُ تتوقف حتى إعادة الرفع | L7: ◆ بلا عكس | M7: ✔ | N7: ✔ | O7: ✔ | P7: ✔ | Q7: ◐ معلَّقُ الربطِ معلَنٌ | R7: ✔ | S7: ✔ | T7: ◐ يحتاج مقارنةً بالكود الحيّ | U7: لا | V7: معلَّقُ الربطِ — 228 من 242
A8: 7 | B8: ach.range | C8: workspace.achievement.execute | D8: اختيارُ مدى الإنجاز | E8: مساحة عملي | F8: إنجازي | G8: المستخدم | H8: — | I8: — | J8: — | K8: يُعاد الحسابُ للمدى: يومًا أو أسبوعًا أو شهرًا أو سنةً أو بتاريخين | L8: ◆ بلا عكس | M8: ✔ | N8: ✔ | O8: ✔ | P8: ✔ | Q8: ◐ معلَّقُ الربطِ معلَنٌ | R8: ✔ | S8: ✔ | T8: ◐ يحتاج مقارنةً بالكود الحيّ | U8: لا | V8: معلَّقُ الربطِ — 228 من 242
A9: 8 | B9: plan.submit | C9: site.plan.submit | D9: رفعُ خطة الغد | E9: إدارة الموقع | F9: خطة عمل الغد | G9: مديرُ الموقع | H9: daily_plans · resource_locks | I9: PlanSubmitted | J9: التشغيل · القوى · الأسطول | K9: الحارسُ يفحص التأهيلَ والجاهزيةَ والوثائق · والمواردُ تُحجز مبدئيًّا | L9: سحبٌ قبل الاعتماد | M9: ✔ | N9: ✔ | O9: ✔ | P9: ✔ | Q9: ◐ معلَّقُ الربطِ معلَنٌ | R9: ✔ | S9: ✔ | T9: ◐ يحتاج مقارنةً بالكود الحيّ | U9: لا | V9: معلَّقُ الربطِ — 228 من 242
A10: 9 | B10: plan.approve | C10: site.plan.approve | D10: اعتمادُ خطة الموقع | E10: إدارة الموقع | F10: خطة عمل الغد | G10: مديرُ التشغيل | H10: daily_plans.state | I10: PlanApproved | J10: الموقع · القوى · الأسطول · النقل | K10: الخطةُ تصير نافذةً · ويُفتح التايم شيت عليها · وتُطلب رحلاتُ الترحيل الناقصة | L10: إعادةٌ بسببٍ محكوم | M10: ✔ | N10: ✔ | O10: ✔ | P10: ✔ | Q10: ◐ معلَّقُ الربطِ معلَنٌ | R10: ✔ | S10: ✔ | T10: ◐ يحتاج مقارنةً بالكود الحيّ | U10: لا | V10: معلَّقُ الربطِ — 228 من 242
A11: 10 | B11: plan.copy | C11: site.plan.execute | D11: نسخُ خطة الأمس | E11: إدارة الموقع | F11: خطة عمل الغد | G11: مديرُ الموقع | H11: daily_plans | I11: PlanDrafted | J11: الموقعُ وحدَه | K11: مسودةٌ بالتوزيع نفسِه — والحارسُ يعيد فحصَ الجاهزية والتأهيل قبل الرفع | L11: حذفُ المسودة | M11: ✔ | N11: ✔ | O11: ✔ | P11: ✔ | Q11: ◐ معلَّقُ الربطِ معلَنٌ | R11: ✔ | S11: ✔ | T11: ◐ يحتاج مقارنةً بالكود الحيّ | U11: لا | V11: معلَّقُ الربطِ — 228 من 242
A12: 11 | B12: asset.assign | C12: ops.asset.assign | D12: تخصيصُ معدةٍ لموقع | E12: إدارة التشغيل | F12: توزيع المعدات والمشغّلين | G12: مديرُ التشغيل | H12: assignments · equipment.location | I12: EquipmentAssigned | J12: الموقع · القوى · النقل · الأسطول | K12: المعدةُ تظهر في لوحة الموقع · وتُطلب رحلةُ ترحيلٍ إن اختلف الموقع · وتُطلب موافقةُ القوى | L12: إنهاءُ تخصيصٍ بتاريخٍ وسبب | M12: ✔ | N12: ✔ | O12: ✔ | P12: ✔ | Q12: ◐ معلَّقُ الربطِ معلَنٌ | R12: ✔ | S12: ✔ | T12: ◐ يحتاج مقارنةً بالكود الحيّ | U12: لا | V12: معلَّقُ الربطِ — 228 من 242
A13: 12 | B13: operator.swap | C13: ops.operator.execute | D13: تبديلُ مشغّلٍ على معدة | E13: إدارة التشغيل | F13: توزيع المعدات والمشغّلين | G13: مديرُ التشغيل | H13: operator_assignments · approvals | I13: OperatorSwapRequested | J13: القوى · الموارد · الموقع | K13: لا يقع التبديلُ قبل موافقة القوى · وبعدها يتغير التايم شيت والاستحقاق والحافز | L13: إلغاءُ الطلب أو عكسُ التبديل | M13: ✔ | N13: ✔ | O13: ✔ | P13: ✔ | Q13: ◐ معلَّقُ الربطِ معلَنٌ | R13: ✔ | S13: ✔ | T13: ◐ يحتاج مقارنةً بالكود الحيّ | U13: لا | V13: معلَّقُ الربطِ — 228 من 242
... A363: 362 | B363: risk.settings.review | C363: core.risk.define_settings | D363: ضبطُ دوريةِ المراجعةِ بحسب الدرجة | E363: RSK | F363: إعدادات المخاطر والتصنيف | G363: مديرُ المخاطر | H363: risk_settings | I363: RiskReviewCycleSet | J363: المخاطرُ والإداراتُ المالكة | K363: الحرجُ شهريًّا والمرتفعُ ربعَ سنويٍّ والمتوسطُ نصفَ سنويٍّ والمنخفضُ سنويًّا | L363: إعادةُ الدوريةِ السابقة | M363: ✔ | N363: ✘ معنًى بعدةِ رموزٍ بلا alias | O363: ✘ بلا مالك | P363: ✔ | Q363: ◐ معلَّقُ الربطِ معلَنٌ | R363: ✔ | S363: ✔ | T363: ◐ يحتاج مقارنةً بالكود الحيّ | U363: نعم | V363: معلَّقُ الربطِ — 228 من 242

Sheet 08 — خطة ترحيل الرموز
A1: # | B1: الخطوة | C1: ما يُفعل | D1: الشاهد | E1: لا يُنتقل قبلها | F1: الحالة
A2: 1 | B2: مصفوفةُ استعمال | C2: حصرُ كلِّ موضعٍ يقرأ الرمزَ أو يكتبه: الكودُ والقاموسُ والتقاريرُ وAPI | D2: جدولٌ بالرمزِ وعددِ مواضعه ومساراتها | E2: Dry Run | F2: لم تبدأ — تحتاج الكودَ الحيّ
A3: 2 | B3: Dry Run | C3: تشغيلُ الترحيلِ على نسخةٍ بلا كتابةٍ وقياسُ الفرق | D3: تقريرُ فرقٍ يبيّن كلَّ تغييرٍ متوقَّع | E3: خريطةِ alias | F3: لم تبدأ
A4: 3 | B4: خريطةُ alias | C4: الرمزُ القديمُ يبقى alias للجديدِ دورةَ إصدارٍ كاملة | D4: جدولُ قديمٍ ← جديدٍ بتاريخِ الهجران | E4: اختبارِ الرجوع | F4: لم تبدأ
A5: 4 | B5: اختبارُ الرجوع | C5: إثباتُ إمكانيةِ العودةِ للرموز القديمةِ بلا فقدِ بيانات | D5: تقريرُ رجوعٍ ناجحٍ في بيئةِ ما قبل الإنتاج | E5: اعتمادِ التنفيذ | F5: لم تبدأ
A6: 5 | B6: اعتمادُ التنفيذ | C6: توقيعُ المالكِ على الترحيلِ بعد الشواهد الأربعة | D6: اعتمادٌ موثَّقٌ بتاريخه | E6: التنفيذ | F6: لم تبدأ
A7: 6 | B7: التنفيذُ التدريجي | C7: ترحيلٌ بدفعاتٍ — تبدأ بالرموز الأربعةِ الحاجبة | D7: صفرُ كسرٍ بعد كل دفعة | E7: — | F7: لم تبدأ
A8: ◆ | B8: الحكم | C8: لا يُغيَّر رمزٌ في الكودِ مباشرةً — والأربعةُ الحاجبةُ تُصلَح في الوثيقةِ والقاموسِ أولًا ثم في الكودِ بالخطوات الستّ | D8: — | E8: — | F8: —

Sheet 09 — سجل العيوب المفتوحة
A1: معرّفٌ ثابت | B1: الوصف | C1: الخطورة | D1: الطبقةُ المتأثرة | E1: المالك | F1: سببُ المشكلة | G1: الأثر | H1: أيمنع الإطلاق | I1: القرارُ المطلوب | J1: المهلة | K1: دليلُ الإصلاح | L1: اختبارُ الإغلاق | M1: تاريخُ الإغلاق | N1: من راجع
A2: DEF-001 | B2: أربعةُ رموزِ أفعالٍ تحمل معنيين — model.define و req.raise | C2: حرجة | D2: قاموسُ الأفعالِ والكود | E2: مكتبُ الهندسة | F2: الرمزُ القصيرُ بلا نطاقٍ يتصادم | G2: حملةُ ربطِ الـ228 ستربط معنيين بمعالجٍ واحد | H2: نعم | I2: أيُعتمد نمطُ domain.resource.action للكلِّ أم للحاجبةِ وحدَها؟ | J2: قبل حملةِ الربط | K2: الورقةُ 07 تُظهر صفرَ رمزٍ لأكثرَ من معنى | L2: التدقيقُ العالميُّ يعيد صفرًا في الفحص الأول
A3: DEF-002 | B3: نواةُ التأجيرِ تُبنى خارجَ المعماريةِ الموثَّقة | C3: حرجة | D3: المعماريةُ ونظامُ الشاشات | E3: الرئيسُ التنفيذي | F3: جلسةٌ موازيةٌ بنت ثلاثَ شاشاتٍ خارج NAV-09 | G3: يكسر PR-01 مصدرَ الحقيقةِ الواحد · ولا نموذجَ رابعًا في E-09 | H3: نعم | I3: أتُوثَّق نواةُ التأجيرِ في الحزمةِ أم تُعلَن خارجَ النطاق؟ | J3: عاجل | K3: NAV-09 v5 يضمُّ شاشاتِها بمراحلها وأحكامها | L3: صفرُ رابطٍ خارجَ الوثيقةِ في فاحص nav09_verify
A4: DEF-003 | B4: 228 فعلًا من 242 معلَّقُ الربطِ بمعالجه الحي | C4: عالية | D4: طبقةُ الأفعال | E4: مكتبُ الهندسة | F4: القاموسُ استُورد كاملًا والربطُ في أوله | G4: الأثرُ لا يُتتبَّع من الزرِّ إلى القيد | H4: لا | I4: لا يحتاج قرارًا — يحتاج حملةً بعد DEF-001 | J4: بعد DEF-001 | K4: nav09_action_map: live_code لكل رمز | L4: صفرُ رمزٍ بحالة pending
A5: DEF-004 | B5: 67 وجهةً بلا وحدةِ صلاحياتٍ مسجَّلة من 203 | C5: عالية | D5: الصلاحياتُ والحوكمة | E5: الحوكمةُ والالتزام | F5: الشاشاتُ محميةٌ بحارسها وأرضيةِ الحوكمةِ بلا وحدةٍ مسجَّلة | G5: تُحرَم من صفوف can_view/can_edit ومن شاشة الصلاحيات | H5: لا | I5: لا يحتاج قرارًا — تسجيلٌ إجرائي | J5: قبل الإطلاق | K5: modules: 203/203 | L5: صفرُ وجهةٍ بلا وحدة
A6: DEF-005 | B6: فاحصُ الحوكمةِ يغطي 194 شاشةً من 203 | C6: متوسطة | D6: الحوكمةُ والالتزام | E6: الحوكمةُ والالتزام | F6: تسعُ شاشاتٍ خارجَ نطاق الفاحصِ بلا سببٍ معلَن | G6: مخالفةُ أعمدةٍ حاكمةٍ قد تمرُّ غيرَ مكتشفة | H6: لا | I6: أالتسعُ مستثناةٌ بقصدٍ أم سقطت؟ | J6: قبل الإطلاق | K6: cmp03_gov_check: 203/203 أو استثناءٌ معلَن | L6: الفاحصُ يعلن نطاقَه صريحًا
A7: DEF-006 | B7: عدّادا تبنّي E-03 على 286 والشاشاتُ القانونيةُ 203 | C7: متوسطة | D7: نظامُ الشاشات | E7: مكتبُ الهندسة | F7: مقامٌ مختلفٌ بلا تعريفٍ معلَن | G7: النسبُ غيرُ قابلةٍ للمقارنةِ بأرقام NAV-09 | H7: لا | I7: ما تعريفُ الـ286؟ أهي 203 + التأجيرُ + غيرُها؟ | J7: قبل التقرير القادم | K7: تعريفٌ معلَنٌ للمقامِ في كل عدّاد | L7: كلُّ نسبةٍ تذكر مقامَها ومصدرَه
A8: DEF-007 | B8: «الحالاتُ الخمسُ» بُنيت مركزيًّا — والنموذجُ المعتمدُ خمسةُ محاور | C8: عالية | D8: النظامُ التصميميُّ والشاشات | E8: مكتبُ الهندسة | F8: قائمةٌ واحدةٌ تخلط محاورَ مختلفةً بدل تركيبها | G8: الشاشةُ ببياناتٍ وقراءةٍ فقط ودون اتصالٍ لا تُمثَّل بحالةٍ واحدة | H8: لا | I8: أتُعاد النمذجةُ إلى المحاور الخمسةِ بـCM-00؟ | J8: قبل تعميقِ التبنّي | K8: CM-00 مبنيٌّ ويركّب المحاورَ الخمسة | L8: اختبارُ تركيبةِ «بياناتٌ + قراءةٌ فقط + دون اتصال»
A9: DEF-008 | B9: ورقةُ الزائدِ 1261 صفًّا والمصنَّفُ 870 | C9: عالية | D9: قاموسُ البياناتِ والأعمدة | E9: مكتبُ الهندسة | F9: نسخةُ الفريقِ أحدثُ من نسخةِ التصنيف | G9: 391 صفًّا بلا حكم | H9: لا | I9: لا يحتاج قرارًا — يحتاج ورقةَ مصالحة | J9: عاجل | K9: DEC-SCR-01 يُعاد تشغيلُه على 1261 | L9: صفرُ صفٍّ بلا حكمٍ من التسعة
A10: DEF-009 | B10: 65 جدولًا قديمًا بلا عمود كيان | C10: عالية | D10: العزلُ وتعددُ الشركات | E10: مكتبُ الهندسة | F10: جداولُ سابقةٌ لمبدأ العزل | G10: يخالف PR-02 — واستعلامٌ قد يتجاوز الكيان | H10: نعم | I10: أُقِرَّ: فاحصٌ يبلّغ لا هجرة — أيُرفع إلى هجرةٍ قبل الإطلاق؟ | J10: قبل GA | K10: كلُّ جدولٍ يحمل عمودَ الكيانِ أو استثناءً معلَنًا | L10: اختبارُ تسربٍ يفشل في كل المسارات
A11: DEF-010 | B11: 5,986 تصادمًا تاريخيًّا يمنع قيدَ UNIQUE | C11: عالية | D11: دورةُ الوحدةِ والتايم شيت | E11: الرئيسُ التنفيذي | F11: بياناتٌ تاريخيةٌ بمعدةٍ وتاريخٍ ووردية مكررة | G11: لا يمكن فرضُ التفردِ بلا معالجةِ القائم | H11: نعم | I11: أتُدمج التصادماتُ أم تُوسَم استثناءً تاريخيًّا؟ | J11: قبل GA | K11: قيدُ UNIQUE مفعَّلٌ وصفرُ تصادمٍ جديد | L11: محاولةُ إدخالٍ مكررٍ تُرفض
A12: DEF-011 | B12: مخالفتا أعمدةِ حوكمةٍ في المشتريات | C12: متوسطة | D12: الحوكمةُ والالتزام | E12: المشتريات | F12: تعديلاتُ اليومِ أسقطت أعمدةً حاكمة | G12: wh_receipt تنقصها ستةٌ و po_match عمودان | H12: لا | I12: لا يحتاج قرارًا — استدراكٌ قبل الالتزام | J12: فوري | K12: cmp03_gov_check: 194/194 | L12: صفرُ شاشةٍ بعمودٍ حاكمٍ ناقص
A13: DEF-013 | B13: ثلاثُ إداراتٍ مركزيةٍ ناقصةٌ من الهيكل: المخاطرُ والمشترياتُ المركزيةُ وشؤونُ العاملين بالمشروعات | C13: عالية | D13: الهيكلُ التنظيميُّ والحزمة | E13: الرئيسُ التنفيذي | F13: بُني الهيكلُ على سبعَ عشرةَ إدارةً ولم تُحسم الثلاث | G13: لا وثيقةَ لها ولا شاشاتَ ولا صلاحياتٍ ولا فصلَ في FRD | H13: نعم | I13: أتُعتمد الثلاثُ إداراتٍ مستقلةً؟ وما اختصاصُ كلٍّ وحدُّها مع القائم؟ | J13: عاجل | K13: الورقةُ 05 تحمل الثلاثَ بحالةِ «نافذ» وفصلٍ في FRD | L13: صفرُ إدارةٍ بحالة «◆ ناقص» في الورقة 05
A14: DEF-014 | B14: علاقةُ مديرِ الموقعِ كانت خاطئةً في الهيكلِ المنشور | C14: حرجة | D14: الهيكلُ والصلاحياتُ والموافقات | E14: مكتبُ الهندسة | F14: عُدَّت إدارةُ الموقعِ تابعةً للإداراتِ التشغيليةِ الخمس | G14: مديرُ الموقعِ تحت خمسةِ رؤساءَ · وparent_org_unit ومساراتُ الموافقةِ والصلاحياتُ والسايدبار مبنيةٌ على علاقةٍ خاطئة | H14: نعم | I14: لا يحتاج قرارًا — صُحِّح: الفرعان متوازيان تحت مدير التشغيل | J14: منفَّذٌ في هذه الجولة | K14: الورقةُ 12 تُظهر الفرعين متوازيين | L14: parent_org_unit لمديرِ الموقعِ = مديرُ التشغيلِ وحدَه | M14: 2026-08-06 | N14: مكتبُ الهندسة
A15: DEF-015 | B15: أرقامٌ أُعلنت بلا حساب — توزيعُ الأحكامِ على الوجهات | C15: متوسطة | D15: التقاريرُ والإعلان | E15: مكتبُ الهندسة | F15: أُعلنت تقديراتٌ (≈2,850 و≈1,900 و≈750) مجموعُها 5,548 والواقعُ 3,815 | G15: تناقضٌ ظاهرٌ يُفقد الثقةَ في بقيةِ الأرقام | H15: لا | I15: لا يحتاج قرارًا — قاعدةٌ منهجية: لا يُعلَن رقمٌ لم يُحسب من الملف | J15: منفَّذٌ في هذه الجولة | K15: لوحةُ الاتساقِ تحسب كلَّ رقمٍ بصيغةٍ من الورقة نفسِها | L15: صفرُ رقمٍ تقديريٍّ في أي تقرير | M15: 2026-08-06 | N15: مكتبُ الهندسة
A16: DEF-016 | B16: ثلاثةُ أعمدةٍ في SCR-DES-01 تحمل المسمّى القياديَّ القديم «الإدارة العامة» | C16: منخفضة | D16: تصميمُ الأعمدةِ والشاشات | E16: مكتبُ الهندسة | F16: أُنشئت قبل اعتماد نموذجِ الرئيسِ والنواب | G16: تظهر في M-10 و M-13 — وتُربك القارئَ الخارجيَّ ولا تُفسد وظيفة | H16: لا | I16: لا يحتاج قرارًا — تصحيحٌ في SCR-DES-01 عبر مسار التغييرِ الرسميّ | J16: قبل العرض الخارجي | K16: ◆ لا تُصحَّح من مولّد الوثائق — فالملفُّ حيٌّ ومصدرُ تحققٍ حاكم | L16: صفرُ عمودٍ يحمل المسمّى القديمَ في SCR-DES-01 v2
A17: DEF-012 | B17: NAV-09 يحتاج نسخةً خامسةً تضمُّ التأجير | C17: عالية | D17: نظامُ الشاشات | E17: مكتبُ الهندسة | F17: شاشاتٌ حيةٌ خارجَ الوثيقة | G17: «التوليدُ من الوثيقة» يفقد صدقَه | H17: نعم | I17: مرتبطٌ بـDEF-002 — بعد قرارِ التوثيق | J17: بعد DEF-002 | K17: NAV-09 v5 ببصمةٍ جديدةٍ في الورقة 01 | L17: فاحصُ nav09_verify صفرُ مخالفة

Sheet 10 — القرارات وحالة الحسم
A1: الرمز | B1: الموضوع | C1: حالةُ الحسم | D1: الحكمُ النافذُ الآن | E1: السببُ المهني | F1: ما يبقى للمالك
A2: ◆ القراراتُ الحرجةُ الأربعة
A3: CR-01 | B3: نمذجةُ حالاتِ الشاشةِ — bootFiveStates | C3: ◆ محسومٌ تقنيًّا الآن — ولا يحتاج قرارَ مالك | D3: الحكم: تُعاد النمذجةُ إلى خمسةِ محاورَ مستقلةٍ يركّبها الغلافُ الحاكمُ CM-00 — ولا تُبنى قائمةً واحدة · لماذا: «تحميل · فارغة · خطأ» محورٌ واحد · و«دون اتصال» محورٌ آخر · و«نجاح» ليست حالةَ شاشةٍ بل تغذيةً راجعةً لحظية · والغائبُ: لا نتائجَ للبحثِ وبلا صلاحيةٍ وقراءةٌ فقط والبياناتُ القديمة · الحالةُ الواقعية: الشاشةُ الميدانيةُ تكون «ببياناتٍ + قراءةٌ فقط + دون اتصال + بياناتٌ من قبل ثلاثِ ساعات» في آنٍ واحد — ولا تُمثَّل بحالةٍ واحدة · ◆ الصياغةُ الدقيقة: لا يُقال «العيبُ مزروعٌ في 288 شاشة» — فـv13 تثبت مركزيةَ النموذجِ ولا تثبت تبنّيَه في كلٍّ. والصحيح: النموذجُ المركزيُّ يحتاج تصحيحًا · وكلُّ شاشةٍ تتبناه تحمل العيبَ · ويُقاس التبنّي الفعليُّ أولًا · ما يُنفَّذ الآن: يوقف تعميقُ bootFiveStates · ويُبنى CM-00 بثمانِ خطواتٍ · ويُقاس التبنّي الفعليُّ · ثم تُهاجَر الشاشاتُ بدفعاتٍ من عشرين · الأثرُ إن تأخر: كلُّ شاشةٍ جديدةٍ تتبنى النموذجَ الخطأ — والتصحيحُ يتضاعف بعددها | E3: — | F3: —
A4: CR-02 | B4: تعريفُ المقاييسِ — 249 و288 و203 و1,075 | C4: ◆ محسومٌ تقنيًّا الآن — قاموسُ مقاييسٍ لا توحيدٌ قسري | D4: الحكم: تُعرَّف المقاييسُ الأربعةُ صريحةً في قاموسٍ داخلَ المعمارية — ولا تُوحَّد قسرًا · Legal Screen شاشةٌ قانونيةٌ فريدةٌ في NAV-09 — المصدر: NAV-09 · العدد: 203 · Registered Screen سجلُّ شاشةٍ في جدول modules — المصدر: القاعدةُ الحية · العدد: 249 · UX Adoption Unit وحدةٌ يُطبَّق عليها معيارُ E-03 — المصدر: عدّادُ التبنّي · العدد: 288 · Navigation Item ظهورٌ فعليٌّ لدورٍ ونطاق — المصدر: nav_items · العدد: 1,075 · الحكمُ الملزم: ◆ كلُّ نسبةٍ تُعلَن تذكر مقامَها ومصدرَه — ولا نسبةَ بلا مقامٍ معرَّف | E4: — | F4: —
A5: CR-03 | B5: نواةُ التأجيرِ وقاعدةُ NAV-09 | C5: ◆ القاعدةُ محسومةٌ الآن — والقرارُ التجاريُّ للمالك | D5: ◆ القاعدةُ الحاكمة: Build ahead — never release ahead · يُبنى قبل التوثيقِ ولا يُصدَر قبله · ما يجوز: بناءُ شاشةٍ جديدةٍ في فرع تطويرٍ أو بيئةِ اختبارٍ قبل تحديث NAV-09 · ما لا يجوز: دخولُها إصدارًا · ظهورُها في الإنتاج · صيرورتُها جزءًا من السايدبار النافذ · الشروطُ الخمسةُ للإفراج: تُضاف إلى NAV-09 · تُحدَّد مرحلتُها ومالكُها ونطاقُها · تُبصَم النسخةُ · يُعاد توليدُ التنقلِ منها · يجتاز فحصَ المطابقة · أثرُها على ق-16: يبقى «الأحدثُ يغلب» نافذًا في المضمون — ويُقيَّد بألّا يتحول الرابطُ الجديدُ مصدرًا ثانيًا للتنقل · ◆ ما يبقى للمالك: أتُوثَّق نواةُ التأجيرِ نموذجًا رابعًا في E-09 أم تُعلَن خارجَ النطاقِ بقرار؟ — والقاعدةُ أعلاه تحكمها في الحالين | E5: — | F5: —
A6: CR-04 | B6: طوبولوجيا القاعدتين 3306 و3307 | C6: ◆ خطرٌ حاكمٌ — يحتاج بيانًا من الفريقِ وقرارَ المالك | D6: الخطر: التشغيلُ المزدوجُ إن كانت القاعدتان قابلتين للكتابةِ معًا يُنتج انقسامَ العقل Split Brain — وهو أخطرُ من فجوةِ الواجهةِ كلِّها · الأسئلةُ الثمانيةُ التي يجب أن يجيبها قسمٌ جديد: أيُّ قاعدةٍ مصدرُ الحقيقة؟ · أ3306 للقراءةِ فقط أم قابلةٌ للكتابة؟ · أتوجد مزامنةٌ وما اتجاهُها؟ · ما سلوكُ التعارض؟ · ما خطةُ القلب؟ · متى تُطفأ القديمة؟ · كيف نرجع إن فشل الانتقال؟ · من يملك القرار؟ · الحكمُ المؤقتُ الآمن: حتى يصدر البيانُ — تُعامَل 3306 قاعدةً موروثةً للقراءةِ فقط · ولا كتابةَ فيها · ويُوثَّق أيُّ استثناءٍ صريحًا · ◆ إن كانت الاثنتان قابلتين للكتابةِ فعلًا: فهذا عيبٌ حرجٌ يمنع الإطلاقَ ويُرفع فورًا — لا دَينٌ يُؤجَّل | E6: — | F6: —
A7: ◆ القراراتُ التسعة
A8: DEC-A | B8: نمطُ تسميةِ الأفعال | C8: ◆ محسومٌ تقنيًّا | D8: domain.resource.action لكل الرموزِ الـ242 — بمميِّزٍ عند التصادمِ وترحيلٍ بمرادفاتٍ دورةَ إصدارٍ كاملة | E8: النمطُ الجزئيُّ يُنتج قاموسًا مختلطًا يصعب صيانتُه · والمرادفُ يمنع الكسرَ أثناء الترحيل | F8: أربعةُ صفوفٍ برمزين يحملان معنيين تُصلَح أولًا قبل حملةِ الربط
A9: DEC-B | B9: نواةُ التأجير | C9: ◆ القاعدةُ محسومةٌ · والقرارُ التجاريُّ للمالك | D9: Build ahead — never release ahead · وأيًّا كان قرارُ التوثيقِ فالقاعدةُ تحكم | E9: تفصل بين سرعةِ التطويرِ ووحدةِ مصدرِ الحقيقةِ بلا كسرِ أحدهما | F9: يبقى سؤالُ المالك: نموذجٌ رابعٌ في E-09 أم خارجُ النطاق؟
A10: DEC-C | B10: التصادماتُ التاريخيةُ 5,986 | C10: ✔ حُسم — قرارُ مالكٍ نافذ | D10: الموروثُ معلَنٌ خارجَ الدرعِ · والدرعُ يعمل على السكةِ الجديدةِ بقادحين | E10: مطابقٌ للتوصيةِ المهنيةِ — فالدمجُ الآليُّ يفقد بياناتٍ واليدويُّ يستحيل في 5,986 | F10: ◆ مغلقٌ — ق-18
A11: DEC-D | B11: الـ65 جدولًا بلا عمود كيان | C11: ◆ المنهجُ محسومٌ — والتصنيفُ يحتاج القاعدةَ الحية | D11: لا يُفرَض company_id على الكلِّ — بل يُصنَّف كلُّ جدولٍ في أحد أربعةِ أصناف: Global · معزولٌ عبر الأبِ · موروثٌ محجورٌ · مستأجَرٌ يجب ترحيلُه | E11: ◆ الحكمُ المهني: إثباتُ مسارِ العزلِ لكلٍّ · فما كان آمنًا عبر أبيه أو عامًّا فلا مشكلةَ معماريةً فيه | F11: المستأجَرُ الحقيقيُّ بلا عزلٍ مباشرٍ ولا غيرِ مباشرٍ = دَينٌ أمنيٌّ يمنع الإطلاق
A12: DEC-E | B12: نمذجةُ حالاتِ الشاشة | C12: ◆ محسومٌ تقنيًّا | D12: خمسةُ محاورَ مستقلةٍ يركّبها CM-00 — ويوقف تعميقُ bootFiveStates | E12: القائمةُ الواحدةُ تخلط محاورَ وتُسقط أربعَ قيمٍ ضرورية | F12: يُقاس التبنّي الفعليُّ قبل تحديدِ عددِ الشاشات المتأثرة
A13: DEC-F | B13: تعريفُ المقاييس | C13: ◆ محسومٌ تقنيًّا | D13: قاموسُ مقاييسٍ بأربعةِ تعريفاتٍ داخلَ المعمارية — ولا توحيدَ قسريّ | E13: الأرقامُ ليست متناقضةً بل غيرَ معرَّفةٍ — والتعريفُ ينهي المشكلةَ نهائيًّا | F13: ◆ كلُّ نسبةٍ تذكر مقامَها ومصدرَه
A14: DEC-G | B14: إدارةُ المخاطر | C14: ◆ يبقى للمالك — والحكمُ المؤقتُ نافذ | D14: التوصية: إدارةٌ مركزيةٌ مستقلةٌ بوصولٍ مباشرٍ للرئيسِ في المخاطر الجوهرية | E14: المخاطرُ التي تُدار من داخل الحوكمةِ تفقد استقلالَها عن الجهةِ التي تراقبها | F14: الحكمُ المؤقت: تبقى «المخاطرُ التجارية» شاشةً في التنفيذيةِ ولا تُخترع لها دورةٌ ولا شاشات
A15: DEC-H | B15: المشترياتُ المركزية | C15: ◆ يبقى للمالك — والحكمُ المؤقتُ نافذ | D15: التوصية: إدارةٌ مركزيةٌ للشراءِ الاستراتيجيِّ والعقودِ الإطاريةِ وما فوقَ سقفِ التشغيلية | E15: الشراءُ الاستراتيجيُّ قرارٌ ماليٌّ لا تشغيليّ · والدمجُ يجعل التشغيليةَ تقرر ما يفوق سقفها | F15: الحكمُ المؤقت: كلُّ شراءٍ يمرُّ بالتشغيليةِ · وما فوقَ سقفِها يُرفع للنائبِ المالي
A16: DEC-I | B16: شؤونُ العاملين بالمشروعات | C16: ◆ يبقى للمالك — والحكمُ المؤقتُ نافذ | D16: التوصية: وحدةٌ مركزيةٌ تحت نائب الشؤون الإداريةِ والحوكمة | E16: العقودُ المشروعيةُ والتعبئةُ والتسريحُ التزامٌ وظيفيٌّ لا تشغيليّ · وإخضاعُها للتشغيلِ يخلط الأجرَ بالإنتاج | F16: الحكمُ المؤقت: تُدار من الموارد البشريةِ بوسمٍ «مشروعيّ» ولا وحدةَ مستقلةٌ بعد

Sheet 11 — لوحة الاتساق
A1: البند | B1: العدد | C1: المصدر | D1: الحكم
A2: ملفاتٌ مبصومةٌ في خط الأساس | B2: =COUNTA('01 — بيان التجميد وسجل الوثائق'!$A$2:$A$64) | C2: الورقةُ 01 | D2: كلُّها ببصمةٍ وحجمٍ وتاريخٍ وحالة
A3: ◆ ملفاتٌ حيةٌ تبقى مستقلة | B3: =COUNTIF('01 — بيان التجميد وسجل الوثائق'!$G$2:$G$64,"ملفٌّ حيّ*") | C3: الورقةُ 01 | D3: NAV-09 و SCR-DES-01 و CMP-03 — لا تُدمج
A4: وثائقُ أحكامٍ نافذةٌ تُدمج | B4: =COUNTIF('01 — بيان التجميد وسجل الوثائق'!$G$2:$G$64,"نافذة*") | C4: الورقةُ 01 | D4: تُقرأ ثم تُؤرشَف
A5: مراجعُ بياناتٍ تُنقل أوراقُها | B5: =COUNTIF('01 — بيان التجميد وسجل الوثائق'!$G$2:$G$64,"مرجع*") | C5: الورقةُ 01 | D5: إلى أوراق هذا الملف
A6: وثائقُ تاريخية | B6: =COUNTIF('01 — بيان التجميد وسجل الوثائق'!$G$2:$G$64,"تاريخية") | C6: الورقةُ 01 | D6: أرشيفٌ مرجعيٌّ غيرُ نافذ
A7: ◆ الأحكامُ المنقولة
A8: إجماليُّ الأحكام | B8: =COUNTA('03 — سجل الأحكام النهائية'!$A$2:$A$5531) | C8: الورقةُ 03 | D8: كلٌّ بمصدرِه وقسمِه ووجهتِه واختبارِه
A9: إلى INJAZ-CORE-01 | B9: =COUNTIF('03 — سجل الأحكام النهائية'!$H$2:$H$5531,"INJAZ-CORE-01") | C9: الورقةُ 03 | D9: الدستورُ والمعماريةُ والحوكمة
A10: إلى INJAZ-FRD-01 | B10: =COUNTIF('03 — سجل الأحكام النهائية'!$H$2:$H$5531,"INJAZ-FRD-01") | C10: الورقةُ 03 | D10: المتطلباتُ الوظيفيةُ بفصلٍ لكل إدارة
A11: إلى INJAZ-UX-01 | B11: =COUNTIF('03 — سجل الأحكام النهائية'!$H$2:$H$5531,"INJAZ-UX-01") | C11: الورقةُ 03 | D11: الشاشاتُ والتجربةُ والنظامُ التصميمي
A12: إلى INJAZ-DELIVERY-01 | B12: =COUNTIF('03 — سجل الأحكام النهائية'!$H$2:$H$5531,"INJAZ-DELIVERY-01") | C12: الورقةُ 03 | D12: التنفيذُ والتتبعُ والاختبار
A13: ◆ التدقيقُ العالميُّ للأفعال
A14: أفعالٌ مدقَّقة | B14: =COUNTA('07 — سجل الأفعال والتدقيق'!$A$2:$A$363) | C14: الورقةُ 07 | D14: بثمانيةِ فحوصٍ لكلٍّ
A15: حاجبةٌ للتجميع | B15: =COUNTIF('07 — سجل الأفعال والتدقيق'!$U$2:$U$363,"نعم") | C15: الورقةُ 07 | D15: ◆ تُصلَح قبل نقلِ القاموس
A16: رمزٌ لأكثرَ من معنى | B16: =COUNTIF('07 — سجل الأفعال والتدقيق'!$M$2:$M$363,"✘*") | C16: الورقةُ 07 | D16: الفحصُ الأول
A17: معنًى بعدةِ رموزٍ بلا alias | B17: =COUNTIF('07 — سجل الأفعال والتدقيق'!$N$2:$N$363,"✘*") | C17: الورقةُ 07 | D17: الفحصُ الثاني — صفرٌ بعد النمط
A18: ماليٌّ أو تعاقديٌّ بلا عكس | B18: =COUNTIF('07 — سجل الأفعال والتدقيق'!$R$2:$R$363,"✘*") | C18: الورقةُ 07 | D18: الفحصُ السادس
A19: معلَّقُ الربطِ بالمعالج | B19: =COUNTIF('07 — سجل الأفعال والتدقيق'!$Q$2:$Q$363,"◐*") | C19: الورقةُ 07 | D19: يحتاج الكودَ الحيّ
A20: ◆ الهيكلُ التنظيمي
A21: إداراتٌ ووحداتٌ في الهيكل | B21: =COUNTA('05 — الإدارات والدورات'!$C$2:$C$40)-1 | C21: الورقةُ 05 | D21: بأنواعِ عقدٍ سبعةٍ لا بجمعٍ أعمى
A22: منها مبنيٌّ في الحزمة | B22: 18 | C22: orgmodel2 | D22: له وثيقةٌ وشاشاتٌ وأحكام
A23: ◆ ناقصٌ يحتاج قرارَ المالك | B23: 2 | C23: orgmodel2 | D23: المخاطرُ والمشترياتُ المركزيةُ وشؤونُ العاملين
A24: أدوارٌ بتبعيةٍ مزدوجة | B24: 9 | C24: الورقةُ 13 | D24: التقاطعُ في الطبقة الخامسةِ — أدوارٌ لا إدارات
A25: ◆ تصادمُ رموز الأفعال
A26: رموزٌ متصادمةٌ مسجَّلة | B26: =COUNTA('14 — تصادم رموز الأفعال'!$A$2:$A$40)-1 | C26: الورقةُ 14 | D26: بنوعِ تصادمٍ وحالةٍ لكلٍّ
A27: MEANING_COLLISION حاجب | B27: =COUNTIF('14 — تصادم رموز الأفعال'!$D$2:$D$40,"MEANING*") | C27: الورقةُ 14 | D27: ◆ يُصلَح قبل نقل القاموس
A28: ALIAS محلول | B28: =COUNTIF('14 — تصادم رموز الأفعال'!$D$2:$D$40,"ALIAS*") | C28: الورقةُ 14 | D28: معنًى واحدٌ في شاشاتٍ عدة
A29: ◆ تصنيفُ الكتابةِ وطبيعةُ الشاشة
A30: Domain Write | B30: =COUNTIF('21 — تصنيف الكتابة للأفعال'!$F$2:$F$300,"Domain Write") | C30: الورقةُ ٢١ | D30: يغيّر بيانَ العملِ وينشر حدثًا
A31: Governance Write | B31: =COUNTIF('21 — تصنيف الكتابة للأفعال'!$F$2:$F$300,"Governance Write") | C31: الورقةُ ٢١ | D31: ◆ تصديرٌ يكتب سجلَّ حوكمةٍ لا بيانَ مجال
A32: Read Only | B32: =COUNTIF('21 — تصنيف الكتابة للأفعال'!$F$2:$F$300,"Read Only") | C32: الورقةُ ٢١ | D32: لا يكتب ولا ينشر
A33: External Side Effect | B33: =COUNTIF('21 — تصنيف الكتابة للأفعال'!$F$2:$F$300,"External Side Effect") | C33: الورقةُ ٢١ | D33: إرسالٌ خارجَ النظام
A34: شاشاتٌ مستندٌ يُعتمد | B34: =COUNTIF('22 — طبيعة الشاشة'!$E$2:$E$300,"مستندٌ يُعتمد") | C34: الورقةُ ٢٢ | D34: تلزمها الأعمدةُ السبعةُ كاملةً
A35: شاشاتٌ سجلٌّ أو إعداد | B35: =COUNTIF('22 — طبيعة الشاشة'!$E$2:$E$300,"سجلٌّ أو إعداد") | C35: الورقةُ ٢٢ | D35: تلزمها أربعةٌ
A36: شاشاتٌ قارئة | B36: =COUNTIF('22 — طبيعة الشاشة'!$E$2:$E$300,"قارئة") | C36: الورقةُ ٢٢ | D36: يلزمها الكيانُ وحدَه
A37: ◆ تحتاج مراجعةً بشرية | B37: =COUNTIF('22 — طبيعة الشاشة'!$J$2:$J$300,"◆*") | C37: الورقةُ ٢٢ | D37: لم يحسمها الفعلُ ولا الاسم
A38: ◆ العيوبُ المفتوحة
A39: عيوبٌ مسجَّلة | B39: =COUNTA('09 — سجل العيوب المفتوحة'!$A$2:$A$17) | C39: الورقةُ 09 | D39: سجلٌّ حيٌّ يبدأ بها ولا يقتصر عليها
A40: حرجة | B40: =COUNTIF('09 — سجل العيوب المفتوحة'!$C$2:$C$17,"حرجة") | C40: الورقةُ 09 | D40: تمنع الإطلاق
A41: عالية | B41: =COUNTIF('09 — سجل العيوب المفتوحة'!$C$2:$C$17,"عالية") | C41: الورقةُ 09 | D41: تحتاج معالجةً قبل GA
A42: تمنع الإطلاق | B42: =COUNTIF('09 — سجل العيوب المفتوحة'!$H$2:$H$17,"نعم") | C42: الورقةُ 09 | D42: حاجبةٌ صريحة

Sheet 12 — الهيكل التنظيمي
A1: الرمز | B1: الطبقة | C1: من فيها | D1: السلطةُ والاختصاص | E1: التابعُ له | F1: نوعُ العقد
A2: L1 | B2: الطبقةُ الأولى — السلطةُ التنفيذيةُ العليا | C2: الرئيسُ التنفيذي | D2: السلطةُ الأصليةُ بالنظام الأساسي — التوقيعُ والاعتمادُ الأعلى وفتحُ المشاريع وحسمُ المخاطر | E2: لا يعلوه أحد | F2: EXECUTIVE_ROLE
A3: L2 | B3: الطبقةُ الثانية — نوابُ الرئيس التنفيذي | C3: نائبُ العمليات · نائبُ الشؤون المالية والاستثمار · نائبُ الشؤون الإدارية والحوكمة | D3: يمارسون صلاحياتِهم بتفويضٍ ونطاقٍ وسقفٍ معتمد — ولا يملكون السلطةَ الأصلية | E3: الرئيسُ التنفيذي | F3: EXECUTIVE_ROLE
A4: L3 | B4: الطبقةُ الثالثة — الإداراتُ المركزيةُ المتوازية | C4: إحدى عشرةَ إدارةً مركزيةً ومركزٌ رقابيٌّ واحد — لا تتبع إحداها الأخرى | D4: كلٌّ تتبع نائبَها المختصَّ — ومديرُ التشغيلِ واحدٌ منها لا يعلوها | E4: النائبُ المختص | F4: CENTRAL_DEPARTMENT
A5: L4 | B5: الطبقةُ الرابعة — تحت مدير التشغيل: فرعان متوازيان | C5: ◆ الفرعُ الأول: خمسُ إداراتٍ تشغيليةٍ مركزية · ◆ الفرعُ الثاني: مديرو المواقع | D5: الفرعان متوازيان — ولا يتبع مديرُ الموقعِ الإداراتِ التشغيليةَ ولا العكس | E5: مديرُ التشغيلِ لكلا الفرعين | F5: OPERATIONAL_DEPARTMENT + SITE_UNIT
A6: L5 | B6: الطبقةُ الخامسة — الأدوارُ الميدانيةُ داخلَ الموقع | C6: ثمانيةُ أدوارٍ ميدانيةٍ بتبعيةٍ مزدوجة | D6: ◆ هنا يقع التقاطعُ: إداريًّا لمدير الموقعِ وفنيًّا لإدارته المركزية | E6: مديرُ الموقعِ إداريًّا · والإدارةُ المركزيةُ فنيًّا | F6: FIELD_ROLE
A7: L6 | B7: الطبقةُ السادسة — المنفِّذون | C7: المشغّلون والفنيون والعمالُ والسائقون | D7: ينفّذون بتكليفٍ يوميٍّ من دورِ الطبقةِ الخامسةِ المختص | E7: الدورُ الميدانيُّ المختص | F7: FIELD_ROLE
A8: ◆ الحكمُ الحاكم
A9: — | B9: ◆ الفرعان المتوازيان | C9: تحت مديرِ التشغيلِ فرعان لا يتبع أحدُهما الآخر | D9: الفرعُ الأولُ خمسُ إداراتٍ تشغيليةٍ مركزية · والفرعُ الثاني مديرو المواقع | E9: مديرُ التشغيلِ لكليهما | F9: OPERATIONAL + SITE_UNIT
A10: — | B10: التوازي في الطبقة الثالثة | C10: إحدى عشرةَ إدارةً مركزيةً ومركزٌ رقابي | D10: لا تتبع إحداها الأخرى — ومديرُ التشغيلِ واحدٌ منها لا يعلوها | E10: النائبُ المختص | F10: CENTRAL_DEPARTMENT
A11: — | B11: ◆ موضعُ التقاطع | C11: الطبقةُ الخامسةُ داخلَ الموقعِ — أدوارٌ لا إدارات | D11: ثمانيةُ أدوارٍ ميدانيةٍ بتبعيةٍ مزدوجة | E11: مديرُ الموقعِ إداريًّا · والمركزيةُ فنيًّا | F11: FIELD_ROLE

Sheet 13 — التبعية المزدوجة
A1: # | B1: الدورُ الميداني | C1: التبعيةُ الإدارية | D1: التبعيةُ الفنية | E1: ما يقرره الإداريُّ | F1: ما يقرره الفنيُّ | G1: الحكمُ عند التعارض
A2: 1 | B2: مسؤولُ صيانةِ الموقع | C2: مديرُ الموقع | D2: مديرُ الصيانة | E2: الحضورُ والوردياتُ وأذونُ الحركةِ وجدولُ العملِ اليومي | F2: التشخيصُ والحكمُ الفنيُّ وشهادةُ الجاهزيةِ وشجرةُ الأعطال | G2: ◆ لا يُعارَض الحكمُ الفنيُّ بقرارٍ إداريٍّ ولو من مدير الموقع
A3: 2 | B3: مسؤولُ المشغّلينَ في الموقع | C3: مديرُ الموقع | D3: مديرُ القوى التشغيلية | E3: التكليفُ اليوميُّ والورديةُ والحضورُ والانصراف | F3: التأهيلُ والرخصةُ والأهليةُ للمعدةِ وتقييمُ الأداء | G3: لا يُكلَّف مشغّلٌ بمعدةٍ لا يملك أهليتَها
A4: 3 | B4: أمينُ مخزنِ الموقع | C4: مديرُ الموقع | D4: مديرُ المخازن | E4: الصرفُ اليوميُّ والاستلامُ الميدانيُّ وحفظُ العهد | F4: الرصيدُ والتقييمُ والجردُ وسياسةُ إعادة الطلبِ وحدودُه | G4: الرصيدُ لا يُعدَّل ميدانيًّا
A5: 4 | B5: منسّقُ النقلِ في الموقع | C5: مديرُ الموقع | D5: مديرُ النقل والترحيل | E5: طلبُ الترحيلِ وتوقيتُه ميدانيًّا وتأكيدُ الوصول | F5: تخصيصُ الوسيلةِ وأمرُ الترحيلِ وأولوياتُ الأسطول | G5: لا يُصدر أمرَ ترحيلٍ من الموقعِ بلا تخصيصِ الإدارة
A6: 5 | B6: مسؤولُ الشؤون الإداريةِ بالموقع | C6: مديرُ الموقع | D6: الموارد البشريةُ وشؤونُ العاملين بالمشروعات | E6: الإسكانُ والإعاشةُ والانتقالاتُ والحضورُ الإداري | F6: العقدُ والأجرُ والإجازاتُ والتسريحُ والملفُّ الوظيفي | G6: لا يُنهى عقدٌ ولا يُعدَّل أجرٌ ميدانيًّا
A7: 6 | B7: مسؤولُ مشترياتِ الموقع | C7: مديرُ الموقع | D7: إدارةُ المشتريات التشغيلية | E7: طلبُ الاحتياجِ العاجلِ ميدانيًّا واستلامُ التوريد | F7: الترسيةُ وأمرُ الشراءِ والموردُ المعتمدُ والسقوف | G7: لا شراءَ ميدانيٌّ خارجَ سقفٍ معتمدٍ ومورّدٍ مؤهَّل
A8: 7 | B8: ضابطُ بوابةِ الموقع | C8: مديرُ الموقع | D8: الحوكمةُ والالتزام | E8: تسجيلُ الدخولِ والخروجِ ومطابقةُ الأذون | F8: قواعدُ الأذونِ والسريةُ وسجلُّ الاطّلاعِ والاستثناءات | G8: لا يُسمح بدخولٍ بلا إذنٍ ولو بأمرٍ ميداني
A9: 8 | B9: منسّقُ المخاطرِ بالموقع | C9: مديرُ الموقع | D9: إدارةُ المخاطرِ المؤسسية | E9: الإبلاغُ عن الإشاراتِ والوقائعِ وتنفيذُ إجراءاتِ المعالجةِ الميدانية | F9: منهجُ التقييمِ وتصنيفُ الخطرِ ودرجتُه وحدودُ التصعيد | G9: ◆ لا يُصنَّف خطرٌ ولا تُحدَّد درجتُه ميدانيًّا
A10: 9 | B10: مسؤولُ الوقودِ بالموقع | C10: مديرُ الموقع | D10: المخازنُ والتشغيلُ بحسب النموذج | E10: التزويدُ اليوميُّ وقراءةُ العدّادِ وتسجيلُ الاستهلاك | F10: الرصيدُ والمعياريةُ وحدُّ الاستهلاكِ وكشفُ الفروق | G10: الفرقُ فوق الحدِّ يُرفع ولا يُسوَّى ميدانيًّا
A11: ◆ | B11: الحكمُ العام | C11: مديرُ الموقعِ أعلى سلطةٍ ميدانيةٍ إداريًّا | D11: والإدارةُ المركزيةُ أعلى سلطةٍ فنيًّا | E11: الحضورُ والوردياتُ والحركةُ والجدولُ اليومي | F11: التأهيلُ والحكمُ الفنيُّ والرصيدُ والمطابقة | G11: لا يُعارَض الحكمُ الفنيُّ بقرارٍ إداريٍّ ولو من الأعلى

Sheet 14 — تصادم رموز الأفعال
A1: original_code | B1: occurrences | C1: meanings | D1: collision_type | E1: recommended_code | F1: evidence | G1: status
A2: rpt.export | B2: 3 | C2: تصديرُ تقرير | D2: ALIAS — معنًى واحدٌ في شاشاتٍ عدة | E2: finance.report.export | F2: 3 صفًّا بمعنًى واحد: تصديرُ تقرير | G2: resolved — alias معتمد
A3: model.define | B3: 2 | C3: تعريفُ موديلٍ ومواصفاتِه | تعريفُ نموذج عمل | D3: MEANING_COLLISION — معنيان | E3: fleet.model.define · sales.model.define | F3: 2 صفًّا بمعنيين: تعريفُ موديلٍ ومواصفاتِه | تعريفُ نموذج عمل | G3: ◆ حاجبٌ — يُصلَح قبل نقل القاموس
A4: req.raise | B4: 2 | C4: تقديمُ طلبٍ شخصي | رفعُ طلب ترحيل | D4: MEANING_COLLISION — معنيان | E4: transport.request.submit · workspace.request.submit | F4: 2 صفًّا بمعنيين: تقديمُ طلبٍ شخصي | رفعُ طلب ترحيل | G4: ◆ حاجبٌ — يُصلَح قبل نقل القاموس
A5: ◆ الحكم | B5: — | C5: — | D5: لا يُنقل قاموسُ الأفعالِ قبل إغلاق كلِّ MEANING_COLLISION | E5: — | F5: الورقةُ 07 بالفحوصِ الثمانية | G5: الورقةُ 08 خطةُ الترحيل

Sheet 15 — بوابتا الرموز
A1: البوابة | B1: النطاق | C1: ما فُحص | D1: النتيجة | E1: الحالةُ الرسمية | F1: ما يلزم لإغلاقها
A2: Static Gate — الساكنة | B2: الوثيقةُ والقاموسُ بلا كودٍ حيّ | C2: الفحوصُ ① إلى ④ و⑥ و⑦ | D2: ◆ 72 حاجبًا من 362 | E2: Passed with 4 blockers | F2: إصلاحُ MEANING_COLLISION — رمزان بأربعةِ صفوف
A3: Live-Code Gate — الحية | B3: الكودُ العاملُ والمعالجاتُ الحية | C3: الفحصان ⑤ و⑧ | D3: ◐ 362 معلَّقًا | E3: Pending — لم تبدأ | F3: حملةُ الربطِ · ومصفوفةُ استعمالٍ من الكود · وDry Run
A4: ◆ الحكمُ المعلَن | B4: — | C4: — | D4: — | E4: لا يُقال «البوابةُ اجتازت» مطلقًا | F4: بل تُذكر البوابتان منفصلتين — والساكنةُ لا تُغني عن الحية

Sheet 16 — سجل تصحيح الهيكل
A1: # | B1: ما تغيَّر | C1: ما كان | D1: ما صار | E1: الأساسُ والأثر
A2: 1 | B2: علاقةُ مديرِ الموقع | C2: «التابعُ له: الإداراتُ التشغيليةُ ومديرُ التشغيل» | D2: «التابعُ له: مديرُ التشغيلِ» — والفرعان متوازيان | E2: ◆ خطأٌ حاكم: كان يجعل مديرَ الموقعِ تحت خمسةِ رؤساءَ · والأثرُ على parent_org_unit والموافقاتِ والصلاحياتِ والسايدبار
A3: 2 | B3: موضعُ التقاطع | C3: كان في علاقةِ الإداراتِ بالموقع | D3: صار في الطبقة الخامسةِ داخلَ الموقعِ — أدوارٌ لا إدارات | E3: التبعيةُ المزدوجةُ للأدوارِ لا للوحدات
A4: 3 | B4: أنواعُ العقد التنظيمي | C4: غيرُ موجودة — كلٌّ «إدارة» | D4: سبعةُ أنواعٍ: دورٌ تنفيذيٌّ · مركزيةٌ · تشغيليةٌ · وحدةُ موقعٍ · مركزٌ رقابيٌّ · مساحةُ عملٍ · دورٌ ميداني | E4: فلا تُحسب مساحةُ عملي إدارةً ولا تُمنح مديرًا ولا ميزانيةً ولا خطَّ تبعية
A5: 4 | B5: مساحةُ عملي | C5: رتبةً 17 في عدّ الإدارات | D5: WORKSPACE — لا تُحسب إدارةً إطلاقًا | E5: ولا مديرَ لها ولا ميزانيةَ ولا تبعية
A6: 5 | B6: مركزُ البلاغات | C6: إدارةً مركزيةً كالمالية | D6: SHARED_CONTROL_CENTER — مركزٌ رقابيٌّ وخدميٌّ عابر | E6: يخدم كلَّ الإداراتِ ولا يخصُّ واحدةً · ولا ميزانيةَ تشغيليةً مستقلة
A7: 6 | B7: إدارةُ المخاطر | C7: غائبةٌ من الهيكل | D7: أُضيفت مركزيةً تحت نائب الشؤون الإداريةِ والحوكمةِ ◆ بوصولٍ مباشرٍ للرئيس في الجوهرية | E7: ◆ ناقصٌ — يحتاج قرارَ المالكِ في استقلالها ومسارِ تصعيدها
A8: 7 | B8: المشترياتُ المركزية | C8: غائبةٌ — والتشغيليةُ وحدَها موجودة | D8: أُضيفت مركزيةً: الشراءُ الاستراتيجيُّ والعقودُ الإطاريةُ وما فوقَ سقفِ التشغيلية | E8: ◆ ناقصٌ — يحتاج قرارَ المالكِ في حدِّها مع التشغيلية
A9: 8 | B9: شؤونُ العاملين بالمشروعات | C9: غائبة | D9: أُضيفت مركزيةً تحت نائب الشؤون الإداريةِ — العقودُ المشروعيةُ والتعبئةُ والتسريح | E9: ◆ ناقصٌ — يحتاج قرارَ المالك: وحدةٌ تحت التشغيلِ أم فرعٌ من الموارد؟
A10: 9 | B10: عددُ الإدارات | C10: سبعَ عشرةَ بلا تمييز | D10: إحدى عشرةَ مركزيةً + خمسٌ تشغيليةٌ + وحدةُ موقعٍ + مركزٌ رقابي — ومساحةُ عملي لا تُحسب | E10: العدُّ صار بأنواعِ العقدِ لا بالجمعِ الأعمى
A11: ◆ | B11: الأثرُ على الحزمة | C11: ترتيبُ فصولِ FRD وترتيبُ السايدبار وأوراقُ التتبع | D11: أُعيدت كلُّها على الترتيبِ المصحَّحِ من الأعلى تنازليًّا | E11: قرارُ المالك — والفرعان متوازيان

Sheet 17 — المحاورُ الحاكمةُ الإضافية
A1: # | B1: ما أُضيف | C1: نوعُه | D1: لماذا فاتني | E1: موضعُ المعالجة
A2: 1 | B2: طوبولوجيا 3306/3307 | C2: خطرُ Split Brain | D2: لم أرصده إطلاقًا — وهو أخطرُ من فجوةِ الواجهةِ كلِّها | E2: ◆ CR-04 · قسمٌ جديدٌ بثمانيةِ أسئلةٍ وحكمٍ مؤقتٍ آمن
A3: 2 | B3: تصنيفُ الـ65 جدولًا أربعةَ أصناف | C3: منهجٌ أدقُّ من توصيتي | D3: طلبتُ هجرةً بدفعاتٍ — والأصوبُ إثباتُ مسارِ العزلِ لكلٍّ | E3: DEC-D بأصنافه الأربعة
A4: 3 | B4: فصلُ السجلاتِ الثلاثة | C4: صياغةٌ مهنيةٌ أدق | D4: «لم يتبق إلا اثنان» تُضلِّل أمام المستثمرِ والجهةِ السيادية | E4: Release Blockers + Architectural Debt + Adoption Debt منفصلةً
A5: 4 | B5: Build ahead — never release ahead | C5: قاعدةٌ أفضلُ من اقتراحي | D5: اقترحتُ «تلحق خلال دورة» — وقاعدتُه أوضحُ وأقوى | E5: CR-03 · وتُضاف حكمًا في CORE-01
A6: 5 | B6: قاموسُ المقاييس | C6: حلٌّ أنظفُ من التوحيد | D6: الأرقامُ ليست متناقضةً بل غيرَ معرَّفة | E6: CR-02 · أربعةُ تعريفاتٍ بمصادرها
A7: 6 | B7: فجوةُ أدلةِ NFR | C7: لم أرصدها | D7: لا Load ولا p95 ولا RPO/RTO ولا DR ولا DLQ ولا event-bus lag | E7: لوحةُ أدلةِ NFR في DELIVERY-01
A8: 7 | B8: أضيقُ نطاقِ عرضٍ حكمًا معماريًّا | C8: صياغةٌ أقوى | D8: كانت عندي مبدأً في UX — ويرفعها حكمًا معماريًّا | E8: مبدأٌ في CORE-01 وفصلٌ في UX-01
A9: ◆ الأحكامُ الدقيقة
A10: 1 | B10: «العيبُ مزروعٌ في 288 شاشة» | C10: الصياغةُ الدقيقة | D10: v13 تثبت مركزيةَ النموذجِ ولا تثبت تبنّيَه في كلٍّ | E10: الصحيح: النموذجُ المركزيُّ يحتاج تصحيحًا · وكلُّ شاشةٍ تتبناه تحمل العيبَ · ويُقاس التبنّي أولًا
A11: 2 | B11: «32 شاشةً بلا المُنشئ أو المعتمِد أو مرجع التفويض» | C11: الصياغةُ الدقيقة | D11: قد يختلف العمودُ الناقصُ من شاشةٍ لأخرى | E11: الصحيح: 32 وحدةَ تبنٍّ ناقصةٌ في معيار الأعمدةِ الحاكمة · ويُستخرج نوعُ النقصِ لكلٍّ من SCR-DES-01 والفحصِ الحيّ
A12: 3 | B12: «WCAG 2.2 AA تُطلب في مشترياتِ السعوديةِ والإمارات» | C12: الصياغةُ الدقيقة | D12: ادعاءٌ تنظيميٌّ لا أملك مصدرَه | E12: ◆ الصحيح: WCAG 2.2 AA معيارٌ مستهدَفٌ مناسبٌ لمنصةٍ تريد مستوًى مؤسسيًّا وسياديًّا — وأيُّ إلزامٍ في جهةٍ بعينها يحتاج تحققًا مستقلًّا ولا يدخل الوثيقةَ حقيقةً عامةً بلا مصدر

Sheet 18 — قاموس المقاييس
A1: المقياس | B1: التعريف | C1: المصدر | D1: العدد | E1: الملاحظة
A2: Legal Screen | B2: شاشةٌ قانونيةٌ فريدةٌ في نظام الشاشات | C2: NAV-09 · الورقةُ 98 | D2: 203 | E2: المرجعُ الحاكمُ للتنقلِ والتوليد
A3: Registered Screen | B3: سجلُّ شاشةٍ في جدول الوحدات | C3: القاعدةُ الحية · modules | D3: 249 | E3: يشمل شاشاتٍ فنيةً ومكرَّرةَ الظهور
A4: UX Adoption Unit | B4: وحدةٌ يُطبَّق عليها معيارُ محرّك الشاشات | C4: عدّادُ التبنّي | D4: 288 | E4: مقامُ نسبِ التبنّي وحدَه
A5: Navigation Item | B5: ظهورٌ فعليٌّ لدورٍ ونطاقٍ في السايدبار | C5: nav_items | D5: 1,075 | E5: الشاشةُ الواحدةُ تظهر لأدوارٍ عدة
A6: Governing Column Unit | B6: وحدةٌ تُقاس بمعيار الأعمدة الحاكمة | C6: cmp03_gov_check | D6: 288 | E6: و256 منها مكتملٌ · و32 ناقصٌ بنوعٍ يُستخرج لكلٍّ
A7: Action Code | B7: رمزُ فعلٍ فريدٌ في القاموس | C7: nav09_action_map | D7: 242 | E7: و246 صفًّا لأن ثلاثةً تتكرر بشاشاتٍ مختلفة
A8: Business Event | B8: واقعةُ عملٍ في الجذر المحايد | C8: ems_business_events | D8: 9,971 | E8: بالناشرِ حصرًا
A9: Financial Event | B9: حدثٌ ماليٌّ مشتقٌّ من واقعة | C9: fin_financial_events | D9: 5,257 | E9: بأربعَ عشرةَ حالة
A10: ◆ الحكمُ الملزم | B10: كلُّ نسبةٍ تُعلَن تذكر مقامَها ومصدرَه | C10: — | D10: — | E10: والأرقامُ لم تكن متناقضةً بل غيرَ معرَّفة

Sheet 19 — السجلات الثلاثة
A1: السجل | B1: التعريف | C1: العدد | D1: المحتوى | E1: الحكم
A2: Release Blockers | B2: حواجزُ إصدارٍ — لا يُطلَق قبل إغلاقها | C2: 2 + ما يُكتشف | D2: قلبُ الصلاحياتِ المؤجَّلُ بقرارِ مالكٍ موثَّق · وتواقيعُ محضر UAT | E2: ◆ ويُضاف إليها أيُّ عيبٍ حرجٍ يُكتشف — كطوبولوجيا القاعدتين إن ثبَت أنهما قابلتان للكتابة
A3: Architectural Debt | B3: دَينٌ معماريٌّ — يُعالَج بقرارٍ وخطة | C3: 3 مسجَّلة | D3: الـ65 جدولًا بلا عمود كيانٍ (تُصنَّف أربعةَ أصناف) · نمذجةُ حالاتِ الشاشةِ · طوبولوجيا القاعدتين | E3: لا يمنع الإطلاقَ بذاته — لكنه يتراكم ويصير حاجزًا إن أُهمل
A4: Adoption Debt | B4: دَينُ تبنٍّ — عدّاداتٌ ترتفع بالعمل لا بالقرار | C4: 25 بندًا جزئيًّا | D4: أعمدةُ الحارة · توحيدُ صيغةِ الاختباراتِ القديمةِ · الاستشهادُ الحرفيُّ 65.1٪ · بقايا المخزنِ البيني 30 صفًّا | E4: يُقاس ويُعلَن ولا يُخفى — وارتفاعُه دليلُ تقدمٍ لا عيب

Sheet 20 — لوحة أدلة NFR
A1: # | B1: المحور | C1: ما يُقاس | D1: الحالة | E1: الدليلُ المطلوب
A2: 1 | B2: Load Testing | C2: اختبارُ حملٍ بمستخدمين متزامنين | D2: ◆ لا دليلَ في v13 | E2: عددُ المستخدمين وزمنُ الاستجابةِ عند الذروة
A3: 2 | B3: p95 Latency | C3: زمنُ الاستجابةِ للمئوي الخامسِ والتسعين | D3: ◆ لا دليل | E3: لأثقلِ خمسِ شاشاتٍ في بيئةٍ حقيقية
A4: 3 | B4: Concurrent Users | C4: المستخدمون المتزامنون المدعومون | D4: ◆ لا دليل | E4: الحدُّ المختبَرُ لا المقدَّر
A5: 4 | B5: Database Throughput | C5: إنتاجيةُ القاعدةِ عند الحمل | D5: ◆ لا دليل | E5: عمليات/ثانيةً عند الذروة
A6: 5 | B6: Restore Test | C6: تمرينُ استعادةٍ فعليٌّ موثَّق | D6: ◆ لا دليل | E6: زمنُ استعادةٍ مقيسٌ لا مقدَّر
A7: 6 | B7: RPO | C7: أقصى فقدِ بياناتٍ مقبول | D7: ◆ غيرُ معلَن | E7: بالدقائقِ أو الساعات
A8: 7 | B8: RTO | C8: أقصى زمنِ توقفٍ مقبول | D8: ◆ غيرُ معلَن | E8: بالساعات
A9: 8 | B9: Disaster Recovery | C9: خطةُ تعافٍ من كارثةٍ مختبَرة | D9: ◆ لا دليل | E9: محضرُ تمرينٍ ناجح
A10: 9 | B10: DLQ Health | C10: صحةُ طابورِ الرسائلِ الميتة | D10: ◆ لا دليل | E10: عددُ المعلَّقِ وزمنُ بقائه
A11: 10 | B11: Event-Bus Lag | C11: تأخرُ وسيطِ الأحداث | D11: ◆ لا دليل | E11: الزمنُ بين النشرِ والاستهلاك
A12: 11 | B12: Job Scheduler Health | C12: صحةُ مجدولِ المهام | D12: جزئيٌّ — النبضُ الساعيُّ موثَّق | E12: نجاحُ الكنساتِ الثمانِ وزمنُ كلٍّ
A13: 12 | B13: API Contracts | C13: عقودُ واجهاتِ البرمجة | D13: ◆ لا دليل | E13: مخطَّطٌ معلَنٌ وإصدارٌ وتوافقٌ رجعي
A14: 13 | B14: Offline Sync Conflict | C14: اختبارُ تعارضِ المزامنة | D14: ◆ لا دليل | E14: سيناريو تعديلين متزامنين من جهازين
A15: ◆ | B15: الحكم | C15: — | D15: — | E15: لا يُعلَن «جاهزٌ للتشغيل المؤسسي» قبل دليلٍ لكلٍّ أو إعلانٍ صريحٍ بعدم قياسه

Sheet 21 — تصنيف الكتابة للأفعال
A1: # | B1: الرمز | C1: الفعل | D1: الإدارة | E1: الشاشة | F1: write_class | G1: ما يُكتب | H1: سجلُّ التدقيقِ اللازم
A2: 1 | B2: ticket.open | C2: فتحُ بلاغ | D2: مركز البلاغات | E2: أبلغ عن مشكلة من هذه الشاشة | F2: Read Only | G2: لا يكتب | H2: سجلُّ الاطّلاعِ إن مسّ حقلًا حساسًا
A3: 2 | B3: ticket.ack | C3: استلامُ البلاغ | D3: مركز البلاغات | E3: بلاغات إدارتي | F3: Domain Write | G3: جداولُ المجالِ المعلَنةُ في عقد الفعل | H3: سجلُّ التدقيقِ بالفاعلِ والوقتِ والقيمةِ قبلَ وبعد
A4: 3 | B4: ticket.done | C4: إنجازُ البلاغ | D4: مركز البلاغات | E4: بلاغات إدارتي | F4: Domain Write | G4: جداولُ المجالِ المعلَنةُ في عقد الفعل | H4: سجلُّ التدقيقِ بالفاعلِ والوقتِ والقيمةِ قبلَ وبعد
A5: 4 | B5: approval.grant | C5: اعتمادٌ في سقفي | D5: الحوكمة والالتزام | E5: صندوق ما ينتظر اعتمادي | F5: Domain Write | G5: جداولُ المجالِ المعلَنةُ في عقد الفعل | H5: سجلُّ التدقيقِ بالفاعلِ والوقتِ والقيمةِ قبلَ وبعد
A6: 5 | B6: approval.reject | C6: رفضٌ بسببٍ محكوم | D6: الحوكمة والالتزام | E6: صندوق ما ينتظر اعتمادي | F6: Domain Write | G6: جداولُ المجالِ المعلَنةُ في عقد الفعل | H6: سجلُّ التدقيقِ بالفاعلِ والوقتِ والقيمةِ قبلَ وبعد
A7: 6 | B7: approval.return | C7: إعادةٌ للتصحيح | D7: الحوكمة والالتزام | E7: صندوق ما ينتظر اعتمادي | F7: Domain Write | G7: جداولُ المجالِ المعلَنةُ في عقد الفعل | H7: سجلُّ التدقيقِ بالفاعلِ والوقتِ والقيمةِ قبلَ وبعد
A8: 7 | B8: ach.range | C8: اختيارُ مدى الإنجاز | D8: مساحة عملي | E8: إنجازي | F8: Read Only | G8: لا يكتب | H8: سجلُّ الاطّلاعِ إن مسّ حقلًا حساسًا
A9: 8 | B9: plan.submit | C9: رفعُ خطة الغد | D9: إدارة الموقع | E9: خطة عمل الغد | F9: Domain Write | G9: جداولُ المجالِ المعلَنةُ في عقد الفعل | H9: سجلُّ التدقيقِ بالفاعلِ والوقتِ والقيمةِ قبلَ وبعد
A10: 9 | B10: plan.approve | C10: اعتمادُ خطة الموقع | D10: إدارة الموقع | E10: خطة عمل الغد | F10: Domain Write | G10: جداولُ المجالِ المعلَنةُ في عقد الفعل | H10: سجلُّ التدقيقِ بالفاعلِ والوقتِ والقيمةِ قبلَ وبعد
A11: 10 | B11: plan.copy | C11: نسخُ خطة الأمس | D11: إدارة الموقع | E11: خطة عمل الغد | F11: Domain Write | G11: جداولُ المجالِ المعلَنةُ في عقد الفعل | H11: سجلُّ التدقيقِ بالفاعلِ والوقتِ والقيمةِ قبلَ وبعد
A12: 11 | B12: asset.assign | C12: تخصيصُ معدةٍ لموقع | D12: إدارة التشغيل | E12: توزيع المعدات والمشغّلين | F12: Domain Write | G12: جداولُ المجالِ المعلَنةُ في عقد الفعل | H12: سجلُّ التدقيقِ بالفاعلِ والوقتِ والقيمةِ قبلَ وبعد
A13: 12 | B13: operator.swap | C13: تبديلُ مشغّلٍ على معدة | D13: إدارة التشغيل | E13: توزيع المعدات والمشغّلين | F13: Domain Write | G13: جداولُ المجالِ المعلَنةُ في عقد الفعل | H13: سجلُّ التدقيقِ بالفاعلِ والوقتِ والقيمةِ قبلَ وبعد
... A363: 362 | B363: risk.settings.review | C363: ضبطُ دوريةِ المراجعةِ بحسب الدرجة | D363: RSK | E363: إعدادات المخاطر والتصنيف | F363: Domain Write | G363: جداولُ المجالِ المعلَنةُ في عقد الفعل | H363: سجلُّ التدقيقِ بالفاعلِ والوقتِ والقيمةِ قبلَ وبعد
A364: ◆ | B364: الحكم | C364: التصنيفُ رباعيٌّ لا ثنائيّ | D364: — | E364: — | F364: — | G364: فالتصديرُ لا يغيّر بيانَ المجالِ لكنه يكتب سجلَّ حوكمةٍ بتسعةِ بنود | H364: ولا يُقال عنه «قارئٌ لا يكتب»

Sheet 22 — طبيعة الشاشة
A1: # | B1: الشاشة | C1: الملف | D1: الإدارة | E1: الطبيعة | F1: ما حددها | G1: أفعالُ اعتماد | H1: أفعالُ كتابة | I1: الأعمدةُ الحاكمةُ اللازمة | J1: حالةُ التصنيف
A2: ▸ مكتبُ الرئيس التنفيذي والنواب
A3: 1 | B3: اعتمادات الرئيس التنفيذي | C3: ceo_approvals.php | D3: مكتبُ الرئيس التنفيذي والنواب | E3: مستندٌ يُعتمد | F3: فيها فعلُ اعتماد | G3: نعم | H3: نعم | I3: السبعةُ كاملةً — ومنها المعتمِدُ وتاريخُه ومرجعُ التفويض | J3: مقترحٌ مقبول
A4: 2 | B4: العقود والالتزامات المحجوزة أو المصعَّدة | C4: ceo_contracts.php | D4: مكتبُ الرئيس التنفيذي والنواب | E4: مستندٌ يُعتمد | F4: فيها فعلُ اعتماد | G4: نعم | H4: نعم | I4: السبعةُ كاملةً — ومنها المعتمِدُ وتاريخُه ومرجعُ التفويض | J4: مقترحٌ مقبول
A5: 3 | B5: المخاطر المؤسسية | C5: risk_dept_ceo.php | D5: مكتبُ الرئيس التنفيذي والنواب | E5: قارئة | F5: لا فعلَ كتابةٍ فيها | G5: لا | H5: لا | I5: الكيانُ وحدَه | J5: مقترحٌ مقبول
A6: 4 | B6: المخاطر والقرارات العليا | C6: ceo_risk.php | D6: مكتبُ الرئيس التنفيذي والنواب | E6: سجلٌّ أو إعداد | F6: فيها فعلُ كتابةِ مجال | G6: لا | H6: نعم | I6: الكيانُ والمُنشئُ وتاريخُ الإنشاءِ والمرجعُ الأب | J6: مقترحٌ مقبول
A7: 5 | B7: حوكمة مكتبُ الرئيس التنفيذي والنواب | C7: gov_dept_ceo.php | D7: مكتبُ الرئيس التنفيذي والنواب | E7: قارئة | F7: لا فعلَ كتابةٍ فيها | G7: لا | H7: لا | I7: الكيانُ وحدَه | J7: مقترحٌ مقبول
A8: 6 | B8: قرار فتح مشروع جديد | C8: project_charter.php | D8: مكتبُ الرئيس التنفيذي والنواب | E8: مستندٌ يُعتمد | F8: فيها فعلُ اعتماد | G8: نعم | H8: نعم | I8: السبعةُ كاملةً — ومنها المعتمِدُ وتاريخُه ومرجعُ التفويض | J8: مقترحٌ مقبول
A9: 7 | B9: لوحة الرئيس التنفيذي | C9: ceo_board.php | D9: مكتبُ الرئيس التنفيذي والنواب | E9: قارئة | F9: لا فعلَ كتابةٍ فيها | G9: لا | H9: لا | I9: الكيانُ وحدَه | J9: مقترحٌ مقبول
A10: ▸ إدارة التشغيل
A11: 8 | B11: إسناد المعدات للوحدات | C11: unit_assign.php | D11: إدارة التشغيل | E11: سجلٌّ أو إعداد | F11: فيها فعلُ كتابةِ مجال | G11: لا | H11: نعم | I11: الكيانُ والمُنشئُ وتاريخُ الإنشاءِ والمرجعُ الأب | J11: مقترحٌ مقبول
A12: 9 | B12: الأداء الشهري للوحدة | C12: unit_perf.php | D12: إدارة التشغيل | E12: سجلٌّ أو إعداد | F12: فيها فعلُ كتابةِ مجال | G12: لا | H12: نعم | I12: الكيانُ والمُنشئُ وتاريخُ الإنشاءِ والمرجعُ الأب | J12: مقترحٌ مقبول
A13: 10 | B13: الإقفال الشهري للوحدة | C13: monthly_close.php | D13: إدارة التشغيل | E13: مستندٌ يُعتمد | F13: فيها فعلُ كتابةِ مجال | G13: لا | H13: نعم | I13: السبعةُ كاملةً — ومنها المعتمِدُ وتاريخُه ومرجعُ التفويض | J13: مقترحٌ مقبول
A14: 11 | B14: التوقفات وتحديد المتحمل | C14: stops.php | D14: إدارة التشغيل | E14: سجلٌّ أو إعداد | F14: فيها فعلُ كتابةِ مجال | G14: لا | H14: نعم | I14: الكيانُ والمُنشئُ وتاريخُ الإنشاءِ والمرجعُ الأب | J14: مقترحٌ مقبول
A15: 12 | B15: المخاطر التشغيلية | C15: risk_dept_ops.php | D15: إدارة التشغيل | E15: قارئة | F15: لا فعلَ كتابةٍ فيها | G15: لا | H15: لا | I15: الكيانُ وحدَه | J15: مقترحٌ مقبول
A16: 13 | B16: توزيع المعدات والمشغّلين | C16: distribution.php | D16: إدارة التشغيل | E16: سجلٌّ أو إعداد | F16: فيها فعلُ كتابةِ مجال | G16: لا | H16: نعم | I16: الكيانُ والمُنشئُ وتاريخُ الإنشاءِ والمرجعُ الأب | J16: مقترحٌ مقبول
A17: 14 | B17: حوكمة إدارة التشغيل | C17: gov_dept_ops.php | D17: إدارة التشغيل | E17: قارئة | F17: لا فعلَ كتابةٍ فيها | G17: لا | H17: لا | I17: الكيانُ وحدَه | J17: مقترحٌ مقبول
A18: 15 | B18: غرفة عمليات المواقع | C18: ops_room.php | D18: إدارة التشغيل | E18: سجلٌّ أو إعداد | F18: فيها فعلُ كتابةِ مجال | G18: لا | H18: نعم | I18: الكيانُ والمُنشئُ وتاريخُ الإنشاءِ والمرجعُ الأب | J18: مقترحٌ مقبول
A19: ▸ المبيعات والعقود
A20: 16 | B20: آليات تعديل السعر | C20: price_adjust.php | D20: المبيعات والعقود | E20: سجلٌّ أو إعداد | F20: فيها فعلُ كتابةِ مجال | G20: لا | H20: نعم | I20: الكيانُ والمُنشئُ وتاريخُ الإنشاءِ والمرجعُ الأب | J20: مقترحٌ مقبول
A21: 17 | B21: أحكام العقد — العملات والمقدم والمهل | C21: contract_terms.php | D21: المبيعات والعقود | E21: مستندٌ يُعتمد | F21: فيها فعلُ كتابةِ مجال | G21: لا | H21: نعم | I21: السبعةُ كاملةً — ومنها المعتمِدُ وتاريخُه ومرجعُ التفويض | J21: مقترحٌ مقبول
A22: 18 | B22: الأعمال غير المفوترة | C22: unbilled.php | D22: المبيعات والعقود | E22: سجلٌّ أو إعداد | F22: فيها فعلُ كتابةِ مجال | G22: لا | H22: نعم | I22: الكيانُ والمُنشئُ وتاريخُ الإنشاءِ والمرجعُ الأب | J22: مقترحٌ مقبول
A23: 19 | B23: التزام العقد بنوع المعدة | C23: coverage.php | D23: المبيعات والعقود | E23: مستندٌ يُعتمد | F23: فيها فعلُ كتابةِ مجال | G23: لا | H23: نعم | I23: السبعةُ كاملةً — ومنها المعتمِدُ وتاريخُه ومرجعُ التفويض | J23: مقترحٌ مقبول
A24: 20 | B24: الجزاءات والحوافز التعاقدية | C24: penalties.php | D24: المبيعات والعقود | E24: سجلٌّ أو إعداد | F24: فيها فعلُ كتابةِ مجال | G24: لا | H24: نعم | I24: الكيانُ والمُنشئُ وتاريخُ الإنشاءِ والمرجعُ الأب | J24: مقترحٌ مقبول
A25: 21 | B25: الفرص والزيارات والمناقصات | C25: opportunities.php | D25: المبيعات والعقود | E25: سجلٌّ أو إعداد | F25: فيها فعلُ كتابةِ مجال | G25: لا | H25: نعم | I25: الكيانُ والمُنشئُ وتاريخُ الإنشاءِ والمرجعُ الأب | J25: مقترحٌ مقبول
A26: 22 | B26: المخاطر التجارية | C26: commercial_risks.php | D26: المبيعات والعقود | E26: سجلٌّ أو إعداد | F26: فيها فعلُ كتابةِ مجال | G26: لا | H26: نعم | I26: الكيانُ والمُنشئُ وتاريخُ الإنشاءِ والمرجعُ الأب | J26: مقترحٌ مقبول
A27: 23 | B27: المستخلصات والمطالبات | C27: claims.php | D27: المبيعات والعقود | E27: مستندٌ يُعتمد | F27: فيها فعلُ اعتماد | G27: نعم | H27: نعم | I27: السبعةُ كاملةً — ومنها المعتمِدُ وتاريخُه ومرجعُ التفويض | J27: مقترحٌ مقبول
A28: 24 | B28: المشاريع والمواقع | C28: projects.php | D28: المبيعات والعقود | E28: سجلٌّ أو إعداد | F28: فيها فعلُ كتابةِ مجال | G28: لا | H28: نعم | I28: الكيانُ والمُنشئُ وتاريخُ الإنشاءِ والمرجعُ الأب | J28: مقترحٌ مقبول
A29: 25 | B29: الوحدات التعاقدية المرقَّمة | C29: units.php | D29: المبيعات والعقود | E29: سجلٌّ أو إعداد | F29: فيها فعلُ كتابةِ مجال | G29: لا | H29: نعم | I29: الكيانُ والمُنشئُ وتاريخُ الإنشاءِ والمرجعُ الأب | J29: مقترحٌ مقبول
A30: 26 | B30: حوكمة المبيعات والعقود | C30: gov_dept_sal.php | D30: المبيعات والعقود | E30: قارئة | F30: لا فعلَ كتابةٍ فيها | G30: لا | H30: لا | I30: الكيانُ وحدَه | J30: مقترحٌ مقبول
A31: 27 | B31: سجل العملاء | C31: clients.php | D31: المبيعات والعقود | E31: سجلٌّ أو إعداد | F31: فيها فعلُ كتابةِ مجال | G31: لا | H31: نعم | I31: الكيانُ والمُنشئُ وتاريخُ الإنشاءِ والمرجعُ الأب | J31: مقترحٌ مقبول
... A41: 37 | B41: وحدات القياس والتحويل | C41: units_of_measure.php | D41: المبيعات والعقود | E41: سجلٌّ أو إعداد | F41: فيها فعلُ كتابةِ مجال | G41: لا | H41: نعم | I41: الكيانُ والمُنشئُ وتاريخُ الإنشاءِ والمرجعُ الأب | J41: مقترحٌ مقبول
A42: ▸ إدارة الموردين
A43: 38 | B43: أداء الموردين وجاهزيتهم | C43: supplier_perf.php | D43: إدارة الموردين | E43: سجلٌّ أو إعداد | F43: فيها فعلُ كتابةِ مجال | G43: لا | H43: نعم | I43: الكيانُ والمُنشئُ وتاريخُ الإنشاءِ والمرجعُ الأب | J43: مقترحٌ مقبول
A44: 39 | B44: تسويات ومستحقات الموردين | C44: supplier_settle.php | D44: إدارة الموردين | E44: مستندٌ يُعتمد | F44: فيها فعلُ اعتماد | G44: نعم | H44: نعم | I44: السبعةُ كاملةً — ومنها المعتمِدُ وتاريخُه ومرجعُ التفويض | J44: مقترحٌ مقبول
A45: 40 | B45: تصفية إنهاء عقد مورد | C45: supplier_closure.php | D45: إدارة الموردين | E45: مستندٌ يُعتمد | F45: فيها فعلُ كتابةِ مجال | G45: لا | H45: نعم | I45: السبعةُ كاملةً — ومنها المعتمِدُ وتاريخُه ومرجعُ التفويض | J45: مقترحٌ مقبول
A46: 41 | B46: تقييم المورد الدوري | C46: supplier_evaluation.php | D46: إدارة الموردين | E46: مستندٌ يُعتمد | F46: فيها فعلُ اعتماد | G46: نعم | H46: نعم | I46: السبعةُ كاملةً — ومنها المعتمِدُ وتاريخُه ومرجعُ التفويض | J46: مقترحٌ مقبول
A47: 42 | B47: توزيع وحدات المورد على معداته | C47: equipment_quota.php | D47: إدارة الموردين | E47: سجلٌّ أو إعداد | F47: فيها فعلُ كتابةِ مجال | G47: لا | H47: نعم | I47: الكيانُ والمُنشئُ وتاريخُ الإنشاءِ والمرجعُ الأب | J47: مقترحٌ مقبول
A48: 43 | B48: حسابات الموردين البنكية | C48: supplier_bank.php | D48: إدارة الموردين | E48: سجلٌّ أو إعداد | F48: فيها فعلُ كتابةِ مجال | G48: لا | H48: نعم | I48: الكيانُ والمُنشئُ وتاريخُ الإنشاءِ والمرجعُ الأب | J48: مقترحٌ مقبول
A49: 44 | B49: حصص الموردين من العقود | C49: supplier_quota.php | D49: إدارة الموردين | E49: مستندٌ يُعتمد | F49: فيها فعلُ اعتماد | G49: نعم | H49: نعم | I49: السبعةُ كاملةً — ومنها المعتمِدُ وتاريخُه ومرجعُ التفويض | J49: مقترحٌ مقبول
A50: 45 | B50: حوكمة إدارة الموردين | C50: gov_dept_sup.php | D50: إدارة الموردين | E50: قارئة | F50: لا فعلَ كتابةٍ فيها | G50: لا | H50: لا | I50: الكيانُ وحدَه | J50: مقترحٌ مقبول
A51: 46 | B51: خطة معدات المورد المتعهَّد بها | C51: supplier_plan.php | D51: إدارة الموردين | E51: مستندٌ يُعتمد | F51: فيها فعلُ اعتماد | G51: نعم | H51: نعم | I51: السبعةُ كاملةً — ومنها المعتمِدُ وتاريخُه ومرجعُ التفويض | J51: مقترحٌ مقبول
A52: 47 | B52: دفتر استهلاك حصص الموردين | C52: quota_ledger.php | D52: إدارة الموردين | E52: سجلٌّ أو إعداد | F52: فيها فعلُ كتابةِ مجال | G52: لا | H52: نعم | I52: الكيانُ والمُنشئُ وتاريخُ الإنشاءِ والمرجعُ الأب | J52: مقترحٌ مقبول
A53: 48 | B53: سجل الموردين | C53: suppliers.php | D53: إدارة الموردين | E53: سجلٌّ أو إعداد | F53: فيها فعلُ كتابةِ مجال | G53: لا | H53: نعم | I53: الكيانُ والمُنشئُ وتاريخُ الإنشاءِ والمرجعُ الأب | J53: مقترحٌ مقبول
A54: 49 | B54: سلفيات الموردين | C54: supplier_advances.php | D54: إدارة الموردين | E54: سجلٌّ أو إعداد | F54: فيها فعلُ كتابةِ مجال | G54: لا | H54: نعم | I54: الكيانُ والمُنشئُ وتاريخُ الإنشاءِ والمرجعُ الأب | J54: مقترحٌ مقبول
... A60: 55 | B60: معدات المورد ومالكوها | C60: supplier_equip.php | D60: إدارة الموردين | E60: سجلٌّ أو إعداد | F60: فيها فعلُ كتابةِ مجال | G60: لا | H60: نعم | I60: الكيانُ والمُنشئُ وتاريخُ الإنشاءِ والمرجعُ الأب | J60: مقترحٌ مقبول
A61: ▸ إدارة الأسطول
A62: 56 | B62: أنواع المعدات وفئاتها | C62: equip_types.php | D62: إدارة الأسطول | E62: سجلٌّ أو إعداد | F62: فيها فعلُ كتابةِ مجال | G62: لا | H62: نعم | I62: الكيانُ والمُنشئُ وتاريخُ الإنشاءِ والمرجعُ الأب | J62: مقترحٌ مقبول
A63: 57 | B63: الإهلاك والقيمة الدفترية | C63: depreciation.php | D63: إدارة الأسطول | E63: سجلٌّ أو إعداد | F63: فيها فعلُ كتابةِ مجال | G63: لا | H63: نعم | I63: الكيانُ والمُنشئُ وتاريخُ الإنشاءِ والمرجعُ الأب | J63: مقترحٌ مقبول
A64: 58 | B64: جسر ترقيم المعدات | C64: code_bridge.php | D64: إدارة الأسطول | E64: سجلٌّ أو إعداد | F64: فيها فعلُ كتابةِ مجال | G64: لا | H64: نعم | I64: الكيانُ والمُنشئُ وتاريخُ الإنشاءِ والمرجعُ الأب | J64: مقترحٌ مقبول
A65: 59 | B65: حوكمة إدارة الأسطول | C65: gov_dept_flt.php | D65: إدارة الأسطول | E65: قارئة | F65: لا فعلَ كتابةٍ فيها | G65: لا | H65: لا | I65: الكيانُ وحدَه | J65: مقترحٌ مقبول
A66: 60 | B66: سجل المعدات | C66: equipments.php | D66: إدارة الأسطول | E66: سجلٌّ أو إعداد | F66: فيها فعلُ كتابةِ مجال | G66: لا | H66: نعم | I66: الكيانُ والمُنشئُ وتاريخُ الإنشاءِ والمرجعُ الأب | J66: مقترحٌ مقبول
A67: 61 | B67: سياسات الإهلاك المعتمدة | C67: dep_profiles.php | D67: إدارة الأسطول | E67: مستندٌ يُعتمد | F67: فيها فعلُ اعتماد | G67: نعم | H67: نعم | I67: السبعةُ كاملةً — ومنها المعتمِدُ وتاريخُه ومرجعُ التفويض | J67: مقترحٌ مقبول
A68: 62 | B68: قراءات العدّادات | C68: equip_meters.php | D68: إدارة الأسطول | E68: سجلٌّ أو إعداد | F68: فيها فعلُ كتابةِ مجال | G68: لا | H68: نعم | I68: الكيانُ والمُنشئُ وتاريخُ الإنشاءِ والمرجعُ الأب | J68: مقترحٌ مقبول
A69: 63 | B69: مخاطر الأسطول | C69: risk_dept_flt.php | D69: إدارة الأسطول | E69: قارئة | F69: لا فعلَ كتابةٍ فيها | G69: لا | H69: لا | I69: الكيانُ وحدَه | J69: مقترحٌ مقبول
A70: 64 | B70: مصدر المعدة ونمط تملّكها | C70: equipment_sourcing.php | D70: إدارة الأسطول | E70: سجلٌّ أو إعداد | F70: فيها فعلُ كتابةِ مجال | G70: لا | H70: نعم | I70: الكيانُ والمُنشئُ وتاريخُ الإنشاءِ والمرجعُ الأب | J70: مقترحٌ مقبول
A71: 65 | B71: مطابقة سجل الأصول بالتشغيل | C71: asset_recon.php | D71: إدارة الأسطول | E71: سجلٌّ أو إعداد | F71: فيها فعلُ كتابةِ مجال | G71: لا | H71: نعم | I71: الكيانُ والمُنشئُ وتاريخُ الإنشاءِ والمرجعُ الأب | J71: مقترحٌ مقبول
A72: 66 | B72: ملّاك الأسطول | C72: fleet_owners.php | D72: إدارة الأسطول | E72: سجلٌّ أو إعداد | F72: فيها فعلُ كتابةِ مجال | G72: لا | H72: نعم | I72: الكيانُ والمُنشئُ وتاريخُ الإنشاءِ والمرجعُ الأب | J72: مقترحٌ مقبول
A73: 67 | B73: موديلات المعدات ومواصفاتها | C73: equip_models.php | D73: إدارة الأسطول | E73: سجلٌّ أو إعداد | F73: فيها فعلُ كتابةِ مجال | G73: لا | H73: نعم | I73: الكيانُ والمُنشئُ وتاريخُ الإنشاءِ والمرجعُ الأب | J73: مقترحٌ مقبول
A74: 68 | B74: وثائق المعدات والمشغّلين | C74: equip_docs.php | D74: إدارة الأسطول | E74: سجلٌّ أو إعداد | F74: فيها فعلُ كتابةِ مجال | G74: لا | H74: نعم | I74: الكيانُ والمُنشئُ وتاريخُ الإنشاءِ والمرجعُ الأب | J74: مقترحٌ مقبول
A75: ▸ المالية والخزينة
A76: 69 | B76: أسعار الصرف | C76: fx_rates.php | D76: المالية والخزينة | E76: مستندٌ يُعتمد | F76: فيها فعلُ اعتماد | G76: نعم | H76: نعم | I76: السبعةُ كاملةً — ومنها المعتمِدُ وتاريخُه ومرجعُ التفويض | J76: مقترحٌ مقبول
A77: 70 | B77: إقفال الفترة المحاسبية | C77: period_close.php | D77: المالية والخزينة | E77: مستندٌ يُعتمد | F77: فيها فعلُ كتابةِ مجال | G77: لا | H77: نعم | I77: السبعةُ كاملةً — ومنها المعتمِدُ وتاريخُه ومرجعُ التفويض | J77: مقترحٌ مقبول
A78: 71 | B78: التدفق النقدي والتنبؤ | C78: cash_forecast.php | D78: المالية والخزينة | E78: سجلٌّ أو إعداد | F78: فيها فعلُ كتابةِ مجال | G78: لا | H78: نعم | I78: الكيانُ والمُنشئُ وتاريخُ الإنشاءِ والمرجعُ الأب | J78: مقترحٌ مقبول
A79: 72 | B79: التكاليف والربحية بالمركز | C79: cost_report.php | D79: المالية والخزينة | E79: سجلٌّ أو إعداد | F79: فيها فعلُ كتابةِ مجال | G79: لا | H79: نعم | I79: الكيانُ والمُنشئُ وتاريخُ الإنشاءِ والمرجعُ الأب | J79: مقترحٌ مقبول
A80: 73 | B80: الخزينة والصناديق | C80: treasury.php | D80: المالية والخزينة | E80: سجلٌّ أو إعداد | F80: فيها فعلُ كتابةِ مجال | G80: لا | H80: نعم | I80: الكيانُ والمُنشئُ وتاريخُ الإنشاءِ والمرجعُ الأب | J80: مقترحٌ مقبول
A81: 74 | B81: الفاتورة الضريبية والإقرارات | C81: tax_invoices.php | D81: المالية والخزينة | E81: مستندٌ يُعتمد | F81: فيها فعلُ اعتماد | G81: نعم | H81: نعم | I81: السبعةُ كاملةً — ومنها المعتمِدُ وتاريخُه ومرجعُ التفويض | J81: مقترحٌ مقبول
A82: 75 | B82: القوائم المالية | C82: fin_statements.php | D82: المالية والخزينة | E82: سجلٌّ أو إعداد | F82: فيها فعلُ كتابةِ مجال | G82: لا | H82: نعم | I82: الكيانُ والمُنشئُ وتاريخُ الإنشاءِ والمرجعُ الأب | J82: مقترحٌ مقبول
A83: 76 | B83: القيود اليومية | C83: journal.php | D83: المالية والخزينة | E83: سجلٌّ أو إعداد | F83: فيها فعلُ كتابةِ مجال | G83: لا | H83: نعم | I83: الكيانُ والمُنشئُ وتاريخُ الإنشاءِ والمرجعُ الأب | J83: مقترحٌ مقبول
A84: 77 | B84: المخاطر المالية | C84: risk_dept_fin.php | D84: المالية والخزينة | E84: قارئة | F84: لا فعلَ كتابةٍ فيها | G84: لا | H84: لا | I84: الكيانُ وحدَه | J84: مقترحٌ مقبول
A85: 78 | B85: المطابقة البنكية | C85: bank_recon.php | D85: المالية والخزينة | E85: سجلٌّ أو إعداد | F85: فيها فعلُ كتابةِ مجال | G85: لا | H85: نعم | I85: الكيانُ والمُنشئُ وتاريخُ الإنشاءِ والمرجعُ الأب | J85: مقترحٌ مقبول
A86: 79 | B86: الموازنة العامة | C86: budget_master.php | D86: المالية والخزينة | E86: مستندٌ يُعتمد | F86: فيها فعلُ اعتماد | G86: نعم | H86: نعم | I86: السبعةُ كاملةً — ومنها المعتمِدُ وتاريخُه ومرجعُ التفويض | J86: مقترحٌ مقبول
A87: 80 | B87: تتبّع الأثر من الواقعة إلى القيد | C87: effect_map.php | D87: المالية والخزينة | E87: قارئة | F87: لا فعلَ كتابةٍ فيها | G87: لا | H87: لا | I87: الكيانُ وحدَه | J87: مقترحٌ مقبول
... A103: 96 | B103: هامش الربح للعقد والواقعة | C103: margin.php | D103: المالية والخزينة | E103: مستندٌ يُعتمد | F103: فيها فعلُ كتابةِ مجال | G103: لا | H103: نعم | I103: السبعةُ كاملةً — ومنها المعتمِدُ وتاريخُه ومرجعُ التفويض | J103: مقترحٌ مقبول
A104: ▸ التمويل والملكية
A105: 97 | B105: الأعيان المموَّلة | C105: fin_assets.php | D105: التمويل والملكية | E105: سجلٌّ أو إعداد | F105: فيها فعلُ كتابةِ مجال | G105: لا | H105: نعم | I105: الكيانُ والمُنشئُ وتاريخُ الإنشاءِ والمرجعُ الأب | J105: مقترحٌ مقبول
A106: 98 | B106: الأقساط ومواعيد السداد | C106: installments.php | D106: التمويل والملكية | E106: سجلٌّ أو إعداد | F106: فيها فعلُ كتابةِ مجال | G106: لا | H106: نعم | I106: الكيانُ والمُنشئُ وتاريخُ الإنشاءِ والمرجعُ الأب | J106: مقترحٌ مقبول
A107: 99 | B107: الخروج غير المسجَّل من الملكية | C107: fin_exit.php | D107: التمويل والملكية | E107: سجلٌّ أو إعداد | F107: فيها فعلُ كتابةِ مجال | G107: لا | H107: نعم | I107: الكيانُ والمُنشئُ وتاريخُ الإنشاءِ والمرجعُ الأب | J107: مقترحٌ مقبول
A108: 100 | B108: انحرافات التمويل — السداد والملكية والتوثيق | C108: fin_deviations.php | D108: التمويل والملكية | E108: سجلٌّ أو إعداد | F108: فيها فعلُ كتابةِ مجال | G108: لا | H108: نعم | I108: الكيانُ والمُنشئُ وتاريخُ الإنشاءِ والمرجعُ الأب | J108: مقترحٌ مقبول
A109: 101 | B109: تغيّرات عقود التمويل | C109: fin_changes.php | D109: التمويل والملكية | E109: سجلٌّ أو إعداد | F109: فيها فعلُ كتابةِ مجال | G109: لا | H109: نعم | I109: الكيانُ والمُنشئُ وتاريخُ الإنشاءِ والمرجعُ الأب | J109: مقترحٌ مقبول
A110: 102 | B110: توزيع تكلفة التمويل على المشاريع | C110: fin_cost.php | D110: التمويل والملكية | E110: سجلٌّ أو إعداد | F110: فيها فعلُ كتابةِ مجال | G110: لا | H110: نعم | I110: الكيانُ والمُنشئُ وتاريخُ الإنشاءِ والمرجعُ الأب | J110: مقترحٌ مقبول
A111: 103 | B111: حصص الملكية في الأصول | C111: shares.php | D111: التمويل والملكية | E111: سجلٌّ أو إعداد | F111: فيها فعلُ كتابةِ مجال | G111: لا | H111: نعم | I111: الكيانُ والمُنشئُ وتاريخُ الإنشاءِ والمرجعُ الأب | J111: مقترحٌ مقبول
A112: 104 | B112: حوكمة التمويل والملكية | C112: gov_dept_cap.php | D112: التمويل والملكية | E112: قارئة | F112: لا فعلَ كتابةٍ فيها | G112: لا | H112: لا | I112: الكيانُ وحدَه | J112: مقترحٌ مقبول
A113: 105 | B113: سجل الممولين | C113: financiers.php | D113: التمويل والملكية | E113: سجلٌّ أو إعداد | F113: فيها فعلُ كتابةِ مجال | G113: لا | H113: نعم | I113: الكيانُ والمُنشئُ وتاريخُ الإنشاءِ والمرجعُ الأب | J113: مقترحٌ مقبول
A114: 106 | B114: عقود تمويل بلا حركة | C114: fin_idle.php | D114: التمويل والملكية | E114: سجلٌّ أو إعداد | F114: فيها فعلُ كتابةِ مجال | G114: لا | H114: نعم | I114: الكيانُ والمُنشئُ وتاريخُ الإنشاءِ والمرجعُ الأب | J114: مقترحٌ مقبول
A115: 107 | B115: عمليات التمويل | C115: fin_ops.php | D115: التمويل والملكية | E115: سجلٌّ أو إعداد | F115: فيها فعلُ كتابةِ مجال | G115: لا | H115: نعم | I115: الكيانُ والمُنشئُ وتاريخُ الإنشاءِ والمرجعُ الأب | J115: مقترحٌ مقبول
A116: 108 | B116: فروق السداد والاستحقاق | C116: fin_variance.php | D116: التمويل والملكية | E116: سجلٌّ أو إعداد | F116: فيها فعلُ كتابةِ مجال | G116: لا | H116: نعم | I116: الكيانُ والمُنشئُ وتاريخُ الإنشاءِ والمرجعُ الأب | J116: مقترحٌ مقبول
... A118: 110 | B118: نماذج التمويل ومعالجتها | C118: fin_models.php | D118: التمويل والملكية | E118: مستندٌ يُعتمد | F118: فيها فعلُ اعتماد | G118: نعم | H118: نعم | I118: السبعةُ كاملةً — ومنها المعتمِدُ وتاريخُه ومرجعُ التفويض | J118: مقترحٌ مقبول
A119: ▸ الموارد البشرية
A120: 111 | B120: الإجازات والغياب | C120: leaves.php | D120: الموارد البشرية | E120: مستندٌ يُعتمد | F120: فيها فعلُ اعتماد | G120: نعم | H120: نعم | I120: السبعةُ كاملةً — ومنها المعتمِدُ وتاريخُه ومرجعُ التفويض | J120: مقترحٌ مقبول
A121: 112 | B121: التوظيف من الشاغر إلى المباشرة | C121: recruitment.php | D121: الموارد البشرية | E121: سجلٌّ أو إعداد | F121: فيها فعلُ كتابةِ مجال | G121: لا | H121: نعم | I121: الكيانُ والمُنشئُ وتاريخُ الإنشاءِ والمرجعُ الأب | J121: مقترحٌ مقبول
A122: 113 | B122: الحضور والانصراف | C122: attendance.php | D122: الموارد البشرية | E122: سجلٌّ أو إعداد | F122: فيها فعلُ كتابةِ مجال | G122: لا | H122: نعم | I122: الكيانُ والمُنشئُ وتاريخُ الإنشاءِ والمرجعُ الأب | J122: مقترحٌ مقبول
A123: 114 | B123: الخصومات والجزاءات | C123: deductions.php | D123: الموارد البشرية | E123: مستندٌ يُعتمد | F123: فيها فعلُ اعتماد | G123: نعم | H123: نعم | I123: السبعةُ كاملةً — ومنها المعتمِدُ وتاريخُه ومرجعُ التفويض | J123: مقترحٌ مقبول
A124: 115 | B124: السلف والعهد المالية | C124: advances.php | D124: الموارد البشرية | E124: سجلٌّ أو إعداد | F124: فيها فعلُ كتابةِ مجال | G124: لا | H124: نعم | I124: الكيانُ والمُنشئُ وتاريخُ الإنشاءِ والمرجعُ الأب | J124: مقترحٌ مقبول
A125: 116 | B125: تصفية إنهاء خدمة موظف | C125: final_settlement.php | D125: الموارد البشرية | E125: سجلٌّ أو إعداد | F125: فيها فعلُ كتابةِ مجال | G125: لا | H125: نعم | I125: الكيانُ والمُنشئُ وتاريخُ الإنشاءِ والمرجعُ الأب | J125: مقترحٌ مقبول
A126: 117 | B126: تقييم أداء العاملين | C126: worker_evaluation.php | D126: الموارد البشرية | E126: سجلٌّ أو إعداد | F126: فيها فعلُ كتابةِ مجال | G126: لا | H126: نعم | I126: الكيانُ والمُنشئُ وتاريخُ الإنشاءِ والمرجعُ الأب | J126: مقترحٌ مقبول
A127: 118 | B127: حوكمة الموارد البشرية | C127: gov_dept_hrm.php | D127: الموارد البشرية | E127: قارئة | F127: لا فعلَ كتابةٍ فيها | G127: لا | H127: لا | I127: الكيانُ وحدَه | J127: مقترحٌ مقبول
A128: 119 | B128: سجل الموظفين | C128: employees.php | D128: الموارد البشرية | E128: سجلٌّ أو إعداد | F128: فيها فعلُ كتابةِ مجال | G128: لا | H128: نعم | I128: الكيانُ والمُنشئُ وتاريخُ الإنشاءِ والمرجعُ الأب | J128: مقترحٌ مقبول
A129: 120 | B129: عقود المشاريع المؤقتة | C129: project_contracts.php | D129: الموارد البشرية | E129: مستندٌ يُعتمد | F129: فيها فعلُ اعتماد | G129: نعم | H129: نعم | I129: السبعةُ كاملةً — ومنها المعتمِدُ وتاريخُه ومرجعُ التفويض | J129: مقترحٌ مقبول
A130: 121 | B130: عقود الموظفين | C130: emp_contracts.php | D130: الموارد البشرية | E130: مستندٌ يُعتمد | F130: فيها فعلُ اعتماد | G130: نعم | H130: نعم | I130: السبعةُ كاملةً — ومنها المعتمِدُ وتاريخُه ومرجعُ التفويض | J130: مقترحٌ مقبول
...

Sheet 23 — إطار المخاطر
A1: البند | B1: التفصيل | C1: الحكم
A2: ◆ المبادئُ الثمانيةُ الحاكمة
A3: RK-01 · المخاطرُ تُملك حيث تنشأ | B3: الإدارةُ التي ينشأ عن أعمالها الخطرُ تبقى مالكتَه — ولا تنتقل ملكيتُه إلى إدارةِ المخاطرِ بمجرد تسجيله. | C3: ◆ وإدارةُ المخاطرِ تملك اللغةَ والمنهجَ والقياسَ والتحدي المستقلَّ والتجميعَ والتصعيدَ والتحققَ — لا العملَ التشغيليَّ نفسَه.
A4: RK-02 · المخاطرُ تُراقب مركزيًّا وتُعالَج لامركزيًّا | B4: سجلٌّ مركزيٌّ واحدٌ للمخاطرِ في المنصةِ كلِّها — ولا سجلَّ منفصلٌ لكل إدارة. والخطرُ الواحدُ يُعرض لعدةِ إداراتٍ بزوايا مختلفةٍ ولا يُنسخ. | C4: والمعالجةُ تقع في الإدارةِ المالكةِ وبمواردها — وإدارةُ المخاطرِ تتحقق ولا تنفّذ.
A5: RK-03 · لا خطرَ يُغلق بلا دليل | B5: لا يُغلق خطرٌ لمجرد كتابةِ خطةِ معالجة. بل يلزم دليلُ تنفيذٍ وإعادةُ تقييمٍ وحكمٌ على الخطرِ المتبقي واعتمادٌ وفقَ السقف. | C5: ◆ والتقييماتُ السابقةُ لا تُكتب فوقها — بل تُحفظ نسخًا تاريخيةً مؤرَّخةً بمُقيِّمِها.
A6: RK-04 · لا يقبل مالكُ الخطرِ خطرًا فوقَ سقفه منفردًا | B6: قبولُ الخطرِ قرارٌ رسميٌّ بسلطةٍ محددةٍ بحسب درجةِ الخطرِ المتبقي والمجالِ وقيمةِ التعرض. | C6: ◆ ولا تقبل إدارةُ المخاطرِ الخطرَ نيابةً عن صاحبِ السلطة — ولا يُقبل ما يخالف قانونًا أو حارسًا غيرَ قابلٍ للتجاوز.
A7: RK-05 · ليس كلُّ حدثٍ خطرًا | B7: الحدثُ يمرُّ بفرزٍ قبل أن يصير خطرًا: قد يُهمَل أو يُربط بخطرٍ قائمٍ أو يُنشئ خطرًا جديدًا أو يُصعَّد. | C7: ◆ والتحويلُ الآليُّ لكل بلاغٍ وعطلٍ إلى خطرٍ يُنتج آلافَ المخاطرِ المزعجةِ ويُفقد السجلَّ معناه.
A8: RK-06 · تقييمُ الخطرِ لا يُنشئ قيدًا ماليًّا | B8: تسجّل إدارةُ المخاطرِ التعرضَ المقدَّرَ بمداه واحتمالِه وأفقِه الزمني — ولا تُنشئ مخصَّصًا ولا قيدًا ولا ذمةً. | C8: ◆ وإن تحقق الخطرُ نُشر حدثٌ إلى المالية — والماليةُ وحدَها تقرر المعالجةَ المحاسبيةَ وفقَ قواعدها.
A9: RK-07 · الضابطُ لا يُحتسب إلا بإثبات فعاليته | B9: وجودُ الضابطِ في السجلِّ لا يخفض درجةَ الخطر. بل يلزم دليلُ تنفيذٍ وتحققٌ دوريٌّ ونتيجةُ تحققٍ موثَّقة. | C9: ◆ والضابطُ الحرجُ يُميَّز عن غيره: يمنع حدثًا عاليَ العواقبِ وله معيارُ أداءٍ ومن يتحقق منه وماذا يحدث عند فشله.
A10: RK-08 · الخطرُ الحرجُ لا يختفي عن الرئيس التنفيذي | B10: لا يملك أحدٌ — ولا مديرُ المخاطرِ نفسُه — إخفاءَ خطرٍ حرجٍ عن جهةٍ يفرض النظامُ أن تستلمه. | C10: والتصعيدُ آليٌّ بالمصفوفةِ لا بتقديرٍ فردي.
A11: ◆ القاموس — ما لا يُخلط
A12: Risk — خطر | B12: حالةُ عدمِ يقينٍ قد تؤثر في هدفٍ مستقبلي | C12: ليس المشكلةَ القائمةَ — تلك Issue
A13: Risk Signal — إشارةُ خطر | B13: مؤشرٌ أو حدثٌ يستحق الفحصَ ولا يعني ثبوتَ خطرٍ جديد | C13: لا يُسجَّل خطرًا قبل الفرز
A14: Hazard — مصدرُ خطر | B14: ظرفٌ أو مصدرٌ يمكن أن يؤدي إلى ضرر | C14: ليس الخطرَ — الخطرُ أثرُه على هدف
A15: Issue — مشكلةٌ قائمة | B15: مشكلةٌ حدثت وتحتاج معالجة | C15: وقعت فعلًا — والخطرُ لم يقع بعد
A16: Incident — واقعة | B16: حدثٌ وقع بالفعلِ وأنتج أثرًا | C16: قد يُحقق خطرًا قائمًا فيُعاد تقييمُه
A17: Near Miss — واقعةٌ كادت تقع | B17: لم تنتج أثرًا كاملًا لكنها تكشف تعرضًا | C17: ◆ من أهمِّ مصادرِ الإشاراتِ ولا تُهمَل
A18: Control Failure — فشلُ ضابط | B18: الضابطُ المطلوبُ لم يعمل أو لم يُثبَت | C18: يرفع الخطرَ المتبقيَ فورًا
A19: Loss Event — واقعةُ خسارة | B19: خطرٌ تحقق وأنتج أثرًا | C19: تُنشر إلى الماليةِ ولا تُقيَّد من المخاطر
A20: Risk Treatment — معالجة | B20: الإجراءُ المختارُ لتغيير مستوى الخطر | C20: تجنبٌ · تقليلٌ · نقلٌ · قبول
A21: Risk Acceptance — قبولُ الخطر | B21: قرارٌ رسميٌّ بقبول الخطرِ المتبقي ضمن سلطةٍ محددة | C21: ◆ ليس إهمالًا — بل قرارٌ موقَّعٌ بمهلةِ مراجعة
A22: Risk Appetite — شهيةُ المخاطر | B22: مستوى الخطرِ الذي تقبله الشركةُ سعيًا لأهدافها | C22: يحددها الرئيسُ التنفيذيُّ بحسب الخطةِ العامة
A23: Risk Tolerance — حدُّ التحمل | B23: الانحرافُ المقبولُ حول الشهيةِ قبل التصعيد | C23: أضيقُ من الشهيةِ وأدقُّ منها
... A29: Critical Control — ضابطٌ حرج | B29: ضابطٌ يمنع حدثًا عاليَ العواقبِ أو يحدُّ أثرَه | C29: ◆ قليلٌ ومحدَّدٌ — لا مئاتٌ متساوية
A30: ◆ دورةُ حياةِ الخطرِ — أربعَ عشرةَ مرحلة
A31: 1. الإشارةُ أو التحديد | B31: إشارةٌ آليةٌ من النظامِ أو تحديدٌ يدويٌّ من الإدارة · المخرَج: إشارةُ خطرٍ مسجَّلة | C31: المسؤول: المُنشئُ أو المحرّك
A32: 2. الفرز | B32: أيُهمَل أم يُربط بقائمٍ أم يُنشئ جديدًا أم يُصعَّد؟ · المخرَج: قرارُ فرزٍ بسببه | C32: المسؤول: محللُ المخاطر
A33: 3. التصنيف | B33: الوحدةُ والمجالُ والنطاقُ: مؤسسيٌّ أو إداريٌّ أو مشروعيٌّ أو موقعي · المخرَج: خطرٌ مصنَّف | C33: المسؤول: محللُ المخاطر
A34: 4. تعيينُ المالك | B34: مالكُ الخطرِ ومالكُ الضابطِ ومسؤولُ المعالجة · المخرَج: خطرٌ بمالكٍ معيَّن | C34: المسؤول: مديرُ المخاطر
A35: 5. التقييمُ المتأصل | B35: درجةُ الخطرِ قبل أيِّ ضابطٍ بأبعادِ الأثرِ الثمانية · المخرَج: تقييمٌ متأصلٌ مؤرَّخ | C35: المسؤول: مالكُ الخطرِ بمراجعةِ المخاطر
A36: 6. ربطُ الضوابط | B36: الضوابطُ الوقائيةُ والكاشفةُ والتصحيحيةُ القائمة · المخرَج: خريطةُ ضوابطِ الخطر | C36: المسؤول: مالكُ الضابط
A37: 7. تقييمُ فعاليةِ الضوابط | B37: أتعمل الضوابطُ فعلًا؟ بدليلِ تحققٍ لا بادعاء · المخرَج: تقريرُ فعاليةٍ بشاهده | C37: المسؤول: محللُ المخاطر
A38: 8. التقييمُ المتبقي | B38: درجةُ الخطرِ بعد الضوابطِ المثبَتة · المخرَج: تقييمٌ متبقٍّ مؤرَّخ | C38: المسؤول: مالكُ الخطرِ بتحدي المخاطر
A39: 9. مقارنةُ الشهية | B39: أالخطرُ المتبقي داخلَ الشهيةِ أم فوقها؟ · المخرَج: حكمُ شهيةٍ آلي | C39: المسؤول: محرّكُ الشهية
A40: 10. المعالجة | B40: تجنبٌ أو تقليلٌ أو نقلٌ أو قبولٌ — بخطةٍ ومسؤولٍ وموعد · المخرَج: خطةُ معالجةٍ مسنَدة | C40: المسؤول: مالكُ الخطر
A41: 11. الاعتمادُ أو القبول | B41: قرارٌ رسميٌّ بالسلطةِ المحددةِ في مصفوفة الاعتماد · المخرَج: قرارُ قبولٍ موقَّعٌ بمهلةِ مراجعة | C41: المسؤول: صاحبُ السلطةِ بحسب الدرجة
A42: 12. المراقبة | B42: مؤشراتُ الخطرِ والضابطِ تُقرأ من النظامِ آليًّا · المخرَج: تنبيهاتٌ ولوحاتُ حالة | C42: المسؤول: محرّكُ المؤشرات
... A44: 14. الإغلاقُ أو إعادةُ الفتح | B44: ◆ لا يُغلق بلا دليلِ تنفيذٍ وإعادةِ تقييمٍ واعتمادٍ بالسقف · المخرَج: محضرُ إغلاقٍ بشواهده | C44: المسؤول: صاحبُ السلطة

Sheet 24 — وحدات المخاطر
A1: الرمز | B1: الوحدة | C1: الإداراتُ المرتبطة | D1: نطاقُ التغطية | E1: المخرَج | F1: المعيارُ المرجعي
A2: RU-01 | B2: المخاطرُ المؤسسيةُ والاستراتيجية | C2: الرئيسُ التنفيذيُّ ومكتبُه | D2: الاستراتيجيةُ · النموُّ والتوسعُ · تركّزُ العملاءِ والمشروعاتِ · الجغرافيا · السياسيةُ والأمنيةُ · التنظيميةُ الناشئةُ · السمعةُ · المخاطرُ الناشئةُ · استمراريةُ الأعمالِ والأزمات | E2: سجلُّ المخاطرِ المؤسسيُّ ولوحةُ المخاطرِ العليا | F2: COSO ERM · ISO 31000
A3: RU-02 | B3: المخاطرُ التشغيليةُ والمواقع | C3: إدارةُ التشغيلِ وإدارةُ الموقع | D3: القدرةُ على تنفيذ الخطةِ · التوقفاتُ · فجواتُ المعداتِ · ضعفُ الإنتاجيةِ · حالةُ الطرقِ · ظروفُ الموقعِ · تعارضُ المعداتِ · ضعفُ التنسيقِ بين الوردياتِ · الدخولُ والخروجُ · الاتصالاتُ · تأخرُ الإقفالِ التشغيلي | E3: سجلُّ مخاطرِ التشغيلِ ولوحةُ مخاطرِ الموقع | F3: ISO 31000 · IEC 31010
A4: RU-03 | B4: مخاطرُ الصيانةِ والاعتمادية | C4: إدارةُ الصيانة | D4: الأعطالُ المتكررةُ · الصيانةُ الوقائيةُ المتأخرةُ · فشلُ الإصلاحِ · نقصُ الجاهزيةِ · أخطاءُ التشخيصِ · نقصُ قطعِ الغيارِ · تجاوزُ ساعاتِ الصيانةِ · العودةُ للخدمةِ بلا تحققٍ كافٍ | E4: سجلُّ مخاطرِ الصيانةِ وتحليلُ أنماطِ الفشل | F4: FMEA/FMECA · IEC 31010
A5: RU-04 | B5: مخاطرُ القوى التشغيلية | C5: القوى التشغيليةُ والموارد البشرية | D5: نقصُ المشغّلينَ · عدمُ ملاءمةِ التأهيلِ للمعدةِ · انتهاءُ الرخصِ · الإجهادُ والإرهاقُ · خللُ دوراتِ التناوبِ · غيابُ البديلِ · ضعفُ الكفاءةِ · عدمُ استقرارِ القوى بالموقع | E5: سجلُّ مخاطرِ القوى ولوحةُ الأهليةِ والرخص | F5: ISO 45001
A6: RU-05 | B6: مخاطرُ النقلِ والترحيل | C6: النقلُ والترحيل | D6: التأخرُ في التحريكِ · أعطالُ مركباتِ النقلِ · الطرقُ والمساراتُ · الحمولةُ · مخاطرُ الوصولِ · تعطلُ نقلِ العاملينَ · تأخرُ التعبئةِ · نقلُ المعداتِ بين المواقع | E6: سجلُّ مخاطرِ النقلِ وخريطةُ مخاطرِ المسارات | F6: ISO 39001 مرجعيًّا · IEC 31010
A7: RU-06 | B7: مخاطرُ سلسلةِ الإمدادِ والمشترياتِ والمخازن | C7: المشترياتُ التشغيليةُ والمخازنُ والموردون | D7: نفادُ الأصنافِ الحرجةِ · التأخرُ في الشراءِ · ضعفُ الموردِ · عدمُ مطابقةِ القطعِ · القطعُ المقلَّدةُ · تأخرُ الاستلامِ · أخطاءُ الصرفِ · المخزونُ الراكدُ · الوقودُ · المواد المقيَّدةُ · تركّزُ الموردينَ · أزمنةُ التوريد | E7: سجلُّ مخاطرِ الإمدادِ وتحليلُ التركّز | F7: ISO 28000 مرجعيًّا
A8: RU-07 | B8: المخاطرُ التعاقديةُ والتجارية | C8: المبيعاتُ والعقودُ وإدارةُ الموردين | D8: غموضُ نطاقِ العملِ · مؤشراتُ الأداءِ · الجزاءاتُ · الالتزاماتُ غيرُ المتوازنةِ · شروطُ الدفعِ · العملاتُ · تعديلُ الأسعارِ · التعبئةُ · الانتظارُ · ضمانُ الحدِّ الأدنى · القوةُ القاهرةُ · مسؤوليةُ الموقعِ · التأمينُ · الكفالاتُ · الإنهاءُ · التجديدُ · الملاحقُ · النزاعاتُ · نقلُ المخاطرِ للمقاولين | E8: مراجعةُ المخاطرِ قبل التعاقدِ وسجلُّ المخاطرِ التعاقدية | F8: ISO 31000 · Contract Risk Checklist
A9: RU-08 | B9: المخاطرُ الماليةُ والخزينة | C9: الماليةُ والخزينة | D9: التحصيلُ والائتمانُ · تركّزُ الذممِ · تجاوزُ حدودِ الائتمانِ · العملةُ وسعرُ الصرفِ · التعرضُ المفتوحُ · السيولةُ وفجوةُ التدفقاتِ · البنوكُ والدفعُ والاحتيالُ · المطابقةُ البنكيةُ · التقاريرُ والإقفالُ والتسوياتُ · القيودُ غيرُ المربوطةِ بوقائع | E9: سجلُّ المخاطرِ الماليةِ ولوحةُ التعرض | F9: COSO ERM · تحليلُ الحساسيةِ والضغط
A10: RU-09 | B10: مخاطرُ التمويلِ والملكيةِ والأصول | C10: التمويلُ والملكيةُ وإدارةُ الأسطول | D10: شروطُ التمويلِ · الأقساطُ · التعثرُ · التعهداتُ · الضماناتُ والرهونُ · ملكيةُ الأصلِ · حصصُ الملكيةِ · حقوقُ الممولِ وخروجُه · إعادةُ التمويلِ · تركّزُ التمويلِ · التأمينُ · استردادُ الأصلِ · تقادمُ الأصلِ · التركّزُ في نوعٍ واحدٍ · القيمةُ المتبقيةُ · عدمُ ملاءمةِ المعدةِ لطبيعةِ العقد | E10: سجلُّ مخاطرِ التمويلِ ومحفظةِ الأصول | F10: IEC 31010 · تحليلُ السيناريوهات
A11: RU-10 | B11: مخاطرُ السلامةِ والأمنِ والضوابطِ الحرجة | C11: الحوكمةُ والالتزامُ والموقعُ والتشغيل | D11: حركةُ المعداتِ الثقيلةِ · الاصطداماتُ · الرجوعُ للخلفِ · الانقلابُ · الطرقُ والمنحدراتُ · التعبُ والإجهادُ · النقاطُ العمياءُ · عزلُ الطاقةِ عند الصيانةِ · الحرائقُ والوقودُ · الرفعُ · الأعمالُ عاليةُ الخطورةِ · أمنُ الموقعِ · الاستجابةُ للطوارئ | E11: سجلُّ الأحداثِ عاليةِ العواقبِ ولوحةُ الضوابطِ الحرجة | F11: ◆ ISO 45001 · ICMM Critical Control Management
A12: RU-11 | B12: مخاطرُ التقنيةِ والبياناتِ واستمراريةِ الأعمال | C12: مكتبُ هندسةِ النظمِ والحوكمة | D12: أمنُ المعلوماتِ · الصلاحياتُ · تسربُ بياناتِ الكياناتِ · فسادُ البياناتِ · فشلُ المزامنةِ دون اتصالٍ · تعطلُ النظامِ · النسخُ الاحتياطيُّ والاستعادةُ · أهدافُ نقطةِ وزمنِ الاستعادةِ · واجهاتُ البرمجةِ · أداءُ النظامِ · فقدُ الاتصالِ بالمواقعِ · استمراريةُ الأعمالِ والتعافي | E12: سجلُّ مخاطرِ التقنيةِ وتحليلُ أثرِ الأعمال | F12: ISO 27001 · ISO 22301 مرجعيًّا

Sheet 25 — القياس والشهية
A1: الفئة | B1: البند | C1: التفصيل | D1: الحكم
A2: بُعدُ أثر | B2: السلامةُ والصحة | C2: إصابةٌ أو مرضٌ مهنيٌّ أو وفاة | D2: ◆ لا يُدمج مع غيره ولا يُقايَض بالمال
A3: بُعدُ أثر | B3: التشغيلُ والإنتاج | C3: توقفٌ أو انخفاضُ إنتاجٍ أو إخلالٌ بالخطة | D3: بالساعاتِ أو الوحداتِ المفقودة
A4: بُعدُ أثر | B4: المالُ والتعرض | C4: خسارةٌ مباشرةٌ أو تعرضٌ محتمل | D4: بالمدى: أدنى · متوقَّع · أقصى
A5: بُعدُ أثر | B5: العقدُ والقانون | C5: جزاءٌ أو نزاعٌ أو إخلالٌ أو مسؤوليةٌ قانونية | D5: بقيمةِ الجزاءِ أو أثرِ الإخلال
A6: بُعدُ أثر | B6: السمعة | C6: أثرٌ على العميلِ أو السوقِ أو الجهاتِ الرقابية | D6: بمدى الانتشارِ ومدةِ الأثر
A7: بُعدُ أثر | B7: البيئة | C7: تلوثٌ أو ضررٌ بيئيٌّ عند الانطباق | D7: بحجم الأثرِ وقابليةِ الإصلاح
A8: بُعدُ أثر | B8: البياناتُ والتقنية | C8: تسربٌ أو فقدٌ أو تعطلٌ أو فسادُ بيانات | D8: بعدد الكياناتِ المتأثرةِ ومدةِ التعطل
A9: بُعدُ أثر | B9: الأفرادُ والقدرة | C9: فقدُ كفاءاتٍ أو نزاعٌ عماليٌّ أو نقصُ قدرة | D9: بعدد المتأثرينَ ومدةِ التعافي
A10: عنصرُ قياس | B10: الخطرُ المتأصل | C10: درجةُ الخطرِ قبل أيِّ ضابط · احتمالٌ × أثرٌ بأبعاده الثمانية | D10: تُقاس أولًا ولا تُتجاوز
A11: عنصرُ قياس | B11: فعاليةُ الضوابط | C11: أتعمل الضوابطُ القائمةُ فعلًا؟ · فعّالٌ · فعّالٌ جزئيًّا · غيرُ فعّالٍ · غيرُ مُثبَت | D11: ◆ بدليلِ تحققٍ لا بادعاء
A12: عنصرُ قياس | B12: الخطرُ المتبقي | C12: درجةُ الخطرِ بعد الضوابطِ المثبَتة · المتأصلُ معدَّلًا بفعاليةِ الضوابط | D12: ◆ عليها يُبنى قرارُ القبول
... A38: نمطُ خطة | B38: الحمايةُ والانكماش | C38: الهدفُ حمايةُ السيولةِ والأصولِ في ظرفٍ صعب · ◆ تُخفض الشهيةُ في المجالاتِ كلِّها | D38: وتُرفع حدودُ التصعيدِ فيصل للرئيسِ ما كان يُحسم أدنى · ويُراجَع كلُّ قبولٍ سابقٍ للخطر

Sheet 26 — الضوابط والمؤشرات
A1: الفئة | B1: البند | C1: التفصيل | D1: المصدرُ أو الحكم
A2: حقلُ ضابط | B2: المعرّف | C2: رمزٌ فريدٌ للضابط | D2: إلزامي
A3: حقلُ ضابط | B3: النوع | C3: وقائيٌّ · كاشفٌ · تصحيحي | D3: إلزامي
A4: حقلُ ضابط | B4: المالك | C4: من يشغّل الضابطَ فعلًا | D4: إلزامي
A5: حقلُ ضابط | B5: العمليةُ التي ينفَّذ فيها | C5: أينَ يقع في الدورة | D5: إلزامي
A6: حقلُ ضابط | B6: التكرار | C6: كلَّ ورديةٍ · يوميًّا · أسبوعيًّا · شهريًّا · عند الحدث | D6: إلزامي
A7: حقلُ ضابط | B7: دليلُ التنفيذ | C7: ما يُثبت أنه نُفِّذ فعلًا | D7: ◆ إلزاميٌّ — ولا يُحتسب الضابطُ بدونه
A8: حقلُ ضابط | B8: آخرُ تحققٍ ونتيجتُه | C8: التاريخُ والنتيجةُ ومن تحقق | D8: إلزامي
A9: حقلُ ضابط | B9: الفعالية | C9: فعّالٌ · فعّالٌ جزئيًّا · غيرُ فعّالٍ · غيرُ مُثبَت | D9: إلزامي
A10: حقلُ ضابط | B10: تاريخُ التحققِ التالي | C10: متى يُعاد التحقق | D10: إلزامي
A11: ضابطٌ حرج | B11: الحدثُ عاليُ العواقبِ الذي يمنعه | C11: ما الكارثةُ التي يقف أمامها | D11: ◆ إلزاميٌّ للحرج
A12: ضابطٌ حرج | B12: معيارُ الأداء | C12: ما الحدُّ الذي يُعدُّ الضابطُ عنده عاملًا | D12: ◆ إلزامي
... A71: قرارُ فرز | B71: يُصعَّد فورًا | C71: تعرضٌ حرجٌ لا يحتمل الدورةَ العادية | D71: ◆ يصل للرئيس التنفيذيِّ في اليوم نفسه

Sheet 27 — أدوار المخاطر
A1: الفئة | B1: البند | C1: التفصيل | D1: الحدُّ أو الحكم
A2: دور | B2: Risk Owner — مالكُ الخطر | C2: مديرُ الإدارةِ المسؤولةِ عن التعرض · يقيّم ويعالج ويقبل ضمن سقفه | D2: ◆ لا يقبل خطرًا فوقَ سقفه منفردًا
A3: دور | B3: Control Owner — مالكُ الضابط | C3: من يشغّل الضابطَ فعلًا · ينفّذ الضابطَ ويقدّم دليلَ تنفيذه | D3: ◆ لا يتحقق من ضابطِ نفسِه
A4: دور | B4: Action Owner — مسؤولُ المعالجة | C4: من ينفّذ إجراءَ المعالجة · ينفّذ ويقدّم دليلَ الإنجاز | D4: ويظهر الإجراءُ في مهامِّه
A5: دور | B5: Risk Analyst — محللُ المخاطر | C5: من إدارةِ المخاطر · يفرز ويصنّف ويتحدى التقييمَ ويراقب | D5: ◆ لا يملك الخطرَ ولا يقبله
A6: دور | B6: Risk Manager — مديرُ المخاطر | C6: رئيسُ إدارةِ المخاطر · يملك الإطارَ والتصنيفَ والمنهجَ والتصعيدَ ويعتمد الشهيةَ المقترحة | D6: ◆ يتبع الرئيسَ التنفيذيَّ مباشرةً
A7: دور | B7: Risk Approver — مُقِرُّ الخطر | C7: صاحبُ السلطةِ بحسب الدرجة · يقبل الخطرَ المتبقيَ رسميًّا بمهلةِ مراجعة | D7: بحسب مصفوفةِ الاعتماد
A8: دور | B8: Executive Owner — المالكُ التنفيذي | C8: النائبُ أو الرئيسُ عند التصعيد · يحسم ما تجاوز سقفَ الإدارة | D8: والمخاطرُ الحرجةُ تصله إلزامًا
A9: دور | B9: Independent Verifier — المتحقِّق المستقل | C9: من غيرِ مالكِ الضابط · يتحقق من الضوابطِ الحرجةِ بدليل | D9: ◆ إلزاميٌّ للضوابطِ الحرجةِ وحدَها
A10: مستوى خطر | B10: منخفض | C10: يقبله مالكُ الخطرِ نفسُه · يُراجَع سنويًّا | D10: لا تصعيد · يُسجَّل ويُراقب
A11: مستوى خطر | B11: متوسط | C11: يقبله مالكُ الخطرِ بمراجعةِ محللِ المخاطر · يُراجَع نصفَ سنويّ | D11: إشعارُ مديرِ المخاطر · خطةُ معالجةٍ إلزامية
A12: مستوى خطر | B12: مرتفع | C12: يقبله ◆ النائبُ المختصُّ — لا مالكُ الخطرِ منفردًا · يُراجَع ربعَ سنويّ | D12: تصعيدٌ لمديرِ المخاطرِ والنائب · معالجةٌ بمهلةٍ ومسؤول
... A49: سيناريو قبول | B49: مديرُ المخاطرِ لا يُخفي خطرًا حرجًا | C49: عند محاولةُ إخفاءٍ من لوحةِ الرئيس | D49: المتوقَّع: رفضٌ — والتصعيدُ آليٌّ بالمصفوفة

Sheet 28 — التصنيف الخماسي والدَّين
A1: الفئة | B1: البند | C1: التعريف | D1: المصدر | E1: العدد | F1: الحكم
A2: مقياس | B2: Screen Definition — تعريفُ الشاشة | C2: ملفُّ شاشةٍ فريدٌ له غرضٌ ومالكٌ وأعمدةٌ وأفعال | D2: NAV-09 · ملفاتُ الشاشات | E2: ٢٠٦ | F2: ◆ الوحدةُ الوحيدةُ التي تُقاس بها «كم شاشةً في النظام»
A3: مقياس | B3: Navigation Appearance — ظهورُ تنقّل | C3: ظهورُ شاشةٍ في السايدبار لدورٍ ونطاقٍ بعينه | D3: nav_items | E3: ١٠٧٥ | F3: الشاشةُ الواحدةُ تظهر لأدوارٍ عدةٍ — والعددُ لا يساوي عددَ الشاشات
A4: مقياس | B4: Route Instance — نسخةُ مسار | C4: مسارٌ حيٌّ يستقبل طلبًا — قد يخدم شاشةً أو جزءًا منها | D4: القاعدةُ الحية · modules | E4: ٣١٠ | F4: ◆ يشمل مساراتٍ فنيةً ومكرَّرةَ الغرضِ — ولا يُقاس به عددُ الشاشات
A5: مقياس | B5: UX Adoption Unit — وحدةُ تبنٍّ | C5: وحدةٌ يُقاس عليها تبنّي معيارِ الشاشات | D5: عدّادُ التبنّي | E5: ٢٨٨ | F5: مقامُ نسبِ التبنّي وحدَه — ولا يُخلط بغيره
A6: مقياس | B6: Governing Column Unit — وحدةُ أعمدةٍ حاكمة | C6: وحدةٌ تُقاس بمعيار الأعمدة الحاكمة | D6: فاحصُ الحوكمة | E6: ٢٨٨ | F6: ٢٦٣ مكتملٌ · ٢٥ معلَنٌ بدفتر
A7: مقياس | B7: Action Definition — تعريفُ فعل | C7: رمزُ فعلٍ فريدٌ في القاموس بمعنًى واحد | D7: قاموسُ الأفعال | E7: ٢٤٤ | F7: ◆ المعنى لا الظهور
A8: مقياس | B8: Action Instance — نسخةُ فعل | C8: ظهورُ الفعلِ زرًّا في شاشةٍ بعينها | D8: الشاشاتُ والأزرار | E8: ٣١٦ | F8: الرمزُ الواحدُ قد يظهر زرًّا في أكثرَ من شاشة
A9: مقياس | B9: ◆ الحكمُ الملزم | C9: كلُّ نسبةٍ تُعلَن تذكر مقياسَها ومقامَه ومصدرَه وتاريخَ قياسه | D9: — | E9: — | F9: ولا نسبةَ بلا هذه الأربعة
A10: سجلُّ دَين | B10: Release Blockers — حواجزُ الإصدار | C10: لا يُطلَق قبل إغلاقها بالحالات الثلاث | D10: — | E10: — | F10: ◆ لا يُنقل بندٌ منها إلى غيرها لتجميلِ نسبةِ الإنجاز — والنقلُ يحتاج قرارَ مالكٍ موثَّقًا بحيثياته
A11: سجلُّ دَين | B11: Architectural Debt — دَينٌ معماري | C11: بنيةٌ تحتاج قرارًا وخطةً — لا تمنع الإطلاقَ بذاتها | D11: — | E11: — | F11: تتراكم فتصير حاجزًا إن أُهملت — وتُراجَع كلَّ إصدار
A12: سجلُّ دَين | B12: Adoption Debt — دَينُ تبنٍّ | C12: عدّاداتٌ ترتفع بالعملِ لا بالقرار | D12: — | E12: — | F12: ارتفاعُها دليلُ تقدمٍ — والصدقُ في إعلانها أهمُّ من رقمها
... A34: بوابةُ إغلاق | B34: G7 · القبولُ والإطلاق | C34: محضرٌ أحدثُ من آخرِ تغييرٍ وتواقيعُ مكتملةٌ وتمرينُ رجوعٍ ناجحٌ وملاحظةُ إصدارٍ ومراقبةُ ما بعدَه وقرارُ المضيِّ | D34: الرئيسُ التنفيذي | E34: — | F34: لا تُقفز

Sheet 29 — إعادة بناء الواجهة
A1: الفئة | B1: الرمز | C1: البند | D1: المواصفةُ أو الحكم | E1: معيارُ القبول
A2: قشرة | B2: AS-01 | C2: الشريطُ العلوي | D2: ٥٦–٦٤ بكسلًا · شعارٌ في طرفٍ ومبدّلُ سياقٍ في الوسطِ وأربعةُ أفعالٍ عالميةٍ في الطرف · ◆ يُلغى الصندوقان الزائدان — الإدارةُ والمسمّى والموظفُ تندمج في مبدّلٍ واحد | E2: صفرُ شريطٍ يتجاوز ٦٤ بكسلًا · وصفرُ أكثرَ من خمسةِ أفعالٍ ظاهرة
A3: قشرة | B3: AS-02 | C3: مبدّلُ السياق | D3: عنصرٌ واحدٌ يعرض «الإدارة — الصفةُ النشطة» ويفتح: الصفةَ والإدارةَ والنطاقَ وتبديلَ الصفة · ◆ اسمُ الشخصِ في قائمةِ الحسابِ لا صندوقًا ثالثًا دائمًا | E3: المستخدمُ بصفتين يعرف بأيِّهما يعمل في أقلَّ من ثانيتين
A4: قشرة | B4: AS-03 | C4: السايدبار | D4: حالتان فقط: موسَّعٌ ٢٦٤ بكسلًا · ومختصرٌ ٦٨ بكسلًا بأيقوناتٍ وتلميح · ◆ لا ترقيمَ «أولًا/ثانيًا» في النصِّ اليوميِّ · والمجموعةُ المفتوحةُ ظاهرةٌ والعنصرُ النشطُ مميَّز | E4: صفرُ عنصرٍ مكرر · وصفرُ عنصرٍ لا يملكه المستخدم
A5: قشرة | B5: AS-04 | C5: عنوانُ الصفحة | D5: سطرٌ واحدٌ بالعنوانِ وسطرٌ ثانٍ صغيرٌ بالأرقامِ السياقية · ◆ لا ترويسةً برتقاليةً تملأ ربعَ الشاشة | E5: الجدولُ يبدأ في أول ٣٠٪ من ارتفاع الصفحة
A6: قشرة | B6: AS-05 | C6: شريطُ الأفعال | D6: إجراءٌ رئيسٌ واحدٌ مملوءٌ · وبحثٌ · ومنظرٌ محفوظٌ · وفلاترُ · وتخصيصُ أعمدةٍ · وتصديرٌ · وقائمةُ أفعال · ◆ ثلاثةُ مستوياتٍ بصريةٍ لا لونيةٍ فقط — ولا تسعةُ أزرارٍ متساويةِ الوزن | E6: المستخدمُ يميّز الإجراءَ الرئيسَ من الثانويِّ بلا قراءة
A7: قشرة | B7: AS-06 | C7: شريطُ الفلاتر | D7: مطويٌّ افتراضيًّا · يُظهر عددَ المفعَّلِ ويتيح تفريغَه بضغطة · والبحثُ داخلَ شريطِ أدواتِ الجدولِ لا بعيدًا عنه | E7: صفرُ فلترٍ مفعَّلٍ لا يظهر عدَدُه
A8: قشرة | B8: AS-07 | C8: منطقةُ المحتوى | D8: شبكةُ اثني عشرَ عمودًا · حاشيةٌ ٢٤–٣٢ · بين البطاقاتِ ١٦–٢٤ · حشوةُ البطاقةِ ٢٠–٢٤ · ◆ وأقصى عرضِ محتوًى ١٤٤٠ يتوسط فوقه | E8: صفرُ تمريرٍ أفقيٍّ للصفحةِ على ١٢٨٠ فأعلى
A9: قشرة | B9: AS-08 | C9: التنبيهاتُ والبلاغ | D9: جرسٌ بعددٍ حقيقيٍّ · وزرُّ بلاغٍ سياقيٌّ ثابتُ الموضع · ◆ ورسائلُ النظامِ تُعرض في الشاشةِ لا في الرابط | E9: صفرُ رسالةِ حوكمةٍ تظهر في شريط العنوان
A10: مكوّن | B10: UI-01 | C10: Page Header | D10: العنوانُ والأرقامُ السياقيةُ ومسارُ التنقل | E10: صفرُ ترويسةٍ مختلفةٍ بلا مبرر
A11: مكوّن | B11: UI-02 | C11: Toolbar | D11: الإجراءُ الرئيسُ والبحثُ والمناظرُ والتصدير | E11: ثلاثةُ مستوياتٍ بصرية
A12: مكوّن | B12: UI-03 | C12: Filter Bar | D12: مطويٌّ بعدَّادٍ وتفريغٍ بضغطة | E12: يعرض عددَ المفعَّل
... A54: ◆ تمييز | B54: — | C54: ◆ تمييزٌ لازم | D54: بوابةُ التسليمِ الوظيفيةُ العشرون في خطِّ التسليم (التنقلُ والحوكمةُ والأفعالُ والعزلُ والطوبولوجيا) ليست الفحوصَ البصريةَ العشرين في النظام التصميمي (اللونُ والمكوّنُ والغلافُ والمنظرُ والعمودُ الحاكمُ ومساحةُ اللمس). عشرون ضدَّ عشرين بمضمونين مختلفين — فتُسمّى الأولى «بوابةَ التسليم الوظيفية» والثانيةُ «بوابةَ القبول البصري»، ولا يُقرأ نجاحُ إحداهما نجاحًا للأخرى. | E54: لا يُقرأ نجاحُ إحداهما للأخرى

Sheet 30 — عيوب النظام الحي
A1: الرمز | B1: العيب | C1: الخطورة | D1: الشاهدُ المرصود | E1: السبب | F1: المالك | G1: دليلُ الإغلاق
A2: UI-DEF-01 | B2: المسمّى الوظيفيُّ يعرض اسمَ الشخصِ بدل المسمّى | C2: حرجة | D2: ظهر في ستِّ شاشاتٍ بصفةِ «الإدارة التنفيذية» وصحيحًا بصفةِ «مسؤول التشغيل» | E2: عيبُ ربطِ حقلٍ لا عيبُ تصميم | F2: الحوكمةُ ومكتبُ الهندسة | G2: الحقلُ يعرض المسمّى في كل الصفاتِ الـ27
A3: UI-DEF-02 | B3: عدّادُ العقودِ يعرض صفرًا واللوحةُ فيها ٢٥٠ عقدًا | C3: ◆ حرجة | D3: لوحةُ الرئيسِ تعرض العملاءَ والمشاريعَ والمستخدمينَ والعقودَ صفرًا · وشاشةُ العقودِ تعرض ٢٥٠ | E3: ◆ استعلامٌ مكسورٌ لا نطاقٌ خاطئ — ويضرب الثقةَ في كل رقمٍ آخر | F3: المالكُ الوظيفيُّ للوحة | G3: العدّادُ يطابق الجدولَ المصدرَ في كل نطاق
A4: UI-DEF-03 | B4: عدّادٌ أكبرُ من مقامِ بياناتِه المحتمل | C4: عالية | D4: «٤٨٧٤٦ وحدةً تنتظر الاعتماد» وإجماليُّ الوحداتِ في القاعدةِ ٤٨٥٢٥ | E4: إما يعدّ شيئًا آخرَ أو أحدُهما خطأ — ولا مقامَ معلَنًا | F4: مكتبُ الهندسة | G4: كلُّ عدّادٍ يذكر مقامَه ومصدرَه بحسب التصنيف الخماسي
A5: UI-DEF-04 | B5: الجدولُ يبلغ صفرَ أعمدةٍ بعد «إخفاء الكل» | C5: عالية | D5: بقي عمودان فقط والحالةُ حُفظت — والمستخدمُ يرى جدولًا فارغًا لا يعرف سببَه | E5: لا حارسَ يمنع إخفاءَ كلِّ الأعمدة | F5: فريقُ الواجهة | G5: UI-06 يمنع النزولَ تحت حدٍّ أدنى ويبيّن السبب
A6: UI-DEF-05 | B6: تكرارُ عناصرَ في السايدبار | C6: متوسطة | D6: «للخاطر والقرارات العليا» و«للخاطر التجارية» ظهر كلٌّ مرتين | E6: ◆ خطأُ توليدٍ لا يكشفه فاحصُ التنقل | F6: مكتبُ الهندسة | G6: فاحصُ التنقلِ يكشف التكرارَ ويوقف التوليد
A7: UI-DEF-06 | B7: رسالةُ حوكمةٍ تظهر في شريط العنوانِ ولا تُعرض في الشاشة | C7: متوسطة | D7: «الشاشةُ غيرُ مسجَّلة — فلا تُمنح صلاحيتُها لأحد» تُمرَّر في الرابط | E7: الحكمُ ضاع — والمستخدمُ لا يراه | F7: فريقُ الواجهة | G7: UI-13 يعرضها في الشاشةِ وصفرُ رسالةٍ في الرابط
A8: UI-DEF-07 | B8: الرسمُ يعرض محاورَ افتراضيةً بلا بيانات | C8: عالية | D8: «مسارُ الأداء اليومي» من ‎−١ إلى ١ بخطٍّ مسطحٍ عند الصفر | E8: سلوكٌ افتراضيٌّ للمكتبةِ يبدو خللًا | F8: فريقُ الواجهة | G8: UI-17: لا رسمَ بلا بياناتٍ — بل حالةٌ فارغةٌ مفسَّرة
A9: UI-DEF-08 | B9: أصفارٌ عملاقةٌ بدل حالةٍ فارغة | C9: عالية | D9: «٠٠» بحجمٍ ضخمٍ في أربعِ بطاقاتٍ على مساحةٍ برتقاليةٍ واسعة | E9: يبدو خللًا أو نائبَ محتوًى لا حالةً محكومة | F9: فريقُ الواجهة | G9: UI-11 يعرض السببَ والإجراءَ لا رقمًا
A10: UI-DEF-09 | B10: اللونُ المؤسسيُّ يملأ ولا يوجّه | C10: عالية | D10: البرتقاليُّ يملأ الترويسةَ والفلاترَ والبطاقاتِ ونصفَ اللوحة | E10: يلغي التسلسلَ البصريَّ ويضعف دلالاتِ الخطرِ والنجاح | F10: فريقُ التصميم | G10: الواجهةُ محايدةٌ والمؤسسيُّ لونُ تمييزٍ محدود
A11: UI-DEF-10 | B11: لا شبكةَ محاذاةٍ ولا سلّمَ مسافات | C11: عالية | D11: بطاقاتٌ متفاوتةٌ وفراغاتٌ بلا وظيفةٍ وعناصرُ من خطوطٍ مختلفة | E11: الصفحاتُ لا تتبع شبكةً ولا سلّمًا موحَّدًا | F11: فريقُ التصميم | G11: AS-07: شبكةُ اثني عشرَ وسلّمُ مسافاتٍ من ٤
A12: UI-DEF-11 | B12: الخطوطُ والأرقامُ والتواريخُ غيرُ متسقة | C12: متوسطة | D12: أحجامٌ متعددةٌ · وتاريخٌ إنجليزيٌّ في واجهةٍ عربيةٍ · وأرقامٌ مختلطة | E12: لا سلّمَ خطوطٍ موحَّدًا ولا حكمًا للأرقامِ والتقويم | F12: فريقُ التصميم | G12: أحدَ عشرَ نمطًا · والغربيةُ للتخزينِ والميلاديُّ للحساب
... A14: ◆ | B14: الحكم | C14: — | D14: لا يقتصر الفحصُ على الاثني عشرَ — بل تدقيقٌ بصريٌّ كاملٌ بقائمةِ الفحصِ المعتمدة | E14: — | F14: فريقُ الواجهة | G14: تقريرُ تدقيقٍ يغطي كلَّ شاشةٍ مؤهَّلة

Sheet 31 — حد التسليم
A1: المخرَج | B1: الحال | C1: السبب
A2: ① وثائقٌ ومواصفاتٌ حاكمة | B2: ✔ أستطيع | C2: المواصفةُ الكاملةُ بأحكامها الذريةِ وشواهدِ قبولها
A3: ② سجلاتُ عيوبٍ وقراراتٍ وبوابات | B3: ✔ أستطيع | C3: بحقولها كاملةً ومالكٍ ومهلةٍ ودليلِ إغلاق
A4: ③ تصنيفُ المقاييسِ ومصالحةُ الأرقام | B4: ✔ أستطيع | C4: بالتصنيفِ الخماسيِّ وتاريخِ كلِّ قياس
A5: ④ خططُ الهجرةِ والدفعاتِ والترتيب | B5: ✔ أستطيع | C5: بالاعتماديةِ والمخاطرةِ والشاهد
A6: ◆ ⑤ الكودُ والهجراتُ والتحديثات | B6: ✘ لا أستطيع | C6: لا وصولَ لي إلى النظام العاملِ ولا مستودعِه
A7: ◆ ⑥ القياساتُ الحيةُ من القاعدة | B7: ✘ لا أستطيع | C7: p95 والاستعادةُ والحملُ تُقاس على بيئتكم
A8: ◆ ⑦ تقريرُ قلبِ الصلاحيات | B8: ✘ لا أستطيع | C8: يُنتَج بعد التنفيذِ الفعليِّ لا قبله
A9: ◆ ⑧ محضرُ القبولِ وتواقيعُه | B9: ✘ لا أستطيع | C9: بيدِ مستخدمي الشركةِ حصرًا
A10: ◆ ⑨ تقريرُ تبنّي الواجهة | B10: ✘ لا أستطيع قياسَه | C10: ◆ لكنّي أسلّم مواصفتَه وقائمةَ فحصِه وعدّاداتِه
A11: ◆ ⑩ تقريرُ ترحيلِ المخاطرِ ومنعِ التكرار | B11: ✘ لا أستطيع تنفيذَه | C11: ◆ لكنّي أسلّم منهجَه ومفتاحَ منعِ التكرارِ وشاهدَ قبوله

Sheet 32 — الميداني والتكرار والحوكمة
A1: الفئة | B1: البند | C1: التفصيل | D1: الحكم
A2: مخاطرُ الميدان | B2: رفعُ إشارةِ خطرٍ من الميدان | C2: نعم — بصورةٍ وموقعٍ ومعدةٍ ووردية | D2: تدخل الفرزَ ولا تُنشئ خطرًا
A3: مخاطرُ الميدان | B3: العملُ دون اتصال | C3: نعم — تُحفظ محليًّا وتُزامن لاحقًا | D3: والضغطُ يحفظ قبل الشبكة
A4: مخاطرُ الميدان | B4: حالةُ المزامنةِ ظاهرة | C4: نعم — بعددِ المعلَّقِ وأعمارِه | D4: ولا تُخفى
A5: مخاطرُ الميدان | B5: منعُ التكرار | C5: مفتاحٌ لكل إشارةٍ ميدانية | D5: إعادةُ المزامنةِ ترجع مرجعَ الأولى
A6: مخاطرُ الميدان | B6: التقاطُ الصور | C6: من الكاميرا مباشرةً بضغطِ حجمٍ محكوم | D6: وتُرفع عند عودةِ الاتصال
A7: مخاطرُ الميدان | B7: تسجيلُ دليلِ ضابط | C7: نعم لمالكِ الضابطِ في الموقع | D7: ◆ والفعاليةُ يحكمها متحقِّقٌ مستقل
A8: مخاطرُ الميدان | B8: استلامُ إجراءِ معالجة | C8: نعم — يظهر في مهامِّه الميدانية | D8: ويُغلق بقبولِ المتحقِّق
A9: مخاطرُ الميدان | B9: ◆ مساحةُ اللمس | C9: ستةٌ وخمسون بكسلًا للاستعمالِ بقفاز | D9: لا أربعةٌ وأربعون
A10: مخاطرُ الميدان | B10: ◆ التعارض | C10: تعديلان من جهازين يُعرضان ولا يُدمجان صامتًا | D10: بمكوّن التعارضِ والمصالحة
A11: منعُ التكرار | B11: مكوّناتُ المفتاح | C11: الوحدةُ + الكيانُ المتأثرُ + السببُ الجذريُّ + النطاقُ (موقعٌ/عقدٌ/معدةٌ/موردٌ) + نافذةُ الزمن | D11: ◆ لا يدخل اسمُ الإدارةِ العارضةِ في المفتاح — فالإدارةُ زاويةٌ لا هوية
A12: منعُ التكرار | B12: قاعدةُ التطابق | C12: خطران بالمفتاحِ نفسِه في نافذةٍ زمنيةٍ واحدةٍ = خطرٌ واحدٌ بزاويتين | D12: ويُدمجان بقرارِ محللِ المخاطرِ لا آليًّا
... A26: حوكمةُ إدارتي | B26: ◆ الحكم | C26: مكوّنٌ نطاقيٌّ واحدٌ على مصادرِ الحوكمةِ المركزية | D26: لا نظامَ حوكمةٍ مستقلٌّ لكل إدارة

Sheet 33 — التصحيحات بعد التدقيق
A1: الفئة | B1: البند | C1: التفصيل | D1: الحالُ المقيس | E1: الحكمُ أو دليلُ الإغلاق
A2: مقياسٌ مصحَّح | B2: Screen Definition — تعريفُ الشاشة | C2: ملفُّ شاشةٍ فريدٌ بغرضٍ ومالكٍ وأعمدةٍ وأفعال · المصدر: nav09_file_map | D2: القيمة ٢٠٦ · القياس 2026-08-08 | E2: ✔ مطابقٌ للقياس الحي · ◆ الوحدةُ الوحيدةُ التي يُقاس بها «كم شاشةً في النظام»
A3: مقياسٌ مصحَّح | B3: Navigation Appearance — ظهورُ تنقّل | C3: ظهورُ شاشةٍ في السايدبار لدورٍ ونطاق · المصدر: nav_items · active | D3: القيمة ١١١٠ · القياس 2026-08-08 | E3: ◆ صُحِّح من ١٠٧٥ — الزيادةُ ٣٥ من أفعال المخاطر · الشاشةُ الواحدةُ تظهر لأدوارٍ عدةٍ — ولا يُقاس به عددُ الشاشات
A4: مقياسٌ مصحَّح | B4: Route Instance — نسخةُ مسار | C4: مسارٌ حيٌّ مسجَّلٌ في جدولِ الوحدات · المصدر: modules — حصرًا | D4: القيمة ٣٢٠ · القياس 2026-08-08 | E4: ◆ صُحِّح من ٣١٠ · ◆ والمصدرُ محسومٌ modules حصرًا · ◆ وأيُّ أداةٍ تقيسه من nav_items تقيس مقياسًا آخرَ ولا تسمّيه بهذا الاسم
A5: مقياسٌ مصحَّح | B5: UX Adoption Unit — وحدةُ تبنٍّ | C5: وحدةٌ يُقاس عليها تبنّي معيارِ الشاشات · المصدر: عدّادُ التبنّي — بمقامٍ كاملٍ لا مستبعِد | D5: القيمة ٣٤٦ · القياس 2026-08-08 | E5: ◆ صُحِّح من ٢٨٨ — فالمقامُ القديمُ يستبعد ١١ مجلدًا فيها ٦١ شاشةً حية · ◆ ومنها مجلدُ المخاطرِ بعشرِ شاشاتِه — وهو الوحيدُ الذي تبنّى المكوناتِ فعلًا
A6: مقياسٌ مصحَّح | B6: Governing Column Unit — وحدةُ أعمدةٍ حاكمة | C6: وحدةٌ تُقاس بمعيار الأعمدةِ الحاكمة · المصدر: فاحصُ الحوكمة | D6: القيمة ٣٤٦ · القياس 2026-08-08 | E6: ◆ ٢٩٠/٣٤٦ بالمقامِ الكاملِ · و٢٦٣/٢٨٨ بالقديم · ويُعلَن بالمقامِ الكاملِ لا المستبعِد
A7: مقياسٌ مصحَّح | B7: Action Definition — تعريفُ فعل | C7: رمزُ فعلٍ فريدٌ بمعنًى واحدٍ في القاموس · المصدر: nav09_action_map | D7: القيمة ٢٧٢ · القياس 2026-08-08 | E7: ◆ صُحِّح من ٢٤٤ — الزيادةُ ٢٨ فعلًا للمخاطرِ و٥ مرادفات · المعنى لا الظهور — وصفرُ رمزٍ بمعنيين
A8: مقياسٌ مصحَّح | B8: Action Instance — نسخةُ فعل | C8: ظهورُ الفعلِ زرًّا في شاشةٍ بعينها · المصدر: مسحُ الشاشاتِ — منهجٌ معلَنٌ بسقفٍ ظنيّ | D8: القيمة ◆ يُقاس ولا يُنقل · القياس 2026-08-08 | E8: ◆ سُحب الرقمُ ٣١٦ — كان تقديرًا قبليًّا لا قياسًا · ◆ ولا يُنشر رقمٌ له قبل قياسٍ بمنهجٍ معلَنٍ وحدٍّ ظنيٍّ مذكور
A9: مقياسٌ مصحَّح | B9: ◆ الحكمُ الملزم | C9: كلُّ نسبةٍ تذكر مقياسَها ومقامَه ومصدرَه وتاريخَ قياسه · المصدر: — | D9: القيمة — · القياس — | E9: ◆ والأربعةُ معًا لا واحدٌ منها · ◆ ولا يُنشر رقمٌ لم يُقَس — والتقديرُ يُوسَم تقديرًا صريحًا
A10: عيبُ قياس | B10: MD-01 · مقامُ التبنّي يستبعد أحدَ عشرَ مجلدًا فيها إحدى وستون شاشةً حية | C10: العدّادُ الرسميُّ يبلّغ «المكونات ٢/٢٨٨» والقياسُ الكاملُ ٥/٣٤٦ — ومجلدُ المخاطرِ بعشرِ شاشاتِه مستبعَدٌ وهو الوحيدُ المتبنّي فعلًا | D10: حرجة · المالك مكتبُ الهندسة | E10: ◆ العدّادُ يُخفي إنجازَه هو — والاستبعادُ غيرُ معلَنٍ في تعريفِ المقياس · الإغلاق: المقامُ الكاملُ ٣٤٦ معلَنٌ · وأيُّ استبعادٍ مذكورٌ بمجلداتِه وسببِ كلٍّ
A11: عيبُ قياس | B11: MD-02 · «Route Instance» يُقاس بمنهجين تحت اسمٍ واحد | C11: الوثيقةُ تعلن المصدرَ modules · والأداةُ تقيس nav_items — والفرقُ ٣٢٠ مقابلَ ١٠٣٧ | D11: حرجة · المالك مكتبُ الهندسة | E11: ◆ منهجان تحت اسمٍ واحدٍ يُنتجان رقمين لا يُقارَنان · الإغلاق: المصدرُ محسومٌ modules حصرًا · وما يُقاس من nav_items يُسمّى Navigation Appearance
A12: عيبُ قياس | B12: MD-03 · رقمٌ نُشر بلا قياس — Action Instance | C12: نُشر ٣١٦ وهو تقديرٌ قبليٌّ باعترافِ الأداةِ نفسِها | D12: عالية · المالك مكتبُ الهندسة | E12: ◆ خرقٌ لقاعدةِ «كلُّ نسبةٍ بمصدرِها وتاريخِ قياسها» — والقاعدةُ من الوثيقةِ نفسِها · الإغلاق: الرقمُ مسحوبٌ حتى يُقاس · وكلُّ تقديرٍ موسومٌ تقديرًا صريحًا
... A73: تقسيمُ البوابة | B73: ◆ الحكم | C73: لا تُعلَن G5 خضراءَ قبل الثلاثةِ معًا · تُقاس بـ— | D73: ◆ والإعلانُ بواحدةٍ منها هو ما وقع | E73: ◆ وRSK-U5 حذّر منه نصًّا

Sheet 34 — سلّم تشخيص الفتح
A1: # | B1: ما يُفحص | C1: الرمز | D1: ما يُعرض للمستخدم | E1: من يملك الإصلاح
A2: 1 | B2: أالحسابُ موجودٌ ونشط؟ | C2: ACC-404 | D2: الحسابُ غيرُ موجودٍ أو معطَّل — ومن يفعّله | E2: الحوكمةُ والالتزام
A3: 2 | B3: أللحسابِ دورٌ مسنَد؟ | C3: ROLE-404 | D3: لا دورَ مسنَدًا لهذا الحساب — ومن يُسنده | E3: الحوكمةُ والالتزام
A4: 3 | B4: ◆ أللدورِ وحدةٌ تنظيميةٌ مربوطة؟ | C4: UNIT-404 | D4: ◆ الدورُ بلا وحدةٍ تنظيمية — ولا يرى شيئًا حتى يُربط | E4: الحوكمةُ والالتزام
A5: 4 | B5: أللحسابِ مسمًّى وظيفيٌّ مربوط؟ | C5: TITLE-404 | D5: لا مسمًّى مربوطًا — والمسمّى من سجلِّ المسمياتِ لا من الاسم | E5: الموارد البشرية
A6: 5 | B6: أالشاشةُ مسجَّلةٌ في نظام الشاشات؟ | C6: SCR-404 | D6: الشاشةُ غيرُ مسجَّلة — فلا تُمنح صلاحيتُها لأحد | E6: مكتبُ الهندسة
A7: 6 | B7: أللدورِ وحدةُ صلاحياتٍ على هذه الشاشة؟ | C7: PERM-403 | D7: الصلاحيةُ غيرُ ممنوحةٍ — ومن يمنحها | E7: الحوكمةُ والالتزام
A8: 7 | B8: أالنطاقُ يشمل صفوفًا؟ | C8: SCOPE-000 | D8: ◆ ليس خطأً — حالةٌ فارغةٌ مفسَّرة | E8: الإدارةُ المالكة
A9: ◆ | B9: الحكم | C9: — | D9: لا يُعرض سببٌ عامٌّ ولا شاشةٌ فارغة — والرسالةُ في الشاشةِ لا في الرابط | E9: مكتبُ الهندسة
A10: ◆ | B10: فحصٌ دوريٌّ ملزم | C10: — | D10: يشغّل السلّمَ على الأدوارِ كلِّها ويكشف الفشلَ قبل أن يبلّغ عنه مستخدم — وأيُّ دورٍ يفشل عيبٌ حاجب | E10: ضمانُ الجودة

Sheet 99 — شروط القبول
A1: # | B1: الشرط | C1: الشاهد | D1: الورقة | E1: الحالة
A2: 1 | B2: الملفاتُ الحيةُ الثلاثةُ لم تُدمج | C2: الورقةُ 01 تصنّفها «ملفٌّ حيّ» وتحتفظ بمسارها | D2: 01 | E2: محقَّق
A3: 2 | B3: كلُّ ملفٍّ ببصمةٍ وحالة | C3: 61 ملفًّا ببصمةِ MD5 وحجمٍ وتاريخٍ وحالة | D3: 01 | E3: محقَّق
A4: 3 | B4: كلُّ حكمٍ بمصدرِه ووجهتِه | C4: الورقةُ 03 بأحدَ عشرَ عمودًا لكل حكم | D4: 03 | E4: محقَّق
A5: 4 | B5: مصفوفةُ النسخِ معلَنة | C5: ثمانيةُ أزواجِ نسخٍ بأساسِ كلٍّ | D5: 04 | E5: محقَّق
A6: 5 | B6: التدقيقُ العالميُّ منفَّذ | C6: ثمانيةُ فحوصٍ على 246 فعلًا | D6: 07 | E6: محقَّق — واثنان معلَّقان على الكود الحي
A7: 6 | B7: خطةُ ترحيلِ الرموزِ معرَّفة | C7: ستُّ خطواتٍ ولا تغييرَ مباشرًا | D7: 08 | E7: محقَّق — لم تبدأ
A8: 7 | B8: سجلُّ العيوبِ بأربعةَ عشرَ حقلًا | C8: اثنا عشرَ عيبًا مسجَّلًا بكل حقوله | D8: 09 | E8: محقَّق
A9: 8 | B9: قراراتُ المالكِ محصورة | C9: ستةُ قراراتٍ بتوصيةٍ وأثرِ تأخيرٍ لكلٍّ | D9: 10 | E9: تنتظر الاعتماد
A10: 9 | B10: لوحةُ الاتساقِ محسوبة | C10: صيغُ COUNTIF تقرأ من كل الأوراق | D10: 11 | E10: محقَّق
A11: 10 | B11: مسارُ التغييرِ معرَّف | C11: ستُّ خطواتٍ لما بعد القطع | D11: 02 | E11: محقَّق
