Workbook

Sheet الملخص التنفيذي
A1: الملخص التنفيذي — تدقيق نظام إنجاز مقابل الحزمة الحاكمة الست
A2: تدقيق نظام إنجاز (EMS) — شركة تشغيل المعدات · تاريخ التدقيق 2026-08-09 · 595 ملاحظة مؤكَّدة بعد تحقق مضاد مستقل لكل ملاحظة · الدليل من الكود الحي تحت C:\xampp\htdocs\ems
A4: ١ — حجم الفحص
A5: عدد الوثائق الحاكمة المقروءة كاملة | B5: 6 | C5: INJAZ-CORE-01 · INJAZ-DELIVERY-01 · INJAZ-FRD-01 · INJAZ-UX-01 · UXR-01 · M-14 — بإجمالي ٥٧٢١ سطرًا و٩٦٠ كيلوبايت نصًّا
A6: عدد الإدارات المفحوصة | B6: 19 | C6: كل الإدارات المطلوبة، ومنها مساحة عملي والمراجع الداخلي المستقل
A7: عدد ملفات الكود المفحوصة | B7: 2170 | C7: PHP · JS · CSS · SQL · Migrations — باستثناء vendor و.git
A8: عدد الشاشات المجرودة | B8: 491 | C8: ٣٩٣ مربوطة بالسايدبار · ٩٨ يتيمة · ٤٦٤ نقطة API/AJAX
A9: عدد معالجات الكتابة المفحوصة | B9: 174 | C9: من ٥٥ معالج فعل رئيسًا + نقاط CMP-03
A10: عدد الأحداث المفحوصة | B10: 103 | C10: ٦٥ موضع نشر في الإنتاج · ٨٥ حدثًا بلا مستهلك
A12: ٢ — نتيجة التدقيق
A13: إجمالي الملاحظات المؤكَّدة | B13: =COUNTA('السجل الجامع'!$A$5:$A$599) -> 595 | C13: بعد إسقاط ٩٥ ملاحظة سقطت في التحقق المضاد (شيت «مرفوضة بعد التحقق»)
A14: P0 — حاجب إطلاق | B14: =COUNTIF('السجل الجامع'!$K$5:$K$599,"P0") -> 13 | C14: أثر مالي أو قانوني ينفَّذ بلا تفويض · تسريب بيانات · فقدان مصدر الحقيقة · شاشة حاكمة غائبة
A15: P1 — خطر جوهري | B15: =COUNTIF('السجل الجامع'!$K$5:$K$599,"P1") -> 103
A16: P2 — مهم | B16: =COUNTIF('السجل الجامع'!$K$5:$K$599,"P2") -> 294
A17: P3 — متوسط | B17: =COUNTIF('السجل الجامع'!$K$5:$K$599,"P3") -> 180
A18: P4 — تحسين | B18: =COUNTIF('السجل الجامع'!$K$5:$K$599,"P4") -> 5
A19: ملاحظات تمنع الإطلاق | B19: =COUNTIF('السجل الجامع'!$S$5:$S$599,"نعم") -> 308
A20: ملاحظات تمنع العرض الخارجي | B20: =COUNTIF('السجل الجامع'!$T$5:$T$599,"نعم") -> 390
A21: مؤكَّدة بالتحقق المضاد | B21: =COUNTIF('السجل الجامع'!$W$5:$W$599,"مؤكَّدة") -> 447 | C21: المحقق فتح الملف عند السطر المذكور وأثبت الادعاء
A22: مرجَّحة (صحيحة جوهرًا · صياغة أو خطورة عُدِّلت) | B22: =COUNTIF('السجل الجامع'!$W$5:$W$599,"مرجَّحة") -> 148
A24: ٣ — أضعف الإدارات (بعدد P0+P1)
A25: إدارة الحوكمة والالتزام | B25: 16 | C25: من إجمالي 77 ملاحظة في هذه الإدارة
A26: التمويل والملكية | B26: 11 | C26: من إجمالي 27 ملاحظة في هذه الإدارة
A27: المالية والخزينة | B27: 9 | C27: من إجمالي 41 ملاحظة في هذه الإدارة
A28: المشتريات التشغيلية | B28: 8 | C28: من إجمالي 42 ملاحظة في هذه الإدارة
A29: إدارة التشغيل | B29: 7 | C29: من إجمالي 26 ملاحظة في هذه الإدارة
A30: النقل والترحيل | B30: 7 | C30: من إجمالي 44 ملاحظة في هذه الإدارة
A32: ٤ — أكثر الوثائق عدمَ تطبيق
A33: M-14 | B33: 174
A34: INJAZ-FRD-01 | B34: 156
A35: INJAZ-UX-01 | B35: 131
A36: INJAZ-CORE-01 | B36: 59
A37: UXR-01 | B37: 39
A38: INJAZ-DELIVERY-01 | B38: 36
A40: ٥ — أكثر العيوب تكرارًا
A41: Permission Gap | B41: 97
A42: Governance Gap | B42: 68
A43: UX/UI Defect | B43: 68
A44: Missing Screen | B44: 58
A45: Missing Evidence | B45: 48
A46: Data Mismatch | B46: 40
A47: Wrong Sidebar Placement | B47: 38
A48: Event/Integration Gap | B48: 34
A50: ٦ — هل النظام جاهز للعرض الخارجي؟
A51: لا — النظام غير جاهز للعرض الخارجي ولا للإطلاق، وثلاثة أسباب تكفي وحدها: ◆ الحارس المركزي يفشل مفتوحًا: get_current_page_permissions() تُعيد can_view/add/edit/delete = true لأي شاشة لا صف لها في جدول modules (includes/permissions_helper.php:810-818)، وقرابة أربعين شاشة حية — منها ملف العميل وملف المورد وملف عملية التمويل — تعمل بهذا الفرع فعلًا. ◆ آثار مالية ومخزونية تُنفَّذ قبل وصول الحارس: الترسية وتحويل المخزون والجرد وإقفال أمر الترحيل بتكلفته كلُّها تكتب في قاعدة البيانات في أسطر تسبق سطر include '../insidebar.php'، فيُرحَّل الأثر ثم يُعاد توجيه المستخدم برسالة «لا صلاحية». ◆ التصدير الموحَّد يعمل بلا طبقة صلاحيات إطلاقًا: excel.php لا يحمّل permissions_helper.php، فيسقط ExcelService::authorize() في فرعه المفتوح، وتُصدَّر الحقول الحسّاسة كاملة بعد تسجيلها لا حجبها (excel.php:86-99). وفوق ذلك بوابتا الفحص الذاتي tools/u13_gate.php:1172 وtools/m10_ac_gate.php:190 تمرّان خضراوين على شرطين خاويين، أي أنّ تقارير الجاهزية الحالية ليست دليلًا. أمّا بصريًّا فسبعُ قشرات تطبيق متنافسة و7291 لونًا حرفيًّا و4588 نمطًا مضمّنًا تجعل العرض الخارجي غير مقبول قبل إعادة بناء القشرة والشاشات التمثيلية الثماني.

Sheet السجل الجامع
A1: السجل الجامع النهائي — 595 ملاحظة مرقَّمة بلا تكرار
A2: تدقيق نظام إنجاز (EMS) — شركة تشغيل المعدات · تاريخ التدقيق 2026-08-09 · 595 ملاحظة مؤكَّدة بعد تحقق مضاد مستقل لكل ملاحظة · الدليل من الكود الحي تحت C:\xampp\htdocs\ems
A4: رقم الملاحظة | B4: الوثيقة | C4: بند الوثيقة | D4: الإدارة | E4: اسم الشاشة | F4: رابط الشاشة | G4: مجموعة السايدبار | H4: المتوقَّع حسب الوثيقة | I4: الواقع في النظام | J4: نوع الفجوة | K4: الخطورة | L4: الأثر | M4: السبب الجذري | N4: الدليل (ملف:سطر) | O4: لقطة الشاشة | P4: خطوات إعادة الإنتاج | Q4: الإصلاح الموصى به | R4: المالك المقترح | S4: يمنع الإطلاق | T4: يمنع العرض الخارجي | U4: اختبار القبول | V4: الحالة | W4: نتيجة التحقق المضاد | X4: ملاحظة المحقق | Y4: الخطورة قبل التحقق | Z4: الإصلاح قابل للتنفيذ | AA4: الاختبار قابل للتشغيل | AB4: ملف التدقيق | AC4: تصنيف الفجوة | AD4: حالة الإغلاق
A5: INJ-0001 | B5: INJAZ-FRD-01 | C5: INJAZ-FRD-01 §١١-٣ · المرحلة ٣ — مراجعةُ العقد وتوقيعُه | D5: المبيعات والعقود | E5: عقود العملاء | F5: http://localhost/ems/Contracts/contracts.php | G5: ثالثًا: مراجعة العقد وتوقيعه | H5: دورةُ الإدارة: «سجلُّ عميلٍ ← عرضُ سعرٍ ← عقدٌ نافذٌ ← تغطيةٌ ووحداتٌ وأحكامٌ ← أداءٌ شهريٌّ ← مستخلصٌ ← مطالبة»، ومخرَجُ المرحلة الثالثة «عقدٌ نافذ» يعتمده «المخوَّلُ ضمن سقفِه ويُرفع للرئيس التنفيذيِّ إن تجاوز السقفَ». | I5: العمودُ الحاكمُ لحالة العقد `contracts.contract_status` (آلةُ الحالة الاثنتا عشرةَ حالة) لا يكتبه إلا `app/Services/Contract/ContractStateMachine`، ومستدعيها الوحيدُ في المستودع كلِّه هو `Portal/ceo_contracts.php:167`. وشاشةُ «عقود العملاء» — الشاشةُ الأمُّ للإدارة — لا تذكر `contract_status` ولا مرةً واحدة، ولا تملك فعلًا لنقل العقد من «مسودة» إلى «تفاوض» إلى «معتمد». | J5: Wrong Workflow | K5: P0 | L5: لا يوجد في النظام مسارٌ لجعلِ عقدٍ «معتمدًا»، وشاشةُ توقيع القمة تقرأ `WHERE contract_status='معتمد'` — فقائمةُ العقود القابلة للتوقيع تبقى فارغةً أبدًا ولا يمكن توقيعُ عقدٍ واحدٍ من داخل النظام. وبلا «نافذ» لا تُفتح حاويةُ تشغيلٍ (`OperationalTransformService::isEffective`) فتنقطع السلسلةُ كلُّها من أولها. | M5: آلةُ حالةٍ بُنيت كاملةً وربطت بنقطة اختناقٍ واحدةٍ في شاشة القمة، ولم تُزرع أفعالُها (تقديمٌ للمراجعة · اعتماد) في شاشة العقود المالكة. | N5: app/Services/Contract/ContractStateMachine.php:148; :219; Portal/ceo_contracts.php:167; Portal/ceo_contracts.php:243-246; Contracts/contracts.php:1; app/Services/Operations/OperationalTransformService.php:76 | P5: ١) ادخل بدور 12 وأنشئ عقدًا من Contracts/contracts.php. ٢) ابحث عن زرِّ «رفع للمراجعة» أو «اعتماد» ⇒ لا يوجد وحالةُ العقد تبقى NULL. ٣) ادخل بدور 9 وافتح Portal/ceo_contracts.php ⇒ قائمةُ «العقود القابلة للتوقيع» فارغة. | Q5: أضِف في `Contracts/contracts.php` فعلَين محروسَين يستدعيان `ContractStateMachine::transition()`: «رفع للتفاوض» (DRAFT→NEGOTIATION) و«اعتماد» (NEGOTIATION→APPROVED) بحارسِ سقفٍ يقارن قيمةَ العقد بسقف المخوَّل ويُصعّد تلقائيًّا عند التجاوز، واعرِض عمودَ `contract_status` في الشبكة. | R5: فريق الباك-إند — وحدة العقود | S5: نعم | T5: نعم | U5: مستخدمُ المبيعات ينقل عقدًا من مسودة إلى معتمد بفعلين مسجَّلين، ويظهر العقدُ فورًا في قائمة التوقيع لدى القمة. | V5: مفتوح | W5: مؤكَّدة | X5: بحثٌ شاملٌ عن `ContractStateMachine::transition` يُرجع مستدعيًا إنتاجيًّا واحدًا هو Portal/ceo_contracts.php:167 وهو ينقل إلى SIGNED حصرًا، وجدولُ TRANSITIONS يشترط APPROVED قبله، ولا موضعَ في المستودع يكتب «تفاوض» أو «معتمد» (schema.sql:1853 يجعل contract_status DEFAULT NULL، وContracts/contracts.php لا يذكر العمود)؛ فسلسلةُ مسودة→تفاوض→معتمد→موقَّع→نافذ لا تكتمل، وOperationalTransformService.php:76 يمنع فتحَ أيِّ حاويةٍ تبعًا لذلك. | Y5: P0 | Z5: نعم | AA5: نعم | AB5: 02_FRD | AC5: فجوة تنفيذ (Implementation) | AD5: Decision Closed · Implementation Open
A6: INJ-0002 | B6: M-14 | C6: PR-05 · «إخفاءُ الزرِّ تحسينُ تجربةٍ لا حماية» — الحارسُ قبل الكتابة | D6: إدارة الموردين | E6: طلب العروض ومقارنتها (الترسية) | F6: http://localhost/ems/Procurement/rfq_compare_award.php | G6: ثالثًا: طلب العروض والترسية | H6: الحارسُ في الخادمِ يسبق الأثرَ؛ والترسيةُ قرارٌ ماليٌّ يُحرَس بصلاحيةٍ وسقفٍ ومرجعِ تفويض. | I6: صحيحٌ عدا وصفِ حقنِ SQL: القيمُ مُمَرَّرةٌ بـintval/floatval/mysqli_real_escape_string فلا حقنَ عمليًّا — والخللُ هو الأثرُ قبل الحارس وغيابُ فحصِ can_edit. — [مُصحَّح بعد التحقق] الصياغة الأولى: الشاشةُ الوحيدةُ في مجموعة «ثالثًا: طلب العروض والترسية» لدى دور الموردين تنفّذ الترسيةَ في معالجٍ يبدأ في السطر 20: يُدرج `INSERT INTO rfq_awards` في السطر 33 ويحدّث `UPDATE supplier_rfqs SET state=' | J6: Permission Gap | K6: P0 | L6: أيُّ مستخدمٍ مسجَّلِ الدخول يُرسي أيَّ طلبِ عروضٍ على أيِّ موردٍ بأيِّ سعرٍ ثم يُعاد توجيهُه برسالة «لا تملك صلاحية» بعد استقرار الترسية — وهي أخطرُ نقطةِ تسريبٍ ماليٍّ في وحدة الموردين. والاستعلاماتُ مبنيةٌ بدمجٍ نصيٍّ مباشرٍ للمتغيرات. | M6: ترتيبُ الملف: المعالجُ في الأعلى والحارسُ في الأسفل مع تضمين السايدبار، مع كتابةٍ خامٍّ بـmysqli بلا بوابة العزل. | N6: Procurement/rfq_compare_award.php:20; :26; :33-36; :37-38; :66 | P6: ١) ادخل بحسابٍ بلا أيِّ منحةٍ على الشاشة. ٢) أرسل POST بـ award_quote=<quote_id> و award_reason=نص. ٣) لاحظ رسالةَ الرفض، ثم افحص rfq_awards و supplier_rfqs ⇒ الترسيةُ مسجَّلةٌ والحالةُ awarded. | Q6: انقل إلى أعلى `Procurement/rfq_compare_award.php` (قبل السطر 20) كتلةَ `check_page_permissions($conn,'Procurement/rfq_compare_award.php')` مع منعِ POST بلا can_edit، وحوّل الكتابتين إلى `ems_tenant_db()` بعباراتٍ مُعدَّة، وأضِف فحصَ سقفٍ عبر `AuthorityGuard::sign()` بقيمة الترسية. | R6: فريق الباك-إند — وحدة المشتريات والموردين | S6: نعم | T6: نعم | U6: POST إلى الشاشة بحسابٍ بلا can_edit لا ينشئ صفَّ ترسيةٍ ولا يغيّر حالةَ الطلب، ويُسجَّل الرفض. | V6: مفتوح | W6: مؤكَّدة | X6: معالجُ POST في السطر 20 ينفّذ INSERT INTO rfq_awards (33-37) وUPDATE supplier_rfqs SET state='awarded' (38-39) قبل include '../insidebar.php' في السطر 66 حيث الحارسُ الوحيد؛ والموديول 298 مسجَّلٌ لكن مصفوفةَ الصلاحيات تمنح الأدوار 16 و2 و8 can_view فقط ولا تمنح can_add/can_edit لأيِّ دور — فأيُّ مستخدمٍ مصادَقٍ يُرسي ترسيةً لا يملكها أحد. | Y6: P0 | Z6: نعم | AA6: نعم | AB6: 06_M14 | AC6: فجوة تنفيذ (Implementation) | AD6: Decision Closed · Implementation Open
A7: INJ-0003 | B7: INJAZ-CORE-01 | C7: PR-01 · مصدرُ الحقيقة الواحد — «ولا يُدخَل بيانٌ مرتين في شاشتين مختلفتين» | D7: التمويل والملكية | E7: نماذج التمويل ومعالجتها | F7: http://localhost/ems/Financing/fin_models.php | G7: أولًا: النموذج والممول | H7: «لكل بيانٍ موضعٌ واحدٌ يُنشأ فيه ويُعدَّل، وكلُّ عرضٍ آخرَ له قراءةٌ لا نسخة»؛ ونموذجُ التمويل هو أولُ مستندٍ في دورة الإدارة («نموذج بمعالجته») ولا اعتمادَ لعمليةٍ بلا نموذج. | I7: شاشةُ «نماذج التمويل ومعالجتها» تكتب وتقرأ من scr_fin_models عبر cmp03_store_insert/cmp03_store_rows (الأسطر 28 · 80 · 87)، بينما جدولُ المجال الحقيقيُّ financing_models هو الذي يقرؤه منشئُ العملية: Financing/financing_operation_new.php:62 يملأ قائمةَ النماذج منه، و FinancingService::createOperation:169 يتحقق من وجود النموذج فيه ويرفض 422 إن لم يجده. | J7: Data Mismatch | K7: P0 | L7: نموذجٌ يُنشأ من الشاشة المخصَّصة له لا يظهر أبدًا في قائمة إنشاء عملية التمويل، وإنشاءُ العملية به يُرفض برسالة «نموذج تمويل غير معرَّف» — فالمرحلةُ الأولى من دورة الإدارة معطَّلةٌ عمليًّا ولا سبيلَ لإضافة نموذجٍ إلا بإدخالٍ مباشرٍ في القاعدة. | M7: موجةُ CMP-03 وجّهت الشاشةَ إلى المخزن البيني scr_* ولم تُوصل بجدول المجال القائم financing_models. | N7: Financing/fin_models.php:28; Financing/fin_models.php:80; Financing/fin_models.php:87; includes/cmp03_registry.php:252; includes/cmp03_registry.php:254; Financing/financing_operation_new.php:62; app/Services/Financing/FinancingService.php:169; app/Services/Financing/FinancingService.php:174 | P7: ١) بدور ٢٦ افتح «نماذج التمويل ومعالجتها» وأضِف نموذجًا برمزٍ جديدٍ واعتمده. ٢) افتح «إنشاء عملية تمويل» → النموذجُ غيرُ موجودٍ في القائمة. ٣) أرسل الرمزَ يدويًّا في الطلب → يُرفض 422 «نموذج تمويل غير معرَّف». | Q7: غيّر خريطةَ 'fin_models.php' في includes/cmp03_registry.php:252 لتشير إلى جدول financing_models بأعمدته الدلالية، أو استبدل معالجَ الحفظ في Financing/fin_models.php:80 بكتابةٍ مباشرةٍ في financing_models عبر بوابة العزل. | R7: فريق الباك-إند — وحدة التمويل | S7: نعم | T7: نعم | U7: نموذجٌ يُضاف من الشاشة يظهر فورًا في قائمة إنشاء العملية، وإنشاءُ عمليةٍ به ينجح؛ وصفرُ صفٍّ جديدٍ في scr_fin_models. | V7: مفتوح | W7: مؤكَّدة | X7: محقَّقٌ بالكامل: includes/cmp03_registry.php:252-254 يربط `fin_models.php` بجدول `scr_fin_models`، بينما Financing/financing_operation_new.php:62 وFinancingService::createOperation:169-174 يقرآن `financing_models` ويرفضان 422 بلا نموذج — ولا يوجد في المستودع كلِّه أيُّ INSERT في `financing_models` (ولا بذرةٌ في database/seeds خارج قائمة الملء الآلي) — فإنشاءُ أيِّ عمليةِ تمويلٍ متعذّرٌ بنيويًّا والشاشةُ الحاكمةُ تكتب في جدولٍ موازٍ لا يقرؤه أحد. | Y7: P0 | Z7: نعم | AA7: نعم | AB7: 01_CORE | AC7: فجوة تنفيذ (Implementation) | AD7: Decision Closed · Implementation Open
A8: INJ-0004 | B8: M-14 | C8: §٢٧ · الحقلُ الحساس — «لا يُعرض ولا يُصدَّر إلا بمنحٍ فردي» | D8: الموارد البشرية | E8: سجل الموظفين | F8: http://localhost/ems/Employees/employees.php | G8: ثانيًا: التعاقد والمباشرة | H8: «الحقلُ الحساس | حقلٌ لا يُعرض ولا يُصدَّر إلا بمنحٍ فردي | ليس المخفيَّ» — والراتبُ من الحقول التي تفرض M-14 على الموارد البشرية «قراءةً مسجَّلة» عليها (SCN-872). | I8: السطرُ 982 عمودُ ترشيحٍ لـ«نوع الراتب» لا عمودُ راتبٍ في الجدول؛ ومنفذُ الكشف الحقيقيُّ get_employee_data.php الذي يرسل الصفَّ كاملًا (بما فيه monthly_salary ورقمُ الهوية) لأيِّ جلسةٍ مصادَقةٍ بلا فحصِ صلاحيةٍ إطلاقًا. — [مُصحَّح بعد التحقق] الصياغة الأولى: شاشةُ سجل الموظفين تعرض وتحفظ monthly_salary و salary_type مباشرةً (الإدخالُ في السطر 92 والحقلُ في 724 وعمودُ الجدول في 982) لكل من يملك can_view/can_edit على الوحدة، بلا أي فحصِ منحةٍ فرديةٍ وبلا سط | J8: Permission Gap | K8: P0 | L8: راتبُ كل موظفٍ مكشوفٌ في الشاشة الأكثر استعمالًا في الإدارة لكل من يملك عرضَ سجل الموظفين، بينما البيانُ نفسُه محجوبٌ في بطاقة الموظف؛ فالحجبُ يُلتفّ عليه بفتح الشاشة الأخرى، ولا يُسجَّل الاطّلاع. | M8: طُبِّق حارسُ الرؤية على شاشةٍ واحدةٍ (بطاقة الموظف) ولم يُعمَّم على شاشة السجل التي تعرض الحقلَ نفسَه. | N8: Employees/employees.php:92,724,1376; Employees/get_employee_data.php:8-13,31-50; Employees/employee_card.php:164-175 | P8: ١) ادخل بحسابٍ يملك عرضَ سجل الموظفين وبلا صلاحية الأجور. ٢) افتح «سجل الموظفين» → عمودُ «نوع الراتب» وقيمةُ الراتب في نموذج التعديل ظاهرة. ٣) افتح بطاقةَ الموظف نفسِه → تبويبُ الأجور محجوب. ٤) ابحث عن سطر اطّلاع → لا يوجد. | Q8: في Employees/employees.php لفَّ حقلَ monthly_salary وعمودَه بفحص VisibilityGuard::check('card.payroll') كما في employee_card.php:164، ولا تُرسل القيمةَ في HTML لغير المخوَّل، وسجّل الاطّلاعَ عبر ems_log_sensitive_read لمن يراها. | R8: فريق الحوكمة — وحدة الصلاحيات | S8: نعم | T8: نعم | U8: حسابٌ بلا صلاحية الأجور لا يجد قيمةَ الراتب في جسم استجابة سجل الموظفين ولا في نموذج التعديل؛ ومن يراها يُكتب له سطرُ اطّلاع. | V8: مفتوح | W8: مؤكَّدة | X8: مؤكَّدٌ بل أشدّ: employees.php يحفظ monthly_salary (:92) ويعرض حقلَه (:724) بلا أيِّ VisibilityGuard أو ems_log_sensitive_read (بحثٌ = صفر)، والأخطرُ أن Employees/get_employee_data.php:31-50 يعيد صفَّ employees كاملًا (الراتبُ والهوية) لأيِّ مستخدمٍ مصادَقٍ بلا أيِّ فحصِ موديول — بينما employee_card.php:164-175 يحجب التبويبَ نفسَه بـVG::check ويسجّل الاطّلاع. | Y8: P0 | Z8: نعم | AA8: نعم | AB8: 06_M14 | AC8: فجوة تنفيذ (Implementation) | AD8: Decision Closed · Implementation Open
A9: INJ-0005 | B9: INJAZ-CORE-01 | C9: PR-05 · الحارسُ في الخادم · ٤-١ المبادئُ الاثنا عشرَ الحاكمة | D9: إدارة الحوكمة والالتزام | E9: طبقة الصلاحيات المشتركة | F9: http://localhost/ems/includes/permissions_helper.php | G9: - | H9: «كلُّ منعٍ يُنفَّذ في الخادم قبل الحفظ … والنداءُ المخالفُ يُرفض ولو جاء بمساره مباشرةً أو من أداةٍ خارجية — ويُسجَّل الرفضُ بالمستخدم والوقت والرمز». | I9: get_current_page_permissions() تُرجع can_view/add/edit/delete = true حين لا تُحَلّ الشاشةُ إلى موديول (id = null)، و_default_full_permissions() تفعل الشيءَ نفسه، وenforce_current_page_view_permission() لا تحجب إلا حين id !== null. الصمّامُ المضادّ ems_failclosed_screen_guard مقودٌ بـEMS_FAILCLOSED_ENFORCE_PREFIXES وهو فارغٌ افتراضيًّا. النتيجة: أيُّ شاشةٍ غيرِ مسجَّلةٍ في modules مفتوحةٌ لكل مستخدمٍ بصلاحياتٍ كاملة. | J9: Permission Gap | K9: P0 | L9: الافتراضُ المركزي في النظام هو «السماح عند الجهل» — عكسُ PR-05 نصًّا. وكلُّ شاشةٍ جديدةٍ تُنشَر قبل تسجيلها موديولًا تكون مفتوحةً للجميع بلا رفضٍ ولا سجل. وهذا هو الجذرُ الذي يجعل عشراتِ الملاحظات في هذا التقرير قابلةً للاستغلال. | M9: قرارُ توافقيةٍ قديم: أُريد ألّا تنكسر شاشاتٌ موروثةٌ غيرُ مسجَّلة، فجُعل الافتراضُ مفتوحًا بدل تسجيلِ الشاشات. | N9: includes/permissions_helper.php:621; :622; :810; :811; :766; :793 | P9: ١) أنشئ ملفًا جديدًا تحت Settings/ يستدعي get_current_page_permissions ويطبع النتيجة. ٢) لا تسجّله في modules. ٣) افتحه بأيِّ حسابٍ ⇐ can_view وcan_add وcan_edit وcan_delete كلُّها true. | Q9: قلبُ الافتراض في includes/permissions_helper.php:621-629 و810-818 إلى صلاحياتٍ صفريةٍ (كلُّها false) مع تسجيلِ رفضٍ باسم الشاشة، وتشغيلُ ems_failclosed_screen_guard على كلِّ البادئات افتراضيًّا، وإضافةُ فاحصٍ في الإصدار يمنع نشرَ ملفِّ شاشةٍ غيرِ مسجَّلٍ في modules. | R9: مكتب الهندسة — طبقة الحراس المشتركة | S9: نعم | T9: نعم | U9: شاشةٌ غيرُ مسجَّلةٍ في modules تُعيد 403 لكل الأدوار عدا السوبر، وتكتب صفَّ رفضٍ فيه المستخدمُ والوقتُ والرمز. | V9: مفتوح | W9: مؤكَّدة | X9: تحققتُ حرفيًّا: get_current_page_permissions (621-629) تُرجع الأربعَ true حين لا تُحَلّ الشاشة، و_default_full_permissions (810-818) مثلُها، و enforce_current_page_view_permission لا يحجب إلا حين id !== null (770)، والصمّامُ مقودٌ بـEMS_FAILCLOSED_ENFORCE_PREFIXES الفارغِ افتراضًا (والوثيقةُ docs/SUPPLIERS_DEPARTMENT_AUDIT_REPORT_ar.md:323 تقتبس .env:53 فارغًا). والأثرُ حيٌّ لا نظري: نحوُ ٤٠ شاشةً تضمّن insidebar وغيرُ مسجَّلةٍ في modules — منها Clients/client_profile.php و Suppliers/supplier_profile.php و Financing/operation_profile.php و Timesheet/aprovment.php — مفتوحةٌ لكل مصادَقٍ بصلاحياتٍ كاملة. | Y9: P0 | Z9: نعم | AA9: نعم | AB9: 01_CORE | AC9: فجوة تنفيذ (Implementation) | AD9: Decision Closed · Implementation Open
A10: INJ-0006 | B10: M-14 | C10: TABLE 46 (لأفعال التصدير) · ▐ ٨-٤ | D10: إدارة الحوكمة والالتزام | E10: مركز التقارير / التصدير الموحَّد | F10: http://localhost/ems/excel.php | G10: متابعة وتقارير الحوكمة | H10: «صلاحيةُ التصديرِ + حدُّ الحقولِ الحساسة — لأفعال audit.export · rpt.export»، أي صلاحيةُ تصديرٍ مستقلةٌ عن صلاحية العرض، وحجبُ الحقول الحساسة في الملف. | I10: فرعُ الفشلِ المفتوح حيٌّ لا نظري: لا مسارَ في excel.php يحمّل permissions_helper.php، ولا يلتقطه حارسُ AJAX المركزي (اسمُ السكربت ليس get_*/‏*_handler)، فالتصديرُ محكومٌ بعزل الشركة وحدَه دون أيِّ راية دور. — [مُصحَّح بعد التحقق] الصياغة الأولى: excel.php يفحص وجودَ الجلسة فقط، وExcelService::authorize يفحص can_view (صلاحيةَ عرضٍ لا تصدير). والأسوأ: `if (!function_exists('check_page_permissions')) { return; }` يجعل الفحصَ يفشل مفتوحًا إن لم ي | J10: Permission Gap | K10: P0 | L10: من يملك عرضَ شاشةٍ يملك تصديرَها كاملةً بحقولها الحساسة — وهو عكسُ الحكم صراحةً: «فقد يملك المستخدمُ حقَّ التصديرِ لجزءٍ دون عرضِ بعضِ الحقولِ أو العكس — صلاحيتان منفصلتان لا واحدة». الحقلُ الحساس يُسجَّل اطّلاعُه ثم يُسلَّم في الملف. | M10: نموذج الصلاحيات رباعيُّ الأفعال (view/add/edit/delete) بلا فعلِ export، وصنفُ Column بلا خاصيةِ حساسية. | N10: excel.php:16; :65; :99; app/Services/Excel/ExcelService.php:61-63; :91; :150-158 | P10: ١) امنح دورًا can_view على كيانٍ فيه حقلٌ مصنَّف حساسًا في scr_sensitive_fields. ٢) صدّر الكيان من الشاشة. ٣) افتح الملف ⇐ الحقلُ الحساس ظاهرٌ بقيمته. | Q10: إضافة عمودٍ can_export إلى role_permissions وفحصُه في app/Services/Excel/ExcelService::authorize() بدل can_view، وحذفُ فرع الفشلِ المفتوح في السطر 61-63، وتصفيةُ الأعمدة في Exporter::write وفق نتيجة استعلام scr_sensitive_fields بدل الاكتفاء بتسجيلها. | R10: فريق الباك-إند — وحدة الحوكمة والصلاحيات | S10: نعم | T10: نعم | U10: دورٌ بـcan_view وبلا can_export يُرفض تصديرُه 403؛ ودورٌ بـcan_export بلا منحةِ حقلٍ حساس يحصل على ملفٍّ بلا ذلك العمود. | V10: مفتوح | W10: مؤكَّدة | X10: أشدُّ ممّا وُصف: excel.php لا يحمّل includes/permissions_helper.php إطلاقًا (config.php لا يضمّنه) فشرطُ function_exists يفشل ويعود authorize() بلا فحص — تصديرُ أيِّ كيانٍ متاحٌ لأيِّ حسابٍ مسجَّل، وهو تسريبُ بياناتٍ بين الإدارات. | Y10: P1 | Z10: نعم | AA10: نعم | AB10: 06_M14 | AC10: فجوة تنفيذ (Implementation) | AD10: Decision Closed · Implementation Open
A11: INJ-0007 | B11: M-14 | C11: ▐ ١١-١ الحوكمةُ والملكيةُ والحدود · ما لا تملكه: أيَّ قرارٍ تشغيليٍّ | D11: إدارة الحوكمة والالتزام | E11: صفحات النظام والإدارات / الأدوار وقوالب صلاحياتها | F11: http://localhost/ems/Settings/modules.php | G11: رابعًا: الظهور والبوابة والصفحات | H11: الحوكمة والالتزام تملك «الكياناتِ · التفويضَ · قوالبَ الصلاحيات · مفاتيحَ الظهور · مكوّناتِ البوابة · صفحاتِ النظام · الحساب» — وهي وحدَها مَن يملك هذه السجلات؛ وإدارةُ التشغيل إدارةٌ تشغيليةٌ لا حوكمية. | I11: check_page_permissions (112 شاشة) تفشل مغلقةً منذ 2026-08-05، فالفشلُ المفتوحُ محصورٌ في get_current_page_permissions وستِّ شاشاتٍ تستعملها — لكن منها Settings/role_permissions.php وSettings/roles.php وmain/users.php، فسلسلةُ التصعيد مكتملةٌ ومن أخطر ما يكون. — [مُصحَّح بعد التحقق] الصياغة الأولى: الدالة ems_governance_admin_roles() تُرجع الدورين 1 (ادارة التشغيل) و15 (مدير الصلاحيات)، وems_require_governance_screen ترجع لهما صلاحياتٍ كاملةً (can_view/add/edit/delete = true) قبل أيِّ استعلامِ م | J11: Wrong Owner | K11: P0 | L11: مديرُ التشغيل يستطيع حذفَ صفِّ موديولٍ من سجل الشاشات — والشاشةُ غيرُ المسجَّلة تصير مفتوحةً للجميع بسبب الفشل المفتوح في permissions_helper. مسارُ تصعيدِ امتيازٍ مكتمل من دورٍ تشغيليٍّ إلى فتحِ أيِّ شاشةٍ في النظام. | M11: تعليقُ الملف يشرح السبب صراحةً: «الشركةُ 1 ليس فيها أيُّ حسابٍ بالدور 15 — أرضيةٌ بالدور 15 وحدَه تقفلها خارج نظامها». عولجت مشكلةُ بياناتٍ بتوسيعِ أرضيةِ الصلاحية في الكود بدل إنشاء حسابِ حوكمة. | N11: includes/governance_guard.php:42,71,94-97; Settings/modules.php:20-21; includes/permissions_helper.php:614-628; Settings/role_permissions.php:21-28; Settings/roles.php:17-25; main/users.php:32 | P11: ١) ادخل بدور 1 (ادارة التشغيل). ٢) افتح http://localhost/ems/Settings/modules.php ⇐ تُفتح بصلاحياتٍ كاملة. ٣) احذف صفَّ موديولٍ لشاشةٍ ما. ٤) ادخل بأيِّ دورٍ آخر وافتح تلك الشاشة ⇐ تُفتح بصلاحياتٍ كاملة بسبب _default_full_permissions. | Q11: حصرُ ems_governance_admin_roles() في EMS_ROLE_PERMISSIONS_MGR وحدَه في includes/governance_guard.php:42، وإنشاءُ حسابِ حوكمةٍ بالدور 15 في كل شركةٍ ضمن هجرةِ بياناتٍ بدل توسيع الأرضية، وإبقاءُ الدور 1 عارضًا بمنحةٍ صريحةٍ إن لزم. | R11: فريق الباك-إند — وحدة الحوكمة والصلاحيات | S11: نعم | T11: نعم | U11: الدور 1 يُرفض 403 عند فتح Settings/modules.php ما لم تُمنَح له can_view صراحةً، ولا يملك can_delete عليه في أيِّ حال؛ ويُسجَّل الرفضُ في سجل الأمن. | V11: مفتوح | W11: مؤكَّدة | X11: مؤكَّدٌ بالكامل: governance_guard.php:42 يُرجع array(EMS_ROLE_OPERATIONS_MGR, EMS_ROLE_PERMISSIONS_MGR) أي '1' و'15'، وems_require_governance_screen:96-97 تعيد لهما $full (كلُّ الصلاحيات) قبل أيِّ استعلامِ منح، وSettings/modules.php:21 هي هذه البوابةُ نفسُها. وسلسلةُ التصعيد قائمةٌ فعلًا: get_current_page_permissions (permissions_helper.php:621-628) تفشل مفتوحةً، وSettings/role_permissions.php:21-28 يشترط $rp_perms['id'] !== null قبل المنع — فحذفُ صفِّ الموديول 123 من داخل modules.php يفتح شاشةَ منحِ الصلاحيات للجميع. | Y11: P0 | Z11: نعم | AA11: نعم | AB11: 06_M14 | AC11: فجوة تنفيذ (Implementation) | AD11: Decision Closed · Implementation Open
A12: INJ-0008 | B12: M-14 | C12: BR-GOV-01 · الحارسُ المركزي · CORE PR-05/AR-05 | D12: إدارة الحوكمة والالتزام | E12: حارس الصلاحيات المركزي | G12: - | H12: CORE AR-05: «المنعُ يُنفَّذ ثلاثَ مرات … والحارسُ في الخادم يرفض النداءَ ولو جاء بمساره مباشرةً» — والحارسُ **مغلقٌ افتراضًا** (fail-closed). | I12: الحارسُ المركزيُّ مفتوحٌ افتراضًا: `_default_full_permissions()` تُرجع `can_view/can_add/can_edit/can_delete = true` لأيِّ شاشةٍ غيرِ مسجَّلةٍ في `modules` (`includes/permissions_helper.php:810-818`)، وتُستدعى مرتين: عند فشلِ تجهيزِ الاستعلام (`:897-899`) وعند عدمِ العثورِ على الشاشة (`:909-911`). والنمطُ نفسُه في `get_current_page_permissions` (`:621-629`). والتعليقُ يقرُّ بذلك: «إذا لم توجد الصفحة في قاعدة البيانات تُرجع كل الصلاحيات للتوافقية». | J12: Permission Gap | K12: P0 | L12: أيُّ شاشةٍ جديدةٍ أو مُعادةِ التسميةِ أو غيرِ مسجَّلةٍ تُمنح تلقائيًّا صلاحياتٍ كاملةً لكلِّ الأدوار — إضافةً وتعديلًا وحذفًا. ونسيانُ صفٍّ واحدٍ في `modules` يفتح شاشةً حاكمةً للجميع. وفشلُ الاستعلامِ نفسُه (خطأُ قاعدة) يفتح كلَّ شيء. | M12: قرارُ «توافقيةٍ» مع شاشاتٍ قديمةٍ غيرِ مسجَّلةٍ بقي في المسارِ الحرِج بدل هجرةِ تلك الشاشاتِ وإغلاقِ الحارس. | N12: includes/permissions_helper.php:803; :810; :813; :816; :818; :897; :898; :909; :910; :621; :624; :628 | P12: ١) أنشئ ملفًّا `Test/unregistered.php` يستدعي `check_page_permissions($conn,'Test/unregistered.php')`. ٢) لا تُسجّله في `modules`. ٣) افتحه بأيِّ دور: القيمُ الأربعُ `true`. ٤) كرِّر بعد قطعِ الاتصالِ بالقاعدةِ فيفشل `prepare`: النتيجةُ نفسُها (`:897-899`). | Q12: اقلِب الافتراضَ في `includes/permissions_helper.php`: اجعل `_default_full_permissions()` تُرجع الأربعَ `false` (وأعِد تسميتَها `_default_denied_permissions`)، وسجِّل حدثَ أمنٍ `PERM_UNREGISTERED_SCREEN`؛ وفي حالةِ فشلِ `prepare` (`:897`) ارمِ استثناءً بدل الفتح. ثم هاجِر الشاشاتِ غيرَ المسجَّلةِ إلى `modules` قبل النشر بعلَمِ تفعيلٍ تدريجي. | R12: فريق الباك-إند — الحوكمة والمنصة | S12: نعم | T12: نعم | U12: شاشةٌ غيرُ مسجَّلةٍ في `modules` تُعيد `can_view=false` وتُحجب لكلِّ دورٍ عدا السوبر، ويُكتب حدثُ أمنٍ بكلِّ محاولة. | V12: مفتوح | W12: مؤكَّدة | X12: مؤكَّدٌ سطرًا سطرًا: _default_full_permissions (810-818) تُرجع الأربعَ true، وتُستدعى عند فشل prepare (897-899) وعند عدم العثور على الشاشة (909-911)، والنمطُ نفسُه في get_current_page_permissions (621-629)، والتعليقُ 825 يقرُّ به. والأثرُ حيٌّ: نحوُ ٤٠ شاشةً تضمّن insidebar وليست في modules تُمنح صلاحياتٍ كاملةً لكل مصادَق، والصمّامُ المضادُّ فارغُ البادئات في .env حسب docs/SUPPLIERS_DEPARTMENT_AUDIT_REPORT_ar.md:323. | Y12: P0 | Z12: نعم | AA12: نعم | AB12: 06_M14 | AC12: فجوة تنفيذ (Implementation) | AD12: Decision Closed · Implementation Open
A13: INJ-0009 | B13: M-14 | C13: ▐ ١٠ الحرّاس · الحكمُ الرابع «الحارسُ في الخادم ويُفشَل مغلقًا» | D13: النقل والترحيل | E13: إقفال الأمر وتحميل تكلفته | F13: http://localhost/ems/Transport/transfer_close_cost.php | G13: خامسًا: الإقفال وتحميل التكلفة | H13: الحارسُ في الخادمِ قبل الأثر — ولا يُكتفى بإخفاء الزر؛ ولكلِّ فعلٍ حارسٌ مُثبَتٌ بمُنفِّذه | I13: معالجُ POST في السطر ١٩ ينفّذ UPDATE على transfer_orders و INSERT في transfer_events و transfer_cost_lines قبل السطر ٥٥ الذي يُضمِّن insidebar.php (وفيه الحارسُ الوحيدُ enforce_current_page_view_permission عند insidebar.php:14) — فالأثرُ يقع ثم يُعاد التوجيه؛ ولا فحصَ can_edit ولا رمزَ صلاحيةٍ ولا CSRF | J13: Permission Gap | K13: P0 | L13: أيُّ مستخدمٍ مسجَّلِ الدخولِ — من أيِّ إدارةٍ — يستطيع إقفالَ أمرِ ترحيلٍ وتحميلَ تكلفةٍ فعليةٍ بأيِّ مبلغٍ على مركزِ تكلفة؛ أثرٌ ماليٌّ بلا صلاحية | M13: الشاشةُ من موجة update0007 كُتبت بنمطٍ مختصرٍ (فحصُ الجلسة فقط) ولم تستدعِ trs_page_perms كأخواتها، والحارسُ المركزيُّ يفحص can_view وحدَه ويأتي متأخرًا في ترتيب التضمين | N13: Transport/transfer_close_cost.php:11; Transport/transfer_close_cost.php:19; Transport/transfer_close_cost.php:25; Transport/transfer_close_cost.php:34; Transport/transfer_close_cost.php:55; insidebar.php:14 | P13: ١) ادخل بأيِّ حسابٍ لا يملك صلاحيةَ النقل (مثلًا دور الموارد البشرية). ٢) أرسِل POST إلى /ems/Transport/transfer_close_cost.php بالحقلين close_id=<رقم أمرٍ حالتُه arrived> و actual_cost=999999. ٣) استعلِم transfer_orders: الحالةُ صارت closed و actual_cost_usd=999999. | Q13: في Transport/transfer_close_cost.php أضِف قبل السطر ١٩: require_once trs_helpers.php ثم $perms = trs_page_perms($conn,'Transport/transfer_close_cost.php',$is_super); وارفض بـ403 إن !$perms['can_edit']؛ وأضِف تحققَ رمزِ CSRF، وانقل التحققَ كلَّه قبل أيِّ كتابة | R13: فريق الباك-إند — وحدة النقل والترحيل | S13: نعم | T13: نعم | U13: POST من حسابٍ بلا can_edit على الموديول ٣٠٩ يعيد ٤٠٣ ولا يغيّر صفًّا واحدًا في transfer_orders ولا transfer_cost_lines. | V13: مفتوح | W13: مؤكَّدة | X13: تحققتُ: السطر 19 يفتح معالجَ POST، والسطور 25-28 UPDATE transfer_orders، و30-31 INSERT transfer_events، و33-34 INSERT transfer_cost_lines بمبلغٍ من $_POST — كلُّها قبل include '../insidebar.php' في السطر 55 حيث الحارسُ الوحيد. لا can_edit ولا رمزَ CSRF، ومصفوفةُ الصلاحيات تحصر الموديول 309 بالدور 23 كتابةً — فالأثرُ الماليُّ يقع لأيِّ مصادَق. | Y13: P0 | Z13: نعم | AA13: نعم | AB13: 06_M14 | AC13: فجوة تنفيذ (Implementation) | AD13: Decision Closed · Implementation Open
A14: INJ-0010 | B14: M-14 | C14: ▐ ١٠ الحرّاس · الحكمُ الرابع «الحارسُ في الخادم قبل الأثر» | D14: المشتريات التشغيلية | E14: طلب العروض ومقارنتها (الترسية) | F14: http://localhost/ems/Procurement/rfq_compare_award.php | G14: ثانيًا: العروض والترسية | H14: لا فعلَ يقع قبل حارسٍ خادميٍّ يفحص صلاحيةَ الكتابة؛ والترسيةُ فعلٌ حاكمٌ بأثرٍ تعاقديٍّ ومالي | I14: معالجُ الترسية بلا فحصِ صلاحيةٍ إطلاقًا؛ أمّا CSRF فيغطّيه `ems_enforce_csrf_protection` المركزيُّ في config.php:468 حسب وضعه. — [مُصحَّح بعد التحقق] الصياغة الأولى: معالجُ POST في السطر ٢٠ يُدرج صفَّ ترسيةٍ في rfq_awards (السطر ٣٣) ويحدّث supplier_rfqs إلى 'awarded' (السطر ٣٨) داخل معاملة، وكلُّ ذلك قبل السطر ٦٦ الذي يُضمِّن insidebar.php حيث الحارسُ الوحيدُ (enf | J14: Permission Gap | K14: P0 | L14: أيُّ مستخدمٍ مسجَّلِ الدخولِ في النظام يستطيع ترسيةَ أيِّ طلبِ عروضٍ على أيِّ موردٍ بأيِّ سعر؛ الترسيةُ تُلتزم في القاعدة ثم يُعاد توجيهُ المستخدمِ فقط — أثرٌ تعاقديٌّ كاملٌ بلا صلاحية | M14: شاشةُ الترسيةِ كُتبت بالنمط المختصر (فحصُ الجلسة وحدَه) ولم تستدعِ proc_page_perms كأخواتِها في المجلد نفسِه | N14: Procurement/rfq_compare_award.php:11; Procurement/rfq_compare_award.php:20; Procurement/rfq_compare_award.php:33; Procurement/rfq_compare_award.php:38; Procurement/rfq_compare_award.php:66; insidebar.php:14; Procurement/orders_proc.php:29 | P14: ١) ادخل بحسابٍ من إدارةٍ بلا أيِّ صلة بالمشتريات (مثلًا دور الصيانة). ٢) أرسِل POST إلى /ems/Procurement/rfq_compare_award.php بالحقول award_quote=<معرّف عرض> و award_reason=«اختبار». ٣) استعلِم rfq_awards: صفٌّ جديد؛ واستعلِم supplier_rfqs: state='awarded'. | Q14: في Procurement/rfq_compare_award.php أضِف قبل السطر ٢٠: require_once __DIR__.'/proc_helpers.php'; $ctx=proc_ctx(); $perms=proc_page_perms($conn,'Procurement/rfq_compare_award.php',$ctx['is_super']); if(!$perms['can_edit']) { ems_gov_flash_redirect('rfq_compare_award.php','لا صلاحية ترسية ❌','GOV-PERM-403',''); exit(); } وأضِف تحققَ رمز CSRF | R14: فريق الباك-إند — وحدة المشتريات | S14: نعم | T14: نعم | U14: POST من حسابٍ بلا can_edit على الموديول ٢٩٨ يعيد ٤٠٣ ولا يُدرج صفًّا في rfq_awards ولا يغيّر supplier_rfqs. | V14: مفتوح | W14: مؤكَّدة | X14: محقَّقٌ بالكامل: Procurement/rfq_compare_award.php:20 يفتح معالجَ الترسية، و:33 يدرج صفًّا في rfq_awards و:38 يحوّل supplier_rfqs إلى 'awarded' داخل معاملة، وinsidebar في السطر 66 بعد ذلك كلِّه — بلا can_add/can_edit ولا رمزِ فعل؛ وأثرُه ترسيةُ عطاءٍ على موردٍ (أثرٌ ماليٌّ وقانونيٌّ) يقفلُه فحصُ التكرار فلا يُرسى البندُ ثانيةً. (ملاحظة: CSRF محروسٌ مركزيًّا في config.php لا في الشاشة، فالجزءُ الخاصُّ به من الادّعاء غيرُ دقيق.) | Y14: P0 | Z14: نعم | AA14: نعم | AB14: 06_M14 | AC14: فجوة تنفيذ (Implementation) | AD14: Decision Closed · Implementation Open
A15: INJ-0011 | B15: M-14 | C15: ▐ ١٠ الحرّاس · الحكمُ الرابع «الحارسُ في الخادم قبل الأثر» | D15: المخازن | E15: التحويل بين المخازن | F15: http://localhost/ems/Procurement/wh_transfer.php | G15: ثانيًا: الإدخال والرصيد | H15: لا فعلَ يقع قبل حارسٍ خادميٍّ يفحص صلاحيةَ الكتابة — والرصيدُ أثرٌ مادّيٌّ لا يُمسّ بلا صلاحية | I15: معالجُ POST في السطر ١٨ يفتح معاملةً ويُدرج حركتَي مخزونٍ (تحويل صادر/وارد) في السطرين ٣٤ و٣٦ قبل السطر ٦٠ الذي يُضمِّن insidebar.php حيث الحارسُ الوحيدُ (can_view فقط، insidebar.php:14)؛ ولا فحصَ can_edit ولا رمزَ CSRF — رغم أن مصفوفةَ الصلاحيات تحصر الموديول ٣٠١ بدور «أمين المستودع» وحدَه | J15: Permission Gap | K15: P0 | L15: أيُّ مستخدمٍ مسجَّلٍ في النظام يستطيع نقلَ أيِّ كميةٍ من أيِّ صنفٍ بين أيِّ مخزنين؛ ورصيدُ المخزون محسوبٌ من هذه الحركات، فالأثرُ مباشرٌ على قيمةِ المخزون وعلى تكلفةِ ما يُصرَف منه | M15: شاشةٌ من موجة update0007 كُتبت بالنمط المختصر (فحصُ الجلسة وحدَه) ولم تستدعِ proc_page_perms كأخواتها في المجلد نفسِه | N15: Procurement/wh_transfer.php:10; Procurement/wh_transfer.php:18; Procurement/wh_transfer.php:34; Procurement/wh_transfer.php:36; Procurement/wh_transfer.php:60; insidebar.php:14; database/schema/seed_reference.sql:349; database/schema/seed_reference.sql:1969 | P15: ١) ادخل بحسابٍ من إدارةٍ لا علاقةَ لها بالمخازن. ٢) أرسِل POST إلى /ems/Procurement/wh_transfer.php بالحقول item_id و from_wh و to_wh و qty. ٣) استعلِم proc_stock_move: حركتان جديدتان بمرجع TRF. | Q15: في Procurement/wh_transfer.php أضِف قبل السطر ١٨: $ctx=proc_ctx(); $perms=proc_page_perms($conn,'Procurement/wh_transfer.php',$ctx['is_super']); if(!$perms['can_edit']) { ems_gov_flash_redirect('wh_transfer.php','لا صلاحية تحويل ❌','GOV-PERM-403',''); exit(); } مع تحققِ رمز CSRF | R15: فريق الباك-إند — وحدة المخازن | S15: نعم | T15: نعم | U15: POST من حسابٍ بلا can_edit على الموديول ٣٠١ يعيد ٤٠٣ ولا يُدرج أيَّ صفٍّ في proc_stock_move. | V15: مفتوح | W15: مؤكَّدة | X15: تحققتُ: السطر 18 معالجُ POST، والسطور 32-37 تفتح معاملةً وتُدرج حركتَي proc_stock_move (تحويل صادر/وارد) قبل include '../insidebar.php' في السطر 60. لا فحصَ can_edit ولا رمزَ CSRF، ومصفوفةُ الصلاحيات تحصر الموديول 301 بالدور 25 وحدَه (seed_reference.sql:349,1969) — فأيُّ مصادَقٍ يحرّك رصيدَ المخازن. | Y15: P0 | Z15: نعم | AA15: نعم | AB15: 06_M14 | AC15: فجوة تنفيذ (Implementation) | AD15: Decision Closed · Implementation Open
A16: INJ-0012 | B16: M-14 | C16: ▐ ١٠ الحرّاس · «الحارسُ لا يثق بمدخلات العميل» | D16: المخازن | E16: الجرد ومعالجة الفروقات | F16: http://localhost/ems/Procurement/wh_count.php | G16: رابعًا: الجرد والرقابة | H16: «رابعًا: الجرد والرقابة | محضر جرد · قيد تسوية | المعتمِد: مدير المخازن» — والحارسُ في الخادم ولا يُحتسب فرقٌ من قيمةٍ يرسلها المتصفح | I16: الشاشةُ بلا أيِّ حارسِ صلاحيةٍ (فحصُ الجلسة وحدَه في السطر ١٠، والحارسُ المركزيُّ يأتي في السطر ٥٦ بعد الكتابة)، والأخطرُ أن «الرصيدَ الدفتري» يُرسَل من المتصفح في حقلٍ مخفيٍّ book_qty ويُحسب الفرقُ منه في الخادم ($diff = $actual - $book) بلا إعادةِ احتسابِ الرصيد من proc_stock_move — فالمهاجمُ يتحكم بطرفَي المعادلة | J16: Permission Gap | K16: P0 | L16: أيُّ مستخدمٍ مسجَّلٍ يستطيع كتابةَ تسويةِ مخزونٍ بأيِّ مقدارٍ (زيادةً أو عجزًا) بإرسال book_qty=0 و actual_qty=1000 — أي إنشاءَ مخزونٍ من العدم أو إخفاءَ عجزٍ، بسببٍ نصيٍّ حرٍّ وبلا معتمِدٍ ولا محضرِ جرد | M16: حسابُ الفرق مبنيٌّ على قيمةٍ من العميل، والشاشةُ بلا حارسٍ خادميٍّ ولا اعتمادٍ من مدير المخازن | N16: Procurement/wh_count.php:10; Procurement/wh_count.php:19; Procurement/wh_count.php:22; Procurement/wh_count.php:24; Procurement/wh_count.php:29; Procurement/wh_count.php:116; Procurement/wh_count.php:56 | P16: ١) ادخل بأيِّ حسابٍ مسجَّل. ٢) أرسِل POST إلى /ems/Procurement/wh_count.php?wh=1 بالحقول adjust_item=<صنف> و book_qty=0 و actual_qty=1000 و reason=«جرد». ٣) استعلِم proc_stock_move: حركةُ «تسوية زيادة» بكمية ١٠٠٠. | Q16: في Procurement/wh_count.php: (أ) أضِف حارسَ proc_page_perms + can_edit قبل معالج POST؛ (ب) احذف الحقلَ المخفي book_qty وأعِد احتسابَ الرصيد الدفتري في الخادم من proc_stock_move داخل المعاملة؛ (ج) اشترِط اعتمادَ دورِ مدير المخازن قبل كتابة حركة التسوية | R16: فريق الباك-إند — وحدة المخازن | S16: نعم | T16: نعم | U16: POST بقيمة book_qty ملفَّقةٍ يُنتج حركةَ تسويةٍ محسوبةً من الرصيد الحقيقيِّ لا من المُدخَل، ويُرفض كليًّا بلا can_edit وبلا اعتماد مدير المخازن. | V16: مفتوح | W16: مؤكَّدة | X16: محقَّقٌ بالسطر: Procurement/wh_count.php بلا أيِّ فحصِ صلاحية (الجلسةُ وحدَها في السطر 10) والحارسُ المركزيُّ في السطر 56 بعد الكتابة، ومعالجُ السطر 19-32 يحسب `$diff = $actual - $book` من `book_qty` القادمِ في حقلٍ مخفيٍّ من المتصفح ثم يدرج حركةَ «تسوية زيادة/عجز» في `proc_stock_move` — وهو دفترُ الأرصدة الذي يُحسب منه الرصيدُ الدفتريُّ نفسُه (السطر 40-45)، فالمهاجمُ يتحكم بمقدار التسوية بالكامل. | Y16: P0 | Z16: نعم | AA16: نعم | AB16: 06_M14 | AC16: فجوة تنفيذ (Implementation) | AD16: Decision Closed · Implementation Open
A17: INJ-0013 | B17: INJAZ-FRD-01 | C17: §١٢-٣ المرحلة ٤ · «متحقِّقٌ مستقل» — لا مرحلةَ بلا مخرَج | D17: المراجع الداخلي المستقل | E17: ميثاق المراجعة الداخلية / الكون الرقابي / خطة المراجعة / مهام المراجعة | F17: http://localhost/ems/Audit/iaf_charter.php | G17: غير موجود في السايدبار | H17: «لا مهمةَ بلا خطةٍ ولا خطةَ بلا كونٍ رقابيٍّ ولا كونَ بلا ميثاق» (IAF-0044) — ولكلِّ مرحلةٍ مستندٌ يُنتَج ومعتمِدٌ يشهد. | I17: من الشاشاتِ الستَّ عشرةَ في `Audit/` **شاشةٌ واحدةٌ فقط** تحمل كتلةَ `actions` هي `Audit/iaf_findings.php:32-55` (قبولُ دليلٍ وإغلاقُ ملاحظة). أمّا `iaf_charter` و`iaf_universe` و`iaf_plan` و`iaf_engagements` و`iaf_workpapers` و`iaf_independence` وسائرُها فبلا أيِّ فعل — فلا سبيلَ لإنشاءِ ميثاقٍ ولا اعتمادِه ولا بناءِ كونٍ رقابيٍّ ولا خطةٍ ولا مهمةٍ ولا ورقةِ عملٍ ولا حتى **رفعِ ملاحظة**. والدالةُ `assertCycle` (`InternalAuditService.php:99`) بلا نداءات. | J17: Missing Screen | K17: P0 | L17: دورةُ المراجعةِ الداخليةِ كاملةً غيرُ قابلةٍ للبدء: لا ميثاقَ يُعتمد فلا كونَ فلا خطةَ فلا مهمةَ فلا ملاحظة — والشاشتانِ الوحيدتانِ ذواتا الأفعال (`iaf_findings`) تعملان على صفوفٍ لا يمكن إنشاؤها. النتيجةُ ستَّ عشرةَ شاشةً تعرض «لا بيانات» إلى الأبد. | M17: وُلِّدت الشاشاتُ من بيانِ `tools/u13_screens_manifest.php` بعقودِ عرضٍ فقط؛ ولم تُكتب عقودُ الأفعالِ إلا لشاشةٍ واحدة. | N17: Audit/iaf_charter.php:19; :30; Audit/iaf_universe.php:19; Audit/iaf_plan.php:19; Audit/iaf_engagements.php:19; Audit/iaf_findings.php:32; :55; app/Services/Audit/InternalAuditService.php:99; includes/u13_screen_kit.php:145; :254 | P17: ١) بحساب دور 33 افتح `Audit/iaf_charter.php`: لا كتلةَ «الأفعالُ المتاحةُ على هذه الشاشة» لأن `$U13['actions']` غيرُ معرَّفة. ٢) كرِّر على `iaf_universe` و`iaf_plan` و`iaf_engagements`: النتيجةُ نفسُها. ٣) افتح `Audit/iaf_findings.php`: فعلانِ فقط، وكلاهما يفترض ملاحظةً قائمةً لا سبيلَ لإنشائها. | Q17: أضِف في `tools/u13_screens_manifest.php` عقودَ الأفعالِ الناقصةَ وأعِد التوليد: `iaf.charter.approve` · `iaf.universe.build` · `iaf.plan.approve` · `iaf.engagement.open` · `iaf.workpaper.attach` · `iaf.finding.raise` · `iaf.response.submit` · `iaf.actionplan.set`؛ ونفِّذ كلَّ فعلٍ عبر `InternalAuditService` مع نداءِ `assertCycle` قبله. | R17: فريق الباك-إند — وحدة المراجعة الداخلية (IAF-01) | S17: نعم | T17: نعم | U17: بحساب دور 33: اعتمِد ميثاقًا ← ابنِ كونًا ← اعتمِد خطةً ← افتح مهمةً ← ارفع ملاحظةً ← اقبل دليلًا ← أغلِق — السلسلةُ السبعُ تعمل من الشاشات، وكلُّ قفزةٍ في الترتيبِ تُرفض بـIAF-0044. | V17: مفتوح | W17: مؤكَّدة | X17: تحققتُ بالجرد: من الستَّ عشرةَ شاشةً في Audit/ شاشةٌ واحدةٌ فقط (iaf_findings.php:32-55) تعلن كتلةَ actions، و includes/u13_screen_kit.php:145,254 لا يصيّر أفعالًا إلا للمعلَنة ولا يقدّم نموذجَ إنشاءٍ عامًّا، و assertCycle بلا نداءٍ خارجَ tools/u13_gate.php. فلا ميثاقَ يُنشأ ولا كونَ ولا خطةَ ولا مهمةَ ولا ملاحظةَ تُرفع — والفعلان الوحيدان يعملان على صفوفٍ لا تُنشأ. | Y17: P0 | Z17: نعم | AA17: نعم | AB17: 02_FRD | AC17: فجوة تنفيذ (Implementation) | AD17: Decision Closed · Implementation Open
A18: INJ-0014 | B18: INJAZ-FRD-01 | C18: INJAZ-FRD-01 §٢-٢ · الأحكامُ التي لا تُخالَف | D18: مكتب الرئيس التنفيذي والنواب | E18: توقيع العقود والالتزامات | F18: http://localhost/ems/Portal/ceo_contracts.php | G18: ثالثًا: توقيع العقود | H18: «◆ لا يُثبَّت الرئيسُ التنفيذيُّ معتمِدًا لكل عقدٍ — بل المخوَّلُ ضمن سقفِه ويُصعَّد عند التجاوز.» و«نموذجُ القيادةِ الأحدثُ يقوم على الرئيس التنفيذيِّ وثلاثةِ نوابٍ بنطاقٍ وسقفٍ وتفويضٍ لكلٍّ … وإنابتُه». | I18: التوقيعُ والاعتمادُ وفتحُ المشروع كلُّها محروسةٌ بمقارنةٍ نصيةٍ صلبةٍ واحدة: `$actorRole !== '9'` — لا سقفَ مبلغٍ يُقاس، ولا جدولَ `signing_authorities` يُستشار، ولا نائبَ ولا مُناب. و`exec_dept_caps` تُقرأ في بوابة الطلب المالي فقط لا عند التوقيع. | J18: Governance Gap | K18: P1 | L18: نموذجُ «الرئيس ونوابُه الثلاثة» غيرُ منفَّذٍ إطلاقًا: لا يستطيع نائبٌ توقيعَ عقدٍ في نطاقه، ويستطيع أيُّ حاملٍ للدور 9 توقيعَ عقدٍ بأيِّ مبلغٍ بلا سقف. وتوقُّفُ التوقيع على حسابٍ واحدٍ يجمّد التعاقدَ عند غيابه. | M18: تمثيلُ السلطةِ برقمِ دورٍ واحدٍ بدل مصفوفةِ (نطاق × سقف × تفويض)؛ و`app/Core/AuthorityGuard.php::sign()` القائمُ لا يُستدعى من أيِّ شاشةٍ من شاشات القمة. | N18: Portal/ceo_contracts.php:131; :138; :180-185; Portal/ceo_approvals.php:114; Portal/project_charter.php:148; Governance/signing_authority.php:23; Governance/signing_authority.php:63 | P18: ١) ادخل بحساب نائبٍ (أي دورٍ غير 9) له can_edit على Portal/ceo_contracts.php. ٢) افتح الشاشة ولاحظ اختفاءَ لوحة التوقيع. ٣) أرسل POST بـ cmp03_action=sign ⇒ رفضٌ بـ GOV-PERM-403 مهما كان مبلغُ العقد. ٤) ادخل بدور 9 ووقّع عقدًا بمبلغٍ خرافي ⇒ يُقبل بلا سقف. | Q18: في `Portal/ceo_contracts.php` استبدل شرطَ الدور بمستدعٍ لـ`App\Core\AuthorityGuard::sign()` يقرأ `signing_authorities` (النطاق · السقف · التفويض · مدة الإنابة) ويقارن `amount` بسقف الموقِّع؛ وسجّل `authority_ref` من صفِّ التفويض لا من نصٍّ حر. طبّق النمطَ نفسَه في ceo_approvals.php:114 و project_charter.php:148. | R18: فريق الباك-إند — وحدة الحوكمة والصلاحيات | S18: نعم | T18: نعم | U18: نائبٌ بسقف 100,000 يوقّع عقدًا بـ 90,000 ⇒ يُقبل ويُسجَّل مرجعُ تفويضه؛ ويوقّع عقدًا بـ 150,000 ⇒ يُرفض ويُصعَّد تلقائيًّا لصندوق الرئيس. | V18: مفتوح | W18: مؤكَّدة | X18: تحققتُ من الأسطر: ceo_contracts.php:131 و ceo_approvals.php:114 و project_charter.php:148 كلُّها شرطٌ نصيٌّ واحد $actorRole !== '9' بلا قياسِ سقفٍ ولا قراءةِ signing_authorities. و AuthorityGuard::sign يُستدعى إنتاجيًّا من خدماتٍ أخرى لكن لا من شاشات القمة، وexec_dept_caps تُقرأ في FinRequests/_finreq_helpers.php:879 وحدَها. | Y18: P1 | Z18: نعم | AA18: نعم | AB18: 01_CORE | AC18: فجوة تنفيذ (Implementation) | AD18: Decision Closed · Implementation Open
A19: INJ-0015 | B19: INJAZ-FRD-01 | C19: INJAZ-FRD-01 §٤-٥ · المستهلكُ في عقد الفعل السداسي | D19: مكتب الرئيس التنفيذي والنواب | E19: اعتمادات المدير التنفيذي | F19: http://localhost/ems/Portal/ceo_approvals.php | G19: ثانيًا: الاعتمادات العليا | H19: عقدُ كلِّ فعلٍ سداسيٌّ يحدّد «المستهلكَ» — والإداراتُ المتأثرةُ بأفعال القمة تسعٌ: المالية والخزينة · المبيعات والعقود · إدارة الموردين · التمويل والملكية · الموارد البشرية · إدارة التشغيل · الحوكمة والالتزام · إدارة الأسطول · إدارة المخاطر. | I19: التصحيح: `ems_business_events` **يُقرأ** فعلًا (WorkspaceFeedService.php:206 · Portal/ceo_reports.php) لكنها قراءاتُ عرضٍ لا مستهلكٌ يغلق الحلقة. — [مُصحَّح بعد التحقق] الصياغة الأولى: لا مستهلكَ واحدًا لأيٍّ من مفاتيح القمة الأربعة: البحثُ في المستودع عن `exec.approval.granted` يعيد ناشرَين وقارئَي عدٍّ في لوحةٍ وتقرير؛ ولا مستهلكَ يقرأ من `ems_business_events` أصلًا. فالطلبُ المال | J19: Event/Integration Gap | K19: P1 | L19: حلقةُ التصعيد مفتوحةٌ من طرف: الطلبُ يُرفع آليًّا إلى صندوق القمة (BR-CEO-05) لكنّ نتيجةَ الاعتماد لا ترجع إلى الطلب الأصلي — فتبقى الطلباتُ عالقةً في «قيد الاعتماد» في بوابة الطلبات المالية بعد بتِّها فعليًّا. | M19: تصميمُ الجسر أحاديُّ الاتجاه: `finreq_gm_escalate()` يكتب في exec_approvals ويحمل `source_request_id`، ولا يوجد ما يقرأ هذا العمودَ عند البتّ. | N19: FinRequests/_finreq_helpers.php:938; FinRequests/_finreq_helpers.php:964; FinRequests/_finreq_helpers.php:986-995; Portal/ceo_approvals.php:170-197; Portal/ceo_reports.php:60 | P19: ١) أنشئ طلبًا ماليًّا يتجاوز سقفَ الإدارة ⇒ يُرفع صفٌّ إلى exec_approvals ويصل تنبيهٌ للتنفيذي. ٢) اعتمده من Portal/ceo_approvals.php. ٣) افتح FinRequests/my_requests.php ⇒ الطلبُ ما زال في حالته السابقة بلا أثرٍ للاعتماد. | Q19: في `Portal/ceo_approvals.php` بعد نجاح فرع decide: إن كان `$row['source_request_id'] > 0` فحدِّث الطلبَ الأصليَّ عبر خدمةِ الطلبات (تمريرُ القرار والسبب) وأصدِر إشعارًا لمنشئه؛ والأصحُّ معماريًّا: أنشئ مستهلكًا لـ`exec.approval.granted` في `app/Services/Work/RequestService.php` يفعل ذلك بمفتاح عطالة. | R19: فريق الباك-إند — وحدة الطلبات المالية | S19: نعم | T19: لا | U19: اعتمادُ صفٍّ مرفوعٍ من طلبٍ مالي ينقل الطلبَ الأصليَّ إلى الحالة التالية ويصل إشعارٌ لمنشئه خلال دورةٍ واحدة. | V19: مفتوح | W19: مؤكَّدة | X19: تحقّقت: قرارُ ceo_approvals لا يمسّ `source_request_id` ولا يحدّث الطلبَ المصدري، و`publishFact` يكتب في الجذر المحايد وحدَه بينما EventDispatcher يستهلك من `fin_financial_events` — فلا مستهلكَ لـexec.approval.granted. | Y19: P1 | Z19: نعم | AA19: نعم | AB19: 02_FRD | AC19: فجوة تنفيذ (Implementation) | AD19: Decision Closed · Implementation Open
A20: INJ-0016 | B20: M-14 | C20: SEC-015-ب · فصلُ الواجبات — الزوجُ ⑥ إنشاءُ الصلاحيةِ واعتمادُها | D20: مكتب الرئيس التنفيذي والنواب | E20: اعتمادات المدير التنفيذي | F20: http://localhost/ems/Portal/ceo_approvals.php | G20: ثانيًا: الاعتمادات العليا | H20: «لا يعتمد المرءُ ما أعدّ» — والاعتمادُ الأعلى فعلٌ محجوزٌ للإدارة التنفيذية بسلطتها أو بتفويضٍ موثَّق، ويُسجَّل المعتمِدُ بصفته ومرجعِ تفويضه. | I20: مسارُ «إضافة» (cmp03_action=add) يقبل الحقولَ f12..f16 (قراري · سبب القرار · تاريخ القرار · المعتمِد — الاسم والصفة · مرجع التفويض) وحقلَ الحالة f17 الذي تتضمن قائمتُه القيمةَ «معتمد»، ويُدرجها مباشرةً في `exec_approvals` بحارسٍ واحدٍ هو can_add/can_edit على الشاشة — بلا أيِّ فحصٍ للدور 9. فأيُّ مستخدمٍ يملك can_add يفبرك اعتمادًا أعلى كاملَ الحقول بحالة «معتمد». | J20: Permission Gap | K20: P1 | L20: تُلتفّ حراسةُ الدور 9 الموضوعةُ على مسار «القرار» بالكامل: يظهر في سجل الاعتمادات العليا صفٌّ «معتمد» باسم معتمِدٍ ومرجعِ تفويضٍ يكتبهما المُدخِلُ بيده، ويُقرأ لاحقًا سندًا لصرفٍ أو تعاقدٍ تجاوز السقف. | M20: حارسان مختلفان لمسارين يكتبان الأعمدةَ نفسَها: مسارُ القرار محروسٌ بالدور (سطر 114) ومسارُ الإضافة محروسٌ بصلاحية CRUD فقط (سطر 37)، وقادحُ القاعدة BR-CEO-08 يمنع تعديلَ المقرَّر لا إنشاءَه مقرَّرًا. | N20: Portal/ceo_approvals.php:37; :76; :63-68; :87; :99; :114; :294 | P20: ١) امنح دورًا غيرَ 9 صلاحيةَ can_add على Portal/ceo_approvals.php. ٢) ادخل بذلك الدور وافتح الشاشة. ٣) اضغط «إضافة» واملأ «قراري=اعتماد» و«المعتمِد — الاسم والصفة» و«مرجع التفويض» واختر الحالة «معتمد». ٤) احفظ. ٥) لاحظ ظهور الصف معتمدًا في الجدول بلا مرور الدور 9. | Q20: في `Portal/ceo_approvals.php` داخل فرع add (سطر 76): امنع كتابةَ الحقول decision · decision_reason · decision_date · approver_name · authority_ref و status='معتمد' إلا إذا كان `$actorRole==='9'`؛ واجعل الإدراجَ يفرض status='مسودة' و decision=NULL دائمًا للمُدخِل غير التنفيذي، وأزِل «معتمد» من قائمة f17. | R20: فريق الباك-إند — وحدة القمة التنفيذية (Portal) | S20: نعم | T20: نعم | U20: مستخدمٌ بدور غير 9 وله can_add يحفظ صفًّا بحالة «معتمد» ⇒ يجب أن يُرفض برسالة GOV-PERM-403 وأن يبقى الصفُّ «مسودة» بأعمدة القرار فارغة. | V20: مفتوح | W20: مؤكَّدة | X20: فرعُ add في Portal/ceo_approvals.php:76 يُدرج decision/approver_name/authority_ref وstatus='معتمد' (خيارٌ في القائمة سطر 294) بحارس can_add/can_edit وحده (سطر 37)، بينما فرعُ decide وحدَه يفحص الدور 9 (سطر 114)؛ وقادحُ BR-CEO-08 في هجرة 2026_11_14 قبلَ UPDATE لا INSERT فلا يمنع الإنشاءَ مقرَّرًا. | Y20: P1 | Z20: نعم | AA20: نعم | AB20: 06_M14 | AC20: فجوة تنفيذ (Implementation) | AD20: Decision Closed · Implementation Open
A21: INJ-0017 | B21: M-14 | C21: GOV-009-ب · حارسُ منعِ اعتمادِ الذات على كلِّ موافقة | D21: مكتب الرئيس التنفيذي والنواب | E21: اعتمادات المدير التنفيذي | F21: http://localhost/ems/Portal/ceo_approvals.php | G21: ثانيًا: الاعتمادات العليا | H21: «حارسُ منعِ اعتمادِ الذات» يُستدعى على كلِّ نقطةِ اعتماد: من أنشأ المستندَ لا يعتمده — ويُقارَن المعتمِدُ بمنشئِ الصفِّ لحظةَ المعاملة لا عند منحِ الدور. | I21: لا استدعاءَ لـ`ems_no_self_approval()` في الملف كلِّه؛ فرعُ القرار (سطر 111) يقرأ الصفَّ ويحدّث أعمدةَ القرار بلا مقارنةٍ بين `created_by` و`$uid`. والدورُ 9 نفسُه يستطيع إنشاءَ الصفِّ ثم بتَّه في الجلسة نفسِها. | J21: Permission Gap | K21: P1 | L21: أعلى نقطةِ اعتمادٍ ماليٍّ في المنظومة (ما تجاوز سقوفَ الإدارات) بلا فصلِ يدين: التنفيذيُّ يرفع ويعتمد بنفسه، فيسقط الشاهدُ الرقابيُّ الوحيد على تجاوز السقوف. | M21: الحارسُ `includes/self_approval_guard.php:22` قائمٌ ومستعمَلٌ في أربع نقاطٍ فقط، ولم يُزرع في شاشات القمة؛ والحراسةُ هنا رايةُ دورٍ لا فحصُ يد. | N21: Portal/ceo_approvals.php:111; :127; :154; :165; includes/self_approval_guard.php:22; Contracts/claims.php:99 | P21: ١) ادخل بدور 9. ٢) أضِف صفًّا جديدًا في اعتمادات المدير التنفيذي (سيُسجَّل created_by باسمك). ٣) من لوحة القرار الرباعي اختر الصفَّ نفسَه واضغط «قيد القرار» بخيار «اعتماد». ٤) لاحظ نجاحَ الاعتماد بلا أيِّ منع. | Q21: في `Portal/ceo_approvals.php` قبل تنفيذ UPDATE في فرع decide (بعد سطر 134): `require_once includes/self_approval_guard.php;` ثم `$sa = ems_no_self_approval($conn, intval($row['created_by']), $uid, 'EXAP-'.$rowId, $company_id); if ($sa!==null) { $goBack($sa['reason']); }`. | R21: فريق الباك-إند — وحدة القمة التنفيذية (Portal) | S21: نعم | T21: لا | U21: مستخدمٌ أنشأ صفَّ اعتمادٍ ثم حاول بتَّه ⇒ يُرفض برسالة «لا يعتمد المرءُ ما أعدّ»، ومستخدمٌ آخرُ بدور 9 يبتُّه بنجاح. | V21: مفتوح | W21: مؤكَّدة | X21: تحقّقتُ: لا استدعاءَ لـems_no_self_approval في Portal/ceo_approvals.php، وفرعُ القرار (سطر 111) يحدّث exec_approvals بعد فحصِ الدور 9 فقط بلا مقارنةٍ بـcreated_by الموجودِ فعلًا في الجدول. والحارسُ مستعملٌ في أربع نقاطٍ إنتاجيةٍ أخرى فقط. | Y21: P1 | Z21: نعم | AA21: نعم | AB21: 06_M14 | AC21: فجوة تنفيذ (Implementation) | AD21: Decision Closed · Implementation Open
A22: INJ-0018 | B22: INJAZ-FRD-01 | C22: INJAZ-FRD-01 §٤-٣ · BR-CEO-03 — لا فتحَ مشروعٍ بقرارٍ فردي | D22: مكتب الرئيس التنفيذي والنواب | E22: قرار فتح مشروع جديد | F22: http://localhost/ems/Portal/project_charter.php | G22: رابعًا: فتح المشاريع | H22: «المشروعُ يُفتح بمركز تكلفته · ومديرُ الموقع يُعيَّن بصلاحياته · والمواقعُ تُنشأ · والموارد تُحجز — ولا يقع شيءٌ من هذا بقرارٍ فردي» — والإفادةُ رأيٌ ملزمٌ للعرض. | I22: الإفاداتُ الخمسُ (التشغيل · المبيعات · القوى · المالية · الأسطول) خمسةُ حقولِ نصٍّ حرٍّ في الفورم نفسِه يملؤها المستخدمُ الذي يعتمد؛ ولا صفَّ إفادةٍ منفصلٌ بمُفيدٍ وتاريخٍ ومستند، ولا فحصَ أن المُفيدَ ينتمي للإدارة المعنيّة. الشرطُ الوحيدُ أن الحقلَ غيرُ فارغ. | J22: Governance Gap | K22: P1 | L22: حكمُ «لا قرارَ فرديّ» يتحول إلى شرطِ ملءِ خمسِ خانات: يستطيع الدورُ 9 كتابةَ «تمت» في الخمسة واعتمادَ الفتح خلال دقيقة، فيُفتح مشروعٌ بمركزِ تكلفةٍ وموارد بلا موافقةِ إدارةٍ واحدةٍ فعلية. | M22: نمذجةُ الإفادةِ حقلًا نصيًّا في مستند القرار بدل كيانٍ مستقلٍّ (إفادة = مُفيد + إدارة + تاريخ + مستند + حالة) مربوطٍ بصندوق موافقات الإدارة. | N22: Portal/project_charter.php:83-89; :101-112; :166-172; :75 | P22: ١) ادخل بدور 9. ٢) أضِف قرارَ فتحٍ واكتب «تمت» في الحقول الخمسة للإفادات. ٣) اضغط «اعتماد الفتح» ⇒ ينجح فورًا. ٤) ابحث عن أيِّ سجلِّ إفادةٍ في القاعدة ⇒ لا جدولَ ولا صف. | Q22: أنشئ جدول `charter_certifications(charter_id, dept_code, certified_by, certified_at, doc_ref, state)` وحوّل الحقولَ الخمسةَ في `Portal/project_charter.php` إلى قراءةٍ منه؛ واجعل فرعَ charter (سطر 166) يفحص وجودَ خمسِ صفوفٍ بحالة «معتمد» ومُفيدٍ من الإدارة نفسِها. | R22: فريق الباك-إند — وحدة القمة التنفيذية (Portal) | S22: نعم | T22: نعم | U22: محاولةُ اعتماد الفتح مع إفادةٍ واحدةٍ ناقصةٍ أو مكتوبةٍ من غير إدارتها ⇒ رفضٌ يسمّي الإدارةَ الناقصة؛ ولا يُقبل نصٌّ حرٌّ بديلًا عن صفِّ إفادة. | V22: مفتوح | W22: مؤكَّدة | X22: الإفاداتُ الخمسُ حقولُ نصٍّ حرٍّ في الفورم نفسِه ويكفي أن تكون غيرَ فارغةٍ في فرعَي الإضافة والاعتماد؛ ولا جدولَ إفاداتٍ ولا فحصَ انتماءِ المُفيدِ لإدارته، والوثيقةُ تجعل معتمِدَ المرحلة «القرارَ المشترك». | Y22: P1 | Z22: نعم | AA22: نعم | AB22: 06_M14 | AC22: فجوة تنفيذ (Implementation) | AD22: Decision Closed · Implementation Open
A23: INJ-0019 | B23: INJAZ-FRD-01 | C23: INJAZ-FRD-01 §٥ · إدارةُ التشغيل — إسنادُ التوقفات وأثرُه العابر | D23: إدارة التشغيل | E23: التوقفات وتحديد المتحمل | F23: http://localhost/ems/Operations/stops_unattributed.php | G23: ثالثًا: اعتماد الوحدات | H23: من مِلك إدارة التشغيل: «إسنادَ التوقفات» — والأثرُ ينتقل إلى المبيعات (خصمٌ في المطالبة) وإلى الموردين (تحميلٌ وجزاء) وإلى الصيانة، بالأحداث لا بالنداء. | I23: القيمةُ تُكتب في العمود `timesheet.fault_department` ثم لا يقرؤها أحد: مسحُ المستودع كلِّه يُظهر أن العمودَ يُقرأ للعرض فقط في شاشتَي الاعتماد والتايم شيت؛ ولا مطالبةٌ ولا جزاءٌ ولا تسويةُ موردٍ ولا قاعدةُ تحميلٍ تستعمله، ولا يُنشر حدثٌ عند الإسناد. | J23: Event/Integration Gap | K23: P1 | L23: أهمُّ قرارٍ تشغيليٍّ ذي أثرٍ مالي (من يتحمل ساعةَ التعطل) لا يصل أيَّ إدارةٍ أخرى: المطالباتُ تُحتسب بلا خصم، وتسوياتُ الموردين بلا تحميل، فيضيع الأثرُ المالي كاملًا ويُعاد احتسابُه يدويًّا خارج النظام. | M23: نمذجةُ التبعة عمودًا نصيًّا في جدول التايم شيت بدل واقعةٍ (stop event) لها ذمّةٌ ومستهلكون، وغيابُ أيِّ نشرٍ عند الإسناد. | N23: Operations/stops_unattributed.php:22; Timesheet/view_timesheet.php:289; Approvals/hours_approval.php:320; Contracts/penalties.php:1; app/Services/Contract/PenaltyService.php:1 | P23: ١) أسنِد توقفًا إلى «المورد». ٢) افتح Suppliers/settlements.php وولّد تسويةً للمورد نفسِه للفترة ⇒ لا بندَ تحميلٍ للتوقف. ٣) افتح Contracts/penalties.php واحتسب ⇒ لا خصمَ مرتبطٌ بالتوقف. | Q23: بعد نجاح الإسناد في `Operations/stops_unattributed.php` انشر `operations.stop.attributed` بـ`publishFact` (الجهة · الساعات · العقد · الفترة · مفتاح عطالة ts:<id>)، وأضِف مستهلكَين: أحدهما في `app/Services/Contract/PenaltyService::assess` والآخر في `app/Services/Settlement/SettlementService::generate` يقرآن الواقعةَ ويولّدان البندَ. | R23: فريق الباك-إند — وحدة التشغيل | S23: نعم | T23: لا | U23: إسنادُ توقفٍ إلى مورد ثم توليدُ تسويته للفترة يُنتج بندَ تحميلٍ بمرجع التوقف؛ وإسنادُه إلى العميل يُنتج بندَ خصمٍ في مستخلص الفترة. | V23: مفتوح | W23: مؤكَّدة | X23: الإسنادُ يكتب timesheet.fault_department في stops_unattributed.php:22، ومسحُ المستودع يُظهر قراءةً للعرض فقط في hours_approval.php:320 و view_timesheet.php:289 و api/controllers/timesheet.php:368 — لا مطالبةَ ولا جزاءَ ولا تسويةَ تقرؤه ولا حدثَ يُنشر. والخدمتان المذكورتان في الإصلاح قائمتان فعلًا. | Y23: P1 | Z23: نعم | AA23: نعم | AB23: 02_FRD | AC23: فجوة تنفيذ (Implementation) | AD23: Decision Closed · Implementation Open
A24: INJ-0020 | B24: INJAZ-FRD-01 | C24: INJAZ-FRD-01 §٥-٣ · المرحلة ٥ — الإقفالُ الشهري | D24: إدارة التشغيل | E24: الإقفال الشهري للوحدة | F24: http://localhost/ems/Operations/monthly_close.php | G24: خامسًا: إقفال الفترة | H24: مخرَجُ المرحلة الخامسة مستندُ «الإقفال الشهري» بمعتمِدٍ هو مدير التشغيل — «ولا مرحلةَ بلا مخرَج»، والإقفالُ يمنع ما بعده. | I24: الشاشةُ فورمُ إدخالٍ عامٌّ (CMP-03) يكتب صفًّا واحدًا في جدولها الأصلي عبر `cmp03_store_insert()` بحالةٍ نصيةٍ يختارها المُدخِل؛ لا فعلَ اعتمادٍ ولا معتمِد، ولا قفلَ فترةٍ يمنع تعديلَ التايم شيت أو الإنتاج بعده، ولا حدثَ يُنشر، ولا أثرَ على المالية. | J24: Wrong Workflow | K24: P1 | L24: «الإقفالُ» تسميةٌ بلا مضمون: بعد حفظ صفِّ الإقفال تبقى بياناتُ الشهر قابلةً للتعديل والاعتماد، فلا يوجد في المنظومة لحظةٌ تُغلق فيها الفترةُ التشغيلية — وهو شرطُ صحةِ الإيراد والتكلفة الشهرية. | M24: توليدُ الشاشة ضمن دفعة فورمات CMP-03 (إدخالُ صفوفٍ فقط) بلا آلةِ حالةٍ ولا خدمةِ إقفالٍ خلفها. | N24: Operations/monthly_close.php:94; :100-103; :142; includes/cmp03_local_store.php:31; :55-60 | P24: ١) افتح Operations/monthly_close.php وأضِف صفَّ إقفالٍ لشهرٍ ما بحالة «مقفل». ٢) افتح Timesheet/timesheet.php وأضِف/عدّل سطرًا في الشهر نفسِه ⇒ يُقبل بلا منع. | Q24: أنشئ `app/Services/Operations/PeriodCloseService.php` بفعلَي `close()` و`reopen()` (بسببٍ ومعتمِد)، واربطها بجدول `period_locks(company_id, scope, period, state)`؛ واجعل `Operations/monthly_close.php` تستدعيها، وأضِف في حرّاس الكتابة (Timesheet · Operations · Contracts) فحصَ القفل قبل أيِّ كتابةٍ في فترةٍ مقفلة. | R24: فريق الباك-إند — وحدة التشغيل | S24: نعم | T24: نعم | U24: بعد إقفال شهرٍ يُرفض أيُّ تعديلٍ على تايم شيت أو إنتاجِ الشهر نفسِه برسالةٍ تسمّي الفترةَ ومن أقفلها؛ وفتحُ الفترة يتطلب سببًا ومعتمِدًا أعلى. | V24: مفتوح | W24: مؤكَّدة | X24: تحقّقت: الشاشةُ نموذجُ CMP-03 يكتب صفًّا واحدًا بحالةٍ يختارها المُدخِل عبر cmp03_store_insert، بلا فعلِ اعتمادٍ ولا قفلِ فترةٍ ولا حدث؛ ومعالجُ الـPOST (السطر ٩٤) يسبق حارسَ insidebar (السطر ١٤٢) فالكتابةُ بلا حارس. | Y24: P1 | Z24: نعم | AA24: نعم | AB24: 02_FRD | AC24: فجوة تنفيذ (Implementation) | AD24: Decision Closed · Implementation Open
... A64: INJ-0060 | B64: INJAZ-UX-01 | C64: §٦ الشاشاتُ وأعمدتُها · OBL-0052 «والحقلُ بلا صنفٍ لا يُدرَج في شاشةٍ حاكمة» | D64: إدارة الحوكمة والالتزام | E64: الشاشات المولَّدة بعُدّة u13 (٤٤ شاشة) | F64: http://localhost/ems/Audit/iaf_charter.php | G64: - | H64: «كلُّ حقلٍ يُوسَم بصنفٍ … والحقلُ بلا صنفٍ لا يُدرَج في شاشةٍ حاكمة» — والتصنيفُ شرطُ الظهور. | I64: نشرٌ من database/schema + database/migrations يترك gov_field_class فارغًا فتُصيَّر الشاشاتُ الأربعُ والأربعون برسالة «لا عمودَ مصنَّفٌ لهذه الشاشة» — فجوةُ بذرٍ في خط النشر لا عطبٌ في الشاشات. — [مُصحَّح بعد التحقق] الصياغة الأولى: أعمدةُ الشاشاتِ المولَّدةِ تُقرأ حصرًا من `gov_field_class` (`includes/u13_screen_kit.php:42-73`)، وإن خلا الجدولُ فلا عمودَ يُصيَّر وتُطبع الرسالةُ «لا عمودَ مصنَّفٌ لهذه الشاشة» (`:341-342`). والجدو | J64: Data Mismatch | K64: P1 | L64: أيُّ نشرٍ يبني القاعدةَ من `database/schema/` + `database/migrations/` يُنتج **أربعًا وأربعين شاشةً بلا أعمدةٍ إطلاقًا** — منها كلُّ شاشاتِ المراجعةِ الداخليةِ الستَّ عشرةَ وشاشاتِ الالتزاماتِ الماليةِ وشاشاتِ رئيسِ الحسابات. جداولُ فارغةٌ برأسٍ فارغ، والمستخدمُ يظنُّ الشاشةَ معطوبة. | M64: خطوةُ بذرٍ إلزاميةٌ خارجَ مسارِ النشرِ الآلي (أداةُ CLI) وبلا فحصٍ يمنع النشرَ عند خلوِّ الجدول. | N64: includes/u13_screen_kit.php:42-73,206-207,341-342; database/migrations/2026_12_24_u13_field_governance.sql:52-60; tools/u13_seed.php:802 | P64: ١) ابنِ قاعدةً جديدةً من `database/schema/schema.sql` + `seed_reference.sql` + كلِّ الهجرات. ٢) `SELECT COUNT(*) FROM gov_field_class` → صفر. ٣) افتح `Audit/iaf_charter.php` أو `Finance/ob_register.php`: جدولٌ بلا أعمدةٍ ورسالةُ «لا عمودَ مصنَّفٌ لهذه الشاشة». | Q64: حوِّل مخرَجَ `tools/u13_seed.php` إلى هجرةِ SQL ثابتةٍ داخلَ `database/migrations/` (أو صفوفٍ في `seed_reference.sql`) كي يُبذَر الجدولُ في كلِّ نشرٍ آليًّا؛ وأضِف فحصًا في `tools/u13_gate.php` يرسب إن كانت أيُّ شاشةٍ في البيانِ بلا صفوفٍ في `gov_field_class`. | R64: فريق الباك-إند — الحوكمة والمنصة | S64: نعم | T64: نعم | U64: بعد نشرٍ نظيفٍ من `database/` وحدَه: كلُّ شاشةٍ من الأربعِ والأربعين تعرض أعمدتَها المصنَّفة، و`SELECT COUNT(*) FROM gov_field_class` > 0. | V64: مفتوح | W64: مرجَّحة | X64: مؤكَّدٌ بالفحص: u13_columns (includes/u13_screen_kit.php:42-73) تُسقط كلَّ عمودٍ بلا صفٍّ في gov_field_class (:66 «بلا صنفٍ = لا يُصيَّر») وتُطبع رسالةَ الفراغ (:341-342)؛ وgov_field_class لا يرد في seed_reference.sql إطلاقًا، والهجرتان تُنشئان الجدولَ بلا INSERT، والمصدرُ الوحيد tools/u13_seed.php:802 بـ--apply ولا يستدعيه أيُّ سكربتِ نشر. لكنه فجوةُ بذرٍ في النشر تُصلَح بتشغيل أداةٍ واحدة، لا فقدانَ شاشةٍ أو مصدرِ حقيقة. | Y64: P0 | Z64: نعم | AA64: نعم | AB64: 03_UX | AC64: فجوة تنفيذ (Implementation) | AD64: Decision Closed · Implementation Open
A65: INJ-0061 | B65: INJAZ-UX-01 | C65: §٤-٥ · «الرابطُ الميت مستبعدٌ بنيويًّا لا برأي الشاشة» | D65: إدارة الحوكمة والالتزام | E65: السايدبار — مسارات نسبية مزدوجة | G65: - | H65: «الظهور = صفٌّ تابعٌ للدور في nav_items (active=1) **و** can_view=1 … الرابطُ الميت مستبعدٌ بنيويًّا» — والمسارُ في `nav_items` «المسارُ كما في سجلِّ الشاشات». | I65: كلُّ الصفوف الـ41 ذاتِ البادئة `../` تحمل أيضًا `module_id=NULL` مع `permission_code` غيرِ فارغٍ و`door='main'` — فيسقطها شرطُ `getUnifiedNavItems` ولا يُصيَّر أيٌّ منها في أيِّ سايدبار (41 شاشةَ update0013 محجوبةٌ كليًّا). — [مُصحَّح بعد التحقق] الصياغة الأولى: عمودُ `route` في `nav_items` غيرُ متجانس: ١٥٠٧ صفًّا بمسارٍ نسبيٍّ من جذرِ التطبيق (`Risk/risk_board.php`) و٤١ صفًّا بمسارٍ مسبوقٍ بـ`'../'` (`../Audit/iaf_charter.php`). و`printNavLinkItem` يضيف `$ba | J65: Broken Button | K65: P1 | L65: حتى لو صُحِّح البابُ فستُطبع واحدٌ وأربعون رابطًا مكسورًا (404) — إصلاحٌ نصفيٌّ سيُنتج عيبًا ظاهرًا للمستخدم. ويشير إلى غيابِ قيدِ صحةٍ على عمودِ المسار. | M65: أُدرجت الصفوفُ بهجرةٍ يدويةٍ نسخت المسارَ من `href` في الشاشةِ لا من سجلِّ الشاشات. | N65: database/schema/seed_reference.sql:5057; :5077; :5096; includes/dynamic_nav.php:320; includes/unified_nav.php:70-78 | P65: ١) `SELECT COUNT(*) FROM nav_items WHERE route LIKE '../%'` → ٤١. ٢) قارِنها بالصفوفِ الأخرى: بلا بادئة. ٣) اقرأ `includes/dynamic_nav.php:320`: البادئةُ تُضاف دائمًا. | Q65: نفِّذ `UPDATE nav_items SET route = TRIM(LEADING '../' FROM route) WHERE route LIKE '../%'`؛ وأضِف قيدَ فحصٍ (CHECK أو قادحًا) يمنع إدراجَ مسارٍ يبدأ بـ`../` أو `/`، وفحصًا في بوابةِ القبولِ يقارن `route` بـ`modules.code` ويرسب على الاختلاف. | R65: فريق الواجهة — وحدة التنقل | S65: نعم | T65: لا | U65: `SELECT COUNT(*) FROM nav_items WHERE route LIKE '../%' OR route NOT IN (SELECT code FROM modules)` = 0؛ وكلُّ رابطٍ في السايدبار يفتح صفحتَه بلا 404. | V65: مفتوح | W65: مؤكَّدة | X65: العددان مطابقان تمامًا (1507 مقابل 41)، و`printNavLinkItem` يضيف `$basePrefix` دائمًا؛ بل الأسوأُ أن الصفوفَ الأربعين لا تُطبع أصلًا فتختفي الشاشاتُ الجديدةُ كليًّا. | Y65: P1 | Z65: لا — يحتاج مراجعة | AA65: نعم | AB65: 03_UX | AC65: فجوة تنفيذ (Implementation) | AD65: Decision Closed · Implementation Open
A66: INJ-0062 | B66: INJAZ-CORE-01 | C66: ١٠-٣ الحكم · العيوبُ المقياسيةُ الأربعة — MD-05 | D66: إدارة الحوكمة والالتزام | E66: عيبٌ مقياسيٌّ حرج — إعلانُ إغلاقٍ ببناءِ الحارسِ لا بتطبيقِه | G66: - | H66: «MD-05 … سلّمٌ رباعيٌّ — ولا إغلاقَ قبل المستوى الثالث · ◆ ما وقع: عيبٌ أُعلن مغلقًا عند المستوى الأولِ — والشاشةُ المصابةُ لم تُمسّ · وتُعاد قراءةُ المغلقاتِ كلِّها بهذا السلّم». | I66: أربعةُ حرَّاسٍ محقَّقين مبنيّون (L1) وغيرُ مطبَّقين (لا L3): `InternalAuditService::assertReadOnly` بصفرِ نداءات، و`InternalAuditService::logAccess` بصفرِ نداءات، و`App\Core\ProcessedOperations` بصفرِ مستهلكين، و`app/Services/Actions/ReverseService` بصفرِ نداءات. ويُضاف إليها `SensitiveFieldGuard` غيرُ المستدعى من أيِّ ملفٍّ في `Risk/`. | J66: Missing Evidence | K66: P1 | L66: كلُّ ادعاءِ إغلاقٍ مبنيٍّ على «بُني الحارسُ» غيرُ صحيح: الحمايةُ غيرُ عاملةٍ في المواضعِ المصابة — والعيبُ يُعيد فتحَ قراءةِ كلِّ العيوبِ المُعلَنةِ مغلقة. | M66: قياسٌ أو إغلاقٌ أُعلن على أساسٍ لا يطابق ما تُلزم به الوثيقة — والعيبُ مسجَّلٌ ولم يُعلَن إغلاقُه. | N66: app/Services/Audit/InternalAuditService.php:49; :70; app/Core/ProcessedOperations.php:22; app/Services/Actions/ReverseService.php:13; app/Services/Security/SensitiveFieldGuard.php:103 | P66: ١) افتح سجلَّ العيوبِ والقراراتِ في وثيقةِ التنفيذِ وتحقَّق من حالةِ MD-05: مفتوح. ٢) ابحث في النظامِ عن أثرِ إغلاقِه بالأدلةِ المذكورةِ في حقل Evidence: غيرُ موجود. ٣) قارِن بالحكمِ: «لا يُعلَن الإطلاقُ ولا يُقال إن الحزمةَ مكتملةٌ قبل إغلاق كلِّ عيبٍ حاجب». | Q66: أنشئ فاحصًا آليًّا (`tools/guard_adoption_gate.php`) يمرُّ على كلِّ صنفِ حارسٍ في `app/Services/Security` و`app/Core` و`app/Services/Audit` ويرسب إن كان عددُ مستهلكيه في كودِ الإنتاج صفرًا؛ وأعِد تصنيفَ كلِّ عيبٍ مغلقٍ على سلّمِ L1..L4 وأعِد فتحَ ما أُغلق عند L1/L2. | R66: مالكُ الحزمة + إدارة الحوكمة والالتزام | S66: نعم | T66: نعم | U66: سجلُّ حواجزِ الإصدارِ يُظهر MD-05 بحالةِ «مغلق» مع دليلٍ ملفًّا وسطرًا واختبارٍ آليٍّ يمنع عودتَه (المستوى L4). | V66: مفتوح | W66: مؤكَّدة | X66: تحققتُ من الخمسة كلِّها: InternalAuditService::assertReadOnly و::logAccess بلا نداءٍ خارجَ tools/u13_gate.php، و App\Core\ProcessedOperations بلا مستهلكٍ خارجَ tests/n06_transaction_bounds_test.php، و ReverseService:: بصفرِ نداءاتٍ إطلاقًا (ذكرٌ في تعليقٍ فقط بـActionContractService.php:85)، و SensitiveFieldGuard خارجَ الاختبارات والأدوات. لكنها ملاحظةٌ مقياسيةٌ عن ادعاءات الإغلاق لا عيبٌ واحدٌ يحجب الإصدار بذاته. | Y66: P0 | Z66: نعم | AA66: نعم | AB66: 05_DELIVERY | AC66: فجوة دليل (Evidence) | AD66: Implementation Closed · Evidence Open
A67: INJ-0063 | B67: M-14 | C67: SCN-876-أ / glass.break · ▐ ١١-٦ الأفعالُ وعقودُها | D67: إدارة الحوكمة والالتزام | E67: صلاحية الطوارئ اللحظية (كسر الزجاج) | F67: http://localhost/ems/Governance/break_glass.php | G67: خامسًا: المنع والاستثناء | H67: «يجب أن يُنفَّذ فعلُ (منحُ صلاحية طوارئ) من شاشة صلاحية الطوارئ اللحظية (كسر الزجاج) بواسطة الإدارةُ العامة، فيُكتب في break_glass · audit ويُنشر الحدثُ BreakGlassGranted ويستهلكه الحوكمة · الإدارة المعنية» | I67: الشاشة نموذجُ CMP-03 عامّ يكتب صفًّا نصيًّا واحدًا في scr_break_glass عبر cmp03_store_insert فقط. لا تمنح أي صلاحية، ولا تكتب في permission_exceptions، ولا تُعيد بناء الصلاحية المشتقة، ولا تنشر BreakGlassGranted، ولا تكتب سجل تدقيق. زر «حفظ» يحفظ نصًّا يُعرض في جدولٍ ثم ينتهي أثره. | J67: Governance Gap | K67: P1 | L67: «كسر الزجاج» في النظام وهمٌ تشغيليّ: من يحتاج صلاحيةً طارئةً لن يحصل عليها من هذه الشاشة، ومن يريد تجاوزَ حارسٍ سيفعله بطريقٍ آخر بلا أثر. الحوكمة تظنّ أن لديها ضابطًا وهي بلا ضابط. | M67: الشاشة وُلدت من مولّد CMP-03 كنموذج مفاتيح/قيم عام (payload → cmp03_store_insert) ولم تُوصَل بخدمة المنح app/Services/Security/BreakGlassService::grant التي بُنيت لهذا الغرض. | N67: Governance/break_glass.php:73; :82; :83; includes/cmp03_local_store.php:31; :55; app/Services/Security/BreakGlassService.php:22 | P67: ١) ادخل بدور «إدارة الصلاحيات» (15). ٢) افتح خامسًا: المنع والاستثناء ← صلاحية الطوارئ اللحظية (كسر الزجاج). ٣) اضغط «إضافة» واملأ الحقول واضغط «حفظ». ٤) لاحظ ظهور صفٍّ في الجدول. ٥) افتح قاعدة البيانات: صفر صفٍّ جديدٍ في permission_exceptions وصفر صفٍّ في activity_logs وصفر حدثٍ BreakGlassGranted. ٦) جرّب فتح شاشةٍ ممنوعة على المستخدم المذكور في الصف — ما زالت ممنوعة. | Q67: استبدال معالج POST في Governance/break_glass.php:73-85 بنداءٍ إلى App\Services\Security\BreakGlassService::grant($conn, [...]) مع تمرير company_id · person_id · permission_code · scope_rule · reason · granted_by · hours، واستقبال الردّ (403/422) وعرضه، وإبقاء cmp03_store_insert مرآةَ عرضٍ فقط لا مصدرَ حقيقة. | R67: فريق الباك-إند — وحدة الحوكمة والصلاحيات | S67: نعم | T67: نعم | U67: منح كسر زجاجٍ لمستخدمٍ على مفتاحٍ محدد ⇐ يجب أن يظهر صفٌّ في permission_exceptions بحالة active وvalid_to = NOW()+ساعات، وأن يفتح المستخدم الشاشةَ الممنوعة فورًا، وأن تُغلق تلقائيًّا بانتهاء المدة. | V67: مفتوح | W67: مؤكَّدة | X67: معالجُ POST (73-85) لا يفعل إلا cmp03_store_insert في scr_break_glass، و BreakGlassService::grant — المكتملُ بحارس SelfGrantGuard وقيدِ never وفتحِ بلاغٍ آلي — بلا أيِّ مستدعٍ في الشيفرة (المستدعى الوحيدُ sweepUnreviewed من Governance/cron_permissions.php:24). لكن الخللَ يفشل آمنًا: الشاشةُ لا تمنح شيئًا ولا تفتح ثغرةَ صلاحية، فليست حاجزَ إصدار. | Y67: P0 | Z67: نعم | AA67: نعم | AB67: 06_M14 | AC67: فجوة تنفيذ (Implementation) | AD67: Decision Closed · Implementation Open
A68: INJ-0064 | B68: M-14 | C68: SCN-721-أ · SCN-721-ب · ▐ ١١-٣ الشاشاتُ والمناظرُ والعرض | D68: إدارة الحوكمة والالتزام | E68: سجل التدقيق والاطّلاع | G68: غير موجود في السايدبار | H68: «يجب أن تُتاح شاشةُ (سجل التدقيق والاطّلاع) لـالحوكمة والالتزام بنطاق كل النظام · وزاويتُها: من فعل ومن اطّلع ومتى — ولا يُعدَّل» بأعمدتها الستة والعشرين (SCN-722). | I68: لا شاشةَ في نطاق الدور 15 تعرض activity_logs؛ والأثرُ محفوظٌ ويُعرض للسوبر أدمن، وسجلُّ المنع وسجلُّ اطّلاع المراجع موجودان في شاشتين أخريَين. — [مُصحَّح بعد التحقق] الصياغة الأولى: لا وجودَ لشاشةِ سجل تدقيقٍ في مجلد Governance/ ولا في سايدبار الدور 15. الشاشةُ الوحيدة التي تعرض activity_logs هي admin/audit_log.php وهي خلف بوابةِ السوبر أدمن المنفصلة (super_admin_require_login) ف | J68: Missing Screen | K68: P1 | L68: الحوكمةُ لا ترى سجلَّ التدقيق — وهو مصدرُ عملها الأول. اختبارُ M-14 «من فعل ومن اطّلع ومتى» غيرُ قابلٍ للتنفيذ داخل النظام، والمراجعةُ تتم خارجَه بقاعدة البيانات مباشرة. | M68: سجلُّ النشاط صُنّف منصّيًّا (T_PLATFORM) وسُكن في بوابة الأدمن المنفصلة، ولم تُبنَ نسخةٌ مستأجَرةٌ للحوكمة داخل التطبيق. | N68: admin/audit_log.php:2-3; includes/audit_trail.php:68; Governance/guard_denials.php:22; Audit/iaf_access_log.php:3 | P68: ١) ادخل بدور 15. ٢) افتح «سادسًا: التدقيق والمراجعة» في السايدبار. ٣) لا رابطَ لسجل التدقيق. ٤) اكتب http://localhost/ems/admin/audit_log.php ⇐ تُعاد للدخول لأن super_admin_require_login يطلب جلسةَ أدمنٍ مختلفة. | Q68: إنشاء Governance/audit_log.php بأعمدة SCN-722 الستة والعشرين تقرأ activity_logs بنطاق الشركة عبر ems_tenant_db، وتسجيلُها موديولًا بمالكٍ 15، وإضافةُ صفِّ nav_items لها في مجموعة «سادسًا: التدقيق والمراجعة»، مع منعِ كل فعلِ تعديلٍ أو حذفٍ عليها بنيويًّا. | R68: فريق الباك-إند — وحدة الحوكمة والصلاحيات | S68: نعم | T68: نعم | U68: الدور 15 يفتح «سجل التدقيق والاطّلاع» من سايدباره ويرى صفوفَ activity_logs لشركته بأعمدة القيمة قبل/بعد، ولا يجد أيَّ زرِّ تعديلٍ أو حذف. | V68: مفتوح | W68: مرجَّحة | X68: محقَّق: لا استعلامَ واحدًا في المستودع يقرأ `audit_logs`، و`activity_logs` (وجهةُ ems_audit_change في includes/audit_trail.php:68) لا تُعرض إلا في admin/audit_log.php:2-3 خلف `super_admin_require_login`؛ غير أن أثرَ التدقيق ليس محجوبًا كلِّيًّا — Governance/guard_denials.php يعرض سجلَّ المنع الحيَّ وAudit/iaf_access_log.php سجلَّ اطّلاع المراجع — فالناقصُ عارضُ أثرِ التدقيق لدور الحوكمة لا الأثرُ نفسُه. | Y68: P0 | Z68: نعم | AA68: نعم | AB68: 06_M14 | AC68: فجوة تنفيذ (Implementation) | AD68: Decision Closed · Implementation Open
A69: INJ-0065 | B69: M-14 | C69: SCN-869..SCN-871 (سياسات الحقول الحساسة) · ▐ ١١-٥ | D69: إدارة الحوكمة والالتزام | E69: سياسات الحقول الحساسة | F69: http://localhost/ems/Governance/sensitive_fields.php | G69: خامسًا: المنع والاستثناء | H69: الحقلُ الحساس يُصنَّف فيُحجب بالصلاحية ويُسجَّل كلُّ اطّلاعٍ عليه، ويقبل الفعلُ عكسًا: «رفعُ التصنيف» (SCN-871). | I69: الشاشة نموذجُ CMP-03 يكتب صفوفًا في scr_sensitive_fields عبر cmp03_store_insert. الحارسُ الفعلي app/Services/Security/SensitiveFieldGuard يقرأ جدولًا مختلفًا (sensitive_field_policies)، وexcel.php يستعلم scr_sensitive_fields للتسجيل فقط ثم يبثّ الحقلَ كاملًا. لا زرَّ رفعِ تصنيفٍ في الشاشة (زرُّ الرأس الوحيد «إضافة»). | J69: Governance Gap | K69: P1 | L69: تصنيفُ حقلٍ حساسٍ من شاشة الحوكمة لا يحجبه عن أحد ولا يغيّر سلوكَ أيِّ شاشةٍ أو تصدير؛ فالسياسةُ إعلانٌ لا إنفاذ، والعكسُ المنصوصُ عليه غيرُ ممكن. | M69: جدولان لغرضٍ واحد (scr_sensitive_fields للعرض وsensitive_field_policies للإنفاذ) بلا مزامنةٍ ولا مصدرِ حقيقةٍ واحد — مخالفةُ PR-01 داخل الحوكمة نفسها. | N69: Governance/sensitive_fields.php:88; :135-137; app/Services/Security/SensitiveFieldGuard.php:82; excel.php:89-96 | P69: ١) صنّف حقل «الراتب» حساسًا في Governance/sensitive_fields.php. ٢) افتح شاشةً تعرض الراتب بدورٍ بلا منحة ⇐ القيمة ظاهرة. ٣) صدّر الكيان ⇐ العمود في الملف بقيمته. | Q69: توحيدُ المصدر: جعلُ Governance/sensitive_fields.php تكتب في sensitive_field_policies (الجدول الذي يقرؤه الحارس) بدل scr_sensitive_fields، وإضافةُ فعلِ «رفع التصنيف» كسطرٍ جديدٍ يشير إلى الأصل لا كحذف، وتمريرُ نتيجة السياسة إلى Exporter لحجب العمود. | R69: فريق الباك-إند — وحدة الحوكمة والصلاحيات | S69: نعم | T69: نعم | U69: تصنيفُ حقلٍ حساسًا يُخفي قيمتَه فورًا عمّن لا منحةَ له ويُسقطه من ملف التصدير، ويُنتج صفَّ اطّلاعٍ لمن يملك المنحة. | V69: مفتوح | W69: مؤكَّدة | X69: انفصالُ المصدر ثابت: الشاشةُ تكتب scr_sensitive_fields عبر cmp03_store_insert بينما SensitiveFieldGuard يقرأ sensitive_field_policies (سطر 82) وهو بلا مستدعٍ إنتاجيٍّ أصلًا؛ وexcel.php:89 يقرأ scr_sensitive_fields للتسجيل ثم يبثّ الحقلَ كاملًا؛ وأفعالُ رأس الشاشة زرُّ «إضافة» وحده (سطر 135-137). | Y69: P1 | Z69: نعم | AA69: نعم | AB69: 06_M14 | AC69: فجوة تنفيذ (Implementation) | AD69: Decision Closed · Implementation Open
A70: INJ-0066 | B70: M-14 | C70: GOV-009-و (حارسُ التفويض على كلِّ موافقة) · SCN-840 · TABLE 36 (delegations.php) | D70: إدارة الحوكمة والالتزام | E70: التفويض بالتوقيع | F70: http://localhost/ems/Governance/signing_authority.php | G70: غير موجود في سايدبار الحوكمة | H70: «التفويض بالتوقيع» (delegations.php) شاشةٌ من شاشات الحوكمة الأربع عشرة المعلنة في INJAZ-FRD-01 §١٣-٤ ومالكُها الحوكمة والالتزام، وعارضوها «14 إدارة». | I70: الحارسُ في رأس الملف يحصر الوصولَ في الأدوار -1 و1 و19 كتابةً وفي الدور 26 قراءةً: `$gov_write = ($role === '-1' || in_array($role, array('1','19'), true)); if (!$gov_write && $role !== EMS_ROLE_FINANCING_MGR) { redirect }`. الدور 15 (إدارة الصلاحيات — الحوكمة) ليس في القائمتين فيُعاد توجيهُه، والشاشةُ غائبةٌ عن سايدباره تمامًا. | J70: Permission Gap | K70: P1 | L70: الإدارةُ المالكةُ للتفويض بالتوقيع لا تستطيع فتحَ سجلِّ التفويض ولا قراءتَه — بينما إدارةُ التشغيل (1) تملك عليه صلاحيةَ كتابةٍ كاملة. انقلابُ ملكيةٍ صريحٌ في أخطر سجلٍّ قانونيٍّ في النظام. | M70: حارسٌ مكتوبٌ بأرقام أدوارٍ ثابتة في الكود بدل مفتاحِ صلاحيةٍ مسجَّل، وقائمةُ الأرقام نُسخت من شاشةٍ ماليةٍ (ownership_grants) دون مراجعةِ المالك. | N70: Governance/signing_authority.php:24-27,31-33; database/schema/seed_reference.sql:259; database/schema/seed_reference.sql:1431,1432,1447,1729 | P70: ١) ادخل بدور 15. ٢) ابحث في السايدبار عن «التفويض بالتوقيع» ⇐ غير موجود. ٣) اكتب http://localhost/ems/Governance/signing_authority.php ⇐ إعادةُ توجيهٍ برسالة «باب الحوكمة خلف صلاحيته». ٤) ادخل بدور 1 ⇐ تُفتح كاملةً بصلاحية كتابة. | Q70: استبدالُ الفحص المرمَّز في Governance/signing_authority.php:24-26 بـcheck_page_permissions($conn,'Governance/signing_authority.php')، وتسجيلُ الشاشة موديولًا بمالكٍ 15، ومنحُ الدور 15 can_view/can_add/can_edit والدور 1 عرضًا فقط، وإضافةُ صفِّ nav_items في مجموعة «ثالثًا: الحسابات والأدوار» أو مجموعةٍ جديدة «التفويض». | R70: فريق الباك-إند — وحدة الحوكمة والصلاحيات | S70: نعم | T70: نعم | U70: الدور 15 يفتح «التفويض بالتوقيع» من سايدباره ويضيف تفويضًا؛ والدور 1 يفتحها للقراءة ويُرفض POST منه برمز GOV-PERM-403. | V70: مفتوح | W70: مؤكَّدة | X70: الأسطر 24-26 حرفيًّا كما وُصفت، ومصفوفةُ الصلاحيات للموديول 207 تمنح الأدوار 1 و19 كتابةً و26 و9 عرضًا ولا شيءَ للدور 15 — فانقلابُ الملكية حقيقيّ. لكنه خللُ إسنادِ صلاحياتٍ وبذرة، لا أثرًا ماليًّا غيرَ مصرَّحٍ ولا تسريبَ بيانات، وإصلاحُه صفوفُ role_permissions ونداءُ check_page_permissions. | Y70: P0 | Z70: نعم | AA70: نعم | AB70: 06_M14 | AC70: فجوة تنفيذ (Implementation) | AD70: Decision Closed · Implementation Open
A71: INJ-0067 | B71: M-14 | C71: includes/action_guard.php · PR-05 · «الحارسُ في الخادم» | D71: إدارة الحوكمة والالتزام | E71: طبقة حارس الأفعال | F71: http://localhost/ems/includes/action_guard.php | G71: - | H71: «كلُّ منعٍ يُنفَّذ في الخادم قبل الحفظ … والنداءُ المخالفُ يُرفض ولو جاء بمساره مباشرةً» — والحارسُ يفحص مفتاحًا محددًا لا يُخمَّن. | I71: حارسُ الأفعال يمرّر تسعةَ مفاتيحَ زائفةٍ بادئتُها اسمُ مجلد (Contracts/ · Employees/ · Equipments/ · Maintenance/ · Oprators/ · Reports/ · Risk/ · Suppliers/ · Timesheet/) إلى check_page_permissions، والتي تسقط إلى استعلامٍ تقريبيّ `code LIKE '%<prefix>%' ORDER BY CHAR_LENGTH(code) ASC, id ASC LIMIT 1` فيُحَلّ المفتاحُ إلى أيِّ موديولٍ تحت المجلد اعتباطًا. وتعليقُ الملف نفسُه يوثّق أن هذا العطبَ أسقط ٢٧ من ٣٧ اعتمادًا في اختبار شاملٍ سابق. | J71: Permission Gap | K71: P1 | L71: قرارُ السماح أو المنع في تسعة مجلداتٍ كاملة يُبنى على موديولٍ يُختار بطول الاسم لا على الشاشة المقصودة — فقد يُمنح فعلٌ خطيرٌ لأن موديولًا آخر تحت المجلد نفسه ممنوحٌ للدور. حارسٌ غيرُ حتميّ. | M71: غيابُ سجلِّ مفاتيحَ مسمّاة (انظر الملاحظة السابقة) دفع إلى تمرير بادئات مجلدات، وسقطت في مسار التطابق التقريبي في permissions_helper. | N71: includes/action_guard.php:39; :93; :100; includes/permissions_helper.php:512; :518 | P71: ١) امنح دورًا can_edit على شاشةٍ صغيرةٍ تحت Maintenance/ ولا تمنحه Maintenance/orders.php. ٢) نفّذ فعلًا محروسًا بمفتاح 'Maintenance/'. ٣) يُقبل الفعلُ لأن الاستعلامَ التقريبيَّ حلَّ المفتاحَ إلى الموديول الممنوح. | Q71: استبدالُ البادئات التسع في includes/action_guard.php:39-112 بمفاتيحَ مطابقةٍ حرفيًّا لمسارات الشاشات، وإلغاءُ فرع التطابق التقريبي في includes/permissions_helper.php:512-518 واستبدالُه بمطابقةٍ حرفيةٍ ترجع null عند عدم التطابق (ثم fail-closed). | R71: مكتب الهندسة — طبقة الحراس المشتركة | S71: نعم | T71: لا | U71: مفتاحٌ لا يطابق موديولًا مسجَّلًا حرفيًّا يُرجع منعًا مسجَّلًا لا موديولًا مشابهًا؛ واختبارُ الاعتمادات الشامل يمرّ ٣٧/٣٧. | V71: مفتوح | W71: مؤكَّدة | X71: السجلُّ يمرّر بادئاتِ مجلداتٍ (Risk/ · Timesheet/ · Contracts/ · Suppliers/ · Equipments/ …) إلى check_page_permissions التي تسقط إلى LIKE '%prefix%' ORDER BY CHAR_LENGTH(code) ASC (permissions_helper:511-512)، وتعليقُ الملف نفسِه يوثّق الحادثةَ (37←10). والعلمُ الحيُّ EMS_ACTION_GUARD=enforce بنصِّ docs/PHASE1_CLOSURE_REPORT_ar.md فالقرارُ نافذٌ لا مراقَب. | Y71: P1 | Z71: نعم | AA71: نعم | AB71: 06_M14 | AC71: فجوة تنفيذ (Implementation) | AD71: Decision Closed · Implementation Open
A72: INJ-0068 | B72: M-14 | C72: GOVX-0974 · التصديرُ والاستيرادُ والمشاركة | D72: إدارة الحوكمة والالتزام | E72: إطار الاستيراد الموحَّد (Excel) | F72: http://localhost/ems/excel.php?action=import_commit | G72: - | H72: CORE AR-05: «الحارسُ في الخادم يرفض النداءَ ولو جاء بمساره مباشرةً» — وكلُّ كتابةٍ تمرُّ بالحارسِ المالكِ للحكمِ مهما كان مصدرُها. | I72: `Importer::commit` يبني جملةَ إدراجٍ عامةً `INSERT INTO `{$table}` (...) VALUES (...)` (`app/Services/Excel/Importer.php:134`) وينفّذها في معاملةٍ واحدةٍ لكلِّ الصفوف (`:145-186`) — بلا أيِّ نداءٍ للخدماتِ المالكةِ للحكم: لا `RiskService` ولا `WorkItemService` ولا حرَّاسِ فصلِ الواجباتِ ولا قادحاتِ الحالةِ ولا نشرِ أحداث. الحارسُ الوحيدُ فحصُ `can_add` على مودولِ الشاشةِ في `ExcelService` (`:61-65`). | J72: Export/Import Gap | K72: P1 | L72: بابُ كتابةٍ موازٍ يلتفُّ على كلِّ الحرَّاس: يمكن استيرادُ صفوفٍ إلى `commercial_risks` أو أيِّ كيانٍ مسجَّلٍ بحالاتٍ وقيمٍ لا يسمح بها المحرّك، بلا حدثٍ منشورٍ ولا أثرٍ في «مهامي» ولا سجلِّ تدقيقٍ للفعلِ نفسِه — ويُفسد ذلك ثقةَ كلِّ المؤشراتِ المبنيةِ على تلك الجداول. | M72: بُني الإطارُ العامُّ للاستيرادِ على مستوى الجدولِ لا على مستوى الفعل، فتجاوز طبقةَ الخدماتِ كلَّها. | N72: app/Services/Excel/Importer.php:129; :134; :136; :145; :147; app/Services/Excel/ExcelService.php:61; :64; :65; app/Services/Excel/ExcelRegistry.php:941 | P72: ١) نزِّل نموذجَ الاستيرادِ لكيانٍ حاكمٍ (مثلًا `commercial_risks`) من `excel.php?entity=commercial_risks&action=template`. ٢) املأه بصفوفٍ بحالاتٍ نهائيةٍ مباشرةً وارفعه عبر `import_preview` ثم `import_commit`. ٣) الصفوفُ تُدرَج كما هي؛ ولا حدثَ منشورٌ ولا عنصرُ عملٍ ولا تحققٌ من قواعدِ الحالة. | Q72: أضِف إلى `EntityDefinition` خطّافًا إلزاميًّا `serviceInsert` يستدعي الخدمةَ المالكةَ لكلِّ صفّ، واجعل `Importer::commit` يرفض أيَّ كيانٍ لا يعرّف الخطّافَ إن كان جدولُه ضمن الجداولِ الحاكمة (`app/Core/TenantRegistry`)؛ وسجِّل لكلِّ عمليةِ استيرادٍ صفًّا في سجلِّ التدقيقِ بعددِ الصفوفِ ومرجعِ الملف. | R72: فريق الباك-إند — الحوكمة والمنصة | S72: نعم | T72: نعم | U72: استيرادُ صفوفٍ إلى كيانٍ حاكمٍ يمرُّ بخدمتِه: كلُّ صفٍّ يُنتج الحدثَ نفسَه الذي ينتجه الإدخالُ اليدوي؛ والاستيرادُ إلى كيانٍ بلا خطّافٍ يُرفض برسالةٍ واضحة. | V72: مفتوح | W72: مؤكَّدة | X72: محقَّق: Importer::commit يبني `INSERT INTO {$table}` عامًّا (سطر 134) وينفّذه لكلِّ الصفوف في معاملةٍ واحدةٍ (سطر 145-186) بلا نداءِ خدمةٍ مالكةٍ ولا قادحِ حالةٍ ولا نشرِ حدثٍ ولا سطرِ تدقيق؛ والحارسُ الوحيدُ فعلًا هو can_add وCSRF في ExcelService:56-70 و119-124 كما ذكرت الملاحظةُ نفسُها. بابُ كتابةٍ موازٍ حقيقيٌّ لكنه يظلّ خلف صلاحيةِ الإضافة على الشاشة المالكة. | Y72: P0 | Z72: نعم | AA72: نعم | AB72: 06_M14 | AC72: فجوة تنفيذ (Implementation) | AD72: Decision Closed · Implementation Open
A73: INJ-0069 | B73: M-14 | C73: GOVX-0974-أ · «الحقولُ الحساسةُ محجوبةٌ بالصلاحية» · TABLE 46 | D73: إدارة الحوكمة والالتزام | E73: إطار التصدير الموحَّد (Excel) | F73: http://localhost/ems/excel.php?action=export | G73: - | H73: «سجلُّ تصديرٍ … **والحقولُ الحساسةُ محجوبةٌ بالصلاحية**» — فالتسجيلُ لا يُغني عن الحجب. | I73: `excel.php:86-99` يقرأ الحقولَ الحساسةَ من `scr_sensitive_fields` ويكتب لكلٍّ منها صفَّ اطّلاعٍ في `sensitive_read_log`، ثم يستدعي `$service->export($def)` (`:99`) الذي يبثُّ الملفَّ **بالحقولِ كاملةً غيرَ محجوبة**. وأيُّ استثناءٍ في كتلةِ التسجيلِ يُبتلع ولا يعطّل التصدير (`:96-98` — «لا يعطل التصدير»). | J73: Export/Import Gap | K73: P1 | L73: أخطرُ أبوابِ الاطّلاعِ يُسجَّل ولا يُحجب: أيُّ مستخدمٍ يملك `can_view` على الشاشةِ يصدّر ملفًّا يحوي كلَّ الحقولِ الحساسةِ (رواتبَ وأسعارَ وهوامشَ ومالكي مخاطر) خارجَ النظامِ بلا قيد. وإن فشل التسجيلُ خرج الملفُّ بلا أثرٍ إطلاقًا. | M73: نُفِّذ شقُّ «السجل» من الحكمِ دون شقِّ «الحجب»، ولم تُوصَل `SensitiveFieldGuard` بمسارِ التصدير. | N73: excel.php:82; :86; :89; :93; :96; :97; :99; app/Services/Security/SensitiveFieldGuard.php:103; app/Services/Excel/ExcelService.php:64 | P73: ١) بدورٍ غيرِ مخوَّلٍ لحقلٍ حساسٍ في كيانٍ ما، افتح `excel.php?entity=<كيان>&action=export`. ٢) افتح الملفَّ الناتج: العمودُ الحساسُ موجودٌ بقيمِه. ٣) استعلم `sensitive_read_log`: صفٌّ مسجَّلٌ باسمِك — أي أنَّ النظامَ سجَّل التسريبَ ولم يمنعه. | Q73: في `excel.php` قبل السطر 99 مرِّر إلى `ExcelService::export` قائمةَ الحقولِ المحظورةِ على دورِ الجلسةِ من `SensitiveFieldGuard::canRead`، واجعل المصدِّرَ يستبدل قيمَها بـ`●●●` أو يحذف أعمدتَها؛ واجعل فشلَ كتلةِ التسجيلِ يوقف التصديرَ لا يتجاوزَه. | R73: فريق الباك-إند — الحوكمة والمنصة | S73: نعم | T73: نعم | U73: تصديرُ كيانٍ فيه حقلٌ حساسٌ بدورٍ غيرِ مخوَّل: العمودُ محجوبٌ في الملفِّ الناتج؛ وبدورٍ مخوَّل: ظاهرٌ ومسجَّلٌ اطّلاعُه. | V73: مفتوح | W73: مؤكَّدة | X73: ‏excel.php:86-99 يقرأ scr_sensitive_fields ويكتب سطرَ اطّلاعٍ ثم يستدعي export بلا تمريرِ أيِّ قائمةِ حجب، وSensitiveFieldGuard::filterRow (المُقنِّعُ والمُسقِط) بلا مستدعٍ إنتاجيٍّ واحد؛ والاستثناءُ يُبتلع في :96-98 فيخرج الملفُّ بلا تسجيلٍ أصلًا. | Y73: P1 | Z73: نعم | AA73: نعم | AB73: 06_M14 | AC73: فجوة تنفيذ (Implementation) | AD73: Decision Closed · Implementation Open
A74: INJ-0070 | B74: INJAZ-FRD-01 | C74: §١٤-٣ المرحلة ٢ (ثانيًا: التصنيف والتوجيه — بلاغ مصنَّف محال) · ticket_route.php | D74: مركز البلاغات | E74: تصنيف البلاغ وتوجيهه آليًّا | F74: http://localhost/ems/Tickets/ticket_types_config.php | G74: ثانيًا: التصنيف والتوجيه | H74: المرحلة الثانية «التصنيف والتوجيه» مستندُها «بلاغ مصنَّف محال» ومعتمِدُها مركز البلاغات، وشاشتُها ticket_route.php بـ٢٢ عمودًا وفعلٍ واحد. | I74: الرابطُ في مجموعة «ثانيًا: التصنيف والتوجيه» عنوانُه «تصنيف البلاغ وتوجيهه آليًّا» ويقود إلى Tickets/ticket_types_config.php — وهي شاشةُ إعداداتِ أنواعِ البلاغات (مرجعٌ ثابت)، لا شاشةَ تصنيفِ بلاغٍ بعينه. والشاشةُ الحقيقية موجودةٌ وتعمل: Tickets/intake_classify.php تصنّف البلاغَ الجديد وتحدّث owner_role_id وتنقل المرحلةَ إلى 'routed' — وليس لها صفُّ nav_items في أيِّ سايدبار. والملفُّ نفسُه ticket_types_config.php مربوطٌ ثانيةً بمجموعة «إعدادات البلاغات» (المرحلة ٨) بمرساةٍ مختلفة. | J74: Wrong Label | K74: P1 | L74: مديرُ البلاغات لا يجد شاشةَ تصنيف البلاغات في قائمته؛ يفتح شاشةَ الإعدادات ظنًّا أنه يصنّف. والمرحلةُ الثانية — قلبُ عمل المركز اليومي — بلا منفذ. وفي الوقت نفسه ملفُّ الإعدادات مكرَّرٌ في مجموعتين بعنوانين مختلفين. | M74: خريطةُ البذرة أسندت شاشةَ المرحلة إلى ملفِّ الإعدادات، ولم يُنشأ صفٌّ لـintake_classify.php التي بُنيت لاحقًا في موجة update0007-ب. | N74: database/schema/seed_reference.sql:4921 (nav#6742); :4932 (nav#6753); :4014 (nav#1334 active=0) | P74: ١) ادخل بدور 24. ٢) افتح «ثانيًا: التصنيف والتوجيه» ⇐ الرابطُ يفتح إعداداتِ الأنواع. ٣) افتح «إعدادات البلاغات» ⇐ الملفُّ نفسُه. ٤) اكتب http://localhost/ems/Tickets/intake_classify.php ⇐ شاشةُ التصنيف الحقيقية تعمل ولا رابطَ لها. | Q74: تعديلُ صفِّ nav_items للمرحلة ٢ ليشير إلى Tickets/intake_classify.php بعنوان «تصنيف البلاغ وتوجيهه آليًّا»، وإبقاءُ ticket_types_config.php في المرحلة ٨ وحدَها بعنوان «إعدادات البلاغات — الأنواع»، فيزول التكرارُ ويُصحَّح المسار. | R74: مكتب الهندسة — مولّد التنقل NAV-09 | S74: نعم | T74: نعم | U74: مجموعةُ «ثانيًا: التصنيف والتوجيه» تفتح شاشةَ تصنيف البلاغات الجديدة؛ وملفُّ إعدادات الأنواع يظهر مرةً واحدةً في السايدبار. | V74: مفتوح | W74: مؤكَّدة | X74: صفُّ nav 6742 للمرحلة الثانية يقود إلى `Tickets/ticket_types_config.php` (شاشةُ إعداداتٍ تتكرر في المرحلة ٨ بالصف 6753)، بينما `Tickets/intake_classify.php` صفُّه الوحيد active=0 في مجموعة «خارج الوثيقة». | Y74: P1 | Z74: نعم | AA74: نعم | AB74: 02_FRD | AC74: فجوة تنفيذ (Implementation) | AD74: Decision Closed · Implementation Open
A75: INJ-0071 | B75: M-14 | C75: PR-05 الحارسُ في الخادم · TABLE 46 (الحارسُ + مفتاحُ منع التكرار) | D75: مركز البلاغات | E75: لوحة المسارات المتوازية | F75: http://localhost/ems/Tickets/ticket_workstreams_board.php | G75: ثالثًا: التحويل والتفريع | H75: كلُّ منعٍ في الخادم قبل الحفظ، والنداءُ المخالفُ يُرفض ولو جاء من أداةٍ خارجية — ويُسجَّل الرفض. | I75: معالجُ POST يقبل سبعةَ أفعالٍ بشرطٍ واحدٍ هو can_edit على الشاشة، بلا أيِّ تحقّقٍ من أن المستخدم طرفٌ في المسار (مكلَّفٌ أو مبلِّغٌ أو من الإدارة المالكة) وبلا رمز CSRF. واستعلامُ اللوحة يجلب كلَّ بلاغات الشركة المفتوحة بلا أيِّ ترشيحٍ بالسرية (ConfidentialityGuard بلا نداءٍ إنتاجيٍّ في النظام كلِّه). | J75: Permission Gap | K75: P1 | L75: أيُّ حاملٍ لـcan_edit يستلم ويبدأ ويعلّق ويُنجز ويغلق ويعيد فتحَ أيِّ مسارٍ لأيِّ بلاغٍ في الشركة — بما فيها بلاغاتُ الشكاوى والسرية. وغيابُ رمز CSRF يجعل إغلاقَ بلاغٍ ممكنًا بطلبٍ مزوَّرٍ من موقعٍ آخر. | M75: الحراسةُ صُمّمت على مستوى الشاشة لا على مستوى الصف؛ وحارسُ السرية بُني ولم يُوصَل. | N75: Tickets/ticket_workstreams_board.php:38; :41; :71; app/Services/Tickets/ConfidentialityGuard.php:51 | P75: ١) ادخل بدورٍ له can_edit على اللوحة وليس مكلَّفًا بأيِّ مسار. ٢) افتح اللوحة ⇐ ترى كلَّ بلاغات الشركة المفتوحة بما فيها السرية. ٣) اضغط «إنجاز» على مسارٍ لا تخصّك ⇐ ينفَّذ. ٤) أرسل نفسَ POST بلا رمز CSRF ⇐ ينفَّذ. | Q75: إضافةُ فحصِ طرفيةٍ في Tickets/ticket_workstreams_board.php قبل تنفيذ الفعل: يُقبل الفعلُ إن كان المستخدمُ مكلَّفَ المسار أو مبلِّغَ البلاغ أو من دور 24، وإلا 403 مسجَّل؛ وإلزامُ رمز CSRF في النموذج والتحقّقُ منه في المعالج؛ وتمريرُ استعلام اللوحة عبر ConfidentialityGuard لترشيح البلاغات السرية. | R75: فريق الباك-إند — وحدة مركز البلاغات | S75: نعم | T75: نعم | U75: مستخدمٌ ليس طرفًا في مسارٍ يُرفض فعلُه 403 ويُسجَّل؛ والبلاغاتُ السرية لا تظهر في اللوحة لغير أطرافها؛ وطلبٌ بلا رمز CSRF يُرفض. | V75: مفتوح | W75: مؤكَّدة | X75: تحقّقت بدقة: معالجُ الـPOST (:41) يقبل سبعةَ أفعالٍ بشرط can_edit وحدَه بلا تحقّقٍ من كون المستخدم طرفًا وبلا رمز CSRF، واستعلامُ اللوحة (:71) يجلب كلَّ بلاغات الشركة المفتوحة بلا مرشِّح سرية، و`ConfidentialityGuard` بلا مستدعٍ إنتاجيٍّ واحد. | Y75: P1 | Z75: نعم | AA75: نعم | AB75: 06_M14 | AC75: فجوة تنفيذ (Implementation) | AD75: Decision Closed · Implementation Open
A76: INJ-0072 | B76: INJAZ-CORE-01 | C76: AR-02 التكاملُ بالأحداث لا بالنداء · §١٥-٥ «لا إدارةَ تكتب في جداول إدارةٍ أخرى» · §١٥-١ «ما لا تملكه: كرتَ المعدة» | D76: إدارة الصيانة | E76: العودة للخدمة | F76: http://localhost/ems/Maintenance/return_to_service.php | G76: غير موجود في السايدبار | H76: «تتصل الإداراتُ بأحداثٍ منشورةٍ يستهلكها من يعنيه … لا نداءٌ مباشر» (AR-02) و«لا إدارةَ تكتب في جداول إدارةٍ أخرى — والأثرُ ينتقل بالأحداث» (§١٥-٥)، و«ما لا تملكه إدارةُ الصيانة: كرتَ المعدة». | I76: استعلامٌ خامٌّ يتجاوز بوابةَ العزل (والمخاطرةُ نظريةٌ لأن الصفَّ الأبَ مُرشَّحٌ بالشركة)، وصفرُ فحصِ صلاحيةٍ في الشاشة كلِّها — فأيُّ مستخدمٍ في الكيان يُقفل أمرًا ويعيد معدةً للخدمة. — [مُصحَّح بعد التحقق] الصياغة الأولى: السطرُ 27 استعلامٌ خامٌّ مبنيٌّ بدمج النصوص يكتب مباشرةً في جدول الأسطول: UPDATE equipments SET status=1 WHERE id=... — بلا بوابة المستأجر (ems_tenant_db) فبلا حقنِ شرطِ الشركة، وبلا حدثٍ منشور، وبلا | J76: Event/Integration Gap | K76: P1 | L76: إدارةُ الصيانة تغيّر حالةَ أصلٍ في سجلِّ الأسطول بيدها؛ فمصدرُ الحقيقة لحالة المعدة مزدوج. والأخطرُ أن الاستعلامَ بلا عزلِ كيان: قيمةُ equipment_id مأخوذةٌ من صفِّ أمرٍ تحقّق من شركته، لكن الكتابةَ نفسَها بلا شرطِ company_id فتخرج عن الطبقة الوحيدة التي يفرضها AR-01 — سابقةٌ خطيرةٌ في مسارٍ مالي/تشغيليٍّ حسّاس. | M76: كُتب المعالجُ باستعلاماتٍ خامّةٍ (mysqli_query) بدل بوابة المستأجر المستعملة في بقية المجلد، ولم يُبنَ ناشرُ حدثِ الجاهزية. | N76: Maintenance/return_to_service.php:9-16,22-28; Maintenance/mnt_helpers.php:118,186 | P76: ١) اقرأ Maintenance/return_to_service.php:27 ⇐ استعلامٌ خامٌّ على equipments بلا company_id. ٢) نفّذ الفعل ⇐ يتغيّر equipments.status. ٣) ابحث عن حدثٍ منشورٍ للجاهزية ⇐ لا شيء. | Q76: استبدالُ الاستعلام الخام في Maintenance/return_to_service.php:26-28 بنشرِ حدثٍ EquipmentReadinessCertified عبر App\Core\EventPublisher يحمل equipment_id وorder_id وشهادةَ الجاهزية، وبناءُ مستهلكٍ في وحدة الأسطول هو الوحيدُ الذي يكتب equipments.status — فيلتزم AR-02 وتُصان ملكيةُ كرت المعدة. | R76: مكتب الهندسة — طبقة الأحداث والحراس | S76: نعم | T76: نعم | U76: إقفالُ أمرِ صيانةٍ لا يكتب في جدول equipments من كود الصيانة؛ بل ينشر حدثًا يستهلكه الأسطولُ فيغيّر حالةَ المعدة، ويظهر الحدثُ بمفتاح منعِ تكرارٍ ومعرّفِ ارتباط. | V76: مفتوح | W76: مرجَّحة | X76: السطرُ 27 كما وُصف: UPDATE equipments SET status=1 خامًّا بلا بوابة المستأجر وبلا حدث. لكن equipment_id مقروءٌ من صفٍّ مُرشَّحٍ بـcompany_id=$company_id (:23) فلا كتابةَ عابرةَ كيانٍ عمليًّا، وكتابةُ الصيانةِ في equipments نمطٌ قائمٌ ومقنَّنٌ في Maintenance/mnt_helpers.php:118,186 عبر البوابة — فليست سابقةَ ملكيةٍ فريدة. والأخطرُ مما ذُكر: الملفُّ كلُّه بلا أيِّ فحصِ صلاحية. | Y76: P0 | Z76: نعم | AA76: نعم | AB76: 01_CORE | AC76: فجوة تنفيذ (Implementation) | AD76: Decision Closed · Implementation Open
A77: INJ-0073 | B77: INJAZ-FRD-01 | C77: §١٥-٢ الدورةُ المستنديةُ (… محضرُ إقفالٍ · شهادةُ جاهزية) · §١٥-٣ المرحلة ٥ | D77: إدارة الصيانة | E77: العودة للخدمة | F77: http://localhost/ems/Maintenance/return_to_service.php | G77: غير موجود في السايدبار | H77: المرحلةُ الخامسة «الإقفال وإعادة الخدمة» مستندُها «محضر إقفال · شهادة جاهزية» ومعتمِدُها مديرُ الصيانة؛ و«لكل مرحلةٍ مستندٌ يُنتَج ومعتمِدٌ يشهد — ولا مرحلةَ بلا مخرَج»؛ وشهادةُ الجاهزية الفنية هي مستندُ المرحلة الثانية في دورة الأسطول (§٨-٣). | I77: شهادةُ الجاهزية لا تُحفظ إطلاقًا: القيمةُ تُقرأ في المتغير $cert وتُستعمل في نصِّ رسالةِ النجاح فقط ($msg) ثم تُهمَل. لا عمودَ ولا جدولَ يستقبلها، ولا مرفقَ ولا توقيعَ ولا رقمَ مستند. والمُقفِلُ لا يُسجَّل (لا عمودَ closed_by يُكتب) ولا وقتُ الشهادة. | J77: Missing Evidence | K77: P1 | L77: المستندُ الحاكم للمرحلة الخامسة غيرُ موجودٍ في النظام: لا يمكن إثباتُ من شهد بجاهزية المعدة ولا بماذا شهد. والمرحلةُ التي «لا مرحلةَ بلا مخرَج» بلا مخرَج. وإدارةُ الأسطول تستلم معدةً «جاهزة» بلا شهادةٍ تسندها — وهو انقطاعٌ في سلسلة الأدلة يمتدّ إلى الفوترة. | M77: بُني الحقلُ في النموذج كإلزامٍ شكليٍّ (required) ولم يُبنَ له مخزن؛ والشاشةُ خارج السايدبار فلم تُختبر. | N77: Maintenance/return_to_service.php:20,21,28; database/schema/schema.sql:6735 | P77: ١) افتح Maintenance/return_to_service.php. ٢) اكتب شهادةً واضغط «أعد للخدمة وأقفل». ٣) تظهر الشهادةُ في رسالة النجاح. ٤) استعلم mnt_order عن الأمر ⇐ لا عمودَ يحمل نصَّ الشهادة ولا مرجعَ مستند. | Q77: إضافةُ أعمدةِ readiness_note وreadiness_by وreadiness_at إلى mnt_order في هجرة، وكتابتُها في نفس معاملة الإقفال في Maintenance/return_to_service.php:26-28، وعرضُ الشهادة في بطاقة الأمر وفي جدول العودة للخدمة كمستندٍ لا كرسالة. | R77: فريق الباك-إند — وحدة الصيانة | S77: نعم | T77: نعم | U77: إقفالُ أمرٍ بشهادةِ جاهزيةٍ يُخزّن نصَّ الشهادة ومُصدِرَها ووقتَها في صفِّ الأمر، وتظهر في بطاقة الأمر وفي أيِّ تصديرٍ للأوامر المقفلة. | V77: مفتوح | W77: مؤكَّدة | X77: تحققتُ حرفيًّا: $cert يُقرأ في السطر 20 ويُفحَص فراغُه في 21 ويُستعمل في نصِّ $msg في السطر 28 ثم يُهمَل — ولا عمودَ يستقبله؛ و mnt_order فيه closed_by (schema.sql:6735) ولا يُكتب هنا. لكن العيبَ نقصُ حفظِ مستندٍ يُصلَح بهجرةٍ صغيرةٍ وثلاثةِ أعمدة، لا أثرًا غيرَ مصرَّحٍ ولا فقدانَ مصدرِ حقيقةٍ قائم. | Y77: P0 | Z77: نعم | AA77: نعم | AB77: 02_FRD | AC77: فجوة دليل (Evidence) | AD77: Implementation Closed · Evidence Open
A78: INJ-0074 | B78: INJAZ-FRD-01 | C78: §٨-٣ إدارة الأسطول (مرحلة ٢ الجاهزية والتفعيل) · سلسلةُ الجاهزية ← توفرُ التشغيل | D78: إدارة الصيانة | E78: جاهزية الأسطول وتوفر التشغيل | F78: http://localhost/ems/Fleet/readiness_board.php | G78: لوحة الإدارة (الدور 3) | H78: «الجاهزية والتفعيل — المستند: شهادة جاهزية فنية — المعتمِد: الصيانة»؛ والجاهزيةُ محسوبةٌ من مصادرها لا حقولًا محلية، وتُغذّي توفّرَ التشغيل. | I78: السلسلةُ تعمل بالقراءة لا بالمستند: لوحةُ الجاهزية تحسب النسبةَ من مصادرَ حية (وحداتُ اليوم · البلاغاتُ المفتوحة · حالُ الإتاحة) — وهو صحيحٌ — لكن الطرفَ الذي يفترض أن يعتمده (شهادةُ الجاهزية الفنية من الصيانة) غيرُ مخزَّنٍ أصلًا (انظر ملاحظة العودة للخدمة)، وتغييرُ حالة المعدة يقع بكتابةٍ مباشرةٍ من الصيانة على equipments وoperations لا بحدثٍ يحمل الشهادة. فتوفّرُ التشغيل يتغيّر بلا مستندٍ يسنده. | J78: Data Mismatch | K78: P1 | L78: «جاهزيةُ الأسطول» رقمٌ يتغيّر بلا مستندٍ يمكن الرجوعُ إليه: لا يمكن الإجابةُ عن «بأيِّ شهادةٍ عادت هذه المعدةُ للخدمة ومن وقّعها» — وهو سؤالٌ تعاقديٌّ مباشرٌ يؤثر في المطالبة والاستحقاق. | M78: بُنيت اللوحةُ حاسبةً من الحقول التشغيلية، ولم يُبنَ مستندُ الشهادة ولا الحدثُ الذي يحمله. | N78: Fleet/readiness_board.php:2; :6; :24; Maintenance/return_to_service.php:20; :27; Maintenance/mnt_helpers.php:112; :118; :140 | P78: ١) أقفل أمرَ صيانةٍ عبر Maintenance/return_to_service.php. ٢) افتح Fleet/readiness_board.php ⇐ ترتفع نسبةُ الجاهزية. ٣) اضغط على خلية المعدة وابحث عن شهادة الجاهزية التي أعادتها ⇐ لا مستند. | Q78: ربطُ السلسلة بالمستند: تخزينُ شهادة الجاهزية في mnt_order (انظر الملاحظة المخصصة)، ونشرُ حدث EquipmentReadinessCertified يحمل رقمَ الشهادة، وعرضُ رقم آخرِ شهادةِ جاهزيةٍ وتاريخِها في بطاقة كل معدةٍ في لوحة الجاهزية. | R78: فريق الباك-إند — وحدة الصيانة | S78: نعم | T78: نعم | U78: كلُّ معدةٍ في لوحة الجاهزية تعرض مرجعَ آخر شهادةِ جاهزيةٍ وتاريخَها ومُصدرَها، والنقرُ عليه يفتح الأمرَ الذي أصدرها. | V78: مفتوح | W78: مؤكَّدة | X78: return_to_service.php يفرض نصَّ شهادة الجاهزية (السطر 20-21) ثم لا يخزّنه — يعرضه في الرسالة ويحدّث mnt_order وequipments مباشرةً، فلا مستندَ يسند تغيّرَ الجاهزية ولا معتمِدَ يُختم. | Y78: P1 | Z78: نعم | AA78: نعم | AB78: 02_FRD | AC78: فجوة تنفيذ (Implementation) | AD78: Decision Closed · Implementation Open
A79: INJ-0075 | B79: M-14 | C79: PR-05 الحارسُ في الخادم · TABLE 46 (الحارسُ لكلِّ فعلِ كتابة) | D79: إدارة الصيانة | E79: العودة للخدمة | F79: http://localhost/ems/Maintenance/return_to_service.php | G79: غير موجود في السايدبار | H79: «كلُّ منعٍ يُنفَّذ في الخادم قبل الحفظ … والنداءُ المخالفُ يُرفض ولو جاء بمساره مباشرةً أو من أداةٍ خارجية — ويُسجَّل الرفضُ بالمستخدم والوقت والرمز» — ولكلِّ فعلِ كتابةٍ حارسٌ. | I79: الشاشةُ بلا حارسٍ للكتابة **وللعرض** معًا لأنها غيرُ مسجَّلةٍ موديولًا (get_current_page_permissions يعيد can_view=true عند id===null). — [مُصحَّح بعد التحقق] الصياغة الأولى: الشاشة تُضمّن includes/permissions_helper.php ولا تستدعي منه شيئًا: الحارسُ الوحيد وجودُ الجلسة. لا check_page_permissions ولا فحصُ can_edit ولا رمزُ CSRF. ومعالجُ POST يُقفل أمرَ الصيانة ويعيد المعدة | J79: Permission Gap | K79: P1 | L79: أيُّ مستخدمٍ مصادَقٍ في الشركة — سائقٌ أو محاسب — يُقفل أيَّ أمرِ صيانةٍ منجَزٍ ويعيد المعدةَ للخدمة بطلبٍ واحد. شهادةُ الجاهزية الفنية — التي يشهد بها مديرُ الصيانة وتفتح بابَ التشغيل والفوترة — تُصدَر بيد من لا صلاحيةَ له، بلا رفضٍ ولا سجل. | M79: الشاشة بُنيت في موجة update0007 خارج نمط الحراسة المتبع في المجلد (Maintenance/orders.php:35 يستدعي الحارس)، وبقيت خارج السايدبار فلم تُلحظ. | N79: Maintenance/return_to_service.php:18; :26; :27; :46; includes/permissions_helper.php:621-629 | P79: ١) ادخل بحسابٍ بدورٍ غيرِ صيانيٍّ (مثلًا 12 المبيعات) وله company_id. ٢) اكتب http://localhost/ems/Maintenance/return_to_service.php ⇐ تُفتح وتعرض الأوامر المنجَزة. ٣) اكتب شهادةً واضغط «أعد للخدمة وأقفل» ⇐ يُقفل الأمرُ وتعود المعدة. ٤) لا صفَّ رفضٍ في guard_denials. | Q79: إضافةُ الكتلة المتبعة في Maintenance/orders.php:35-43 إلى رأس Maintenance/return_to_service.php قبل معالج POST: check_page_permissions($conn,'Maintenance/return_to_service.php') وحجبُ can_view وحجبُ POST بلا can_edit مع log_security_event، وإلزامُ رمز CSRF في النموذج. | R79: فريق الباك-إند — وحدة الصيانة | S79: نعم | T79: نعم | U79: دورٌ بلا can_edit على شاشة العودة للخدمة يُرفض 403 ويُسجَّل الرفض؛ ودورُ الصيانة يُقفل الأمرَ ويُعيد المعدة. | V79: مفتوح | W79: مؤكَّدة | X79: محقَّق: Maintenance/return_to_service.php:18-32 يُقفل mnt_order ويعيد المعدةَ للخدمة (`UPDATE equipments SET status=1`) بلا أيِّ فحصِ صلاحيةٍ ولا CSRF، وinsidebar في السطر 46 بعد الكتابة؛ والأسوأُ مما ذُكر أن الشاشةَ **غيرُ مسجَّلةٍ في modules** فالحارسُ المركزيُّ يمرّها شفافةً حتى للعرض. أثرٌ تشغيليٌّ غيرُ مأذونٍ وقابلٌ للعكس — دون عتبة P0 المالية/القانونية. | Y79: P0 | Z79: نعم | AA79: نعم | AB79: 06_M14 | AC79: فجوة تنفيذ (Implementation) | AD79: Decision Closed · Implementation Open
A80: INJ-0076 | B80: M-14 | C80: GOV-018-د «اعتمادُ الذات» · §٢٦-٣ مصدر ٤ «أمرُ عملٍ أُقفل | شرطُه: فحصٌ نهائيٌّ ناجح | من يُنسب إليه: الفنيُّ ومديرُ الصيانة» | D80: إدارة الصيانة | E80: أوامر الصيانة | F80: http://localhost/ems/Maintenance/orders.php | G80: ثانيًا: أمر العمل والتكليف | H80: «أمرُ عملٍ أُقفل | شرطُه: فحصٌ نهائيٌّ ناجح | من يُنسب إليه: الفنيُّ ومديرُ الصيانة» — يدان لا يدٌ واحدة؛ و«اعتمادُ الذات» من المنع المطلق. | I80: شاشةُ الأوامر تفحص can_edit وحدَه للانتقال إلى حالة «إغلاق»؛ ولا فحصَ يمنع أن يكون المُقفِلُ هو الفنيَّ المكلَّفَ نفسَه ولا أن يكون منشئَ الأمر. وشاشةُ العودة للخدمة تُقفل بلا أيِّ فحصِ صلاحيةٍ أصلًا. ورأسُ الملف يعلن «بلا اعتماد (DEC-14)» — أي أن الأمرَ يُقفل بيدٍ واحدةٍ بقرارِ تصميم. | J80: Governance Gap | K80: P1 | L80: الفنيُّ الذي نفّذ الإصلاح يقفل أمرَه ويشهد بنجاح الفحص النهائيِّ بنفسه؛ فتسقط «اليدُ الثانية» المنصوصُ عليها في معيار الإنجاز، ويصير إقفالُ الأوامر — وما يترتب عليه من جاهزيةٍ وتكلفةٍ — بلا شاهدٍ مستقلّ. | M80: قرارُ تصميمٍ سابق (DEC-14: «بلا اعتماد») لم يُراجَع بعد صدور معيار §٢٦-٣ الذي ينسب الإقفالَ إلى الفنيِّ ومديرِ الصيانة معًا. | N80: Maintenance/orders.php:4; :35; :38; :46; Maintenance/return_to_service.php:18; app/Services/Security/SelfGrantGuard.php | P80: ١) بدور 13 أنشئ أمرًا وكلّف نفسَك فنيًّا. ٢) انقله إلى حالة «فحص» ثم «إغلاق» ⇐ يُقبل. ٣) لا رسالةَ منعٍ ولا صفَّ رفض. | Q80: إضافةُ حارسٍ في معالج تغيير الحالة في Maintenance/orders.php يمنع الانتقالَ إلى «إغلاق» إن كان المستخدمُ هو الفنيَّ المكلَّفَ أو منشئَ الأمر، ويشترط can_edit على مستوى مديرِ الصيانة؛ وتسجيلُ الرفض؛ وتوثيقُ مراجعة قرار DEC-14 في ملف التتبع. | R80: فريق الباك-إند — وحدة الصيانة | S80: نعم | T80: لا | U80: محاولةُ الفنيِّ المكلَّف إقفالَ أمره تُرفض 403 وتُسجَّل؛ وإقفالُ مديرِ الصيانة يمرّ ويسجّل اسمين: الفنيَّ والمقفِل. | V80: مفتوح | W80: مؤكَّدة | X80: رأسُ Maintenance/orders.php يعلن «بلا اعتماد (DEC-14)» والانتقالُ إلى «إغلاق» يفحص can_edit وحدَه بلا مقارنةٍ بالفنيِّ أو المنشئ؛ وأخطرُ منه أن Maintenance/return_to_service.php يعالج POST (سطر 18) بلا أيِّ فحصِ صلاحيةٍ إطلاقًا وقبل تضمين insidebar. | Y80: P1 | Z80: نعم | AA80: نعم | AB80: 06_M14 | AC80: فجوة تنفيذ (Implementation) | AD80: Decision Closed · Implementation Open
... A126: INJ-0122 | B126: INJAZ-UX-01 | C126: UX-01 §٤ · «أول ما يُفتح — لوحة الدور» | D126: مكتب الرئيس التنفيذي والنواب | E126: الرئيسية (لوحة الدور) | F126: http://localhost/ems/main/role_board.php | G126: لوحة الإدارة التنفيذية | H126: «الرئيسية» تفتح لوحةَ الدور مباشرةً — وهي أولُ رابطٍ في أول مجموعةٍ لكل الأدوار. | I126: المصيّر يحقن «الرئيسية» → `../main/role_board.php` لكل الأدوار بلا استثناء (سطر 231-233)، لكن `roleBoardGenericConfig()` لا تعرف الدورَ 9 (مفاتيحُها: 1·24·12·2·3·4·5·6·15) و`roleBoardRoute()` لا تعرفه أيضًا (مفاتيحُها: 17·13·16·23·26·1·24·12·2·3·4·5·6·15). فيصل الدورُ 9 إلى `main/role_board.php:36` ويُعاد توجيهُه صامتًا إلى main/dashboard.php. | J126: Broken Button | K126: P2 | L126: أولُ رابطٍ في سايدبار الرئيس التنفيذي لا يفتح لوحتَه: يقفز إلى لوحةٍ عامةٍ غيرِ مخصصة بلا رسالةٍ تفسّر، فيبدو النظامُ كأنه يتجاهل النقر. والأثرُ نفسُه على الأدوار 7·8·10·11·14·18-22·25·27-30. | M126: ثلاثةُ سجلاتٍ منفصلةٍ للوحات (المصيّر · roleBoardRoute · roleBoardGenericConfig) بلا فحصِ اتساقٍ بينها، والدورُ 9 له لوحةٌ مخصصةٌ فعلًا (Portal/ceo_board.php) لم تُسجَّل في أيٍّ منها. | N126: includes/role_board.php:47-62; includes/role_board.php:586; main/role_board.php:36; database/schema/seed_reference.sql:4021 | P126: ١) ادخل بدور 9. ٢) اضغط «الرئيسية» أولَ رابطٍ في السايدبار. ٣) لاحظ أنك في main/dashboard.php لا في لوحة القمة. | Q126: في `includes/role_board.php::roleBoardRoute()` أضِف `9 => 'Portal/ceo_board.php'`؛ وفي `main/role_board.php:36` استبدل إعادةَ التوجيه الصامتة برسالة حوكمةٍ مُعلَنة عبر `ems_gov_flash_redirect` تسمّي الدورَ الذي لا لوحةَ له. | R126: فريق الباك-إند — وحدة القمة التنفيذية (Portal) | S126: نعم | T126: نعم | U126: نقرُ «الرئيسية» بدور 9 يفتح Portal/ceo_board.php؛ وأيُّ دورٍ بلا لوحةٍ يرى رسالةً مُعلَنةً بدل قفزةٍ صامتة. | V126: مفتوح | W126: مؤكَّدة | X126: roleBoardRoute وroleBoardGenericConfig لا تعرفان الدور 9 وparent_role_id فارغٌ له فيقع التحويلُ الصامت في main/role_board.php:36 — لكن «لوحة المدير التنفيذي» مربوطةٌ في سايدباره (nav_items 5846) فالأثرُ تنقّليٌّ لا حاجب. | Y126: P1 | Z126: نعم | AA126: نعم | AB126: 02_FRD | AC126: فجوة تنفيذ (Implementation) | AD126: Decision Closed · Implementation Open
A127: INJ-0123 | B127: INJAZ-FRD-01 | C127: INJAZ-FRD-01 §٤-٤ · شاشاتُها وأفعالُها | D127: مكتب الرئيس التنفيذي والنواب | E127: حوكمة مكتب الرئيس التنفيذي والنواب | G127: غير موجود في السايدبار | H127: من شاشات الإدارة السبع المعلَنة: «حوكمة مكتبُ الرئيس التنفيذي والنواب» (gov_dept_ceo.php · 15 عمودًا · فعلان). | I127: الفجوةُ نمطيةٌ لا خاصةً بالقمة: 12 شاشةَ gov_dept_* معلَنةً في FRD غيرُ منشأةٍ أيضًا، ومصادرُ الحوكمةِ المركزيةُ (access_review · guard_denials · sensitive_fields) قائمةٌ وتغطّي الدليلَ مركزيًّا. — [مُصحَّح بعد التحقق] الصياغة الأولى: لا ملفَّ `gov_dept_ceo.php` في المستودع؛ الموجودُ ثلاثةُ نظائرَ لإداراتٍ أخرى فقط: Governance/gov_dept_gov.php · Finance/gov_dept_fin.php · Risk/gov_dept_rsk.php. ولا رابطَ حوكمةٍ في سايدبار الدور 9 ع | J127: Missing Screen | K127: P2 | L127: شاشةٌ حاكمةٌ من السبعِ المعلَنة مفقودة: لا موضعَ يعرض التزامَ مكتب الرئيس بأحكام M-14 (الاستثناءات · التفويضات · سجل الاطّلاع الحساس) — فتسقط قابليةُ إثباتِ الحوكمة على أعلى إدارة. | M127: تعميمُ نمط `gov_dept_*` توقّف عند ثلاث إداراتٍ ولم يشمل القمة، ولا فاحصَ يقارن قائمةَ الشاشات المعلَنة بالملفات الموجودة. | N127: Governance/gov_dept_gov.php:1; Finance/gov_dept_fin.php:1; Risk/gov_dept_rsk.php:1; Governance/signing_authority.php:1 | P127: ١) افتح http://localhost/ems/Portal/gov_dept_ceo.php و http://localhost/ems/Governance/gov_dept_ceo.php ⇒ 404 في الاثنين. ٢) ابحث في سايدبار الدور 9 عن رابطٍ اسمُه «حوكمة …» ⇒ لا يوجد. | Q127: أنشئ `Governance/gov_dept_ceo.php` بنسخ بنية `Governance/gov_dept_gov.php` وتغيير نطاقه إلى EXECUTIVE_ROLE بـ15 عمودًا وفعلين (إقرارٌ حوكمي · رفعُ دليل)، وسجّله في modules و nav_items للدور 9. | R127: فريق الباك-إند — وحدة الحوكمة والالتزام | S127: نعم | T127: لا | U127: فتحُ الشاشة بدور 9 يعرض 15 عمودًا وفعلَي «إقرار» و«رفع دليل»، ويظهر رابطُها في سايدبار الدور 9. | V127: مفتوح | W127: مؤكَّدة | X127: FRD سطر 216 يعلن gov_dept_ceo.php (15 عمودًا · فعلان) ولا ملفَّ بهذا الاسم؛ المكوّنُ النطاقيُّ includes/dept_gov_space.php قائمٌ لكنّه يحتاج شاشةً حاملةً ولم تُنشأ إلا لثلاثِ إداراتٍ، وسايدبار الدور 9 بلا رابطِ حوكمةٍ سوى Governance/signing_authority.php (seed_reference.sql:4025). | Y127: P1 | Z127: نعم | AA127: نعم | AB127: 02_FRD | AC127: فجوة تنفيذ (Implementation) | AD127: Decision Closed · Implementation Open
A128: INJ-0124 | B128: INJAZ-FRD-01 | C128: INJAZ-FRD-01 §٤-٣ · المرحلة ٧ — التأسيسُ والإصدار | D128: مكتب الرئيس التنفيذي والنواب | E128: وضع التأسيس وإغلاقه / بصمة الإصدار وتقرير النشر | F128: http://localhost/ems/Portal/founding_mode.php | G128: سابعًا: التأسيس والإصدار | H128: مخرَجُ المرحلة السابعة مستندان: «محضرُ إغلاقٍ · بصمةُ إصدار» بمعتمِدٍ هو الرئيس التنفيذي — والبصمةُ شاهدٌ يثبت ما نُشر. | I128: Portal/founding_mode.php محروسٌ بـcheck_page_permissions (السطر 33)؛ والذي بلا حارسِ شاشةٍ هو release_stamp.php وحدَه، وإدراجُه (السطر 82) يقع قبل include insidebar فهو أثرٌ قبل الحارس. — [مُصحَّح بعد التحقق] الصياغة الأولى: الشاشتان `Portal/founding_mode.php` و`Portal/release_stamp.php` فورما إدخالٍ عامّان من نمط CMP-03 (16 و18 عمودًا) يكتبان صفًّا نصيًّا عبر `cmp03_store_insert` بلا فعلِ إغلاقٍ ولا توليدِ بصمةٍ من الشيف | J128: Wrong Workflow | K128: P2 | L128: «بصمةُ الإصدار» — وهي الشاهدُ الذي تبني عليه وثيقةُ التسليم قابليةَ الرجوع — نصٌّ يكتبه إنسانٌ ويمكن أن يخالف ما نُشر فعلًا؛ و«إغلاقُ وضع التأسيس» لا يغلق شيئًا في النظام (لا يقفل بذورًا ولا يمنع تعديلًا). | M128: توليدُ الشاشتين ضمن دفعةِ فورمات CMP-03 بدل ربطهما بمصدرٍ آليٍّ (نظامُ الإصدار) وبفعلٍ يغيّر حالةَ النظام. | N128: Portal/founding_mode.php:33; :80; Portal/release_stamp.php:82; includes/cmp03_local_store.php:31; :55 | P128: ١) ادخل بدور 9 وافتح Portal/release_stamp.php. ٢) اضغط «إضافة» واكتب أيَّ نصٍّ في حقول البصمة واحفظ. ٣) قارن بالنسخة المنشورة فعلًا ⇒ لا رابطَ بينهما. | Q128: اجعل `Portal/release_stamp.php` يولّد البصمةَ خادميًّا (هاش آخر commit + قائمةُ الهجرات المطبَّقة + وقتُ النشر) ويعرضها للقراءة فقط، واجعل `Portal/founding_mode.php` ينفّذ فعلَ إغلاقٍ حقيقيًّا يضبط علَمًا في القاعدة يمنع كتابةَ صفوف is_seed. | R128: فريق التشغيل والنشر (DevOps) | S128: نعم | T128: لا | U128: فتحُ شاشة بصمة الإصدار يعرض بصمةً مولَّدةً تطابق النسخةَ المنشورة، ولا يوجد فيها فورمُ إدخالٍ يدوي. | V128: مفتوح | W128: مرجَّحة | X128: الشاشتان فورما CMP-03 بلا توليدِ بصمةٍ ولا فعلِ إغلاق — لكن ادعاءَ «بلا حارسِ صلاحيةٍ لكليهما» خاطئ: founding_mode.php:33 يستدعي check_page_permissions. | Y128: P1 | Z128: نعم | AA128: نعم | AB128: 02_FRD | AC128: فجوة تنفيذ (Implementation) | AD128: Decision Closed · Implementation Open
A129: INJ-0125 | B129: INJAZ-UX-01 | C129: ٤-٥ · قواعدُ السايدبار الثلاثةَ عشرَ — «مساحةُ عملي فوق الإداراتِ دائمًا» | D129: مكتب الرئيس التنفيذي والنواب | E129: مساحة عملي | F129: http://localhost/ems/main/my_workspace.php | G129: غير موجود في السايدبار | H129: «① مساحةُ عملي: ثابتةٌ حرفيًّا — نفسُ الترتيبِ والأسماءِ والأيقونات بين كل الإدارات · محتواها: مهامي · طلباتي · موافقاتي · بلاغاتي · إنجازي · التنبيهات» و«مساحةُ عملي فوق الإداراتِ دائمًا — المنطقةُ ① أعلى السايدبار». | I129: لا توجد منطقةُ «مساحة عملي» في السايدبار إطلاقًا: بابُها أيقونةُ حقيبةٍ في الشريط العلوي. وبديلُها في السايدبار عنوانٌ فرعيٌّ غيرُ قابلٍ للنقر «مساحتي الشخصية» داخل المرحلة صفر، ومحتواه لدور 9: مهامي · إنجازي · بوابتي · طلباتي · المراسلات — أي أن «موافقاتي» و«بلاغاتي» و«التنبيهات» غائبةٌ تمامًا، و«بوابتي» زائدة. | J129: Wrong Sidebar Placement | K129: P2 | L129: المدخلُ اليوميُّ للقمة (ما ينتظر اعتمادَها) غيرُ موجودٍ في القائمة: التنفيذيُّ لا يجد «موافقاتي» ولا «التنبيهات» في سايدباره ويعتمد على أيقونةٍ في الشريط العلوي بلا تسمية. والقاعدةُ «ثابتةٌ حرفيًّا بين كل الإدارات» مخروقةٌ لأن المحتوى يختلف باختلاف صفوف nav_items لكل دور. | M129: قرارُ تنفيذٍ جعل مساحةَ عملي «بابًا في الشريط العلوي» (تعليقُ الكود في topbar.php:184) بدل منطقةٍ أولى في السايدبار كما تنص الوثيقة، ثم أُعيد بعضُ عناصرها في السايدبار كعناوينَ فرعيةٍ من البيانات. | N129: includes/topbar.php:184; includes/topbar.php:186; includes/topbar.php:203; includes/unified_nav.php:205-240; Portal/approvals_inbox.php:1; Portal/notifications.php:1 | P129: ١) ادخل بدور 9. ٢) افحص السايدبار من أعلى ⇒ أول مجموعة «لوحة الإدارة التنفيذية» لا «مساحة عملي». ٣) ابحث عن «موافقاتي» و«بلاغاتي» و«التنبيهات» في القائمة ⇒ غير موجودة رغم وجود Portal/approvals_inbox.php و Portal/notifications.php. | Q129: في `includes/unified_nav.php::printStageNav()` أضِف منطقةً ثابتةً قبل حلقة المراحل تطبع العناصرَ الستةَ بالترتيب والأسماء المنصوص عليها من ثابتٍ في الكود (لا من nav_items)، وأبقِ أيقونةَ الشريط العلوي اختصارًا لا بديلًا. | R129: فريق الواجهة — وحدة التنقل | S129: لا | T129: نعم | U129: فتحُ أيِّ دورٍ من الأدوار الأربعة يعرض في أعلى السايدبار مجموعةً اسمُها «مساحة عملي» بستةِ عناصرَ بالأسماء والترتيب نفسِه حرفيًّا. | V129: مفتوح | W129: مؤكَّدة | X129: لا منطقةَ «مساحة عملي» في السايدبار؛ بديلُها مجموعةُ link_groups id=3253 «مساحتي الشخصية» بعناصر: مهامي · إنجازي · بوابتي · طلباتي · المراسلات (nav_items 5841-5845) — و«موافقاتي» و«بلاغاتي» و«التنبيهات» غائبة فعلًا. والباب أيقونةُ حقيبةٍ في topbar.php:203. | Y129: P2 | Z129: نعم | AA129: نعم | AB129: 03_UX | AC129: فجوة تنفيذ (Implementation) | AD129: Decision Closed · Implementation Open
A130: INJ-0126 | B130: INJAZ-UX-01 | C130: ٧-٣ · التصديرُ والفلاترُ والبحث في الشاشات الطويلة | D130: مكتب الرئيس التنفيذي والنواب | E130: اعتمادات المدير التنفيذي | F130: http://localhost/ems/Portal/ceo_approvals.php | G130: ثانيًا: الاعتمادات العليا | H130: «الشاشاتُ الطويلةُ (٢٠+ عمودًا) تحتاج مناظرَ وزرَّ إظهارِ الكلِّ إلزامًا» و«تصديرٌ يُخرج العرضَ المختارَ أو جميعَ الأعمدةِ المسموحةِ بحسب الصلاحية» و«البحثُ داخلَ شريطِ أدواتِ الجدول». | I130: شاشاتُ القمة الخمسُ (20 · 24 · 27 · 17 · 16 عمودًا) بلا زرِّ «إظهار كل الأعمدة» وبلا منتقي منظر وبلا فلترِ فترةٍ أو إدارةٍ أو حالة وبلا أيِّ تصدير: قائمةُ الشاشات الخمسِ والعشرين التي تملك تصديرَ الإطار الموحَّد لا تضم شاشةً واحدةً من Portal (25 جدول Portal بلا تصدير). | J130: Export/Import Gap | K130: P2 | L130: لا يستطيع الرئيسُ التنفيذيُّ إخراجَ سجل اعتماداته أو توقيعاته لمجلس الإدارة أو للمراجع الخارجي إلا بنسخٍ يدويٍّ من الشاشة؛ ولا يستطيع تصفيةَ الصفوف بفترةٍ أو إدارةٍ في جدولٍ يبلغ 500 صف. | M130: شاشاتُ CMP-03 وُلدت بجدولٍ مكتوبٍ يدويًّا بلا عُدّة `u13_screen_kit` (التي وحدَها تطبع زرَّ «إظهار كل الأعمدة») وبلا تسجيلٍ في سجل كيانات التصدير. | N130: Portal/ceo_approvals.php:346-384; includes/u13_screen_kit.php:317-319; includes/excel_ui.php:45-61; app/Services/Excel/ExcelService.php:56-70 | P130: ١) افتح Portal/ceo_approvals.php. ٢) ابحث عن زرِّ تصديرٍ أو منتقي منظرٍ أو فلترِ فترة ⇒ لا شيء. ٣) قارن بـ Suppliers/suppliers.php حيث يظهر زرُّ التصدير. | Q130: سجّل كياناتِ exec_approvals · exec_contract_signings · exec_project_charters في `app/Services/Excel/` وأضِف `ems_excel_header_actions()` إلى `$header_actions` في الشاشات الخمس، وحوّل الجداولَ إلى `includes/u13_screen_kit.php` لتحصل على منتقي المنظر وزرِّ إظهار كل الأعمدة بالنص الموحَّد. | R130: فريق الواجهة — وحدة القمة التنفيذية | S130: لا | T130: نعم | U130: كلُّ شاشةِ قمةٍ فيها زرُّ «إظهار كل الأعمدة» بالنص الموحَّد وزرُّ تصديرٍ يخرج الأعمدةَ المسموحةَ مع الفلاتر المفعَّلة. | V130: مفتوح | W130: مؤكَّدة | X130: لا ملفَّ واحدًا في Portal/ يستدعي excel_ui أو u13_screen_kit أو EmsColumnGroups، وجدولُ ceo_approvals عشرون عمودًا بلا منتقي منظرٍ ولا زرِّ إظهارِ الكل ولا تصدير. | Y130: P2 | Z130: نعم | AA130: نعم | AB130: 03_UX | AC130: فجوة تنفيذ (Implementation) | AD130: Decision Closed · Implementation Open
A131: INJ-0127 | B131: INJAZ-UX-01 | C131: ٨-١ · الشاشاتُ التسعُ ومصادرُها — «موافقاتي» | D131: مكتب الرئيس التنفيذي والنواب | E131: موافقاتي | F131: http://localhost/ems/Portal/approvals_inbox.php | G131: غير موجود في السايدبار | H131: «موافقاتي» أحدُ عناصر مساحة عملي الستة الثابتة حرفيًّا، «تجمع عناصرَ من مصادرها الأصليةِ في الإدارات … وكلُّ عنصرٍ يرجع إلى مستنده أو سجله الأصليِّ بضغطةٍ واحدة». | I131: الشاشةُ غيرُ مربوطةٍ في السايدبار لكنها ليست بلا منفذ: Portal/my_portal.php يعرض بلاطةً إلى approvals_inbox.php وmy_requests.php. — [مُصحَّح بعد التحقق] الصياغة الأولى: توجد نسختان متوازيتان للشاشة نفسِها — `Portal/approvals_inbox.php` و`Finance/approvals_inbox.php` — ولا واحدةَ منهما مرتبطةٌ في سايدبار الدور 9؛ وكذلك «طلباتي» لها نسختان: `Portal/my_requests.php` و`F | J131: Duplicate Screen | K131: P2 | L131: صندوقُ الموافقات — أهمُّ شاشةٍ يوميةٍ للقمة — غيرُ موجودٍ في قائمتها، ووجودُ نسختين لكلِّ شاشةٍ يعني مصدرَي حقيقةٍ للعدّاد نفسِه ويكسر حكمَ «المصدرُ الموحَّد». | M131: نسخُ شاشةِ صندوقٍ إلى وحدتين (Portal و Finance) دون توحيدٍ ولا حذفٍ، وغيابُ صفوف nav_items لها في الدور 9. | N131: Portal/approvals_inbox.php:1; Finance/approvals_inbox.php:1; Portal/my_requests.php:1; FinRequests/my_requests.php:1 | P131: ١) ادخل بدور 9. ٢) ابحث في السايدبار عن «موافقاتي» ⇒ غير موجود. ٣) افتح http://localhost/ems/Portal/approvals_inbox.php ثم http://localhost/ems/Finance/approvals_inbox.php ⇒ شاشتان متشابهتان بمسارين. | Q131: اختر `Portal/approvals_inbox.php` مصدرًا واحدًا، وحوّل `Finance/approvals_inbox.php` إلى إعادةِ توجيهٍ إليه، وأضِف صفَّ nav_items «موافقاتي» في منطقة مساحة عملي لكلِّ الأدوار بما فيها 9. | R131: فريق الباك-إند — وحدة البوابة الشخصية | S131: لا | T131: نعم | U131: «موافقاتي» ظاهرةٌ في مساحة عملي لكلِّ دور، وتفتح مسارًا واحدًا، وعدّادُها يطابق عدَّ الصندوق. | V131: مفتوح | W131: مرجَّحة | X131: النسختان المتوازيتان ثابتتان و«موافقاتي» بلا صفِّ nav_items للدور 9، لكنها تُبلَغ من بلاطةِ «بوابتي» (Portal/my_portal.php:51) الحاضرةِ في المرحلة صفر لكل دور. | Y131: P2 | Z131: نعم | AA131: نعم | AB131: 03_UX | AC131: فجوة تنفيذ (Implementation) | AD131: Decision Closed · Implementation Open
A132: INJ-0128 | B132: INJAZ-UX-01 | C132: ٤-٥ · «الشاشةُ الجديدةُ لا تظهر قبل اجتياز بوابةِ الشاشةِ كاملةً» | D132: مكتب الرئيس التنفيذي والنواب | E132: تقارير الإدارة التنفيذية الثمانية | F132: http://localhost/ems/Portal/ceo_reports.php | G132: غير موجود في السايدبار | H132: كلُّ شاشةٍ في قائمةِ دورها — «فالمبنيُّ الذي لا يُبلَغ كالمعدوم»؛ ولا شاشةَ تُبنى خارجَ سجل التنقل. | I132: صفّا nav 6900/6901 (role 9 · active=1) يحملان module_id=NULL مع permission_code غيرِ فارغ فيسقطان من شرط getUnifiedNavItems، وdoor='main' ليس من الأبواب الثمانية في unifiedNavDoors() — فلا يُطبعان أبدًا؛ و`Portal/ceo_reports.php` بلا صفِّ nav أصلًا. — [مُصحَّح بعد التحقق] الصياغة الأولى: ثلاثُ شاشاتِ قمةٍ مبنيةٌ وحيةٌ ولا رابطَ لها في سايدبار الدور 9: `Portal/ceo_reports.php` (تقارير القمة الثمانية — تُشار إليها من لوحة القمة برابطٍ نصيٍّ داخل الصفحة فقط) و`Portal/ceo_assignments.php` | J132: Missing Screen | K132: P2 | L132: ثلاثُ شاشاتٍ مبنيةٌ ومدفوعُ ثمنُها لا يبلغها المستخدمُ من قائمته؛ وتقاريرُ القمة الثمانيةُ — وهي مخرَجُ المرحلة السادسة — تعتمد على رابطٍ نصيٍّ داخل لوحةٍ أخرى. | M132: بناءُ شاشاتٍ خارج مسار البذرة في `nav_items`، وغيابُ فاحصٍ يقارن ملفاتِ الشاشات بسجل التنقل. | N132: database/schema/seed_reference.sql:5064-5065; includes/unified_nav.php:70-78; :32-42 | P132: ١) ادخل بدور 9. ٢) ابحث في السايدبار عن «تقارير» ⇒ لا رابطَ لـ ceo_reports.php. ٣) افتح Portal/ceo_board.php واضغط الرابطَ النصيَّ أسفل البطاقات ⇒ تُفتح شاشةٌ كاملةٌ غيرُ مفهرسة. | Q132: أضِف صفوفَ nav_items للشاشات الثلاث في مجموعة «التقارير والتصدير» للدور 9 في `database/schema/seed_reference.sql`، وسجّلها في `modules` بمنحٍ صريح. | R132: فريق الواجهة — وحدة التنقل | S132: لا | T132: نعم | U132: الشاشاتُ الثلاثُ تظهر في سايدبار الدور 9 وتُفتح بنقرةٍ واحدةٍ من القائمة. | V132: مفتوح | W132: مؤكَّدة | X132: الشاشاتُ الثلاثُ فعلًا لا تظهر للدور 9، لكن السببَ أدقُّ مما ذُكر: `ceo_audit_reports` و`ceo_assignments` لهما صفّان (6900 · 6901) لكنهما ميتان بنيويًّا. | Y132: P2 | Z132: لا — يحتاج مراجعة | AA132: نعم | AB132: 03_UX | AC132: فجوة تنفيذ (Implementation) | AD132: Decision Closed · Implementation Open
A133: INJ-0129 | B133: INJAZ-UX-01 | C133: §٦-٢ الشاشاتُ الطويلةُ ومناظرُها · CM-14 | D133: مكتب الرئيس التنفيذي والنواب | E133: لوحة المؤشرات التنفيذية | F133: http://localhost/ems/Portal/ceo_board.php | G133: العمل اليومي | H133: المؤشرُ «قيمةٌ مجمَّعةٌ تُشتق آليًّا» (FRD §٢٦-١ نوع ٨) — «ليس الإنجازَ — الإنجازُ واقعةٌ والمؤشرُ تجميعُها». | I133: حقلُ «المخاطر المفتوحة» في لوحةِ الرئيسِ حقلُ إدخالٍ نصيٍّ يدويٌّ: `Portal/ceo_board.php:62` يُدرجه ضمن `$DB_FIELDS` و`:212-213` يصيّره `<input type="text" name="f12" maxlength="190">` — والعمودُ في المخطط `varchar(20)` (`database/schema/schema.sql:3033`). | J133: Data Mismatch | K133: P2 | L133: أهمُّ لوحةٍ في النظامِ تُملأ يدويًّا: رقمُ المخاطرِ المفتوحةِ قابلٌ للكتابةِ نصًّا («قليلة» مثلًا) ولا يُطابق السجلَّ المركزيَّ ولا يتحدث تلقائيًّا. | M133: لوحةُ CMP-03 وُلِّدت كجدولِ إدخالٍ من المستندِ بدل ربطِ كلِّ عمودٍ بمصدره الحي. | N133: Portal/ceo_board.php:62; :212; :213; database/schema/schema.sql:3033 | P133: ١) بدور 9 افتح `Portal/ceo_board.php` واضغط «إضافة». ٢) اكتب في حقل «المخاطر المفتوحة» نصًّا مثل «١٢ تقريبًا» واحفظ. ٣) الصفُّ يُحفظ كما هو — بلا أيِّ تحققٍ ولا مطابقةٍ مع `risk_register`. | Q133: اجعل الحقلَ محسوبًا: في `Portal/ceo_board.php` احذف `f12` من نموذجِ الإدخال (`:212-213`) واحسب القيمةَ عند العرضِ من `SELECT COUNT(*) FROM risk_register WHERE company_id=? AND state<>'closed' AND merged_into_id IS NULL`، وغيِّر نوعَ العمودِ إلى `int` بهجرة. | R133: فريق الباك-إند — مكتب الرئيس التنفيذي | S133: لا | T133: لا | U133: بعد تسجيلِ خطرٍ جديدٍ في `risk_register` يجب أن تُظهر لوحةُ الرئيسِ الرقمَ الجديدَ بلا أيِّ إدخالٍ يدوي، ولا يوجد في الصفحةِ حقلُ إدخالٍ باسم `f12`. | V133: مفتوح | W133: مؤكَّدة | X133: open_risks حقلُ إدخالٍ نصيٌّ في نموذج الإضافة (السطر 212-213) ضمن DB_FIELDS والعمودُ varchar(20) — فمؤشرُ لوحة الرئيس يُكتب يدويًّا لا يُشتق من risk_register. | Y133: P2 | Z133: نعم | AA133: نعم | AB133: 03_UX | AC133: فجوة تنفيذ (Implementation) | AD133: Decision Closed · Implementation Open
A134: INJ-0130 | B134: M-14 | C134: BR-GOV-01 · الحارسُ في الخادمِ لكلِّ فعلٍ كاتب | D134: مكتب الرئيس التنفيذي والنواب | E134: المخاطر والقرارات العليا | F134: http://localhost/ems/Portal/ceo_risk.php | G134: خامسًا: المخاطر والحسم | H134: القرارُ الأعلى فعلٌ محجوزٌ للقمة، ويقع بعدَ حارسٍ خادميٍّ يفحص الدورَ والسلطةَ — لا بمجرد صلاحية إضافةٍ على الشاشة. | I134: الانكشافُ اليومَ مشروطٌ بمنحةٍ إدارية: role_permissions تمنح الموديول 235 للدور 9 وحدَه حاليًّا — فالفجوةُ بنيويةٌ (حارسُ سلطةٍ مفقود) لا مستغَلَّةٌ بالبذرة الحالية. — [مُصحَّح بعد التحقق] الصياغة الأولى: القرارُ التنفيذيُّ الحاسم يُنشأ كلَّه من فرع «إضافة» (cmp03_action=add): يكفي أن يملأ المستخدمُ `تاريخ القرار` أو يختار حالةً حاسمة ليصير الصفُّ «محسومًا» وتُنشر حقيقةُ `exec.decision.made` وتُفتح مهم | J134: Permission Gap | K134: P2 | L134: أيُّ مستخدمٍ له can_add على الشاشة يصدر «قرارَ إدارةٍ عليا» يُلزم إدارةً أخرى بمهلةِ تنفيذ، ويظهر في تقارير القمة ولوحتها بوصفه قرارًا محسومًا للرئيس التنفيذي. | M134: شاشةٌ وُلدت على نمط CMP-03 (فورمُ إدخالٍ عام) ولم تُزوَّد بحارس الفعل الحاكم الذي زُوّدت به شقيقاتُها ceo_approvals و ceo_contracts و project_charter. | N134: Portal/ceo_risk.php:36-38; :71; :78-80; :112; :116; Portal/ceo_approvals.php:114; Portal/ceo_contracts.php:131 | P134: ١) امنح دورًا غير 9 صلاحيةَ can_add على Portal/ceo_risk.php. ٢) افتح الشاشة واضغط «إضافة». ٣) املأ الجهةَ المكلَّفة ومهلةَ التنفيذ وتاريخَ القرار واحفظ. ٤) لاحظ ظهورَ الصفِّ محسومًا وإنشاءَ مهمةِ متابعة. | Q134: في `Portal/ceo_risk.php` أضِف قبل الإدراج (سطر 90): إن كان `$decisive` صحيحًا فافحص `$is_super_admin || strval($_SESSION['user']['role'])==='9'` وإلا أعِد التوجيه بـ GOV-PERM-403؛ أو افصل «رفع القضية» (متاحٌ للإدارات) عن «الحسم» (فعلٌ مستقلٌّ محروسٌ بالدور) كما في ceo_approvals. | R134: فريق الباك-إند — وحدة القمة التنفيذية (Portal) | S134: نعم | T134: نعم | U134: مستخدمٌ بدور غير 9 يحفظ قرارًا بحالة «محسوم» ⇒ يُرفض؛ والدورُ 9 وحدَه يستطيع الحسم. | V134: مفتوح | W134: مؤكَّدة | X134: الحارسُ الوحيدُ في ceo_risk.php هو can_add/can_edit (السطر 37) وصفرُ فحصٍ للدور 9، بخلاف ceo_approvals.php التي تشترط الدور 9 لفعل القرار؛ والصفُّ الحاسمُ ينشر exec.decision.made. | Y134: P1 | Z134: نعم | AA134: نعم | AB134: 06_M14 | AC134: فجوة تنفيذ (Implementation) | AD134: Decision Closed · Implementation Open
A135: INJ-0131 | B135: M-14 | C135: TABLE 53 · سجلُّ التدقيق — القيمةُ قبل والقيمةُ بعد | D135: مكتب الرئيس التنفيذي والنواب | E135: شاشات القمة التنفيذية (Portal/ceo_*) | F135: http://localhost/ems/Portal/project_charter.php | G135: رابعًا: فتح المشاريع | H135: كلُّ فعلٍ يغيّر الحالةَ يكتب سجلَّ تدقيقٍ يحمل الفاعلَ والوقتَ والقيمةَ قبل والقيمةَ بعد. | I135: `Portal/project_charter.php` (فتحُ مشروعٍ بمركز تكلفةٍ ومواقع) لا يكتب سجلَّ تدقيقٍ إطلاقًا — لا `ems_audit_change()` ولا `log_security_event()`. و`ceo_approvals` و`ceo_contracts` تكتفيان بسطرِ `log_security_event` نصيٍّ بلا قيمةٍ قبل ولا بعد. ووسيطُ `ActivityLogMiddleware` يسجّل الطلبَ لا القيم. | J135: Missing Evidence | K135: P2 | L135: أضخمُ فعلٍ توليديٍّ في المنظومة (يُنشئ مشروعًا ومركزَ تكلفةٍ ومواقعَ ومهمة) يقع بلا أثرٍ تدقيقيٍّ يمكن الرجوعُ إليه؛ ولا يمكن إثباتُ من غيّر ماذا ومتى أمام مراجعٍ خارجي. | M135: الاعتمادُ على وسيطِ تسجيلِ الطلبات بوصفه سجلَّ تدقيق، وهو لا يحمل القيمَ كما تُقرّ ترويسةُ `includes/audit_trail.php` نفسُها. | N135: Portal/project_charter.php:115; :184-222; Portal/ceo_approvals.php:167-169; Portal/ceo_contracts.php:190-192 | P135: ١) اعتمد فتحَ مشروعٍ. ٢) ابحث في سجل التدقيق عن صفٍّ يحمل القيمةَ قبل والقيمةَ بعد لهذا القرار ⇒ لا يوجد. | Q135: في `Portal/project_charter.php` داخل معاملة charter (بعد سطر 226) استدعِ `ems_audit_change('exec_project_charters', $rowId, $before, $after, $uid)` قبل `commit()`؛ وكرّر النمطَ في ceo_approvals.php:160 و ceo_contracts.php:186 و ceo_risk.php:107. | R135: فريق الباك-إند — وحدة الحوكمة والالتزام | S135: لا | T135: لا | U135: بعد كل فعلٍ من أفعال القمة يوجد صفُّ تدقيقٍ واحدٌ على الأقل يحمل الجدولَ والمعرّفَ والقيمةَ قبل والقيمةَ بعد والفاعلَ والوقت. | V135: مفتوح | W135: مؤكَّدة | X135: Portal/project_charter.php خالٍ من ems_audit_change ومن log_security_event، والاعتماداتُ والعقودُ تكتفيان بسطرٍ نصيّ — لكنَّ توقيعَ الإصلاح المقترح خاطئ. | Y135: P2 | Z135: لا — يحتاج مراجعة | AA135: نعم | AB135: 06_M14 | AC135: فجوة دليل (Evidence) | AD135: Implementation Closed · Evidence Open
A136: INJ-0132 | B136: INJAZ-FRD-01 | C136: INJAZ-FRD-01 §٥-٤ · شاشاتُ إدارة التشغيل الثماني | D136: إدارة التشغيل | E136: إسناد المعدات للوحدات | F136: http://localhost/ems/Operations/containers.php#n9g7i1 | G136: ثانيًا: توزيع الموارد | H136: من شاشات الإدارة الثماني المعلَنة: «إسناد المعدات للوحدات» (unit_assign.php · 27 عمودًا · فعلٌ واحد · تراها 3 إدارات) — شاشةٌ لها غرضٌ ومالكٌ وأعمدةٌ وأفعال. | I136: لا وجودَ لملفٍّ بهذا الغرض: الرابطُ في السايدبار يشير إلى `Operations/containers.php#n9g7i1` — أي المقطعُ نفسُه من شاشة «حاويات العقود» المسجَّلةِ مرةً أخرى في المجموعة الأولى باسم «الوحدات التعاقدية المرقَّمة». والشاشةُ المفتوحةُ عنوانُها الحقيقيُّ «حاويات العقود» لا «إسناد المعدات للوحدات». | J136: Duplicate Screen | K136: P2 | L136: عنصران في القائمة يفتحان الملفَّ نفسَه بعنوانَين مختلفين وبعنوانِ صفحةٍ ثالث؛ فيظن المستخدمُ أنه انتقل إلى شاشةٍ أخرى ويجد الشاشةَ نفسَها. ويستحيل قياسُ «عددِ الشاشات» أو إثباتُ اكتمال الشاشات الثماني. | M136: تنفيذُ عنصرِ تنقّلٍ بمقطعٍ `#nNgMiK` على المسار نفسِه للالتفاف على القيد الفريد `uq_nav_role_route(role_id, route)` بدل بناء الشاشة. | N136: database/schema/seed_reference.sql:4136 (nav#5961); :4129 (nav#5954); Operations/containers.php:198,292 | P136: ١) ادخل بدور 1. ٢) افتح «الوحدات التعاقدية المرقَّمة» ثم «إسناد المعدات للوحدات» ⇒ الصفحةُ نفسُها بعنوان «حاويات العقود». ٣) لاحظ إضاءةَ العنصرين معًا. | Q136: إمّا بناءُ `Operations/unit_assign.php` بالأعمدة السبعة والعشرين والفعل المعلَن، وإمّا حذفُ صفِّ nav_items ذي المقطع وتوحيدُ التسمية على «الوحدات التعاقدية المرقَّمة» مع تصحيح `$header_title` في `Operations/containers.php:187` ليطابقها. | R136: فريق الباك-إند — وحدة التشغيل | S136: لا | T136: نعم | U136: لا يوجد في سايدبار الدور 1 رابطان يشيران إلى الملف نفسِه، وعنوانُ الصفحة يطابق تسميةَ الرابط حرفيًّا. | V136: مفتوح | W136: مؤكَّدة | X136: لا ملفَّ unit_assign.php في المستودع، وصفُّ nav 5961 للدور 1 يشير إلى `Operations/containers.php#n9g7i1` بينما المِرساةُ غيرُ موجودةٍ في الملف وعنوانُه الحقيقيُّ «حاويات العقود». | Y136: P2 | Z136: نعم | AA136: نعم | AB136: 02_FRD | AC136: فجوة تنفيذ (Implementation) | AD136: Decision Closed · Implementation Open
A137: INJ-0133 | B137: INJAZ-FRD-01 | C137: INJAZ-FRD-01 §٥-٣ · المرحلة ٨ — مخاطرُ الإدارة · و§٥-٤ حوكمةُ الإدارة | D137: إدارة التشغيل | E137: المخاطر التشغيلية / حوكمة إدارة التشغيل | G137: خارج الوثيقة — بانتظار قرار المالك | H137: لإدارة التشغيل شاشتان معلَنتان: «المخاطر التشغيلية» (risk_dept_ops.php · 22 عمودًا · 3 أفعال) و«حوكمة إدارة التشغيل» (gov_dept_ops.php · 15 عمودًا · فعلان)؛ و«مساحةُ المخاطرِ الموحَّدة: عنصرٌ واحدٌ في سايدبار كلِّ إدارةٍ بعنوانٍ خاصٍّ بها». | I137: الملفّان غيرُ موجودين في المستودع (الموجود: risk_dept_fin.php · risk_dept_gov.php · gov_dept_gov.php · gov_dept_fin.php · gov_dept_rsk.php). وبديلُ المخاطر في سايدبار الدور 1 عنصرٌ عامٌّ اسمُه «مساحة مخاطر الإدارة» → `Risk/dept_risk_space.php` موضوعٌ في المجموعة الأخيرة «خارج الوثيقة — بانتظار قرار المالك»، ومعه «مخاطرُ الميدان». ولا شاشةَ حوكمةٍ للإدارة إطلاقًا. | J137: Missing Screen | K137: P2 | L137: مرحلتان معلَنتان من دورة الإدارة بلا شاشة؛ وعنصرُ المخاطر معروضٌ بعنوانٍ عامٍّ في مجموعةٍ تقول للمستخدم إنه «خارج الوثيقة» — فيتعذر إثباتُ حكم «سجلُّ مخاطرٍ مقروءٌ ودليلُ ضوابط» لإدارة التشغيل. | M137: تعميمُ نمطَي `risk_dept_*` و`gov_dept_*` توقّف عند ثلاث إدارات، والعنصرُ العامُّ أُسند لمجموعةِ القرارات المعلَّقة بدل مرحلته. | N137: Risk/dept_risk_space.php:1; Risk/risk_field.php:1; Risk/risk_dept_fin.php:1; Risk/risk_dept_gov.php:1; Governance/gov_dept_gov.php:1; includes/nav_icon_map.php:391-392 | P137: ١) افتح http://localhost/ems/Risk/risk_dept_ops.php ⇒ 404. ٢) افتح http://localhost/ems/Governance/gov_dept_ops.php ⇒ 404. ٣) ادخل بدور 1 ⇒ عنصرُ المخاطر الوحيدُ في المجموعة الأخيرة بعنوانٍ عام. | Q137: أنشئ `Risk/risk_dept_ops.php` و`Governance/gov_dept_ops.php` على نمط نظائرهما، وسجّلهما في modules و nav_items للدور 1، وانقل عنصرَ المخاطر من stage_no=99 إلى مجموعةٍ باسم «المخاطر التشغيلية». | R137: فريق الباك-إند — وحدة المخاطر | S137: نعم | T137: نعم | U137: سايدبارُ الدور 1 يعرض «المخاطر التشغيلية» و«حوكمة إدارة التشغيل» في مجموعاتهما الصحيحة، وكلٌّ منهما يفتح شاشةً بالأعمدة والأفعال المعلَنة. | V137: مفتوح | W137: مؤكَّدة | X137: risk_dept_ops.php وgov_dept_ops.php غيرُ موجودين في المستودع (الموجودُ نظائرُهما للمالية والحوكمة والمخاطر)، وعنصرا المخاطر للدور 1 في المجموعة 2084 وهي المرحلة 99 «خارج الوثيقة». | Y137: P1 | Z137: نعم | AA137: نعم | AB137: 02_FRD | AC137: فجوة قرار (Decision) | AD137: Decision Open
A138: INJ-0134 | B138: INJAZ-FRD-01 | C138: INJAZ-FRD-01 §٥-١ · ما تملكه إدارةُ التشغيل — الخطةُ الشهرية | D138: إدارة التشغيل | E138: خطة عمل الغد | F138: http://localhost/ems/Operations/daily_plan.php | G138: غير موجود في السايدبار | H138: المرحلةُ الأولى «خطة الشهر» مخرَجُها «خطةٌ شهريةٌ معتمدة» باعتمادِ مدير التشغيل، وست شاشاتٍ تخدمها. | I138: الصفُّ موجودٌ وفعّالٌ (nav_items 5957 · group 3318 · stage 1) ويُحجب بغياب منحةِ العرض على الموديول 152؛ والقائمُ فعلًا هو غيابُ شاشةِ خطةٍ شهريةٍ ومستندِها وفعلِ اعتمادها. — [مُصحَّح بعد التحقق] الصياغة الأولى: مجموعةُ «أولًا: خطة الشهر» في سايدبار الدور 1 تضم خمسةَ روابطَ ليس فيها شاشةُ خطةٍ واحدة: عقودُ العملاء · التزامُ العقد بنوع المعدة · الوحداتُ التعاقدية · حصصُ الموردين · توزيعُ وحدات المورد — كلُّها | J138: Missing Screen | K138: P2 | L138: أولُ مرحلةٍ في دورة الإدارة — وهي مصدرُ كلِّ ما بعدها — بلا مستندٍ ولا شاشةٍ ولا اعتماد: لا يمكن إثباتُ وجود «خطة شهرية معتمدة» ولا قياسُ الانحراف عنها في المرحلة الرابعة. | M138: بذرةُ nav_items ملأت المرحلةَ الأولى بشاشاتِ مرجعٍ من إداراتٍ أخرى بدل شاشة الخطة، وشاشةُ التخطيط اليومي بُنيت ولم تُربَط. | N138: Operations/daily_plan.php:1; app/Services/Operations/DailyPlanService.php:257; Contracts/contracts.php:1; Suppliers/shares_coverage.php:1 | P138: ١) ادخل بدور 1 وافتح مجموعة «أولًا: خطة الشهر» ⇒ خمسةُ روابطَ لعقودٍ وحصص. ٢) ابحث عن شاشةِ خطةٍ شهريةٍ أو زرِّ «اعتماد الخطة» ⇒ لا يوجد. ٣) افتح Operations/daily_plan.php مباشرةً ⇒ تُفتح ولا رابطَ لها. | Q138: أضِف `Operations/monthly_plan.php` بمستندِ خطةٍ شهريةٍ وفعلِ اعتمادٍ محروسٍ بدور مدير التشغيل، واربط `Operations/daily_plan.php` بالمجموعة نفسِها، وانشر `operations.monthly_plan.approved` ليقرأه توزيعُ الموارد وقياسُ الانحراف. | R138: فريق الباك-إند — وحدة التشغيل | S138: نعم | T138: نعم | U138: مجموعةُ «أولًا: خطة الشهر» تحوي شاشةَ خطةٍ شهريةٍ فيها فعلُ اعتمادٍ ينتج مستندًا مؤرَّخًا بمعتمِدٍ، وتقريرُ الانحراف يقيس عليه. | V138: مفتوح | W138: مرجَّحة | X138: صحيحٌ أن مجموعةَ «أولًا: خطة الشهر» للدور 1 تعرض خمسةَ روابطِ عقودٍ وحصصٍ ولا شاشةَ خطةٍ شهريةٍ ولا فعلَ اعتمادها؛ لكن الادعاءَ «لا رابطَ لـdaily_plan في سايدبار الدور 1» غيرُ دقيق: الصفُّ nav_items id=5957 قائمٌ وفعّالٌ في المجموعة 3318 داخلَ المرحلة نفسِها، وسقوطُه سببُه غيابُ can_view للدور 1 على الموديول 152. | Y138: P1 | Z138: نعم | AA138: نعم | AB138: 02_FRD | AC138: فجوة تنفيذ (Implementation) | AD138: Decision Closed · Implementation Open
A139: INJ-0135 | B139: INJAZ-FRD-01 | C139: INJAZ-FRD-01 §٥-٥ · الأثرُ العابرُ — التشغيلُ لا يكتب في جداول غيره | D139: إدارة التشغيل | E139: حاويات العقود (الوحدات التعاقدية) | F139: http://localhost/ems/Operations/containers.php | G139: أولًا: خطة الشهر | H139: «لا إدارةَ تكتب في جداول إدارةٍ أخرى — والأثرُ ينتقل بالأحداث»؛ وتوليدُ الحاويات أثرٌ لتوقيع العقد يستهلكه التشغيل. | I139: الحاوياتُ تُنشأ بنداءٍ مباشرٍ من خدمة العقود `app/Services/Contract/ContractSignedEffects.php:53` (INSERT INTO op_containers) لا بمستهلكٍ لحدث `contract.signed`؛ ولا مستهلكَ لهذا الحدث في المستودع أصلًا. وفي الاتجاه المقابل، شاشةُ التشغيل تقرأ `contracts` وتكتب `operator_rotations` مباشرةً. | J139: Event/Integration Gap | K139: P2 | L139: أولُ حلقةٍ في سلسلة «عقد ← أمر تشغيل» نداءٌ مباشرٌ داخلَ طلبٍ واحد: إن فشل جزءٌ منه لم يُعَد المحاولة، وإن أُضيفت قاعدةُ تشغيلٍ جديدةٌ لم تُطبَّق على العقود الموقَّعة قبلها. والحدثُ المنشورُ يذهب إلى جدولٍ لا يقرؤه أحد. | M139: بناءُ الأثر بنداءٍ متزامنٍ لأن ناقلَ الأحداث معطَّلٌ افتراضيًّا، فصار النداءُ المباشرُ هو المسارَ الوحيد. | N139: app/Services/Contract/ContractSignedEffects.php:54 (INSERT INTO op_containers) | P139: ١) وقّع عقدًا من Portal/ceo_contracts.php مرتبطًا بعقدٍ حقيقي. ٢) لاحظ إنشاءَ op_containers في الطلب نفسِه. ٣) ابحث عن مستهلكٍ لـ contract.signed في المستودع ⇒ لا يوجد. | Q139: حوّل `ContractSignedEffects` إلى مستهلكٍ مسجَّلٍ لحدث `contract.signed` يعمل خارج الطلب (cron_events.php) بمفتاح عطالةٍ على contract_id، واترك آلةَ الحالة تنشر الحدثَ فقط. | R139: فريق الباك-إند — وحدة المعمارية والأحداث | S139: نعم | T139: لا | U139: توقيعُ عقدٍ ينشر حدثًا واحدًا، وتظهر الحاوياتُ خلال دورة المستهلك؛ وإعادةُ تشغيل المستهلك لا تضاعف الحاويات. | V139: مفتوح | W139: مؤكَّدة | X139: ‏ContractSignedEffects ينشئ op_containers بنداءٍ مباشرٍ (السطر 54 هو الـINSERT لا 53) ولا مستهلكَ لحدث contract.signed في المستودع (القراءاتُ الوحيدةُ تقاريرُ في Portal/ceo_*). والخفضُ إلى P2 لأن الأثرَ يقع فعلًا والمخالفةُ معماريةٌ لا وظيفية. | Y139: P1 | Z139: نعم | AA139: نعم | AB139: 02_FRD | AC139: فجوة تنفيذ (Implementation) | AD139: Decision Closed · Implementation Open
A140: INJ-0136 | B140: INJAZ-UX-01 | C140: ٧-٣ · التصديرُ الواعي بالمنظر — والشاشاتُ الطويلة | D140: إدارة التشغيل | E140: جداول إدارة التشغيل | F140: http://localhost/ems/Operations/unit_perf.php | G140: رابعًا: متابعة الانحراف | H140: «تصديرٌ يُخرج العرضَ المختارَ أو جميعَ الأعمدةِ المسموحةِ بحسب الصلاحية» وثمانيةُ خياراتِ تصديرٍ واعيةٍ بالمنظر؛ والشاشاتُ الطويلةُ تحتاج مناظرَ وزرَّ «إظهار كل الأعمدة» إلزامًا. | I140: صفرُ تصديرٍ في تسعةَ عشرَ جدولًا من جداول وحدة التشغيل (قائمةُ الشاشات الخمسِ والعشرين ذاتِ التصدير لا تضم ملفًّا واحدًا من Operations)؛ وصفرُ استيراد؛ وصفرُ زرِّ «إظهار كل الأعمدة»؛ وصفرُ منتقي منظر — رغم أن unit_perf و monthly_close و unbilled و production تتجاوز 28 عمودًا. | J140: Export/Import Gap | K140: P2 | L140: لا يستطيع مديرُ التشغيل إخراجَ الأداء الشهري أو الأعمال غير المفوترة إلى المالية أو المبيعات إلا بنسخٍ يدوي؛ ويُفتح جدولٌ بـ31 عمودًا دفعةً واحدةً على شاشةٍ واحدةٍ بلا منظرٍ يركّز المهمة — وهو نصُّ العيب الذي تسمّيه الوثيقة. | M140: جداولُ الوحدة مكتوبةٌ يدويًّا خارج عُدّة `u13_screen_kit` (التي وحدَها تطبع منتقي المنظر وزرَّ إظهار الكل)، وكياناتُها غيرُ مسجَّلةٍ في إطار التصدير. | N140: Operations/unit_perf.php:1; Operations/monthly_close.php:1; Operations/unbilled.php:1; includes/u13_screen_kit.php:317-319; includes/excel_ui.php:45-61; app/Services/Excel/EntityDefinition.php:109-114 | P140: ١) افتح Operations/unit_perf.php. ٢) ابحث عن زرِّ تصديرٍ أو استيرادٍ أو «إظهار كل الأعمدة» أو منتقي منظر ⇒ لا شيء. ٣) قارن بـ Suppliers/suppliers.php حيث يظهر زرُّ التصدير. | Q140: حوّل جداولَ الوحدة إلى `includes/u13_screen_kit.php` (يعطي المناظرَ وزرَّ إظهار الكل بالنص الموحَّد)، وسجّل كياناتِ scr_unit_perf · scr_monthly_close · scr_unbilled في `app/Services/Excel/` وأضِف `ems_excel_header_actions()` إلى رؤوس الشاشات. | R140: فريق الواجهة — وحدة التشغيل | S140: لا | T140: نعم | U140: كلُّ جدولٍ تشغيليٍّ يتجاوز 20 عمودًا يعرض منتقيَ منظرٍ وزرَّ «إظهار كل الأعمدة» بالنص الموحَّد وزرَّ تصديرٍ يحترم الفلاترَ المفعَّلة. | V140: مفتوح | W140: مؤكَّدة | X140: صفرُ ملفٍّ في Operations/ يستدعي ems_excel_header_actions (الـ25 شاشةً ذاتُ التصدير في Clients/Contracts/Employees/Equipments/… فقط) وصفرُ استعمالٍ لـu13_screen_kit في Operations، فلا منتقيَ منظرٍ ولا زرَّ «إظهار كل الأعمدة» رغم تجاوز الجداولِ 20 عمودًا (ux_readable.md:404). | Y140: P2 | Z140: نعم | AA140: نعم | AB140: 03_UX | AC140: فجوة تنفيذ (Implementation) | AD140: Decision Closed · Implementation Open
A141: INJ-0137 | B141: INJAZ-UX-01 | C141: ٥ · البحثُ والفلاتر — «شريطُ الفلاتر مطويٌّ بعدَّادٍ وتفريغٍ بضغطة» | D141: إدارة التشغيل | E141: التوقفات وتحديد المتحمل | F141: http://localhost/ems/Operations/stops_unattributed.php | G141: ثالثًا: اعتماد الوحدات | H141: «البحثُ داخلَ شريطِ أدواتِ الجدولِ لا بعيدًا عنه» و«شريطُ الفلاتر مطويٌّ افتراضيًّا يُظهر عددَ المفعَّلِ ويتيح تفريغَه بضغطة» و«صفرُ فلترٍ مفعَّلٍ لا يظهر عدَدُه». | I141: جدولُ التوقفات يحمل `data-no-dt` فيتخطاه مُهيِّئُ DataTables، فلا بحثَ ولا فرزَ ولا ترقيم؛ ولا فلترَ فترةٍ ولا موقعٍ ولا نوعِ تعطلٍ ولا حالة. والقائمةُ محدودةٌ بـ`LIMIT 100` صامتةٍ بلا إعلانٍ للمستخدم بأن هناك صفوفًا لم تُعرض. | J141: UX/UI Defect | K141: P2 | L141: شاشةٌ شرطُها المعلَن «صفرُ واقعةٍ بلا مسؤولٍ شرطُ إقفال اليوم» تعرض مئةَ صفٍّ فقط بلا بحثٍ ولا فلتر: إن تجاوزت التوقفاتُ المئةَ يُقفل اليومُ وفيه توقفاتٌ لم تُعرض أصلًا. وفلترُ الإدارة غيرُ موجودٍ في أيِّ شبكةٍ في النظام (صفرُ شبكةٍ من 371). | M141: جدولٌ مكتوبٌ يدويًّا مع تعطيلٍ صريحٍ لمهيِّئ الجداول، وغيابُ مكوّنِ شريطِ فلاترَ موحَّد (UI-03) في المستودع. | N141: Operations/stops_unattributed.php:31-35; Operations/stops_unattributed.php:60; assets/js/ui-unification.js:378-379; assets/js/ems-components.js:52-64 | P141: ١) افتح Operations/stops_unattributed.php في كيانٍ فيه أكثرُ من 100 توقفٍ غير مُسنَد. ٢) لاحظ غيابَ صندوق البحث والترقيم. ٣) لاحظ الشارةَ في الرأس تعرض عددَ المعروض لا عددَ الكل. | Q141: أزِل `data-no-dt` من `Operations/stops_unattributed.php:60` وفعّل المعالجةَ الخادمية عبر `includes/datatable_server.php`، وأضِف شريطَ فلاترٍ (فترة · موقع · نوع تعطل) باستعمال `EmsUI` مع عدّاد المفعَّل وزرِّ التفريغ، وأزِل الحدَّ الصلبَ 100 أو أعلِنه صراحةً. | R141: فريق الواجهة — وحدة التشغيل | S141: لا | T141: نعم | U141: الشاشةُ تعرض كلَّ التوقفات غير المُسنَدة مع بحثٍ وفرزٍ وترقيمٍ وشريطِ فلاترَ يُظهر عددَ المفعَّل ويُفرَّغ بضغطة. | V141: مفتوح | W141: مؤكَّدة | X141: الجدولُ يحمل data-no-dt (سطر 60) ومُهيِّئُ الجداول يتخطاه (ui-unification.js:379)، والاستعلامُ محدودٌ بـLIMIT 100 صامتة (الأسطر 31-34) بلا فلاترَ ولا بحث. | Y141: P2 | Z141: نعم | AA141: نعم | AB141: 03_UX | AC141: فجوة تنفيذ (Implementation) | AD141: Decision Closed · Implementation Open
A142: INJ-0138 | B142: INJAZ-UX-01 | C142: ٤-٥ · «لا يُعرض عنصرٌ لا يملكه المستخدمُ» — عناصرُ مساحة عملي | D142: إدارة التشغيل | E142: مساحتي الشخصية (داخل لوحة الإدارة) | F142: http://localhost/ems/Portal/my_tasks.php | G142: لوحة الإدارة | H142: «① مساحةُ عملي … محتواها: مهامي · طلباتي · موافقاتي · بلاغاتي · إنجازي · التنبيهات» ثابتةٌ حرفيًّا في كل الإدارات. | I142: مجموعةُ «مساحتي الشخصية» في سايدبار الدور 1 تعرض: مهامي · إنجازي · بوابتي · طلباتي · المراسلات — فتنقص «موافقاتي» و«بلاغاتي» و«التنبيهات» وتزيد «بوابتي» و«المراسلات»؛ والمحتوى يختلف من دورٍ لآخر لأنه من صفوف nav_items لا من ثابت. | J142: Wrong Sidebar Placement | K142: P2 | L142: مديرُ التشغيل لا يجد «موافقاتي» في مساحته الشخصية رغم أن دورَه أحدُ مستويات اعتماد الوحدات الأربعة؛ ولا يجد «التنبيهات» رغم وجود `Portal/notifications.php`. ويسقط حكمُ الثباتِ الحرفيِّ بين الإدارات. | M142: بناءُ منطقة مساحة عملي من بياناتٍ لكلِّ دورٍ على حدة بدل ثابتٍ في المصيّر، مع غياب فاحصٍ يقارن العناصرَ الستةَ المنصوصة. | N142: database/schema/seed_reference.sql (nav_items 5945-5949, group_id=3314)؛ includes/unified_nav.php:205-240 | P142: ١) ادخل بدور 1 وافتح المجموعةَ الأولى ⇒ خمسةُ عناصرَ لا ستة. ٢) ابحث عن «موافقاتي» و«التنبيهات» ⇒ غيرُ موجودتين رغم وجود ملفّيهما. | Q142: اطبع منطقةَ مساحة عملي من ثابتٍ في `includes/unified_nav.php` بالعناصر الستة وترتيبها وأيقوناتها، واحذف صفوفَ nav_items الشخصيةَ المكرَّرةَ من البذرة. | R142: فريق الواجهة — وحدة التنقل | S142: لا | T142: نعم | U142: العناصرُ الستةُ تظهر بالترتيب والأسماء نفسِها في سايدبار الأدوار 1 و2 و9 و12، ولا عنصرَ سابعٌ فيها. | V142: مفتوح | W142: مؤكَّدة | X142: صفوفُ nav_items للمجموعة 3314 «مساحتي الشخصية» للدور 1 هي حرفيًّا: مهامي·إنجازي·بوابتي·طلباتي·المراسلات — بلا موافقاتي وبلاغاتي والتنبيهات المنصوصةِ في ux_readable.md:55/84. | Y142: P2 | Z142: نعم | AA142: نعم | AB142: 03_UX | AC142: فجوة تنفيذ (Implementation) | AD142: Decision Closed · Implementation Open
A143: INJ-0139 | B143: M-14 | C143: TABLE 53 · سجلُّ التدقيق — أفعالُ التشغيل | D143: إدارة التشغيل | E143: طلب تبديل / التوقفات / تقويم الأسطول | F143: http://localhost/ems/Operations/swap_request.php | G143: غير موجود في السايدبار | H143: كلُّ معالجٍ يغيّر الحالةَ يكتب سجلَّ تدقيقٍ بالفاعل والوقت والقيمة قبل وبعد. | I143: ثلاثةُ معالجاتٍ في وحدة التشغيل تكتب في القاعدة بلا أيِّ سجلِّ تدقيقٍ على أيِّ مسار: `Operations/swap_request.php` (تغطياتُ إحلالٍ تقود الاستحقاق) و`Operations/stops_unattributed.php` (إسنادُ التبعة) و`Operations/fleet_calendar.php` (حجزُ الأسطول). وكلُّها كذلك بلا نشرِ حدث. | J143: Missing Evidence | K143: P2 | L143: لا يمكن معرفةُ من أنشأ تغطيةَ إحلالٍ أو من غيّر حجزًا في تقويم الأسطول ولا متى ولا ما القيمةُ السابقة — وهي بياناتٌ ذاتُ أثرٍ على الفوترة والالتزام التعاقدي. | M143: معالجاتٌ كُتبت مباشرةً بـ mysqli بلا مرورٍ بالبوابة `TenantDb` ولا باستدعاء `ems_audit_change()`. | N143: Operations/swap_request.php:47-56; :77; Operations/stops_unattributed.php:22-27; :44; Operations/fleet_calendar.php:219 | P143: ١) أنشئ طلبَ تبديلٍ من Operations/swap_request.php. ٢) ابحث في سجل التدقيق عن صفٍّ لهذا الفعل ⇒ لا يوجد. | Q143: مرّر كتاباتِ الملفات الثلاثة عبر `ems_tenant_db()` واستدعِ `ems_audit_change()` بعد كلِّ كتابةٍ ناجحة، وانشر الحدثَ المقابل (`operations.swap.created` · `operations.stop.attributed` · `fleet.reservation.changed`). | R143: فريق الباك-إند — وحدة التشغيل | S143: لا | T143: لا | U143: كلُّ فعلٍ كاتبٍ في وحدة التشغيل ينتج صفَّ تدقيقٍ واحدًا يحمل الجدولَ والمعرّفَ والقيمةَ قبل وبعد. | V143: مفتوح | W143: مؤكَّدة | X143: الثلاثةُ تكتب في القاعدة بلا `ems_audit_change` ولا نشرِ حدث، والكتابةُ تسبق `include '../insidebar.php'` (swap_request:77 · stops_unattributed:44 · fleet_calendar:219). | Y143: P2 | Z143: نعم | AA143: نعم | AB143: 06_M14 | AC143: فجوة دليل (Evidence) | AD143: Implementation Closed · Evidence Open
A144: INJ-0140 | B144: M-14 | C144: GOVX-0975 · مفتاحُ منعِ التكرار — تكرارُ الأثر بإعادة الإرسال | D144: إدارة التشغيل | E144: طلب تبديل | F144: http://localhost/ems/Operations/swap_request.php | G144: غير موجود في السايدبار | H144: «مفتاحُ منع التكرار في كل أثر» — وإعادةُ الإرسال لا تُنتج أثرًا ثانيًا. | I144: معالجُ `Operations/swap_request.php:48` يُدرج صفَّ تغطيةِ إحلالٍ في كل POST بلا مفتاحِ عطالةٍ ولا فحصِ تكرار؛ وكذلك شاشاتُ CMP-03 التشغيليةُ الإحدى عشرةَ (`cmp03_store_insert` بلا مفتاح دمج). فتحديثُ الصفحة بعد الحفظ يضاعف الصف. | J144: Data Mismatch | K144: P2 | L144: تغطياتُ إحلالٍ مكرَّرةٌ تضاعف الاستحقاقَ المحسوبَ للمورد؛ وصفوفُ إنتاجٍ وأداءٍ مكرَّرةٌ تضاعف الأرقامَ في التقارير الشهرية بلا أن يلاحظها أحد. | M144: غيابُ طبقةِ عطالةٍ على مستوى الطلب: لا رمزَ نموذجٍ يُستهلك، ولا قيدَ فريدٍ على مفاتيح العمل، و`app/Core/ProcessedOperations.php` القائمُ بلا مستدعٍ إنتاجي. | N144: Operations/swap_request.php:48-53; includes/cmp03_local_store.php:31; :55-61 | P144: ١) أنشئ طلبَ تبديلٍ واضغط حفظ. ٢) اضغط تحديثَ الصفحة وأكّد إعادةَ الإرسال ⇒ صفٌّ ثانٍ بالبيانات نفسِها. | Q144: أضِف في `Operations/swap_request.php` مفتاحَ عطالةٍ مركّبًا (contract_id + out_ref + in_ref + effective_from) بقيدٍ فريدٍ في القاعدة، وفي `includes/cmp03_local_store.php::cmp03_store_insert()` احسب هاشَ الحمولة واحفظه في عمود `idem_hash` بقيدٍ فريدٍ لكل شاشةٍ وكيان. | R144: فريق الباك-إند — وحدة التشغيل | S144: لا | T144: لا | U144: إعادةُ إرسال الفورم نفسِه لا تنشئ صفًّا ثانيًا وتُعيد رسالةً تشير إلى الصف القائم. | V144: مفتوح | W144: مؤكَّدة | X144: الإدراجُ في substitute_coverages يقع في كل POST بلا مفتاحِ عطالةٍ ولا قيدٍ فريدٍ ولا POST-Redirect-GET، وcmp03_store_insert كذلك بلا هاشِ حمولة. | Y144: P2 | Z144: نعم | AA144: نعم | AB144: 06_M14 | AC144: فجوة تنفيذ (Implementation) | AD144: Decision Closed · Implementation Open
A145: INJ-0141 | B145: M-14 | C145: TABLE 46 · التصديرُ وسجلُّه — وحدةُ التشغيل | D145: إدارة التشغيل | E145: جداول إدارة التشغيل (التصدير) | F145: http://localhost/ems/Operations/unbilled.php | G145: خامسًا: إقفال الفترة | H145: «صلاحيتان منفصلتان لا واحدة» للتصدير والعرض، وسجلُّ تصديرٍ بتسعة بنودٍ إلزامية لكلِّ عمليةِ إخراج. | I145: التغطيةُ الجزئيةُ قائمة: excel.php:82-96 يقيّد اطّلاعَ الحقول الحساسة باسم المصدِّر قبل بثِّ الملف (sensitive_read_log)؛ ونسبةُ العيب إلى شاشات Operations افتراضيةٌ لأنها بلا تصديرٍ أصلًا. — [مُصحَّح بعد التحقق] الصياغة الأولى: لا سجلَّ تصديرٍ عامٌّ في المخطط (الموجودُ `risk_export_log` لوحدة المخاطر فقط)، ولا مفتاحَ صلاحيةِ تصديرٍ منفصل — و`ExcelService::authorize()` يفحص `can_view`. ووحدةُ التشغيل بلا تصديرٍ أصلًا، فحين يُ | J145: Export/Import Gap | K145: P2 | L145: عند إتاحة تصدير «الأعمال غير المفوترة» أو «الأداء الشهري» — وهي بياناتٌ تجاريةٌ حساسة — لن يُعرف من أخرجها ولا متى ولا بأيِّ فلترٍ ولا كم صفًّا، ولن تُفصل صلاحيةُ الإخراج عن صلاحية العرض. | M145: إطارُ تصديرٍ بُني بصلاحيةٍ واحدةٍ وبلا سجلٍّ، وسجلُّ التصدير نُفِّذ لوحدةٍ واحدةٍ فقط دون تعميم. | N145: app/Services/Excel/ExcelService.php:55-70; excel.php:76-99; database/schema/schema.sql:8838; app/Services/Risk/RiskService.php:975 | P145: ١) ابحث في المخطط عن جدولٍ باسم export_log ⇒ لا يوجد إلا risk_export_log. ٢) صدّر من أيِّ شاشةٍ فيها تصدير ⇒ لا صفَّ سجلٍّ يُكتب. | Q145: أنشئ جدول `export_log` بالبنود التسعة (المستخدم · الوقت · الكيان · الشاشة · المنظر · الفلاتر · عددُ الصفوف · الأعمدةُ المستبعدة · رقمُ العملية) واكتبه من `excel.php` قبل بثِّ الملف، وأضِف مفتاحَ صلاحيةِ تصديرٍ مستقلًّا يفحصه `ExcelService::authorize()`. | R145: فريق الباك-إند — وحدة الأمن | S145: لا | T145: نعم | U145: كلُّ تصديرٍ من أيِّ شاشةٍ يكتب صفًّا في export_log بالبنود التسعة، ومن لا يملك صلاحيةَ التصدير يُمنع ولو ملك العرض. | V145: مفتوح | W145: مؤكَّدة | X145: M-14 (m14_readable.md:370,432) يوجب «صلاحيةَ التصديرِ + سجلَّ تصديرٍ بتسعةِ بنودٍ»، وExcelService::authorize يفحص can_view للتصدير (سطر 64-65) ولا جدولَ تصديرٍ عامًّا في المخطط عدا risk_export_log (schema.sql:8838). | Y145: P2 | Z145: نعم | AA145: نعم | AB145: 06_M14 | AC145: فجوة تنفيذ (Implementation) | AD145: Decision Closed · Implementation Open
A146: INJ-0142 | B146: INJAZ-FRD-01 | C146: INJAZ-FRD-01 §١١-٢ · الدورةُ المستندية — العرضُ ثم العقد | D146: المبيعات والعقود | E146: عروض الأسعار للعملاء | F146: http://localhost/ems/Clients/quotations.php | G146: ثانيًا: العرض والتسعير | H146: الدورةُ المستندية: «عرضُ سعرٍ ← عقدٌ نافذ» — ولكلِّ مرحلةٍ مستندٌ يُنتَج، «ولا مرحلةَ بلا مخرَج»، والمستندُ التالي يرجع إلى سابقه (المرجعُ الأب). | I146: لا فعلَ تحويلٍ من العرض إلى العقد: `Clients/quotations.php` تحتوي حالةً نصيةً «مقبول» تُعدّ في إحصائية (`$stat_accepted`) ولا تُنشئ عقدًا ولا تربط به. وجدولُ `contracts` لا يملك عمودَ `quotation_id` ولا `opportunity_id` أصلًا (الموجودُ في `quotations` و`tenders` فقط) — فلا مرجعَ أبٍ بين العرض والعقد. | J146: Wrong Workflow | K146: P2 | L146: ينقطع خيطُ التتبع التجاري: لا يمكن معرفةُ من أيِّ عرضٍ وُلد العقد، ولا قياسُ معدل التحويل الحقيقي، ولا التحقق من أن سعرَ العقد هو السعرُ المعروض. ويُعاد إدخالُ بيانات العرض يدويًّا في العقد فتتباعد الأرقام. | M146: نمذجةُ قبولِ العرض قيمةَ حالةٍ نصيةٍ بدل فعلٍ يولّد المستندَ التالي ويربطه بالمرجع الأب. | N146: Clients/quotations.php:334-335; database/schema/schema.sql:1818-1875 | P146: ١) أنشئ عرضَ سعرٍ واجعل حالتَه «مقبول». ٢) ابحث عن زرِّ «تحويل إلى عقد» ⇒ لا يوجد. ٣) افتح Contracts/contracts.php وابحث عن حقلِ «العرض المرجعي» ⇒ لا وجود له. | Q146: أضِف عمودَي `quotation_id` و`opportunity_id` إلى جدول `contracts` بهجرةٍ جديدة، وأضِف في `Clients/quotations.php` فعلَ «تحويل إلى عقد» محروسًا بـcan_add ينسخ البنودَ والأسعارَ وينشئ العقدَ بحالة «مسودة» مع المرجع الأب، وينشر `quotation.accepted`. | R146: فريق الباك-إند — وحدة المبيعات | S146: نعم | T146: نعم | U146: قبولُ عرضٍ يولّد عقدًا مسودةً يحمل quotation_id، وشاشةُ العقد تعرض رابطًا للعرض الأب، وبنودُ العقد تطابق بنودَ العرض. | V146: مفتوح | W146: مؤكَّدة | X146: جدولُ contracts لا يحوي quotation_id ولا opportunity_id (التعريفُ في schema.sql:1818-1875)، ولا فعلَ تحويلٍ من العرض إلى العقد في Clients/quotations.php ولا في مجلد Contracts — والحالةُ «مقبول» إحصائيةٌ فقط. | Y146: P1 | Z146: نعم | AA146: نعم | AB146: 02_FRD | AC146: فجوة تنفيذ (Implementation) | AD146: Decision Closed · Implementation Open
A147: INJ-0143 | B147: INJAZ-FRD-01 | C147: INJAZ-FRD-01 §١١-٣ · المرحلة ٣ — مراجعةُ العقد وملاحظاتُها | D147: المبيعات والعقود | E147: مراجعة العقود وملاحظاتها | F147: http://localhost/ems/Portal/contract_review.php | G147: ثالثًا: مراجعة العقد وتوقيعه | H147: مراجعةُ العقد مرحلةٌ تُنتج ملاحظاتٍ ملزمةً تحجب التوقيعَ (BR-CEO-02: «الملاحظةُ الحرجةُ المفتوحة تحجب بنيويًّا»)، ولها معتمِدٌ وحالةٌ ودورةُ إغلاق. | I147: m00_review_block تفحص الحقولَ المنظَّمة في scr_contract_review؛ ومطابقةُ الكلمات («حرجة»/«مفتوحة») تقع في فرعٍ احتياطيٍّ واحدٍ على حقل legal_review في ceo_contracts.php:154-155. — [مُصحَّح بعد التحقق] الصياغة الأولى: `Portal/contract_review.php` فورمُ إدخالٍ عامٌّ (CMP-03) بـ22 عمودًا يكتب صفًّا نصيًّا عبر `cmp03_store_insert()`، بلا فحصِ صلاحيةِ شاشةٍ خاصٍّ به، وبلا فعلِ إغلاقِ ملاحظةٍ ولا حالةٍ محكومة؛ والحجبُ ف | J147: Wrong Workflow | K147: P2 | L147: أقوى حاجزٍ حوكميٍّ قبل التوقيع مبنيٌّ على مطابقةِ نصٍّ حرٍّ: كتابةُ «حرجه» أو «حرجة — تمت المعالجة» تُغيّر النتيجةَ عشوائيًّا؛ ولا يمكن إغلاقُ ملاحظةٍ بمستندٍ لأن الشاشةَ لا تملك فعلَ تعديلٍ أصلًا فيُضطر المراجعُ لإضافة صفٍّ جديدٍ يناقض القديم. | M147: تنفيذُ شاشةٍ حاكمةٍ ضمن دفعة فورمات CMP-03 (إدراجٌ فقط) وبناءُ الحارس على تفتيشٍ نصيٍّ بدل حالةٍ منظَّمة. | N147: Portal/contract_review.php:88; includes/m00_exec_helpers.php:29-47; Portal/ceo_contracts.php:91-97; :152-160 | P147: ١) أضِف ملاحظةً في Portal/contract_review.php بنص «حرجة مفتوحة» على عقدٍ ما. ٢) حاول توقيعَه من Portal/ceo_contracts.php ⇒ يُحجب. ٣) أضِف صفًّا ثانيًا يقول «عولجت» ⇒ الحجبُ باقٍ ولا سبيلَ لإغلاق الأول. | Q147: حوّل ملاحظاتِ المراجعة إلى جدولٍ منظَّمٍ (`contract_review_notes`) بحقول: العقد · الخطورة (enum) · الحالة (مفتوحة/مغلقة) · مستندُ المعالجة · المغلِق · وقتُ الإغلاق؛ وأضِف فعلَ «إغلاق ملاحظة» محروسًا، واجعل `m00_review_block()` تفحص الحالةَ لا النص. | R147: فريق الباك-إند — وحدة العقود | S147: نعم | T147: نعم | U147: ملاحظةٌ حرجةٌ تحجب التوقيعَ حتى تُغلق بمستندٍ ومعتمِد؛ ولا يعتمد الحجبُ على أيِّ مطابقةٍ نصية. | V147: مفتوح | W147: مرجَّحة | X147: الشاشةُ فعلًا مخزنُ CMP-03 بلا فعلِ إغلاقٍ محكوم، لكنَّ توصيفَ m00_review_block خاطئ: الدالةُ تقرأ حقولًا منظَّمة (يحجب الاعتماد؟ · تاريخ الإقفال · الحالة) لا كلمتَي «حرجة» و«مفتوحة». | Y147: P1 | Z147: نعم | AA147: نعم | AB147: 02_FRD | AC147: فجوة تنفيذ (Implementation) | AD147: Decision Closed · Implementation Open
A148: INJ-0144 | B148: INJAZ-UX-01 | C148: VA-07 / AC-U7 · «صفرُ جدولٍ يبلغ صفرَ أعمدة» — UI-DEF-04 | D148: المبيعات والعقود | E148: عقود العملاء | F148: http://localhost/ems/Contracts/contracts.php | G148: ثالثًا: مراجعة العقد وتوقيعه | H148: «◆ VA-07 / AC-U7: صفرُ جدولٍ يبلغ صفرَ أعمدة — محاولةُ إخفاءِ الكلِّ تُرفض بحدٍّ أدنى»، والعيبُ الحيُّ UI-DEF-04 يُغلق بحارسٍ في UI-06. | I148: الشاشةُ تُهيّئ `EmsColumnGroups` بوضع `mode: 'classic'` (سطر 1820)، وهذا الوضعُ يخفي الخلايا بصنف CSS ولا يمسّ DataTables — فحدثُ `column-visibility.dt` لا يقع والحارسُ في `assets/js/ems-components.js:202-212` لا يُستدعى. و`setAll(false)` يخفي كلَّ المجموعات ثم `saveState()` يحفظ الحالةَ في localStorage فتبقى بعد إعادة التحميل. | J148: UX/UI Defect | K148: P2 | L148: نقرةٌ واحدةٌ على زرِّ «الكل» تُفرغ شبكةَ العقود من كل أعمدتها بشكلٍ دائم، ولا يعرف المستخدمُ سببَ الجدول الفارغ ولا كيف يعود — على الشاشة الأمِّ لإدارة المبيعات والعقود. ويتكرر العيبُ حرفيًّا في `Suppliers/supplierscontracts.php:1239` و`Employees/employee_contracts.php:1716`. | M148: آليتا أعمدةٍ متوازيتان: الحارسُ مبنيٌّ على أحداث DataTables بينما الشاشةُ تستعمل الوضعَ الكلاسيكيَّ القائمَ على CSS. | N148: Contracts/contracts.php:1820; assets/js/column-groups.js:141-147; :197-204; assets/js/ems-components.js:202-212 | P148: ١) افتح Contracts/contracts.php. ٢) اضغط زرَّ «الكل» مرتين (إظهار ثم إخفاء) ⇒ يختفي كلُّ محتوى الجدول. ٣) حدّث الصفحة ⇒ الجدولُ ما زال فارغًا (الحالةُ محفوظةٌ في localStorage). | Q148: في `assets/js/column-groups.js::setAll()` (سطر 197) امنع النزولَ تحت حدٍّ أدنى (مجموعةٌ واحدةٌ على الأقل) في الوضعين، وأظهِر رسالةَ سببٍ؛ أو حوّل `Contracts/contracts.php:1820` و`Suppliers/supplierscontracts.php:1239` إلى `mode:'datatable'` ليعمل الحارسُ القائم. | R148: فريق الواجهة — النظام التصميمي | S148: لا | T148: نعم | U148: محاولةُ إخفاء كلِّ المجموعات في شبكة العقود تُرفض ببقاء مجموعةٍ واحدةٍ على الأقل ورسالةٍ تُبيّن السبب. | V148: مفتوح | W148: مؤكَّدة | X148: الوضعُ classic يخفي بصنفِ CSS (`group-hidden`) ولا يمسّ DataTables، فحدثُ `column-visibility.dt` لا يقع وحارسُ صفرِ الأعمدة لا يُستدعى؛ و`setAll(false)` يحفظ الحالةَ في localStorage. | Y148: P2 | Z148: نعم | AA148: نعم | AB148: 03_UX | AC148: فجوة تنفيذ (Implementation) | AD148: Decision Closed · Implementation Open
A149: INJ-0145 | B149: INJAZ-UX-01 | C149: ٥ · البحثُ · و٧-٣ خياراتُ التصديرِ الثمانية | D149: المبيعات والعقود | E149: المستخلصات والذمم والتغطية | F149: http://localhost/ems/Contracts/claims.php | G149: سادسًا: المستخلص والمطالبة | H149: «تصديرٌ يُخرج العرضَ المختارَ أو جميعَ الأعمدةِ المسموحةِ بحسب الصلاحية» و«نتائجُ البحثِ والفلاترِ الحالية — كلُّ النتائجِ لا الصفحةَ الحالية». | I149: الجدولُ الوحيدُ ذو التصدير هو Contracts/contracts.php؛ tax_invoices.php بلا تصدير. — [مُصحَّح بعد التحقق] الصياغة الأولى: من واحدٍ وعشرين جدولًا في وحدة العقود، جدولٌ واحدٌ فقط (`Contracts/contracts.php`) فيه تصديرُ الإطار الموحَّد وواحدٌ آخر (`tax_invoices.php`) — و20 بلا تصدير، ومنها المستخلصاتُ والذممُ والتغطيةُ والجز | J149: Export/Import Gap | K149: P2 | L149: لا يمكن إخراجُ كشفِ مستخلصاتٍ لفترةٍ أو لعميلٍ إلى المالية أو للعميل نفسِه؛ وحين يوجد التصديرُ يُخرج كلَّ صفوف الكيان متجاهلًا ما فلتره المستخدمُ على الشاشة — فيُصدَّر ما لم يُطلَب. | M149: إطارُ تصديرٍ يعمل على مستوى الكيان لا على مستوى الاستعلام المعروض، وكياناتُ وحدة العقود غيرُ مسجَّلةٍ فيه. | N149: Contracts/claims.php:1; Contracts/collections.php:1; Contracts/contract_coverage.php:1; excel.php:70-71; app/Services/Excel/ExcelService.php:147; includes/excel_ui.php:55-61 | P149: ١) افتح Contracts/claims.php واختر عقدًا وفترةً. ٢) ابحث عن زرِّ تصدير ⇒ لا يوجد. ٣) افتح Contracts/contracts.php وفلتِر بحالةٍ ثم صدّر ⇒ الملفُّ يحوي كلَّ العقود لا المفلترة. | Q149: سجّل كياناتِ claims · claim_lines · collections · contract_coverage في `app/Services/Excel/`، ومرِّر معاملاتِ الفلترة والمنظر من `includes/excel_ui.php:55-61` إلى `excel.php` ثم إلى `ExcelService::export()` لتُبنى بها جملةُ WHERE. | R149: فريق الباك-إند — وحدة العقود | S149: لا | T149: نعم | U149: تصديرُ شبكةٍ مفلترةٍ يُخرج الصفوفَ المطابقةَ للفلاتر فقط والأعمدةَ الظاهرةَ في المنظر الحالي. | V149: مفتوح | W149: مؤكَّدة | X149: تحقّقتُ: Contracts/contracts.php وحدَها تُضمّن excel_ui في المجلد (وtax_invoices.php بلا تصدير أصلًا، فالفجوةُ أوسعُ مما ذُكر)، وExcelService::export يبني WHERE 1=1 بنطاق الشركة فقط (السطر 147) وexcel.php لا يقرأ إلا entity وaction (70-71). | Y149: P2 | Z149: نعم | AA149: نعم | AB149: 03_UX | AC149: فجوة تنفيذ (Implementation) | AD149: Decision Closed · Implementation Open
... A174: INJ-0170 | B174: INJAZ-DELIVERY-01 | C174: شرط-٥ · وحداتُ الصلاحياتِ مسجَّلةٌ كلُّها — «٢٠٣ من ٢٠٣ أو استثناءٌ معلَن» | D174: إدارة الأسطول | E174: شاشات مجلد المعدات غير المسجَّلة | F174: http://localhost/ems/Equipments/equipment_profile.php | G174: غير موجود في السايدبار | H174: شرطُ الإطلاق الخامس: «وحداتُ الصلاحياتِ مسجَّلةٌ كلُّها — الشاهد: ٢٠٣ من ٢٠٣ أو استثناءٌ معلَن»، ولا شاشةَ تُفتح خارج مصفوفة الظهور. | I174: منها أربعُ نقاطِ get_* ومعالجٌ واحد، والباقي شاشاتُ عرض. — [مُصحَّح بعد التحقق] الصياغة الأولى: ١٣ ملفًّا من ٢٤ في مجلد Equipments لا تظهر في سايدبار أي دور، منها شاشاتُ عرضٍ كاملةٌ يمكن فتحُها بالرابط: equipment_profile.php (١٢٤٢ سطرًا) و fleet_failures.php (٤٥١ سطرًا وفيه تصديرُ xls) و equipme | J174: Missing Evidence | K174: P2 | L174: لا يمكن إثباتُ اجتيازِ شرطِ الإطلاق الخامس: ثلثُ شاشات الإدارة غيرُ مرئيٍّ في مصفوفة الظهور، فلا يُعرف من يملكها ولا بأي زاويةٍ يراها ولا محجوبٌ عنه ماذا. | M174: أُضيفت شاشاتٌ ومعالجاتٌ خارج بذرة nav_items ولم يُسجَّل لكلٍّ منها استثناءٌ معلَن. | N174: Equipments/equipment_profile.php:1; Equipments/fleet_failures.php:1; Equipments/equipments_drivers.php:1; Equipments/equipments_fleet.php:1; Equipments/approve_card.php:1 | P174: ١) اجرد nav_items لكل الأدوار على مسارات Equipments/*. ٢) قارنها بقائمة الملفات في المجلد. ٣) ١٣ ملفًّا بلا ظهور. | Q174: سجّل كلَّ شاشةِ عرضٍ من الثلاثةَ عشرَ في modules و nav_items بزاويتها ودورها، أو أعلنها استثناءً في سجل الاستثناءات مع سببٍ ومدة، أو ألغِ الملفَّ إن كان مكررًا. | R174: مكتب الهندسة — وحدة التنقل | S174: نعم | T174: لا | U174: تقريرٌ آليٌّ: كلُّ ملفِّ شاشةٍ في Equipments/ إمّا له صفُّ nav_items واحدٌ على الأقل، وإمّا مُدرجٌ في سجل الاستثناءات بسببٍ ومدة. | V174: مفتوح | W174: مؤكَّدة | X174: ١٣ ملفًّا من ٢٤ في Equipments/ بلا صفِّ nav_items نشط — والقائمةُ تطابق ما ذُكر (equipment_profile · fleet_failures · equipments_drivers · equipments_fleet · approve_card · equipment_child_save …)، وequipment_profile.php وfleet_failures.php غيرُ مسجَّلين في modules أصلًا. | Y174: P2 | Z174: نعم | AA174: نعم | AB174: 05_DELIVERY | AC174: فجوة دليل (Evidence) | AD174: Implementation Closed · Evidence Open
A175: INJ-0171 | B175: M-14 | C175: GOV-0358-أ · GOV-0358-ب · ▐ ١١-١٢ الصلاحياتُ والنطاق | D175: إدارة الأسطول | E175: حوكمة إدارة الأسطول (gov_dept_flt.php) | G175: غير موجود في السايدبار | H175: «يُضاف لكل إدارةٍ مكوّنٌ نطاقيٌّ واحدٌ باسم «حوكمة إدارتي» · وهو منظرٌ على مصادرِ الحوكمةِ المركزيةِ لا نظامُ حوكمةٍ مستقلٌّ لكل إدارة» — وتعلن INJAZ-FRD-01 §٨-٤ شاشةَ gov_dept_flt.php بـ١٥ عمودًا وفعلين. | I175: لا وجودَ لملف gov_dept_flt.php. الموجودُ فعلًا ثلاثُ نسخٍ فقط: Finance/gov_dept_fin.php و Governance/gov_dept_gov.php و Risk/gov_dept_rsk.php. ولا رابطَ حوكمةٍ في سايدبار دور ٣ إطلاقًا. | J175: Missing Screen | K175: P2 | L175: مديرُ الأسطول لا يرى فريقَه ولا تفويضاتِه ولا تعارضاتِ الواجبات في حسابات إدارته، فلا يستطيع أداءَ واجب التصديق gov.flt.attest المنصوصِ عليه في M-14 §١٠-٢. | M175: مكوّنُ «حوكمة إدارتي» نُفِّذ لثلاث إداراتٍ فقط ولم يُعمَّم بمنظرٍ نطاقيٍّ واحدٍ يتغير عنوانُه ونطاقُه بحسب الإدارة. | N175: Finance/gov_dept_fin.php:1; Governance/gov_dept_gov.php:1; Risk/gov_dept_rsk.php:1 | P175: ١) ادخل بدور ٣. ٢) ابحث في السايدبار عن «حوكمة إدارتي/حوكمة الأسطول» → غير موجودة. ٣) جرّب http://localhost/ems/Governance/gov_dept_flt.php → 404. | Q175: عمّم Finance/gov_dept_fin.php إلى مكوّنٍ واحدٍ Governance/gov_dept.php يقرأ الإدارةَ من دور الجلسة، وأنشئ صفَّ nav_items لدور ٣ يشير إليه بعنوان «حوكمة إدارة الأسطول». | R175: فريق الحوكمة — وحدة الصلاحيات | S175: لا | T175: نعم | U175: بدور ٣ يفتح رابطُ «حوكمة إدارة الأسطول» شاشةً تعرض أعضاءَ الإدارة وأدوارَهم وتفويضاتِهم قراءةً فقط، وصفرَ سجلٍّ من إدارةٍ أخرى. | V175: مفتوح | W175: مؤكَّدة | X175: لا وجودَ لـgov_dept_flt.php؛ الموجودُ ثلاثةٌ فقط (Finance/gov_dept_fin · Governance/gov_dept_gov · Risk/gov_dept_rsk) بينما FRD تُعلن الشاشةَ لكل إدارةٍ (frd_readable.md:611)، ولا صفَّ nav_items للدور 3. لكن الإصلاحَ المقترحَ يتجاهل أن المكوّنَ النطاقيَّ الواحدَ قائمٌ سلفًا في includes/dept_gov_space.php — المطلوبُ غلافٌ رقيقٌ لا تعميمُ شاشةِ المالية. | Y175: P2 | Z175: لا — يحتاج مراجعة | AA175: نعم | AB175: 06_M14 | AC175: فجوة تنفيذ (Implementation) | AD175: Decision Closed · Implementation Open
A176: INJ-0172 | B176: M-14 | C176: SCN-129-أ · SCN-129-ب · ▐ ١١-٣ مصفوفةُ الظهورِ حسبَ الإدارة | D176: إدارة الأسطول | E176: اعتماد كرت المعدة | F176: http://localhost/ems/Equipments/approve_card.php | G176: - | H176: «يجب أن تُعرض شاشةُ «صندوق ما ينتظر اعتمادي» لـإدارة الأسطول … ومحجوبٍ عنه: اعتمادُ ما أنشأتُه» — ومصفوفةُ الواجبات المتعارضة (CORE-01 ٨-٢ الزوج ١): «إنشاءُ المستند × اعتمادُ المستند نفسِه». | I176: أثرُ card_state عرضيٌّ/حوكميٌّ بنصِّ ترويسة الملف: لا مسارَ تشغيليًّا أو ماليًّا يتوقف عليه (يُقرأ في equipments.php وequipment_profile.php شارةً فقط) — فالخطورةُ دون المدَّعى. — [مُصحَّح بعد التحقق] الصياغة الأولى: معالجُ اعتماد الكرت لا يقارن منشئَ المعدة بمن يعتمدها ولا يستدعي ems_no_self_approval الموجودةَ في includes/self_approval_guard.php؛ الفحصُ الوحيدُ هو can_edit على وحدة equipments_fleet. فمن أدخل المع | J176: Permission Gap | K176: P2 | L176: اعتمادُ الذات على المستند المؤسِّس للأصل: تُدخَل معدةٌ ببياناتِ ملكيةٍ وتكلفةٍ ثم يشهد مُدخِلُها بصحتها، فيسقط الفصلُ البنيويُّ عند نقطة دخول الأصل إلى الدفاتر. | M176: الحارسُ العامُّ ems_no_self_approval وُضع في includes/self_approval_guard.php وعُمِّم نصًّا («دالةٌ واحدةٌ يستدعيها كلُّ مسار اعتماد») لكنه لم يُستدعَ إلا في أربعة ملفات، وليس هذا منها. | N176: Equipments/approve_card.php:29; Equipments/approve_card.php:46-51; includes/self_approval_guard.php:23-38 | P176: ١) بحسابٍ واحدٍ له can_add و can_edit على المعدات: أضِف معدةً جديدة. ٢) من صفِّها اضغط «اعتماد الكرت». ٣) لاحظ نجاحَ الاعتماد وأن card_approved_by = منشئُ الصف نفسُه. | Q176: في Equipments/approve_card.php قبل السطر 47: اقرأ created_by للمعدة عبر البوابة، ثم استدعِ ems_no_self_approval($conn,$created_by,$user_id,'كرت معدة #'.$equipment_id,$company_id) وأعِد 403 عند رجوعِ مصفوفة. | R176: فريق الحوكمة — وحدة الصلاحيات | S176: نعم | T176: لا | U176: المستخدمُ الذي أنشأ صفَّ المعدة يتلقى 403 عند اعتماد كرتها مع سطرٍ في سجل التدقيق، ومستخدمٌ آخرُ يعتمد بنجاح. | V176: مفتوح | W176: مؤكَّدة | X176: Equipments/approve_card.php لا يقرأ equipments.created_by ولا يستدعي ems_no_self_approval (includes/self_approval_guard.php:23)، وحارسُه الوحيدُ can_edit على equipments_fleet (سطر 29) — فمُدخِلُ المعدة يعتمد كرتَها. | Y176: P1 | Z176: نعم | AA176: نعم | AB176: 06_M14 | AC176: فجوة تنفيذ (Implementation) | AD176: Decision Closed · Implementation Open
A177: INJ-0173 | B177: M-14 | C177: PR-05 · الحارسُ في الخادم — «ويُسجَّل الرفضُ بالمستخدم والوقت والرمز» | D177: إدارة الأسطول | E177: اعتماد كرت المعدة | F177: http://localhost/ems/Equipments/approve_card.php | G177: - | H177: الفعلُ ذو الأثر يحمل حارسَ رمزٍ مضادًّا للتزوير (CSRF) وسطرًا في سجل التدقيق بقيمِ قبل/بعد. | I177: المعالجُ يقبل POST بلا أي تحقّقٍ من رمز الحماية (لا verify_csrf_token ولا fin_verify_action_token)، ولا يكتب أي سطرٍ في سجل التدقيق (لا ems_audit_change ولا ems_log_*) ولا ينشر حدثًا. | J177: Governance Gap | K177: P2 | L177: اعتمادُ كرتِ أصلٍ يمكن تنفيذُه بتزوير طلبٍ عابرٍ للمواقع من جلسة مدير أسطول، ولا أثرَ يُبيّن مَن اعتمد ومتى وبأي صفة سوى عمودَي card_approved_by/at بلا سياق. | M177: الملفُّ كُتب كمعالجٍ خفيفٍ («حوكمة خفيفة» في تعليق السطر 2) ولم يُلحَق بطبقة الحوكمة الموحّدة. | N177: Equipments/approve_card.php:2; :23; :29-32; :46-52 | P177: ١) سجّل الدخولَ بدور ٣. ٢) من صفحةٍ خارجية أرسل POST إلى http://localhost/ems/Equipments/approve_card.php بحقلَي equipment_id و return. ٣) لاحظ تنفيذَ الاعتماد. ٤) ابحث في سجل التدقيق عن سطرٍ لهذا الاعتماد → لا يوجد. | Q177: أضِف في approve_card.php بعد السطر 26 فحصَ verify_csrf_token($_POST['csrf_token'])، وبعد نجاح التحديث استدعِ ems_audit_change($conn,'fleet','approve_card','approve',$equipment_id, قيمِ قبل, قيمِ بعد, سياق الشركة والمستخدم)، وأضِف حقلَ csrf_token في نموذجَي equipments.php:1065 و equipments_fleet.php:1286. | R177: فريق الباك-إند — وحدة الأسطول | S177: نعم | T177: لا | U177: POST بلا رمزِ حمايةٍ صالحٍ يُرفض 403؛ واعتمادٌ ناجحٌ يُنشئ سطرًا في سجل التدقيق بقيمة قبل/بعد واسمِ المعتمِد. | V177: مفتوح | W177: مؤكَّدة | X177: الملفُّ فعلًا بلا verify_csrf_token وبلا ems_audit_change، ومسارُ /Equipments/ خارج CSRF_ENFORCE_PATHS الحيّة فالحارسُ المركزيُّ في وضع المراقبة. لكن الفعلَ محروسٌ بـcheck_page_permissions can_edit ويكتب card_approved_by/at، وcard_state «عرضيٌّ حوكميٌّ» بنصِّ رأس الملف ⇒ P2. | Y177: P1 | Z177: نعم | AA177: نعم | AB177: 06_M14 | AC177: فجوة تنفيذ (Implementation) | AD177: Decision Closed · Implementation Open
A178: INJ-0174 | B178: M-14 | C178: PR-05 · الحارسُ في الخادم — تطابقُ رمز الوحدة بين الشاشة ومعالجها | D178: إدارة الأسطول | E178: اعتماد كرت المعدة | F178: http://localhost/ems/Equipments/approve_card.php | G178: - | H178: «يمنع الاكتفاءَ بإخفاء الزر في الواجهة» — والزرُّ الظاهرُ في شاشةٍ يجب أن يُنفَّذ بالصلاحية نفسِها التي أظهرته. | I178: زرُّ الاعتماد يُصيَّر في Equipments/equipments.php:1065 وفق صلاحيات وحدة 'equipments' (السطر 48)، بينما المعالجُ Equipments/approve_card.php:29 يفحص صلاحيةَ وحدةٍ أخرى هي 'equipments_fleet'. فالمستخدمُ الذي يملك الأولى دون الثانية يرى الزرَّ ويُرفض عند الضغط. | J178: Permission Gap | K178: P2 | L178: زرٌّ ظاهرٌ لا يعمل لطائفةٍ من المستخدمين، ورسالةُ الرفض تظهر في شريط الرابط لا داخل النظام؛ والمستخدمُ لا يفهم سببَ المنع ولا يُسجَّل رفضُه. | M178: توحيدُ الشاشات لم يُتبَع بتوحيد رموز الوحدات، فبقي المعالجُ مرتبطًا برمز الشاشة القديمة equipments_fleet. | N178: Equipments/equipments.php:48; Equipments/equipments.php:1065; Equipments/approve_card.php:29; Equipments/equipments_fleet.php:81 | P178: ١) امنح دورًا can_edit على 'equipments' فقط دون 'equipments_fleet'. ٢) افتح سجل المعدات — زرُّ «اعتماد الكرت» ظاهر. ٣) اضغطه — رسالةُ «لا توجد صلاحية لاعتماد الكرت». | Q178: وحّد الرمزَ: في Equipments/approve_card.php:29 استبدل 'equipments_fleet' بـ 'Equipments/equipments.php'، أو اجعل الزرَّ في equipments.php:1065 مشروطًا بنفس الصلاحية التي يفحصها المعالج. | R178: فريق الحوكمة — وحدة الصلاحيات | S178: لا | T178: نعم | U178: لكل حسابٍ: ظهورُ زرِّ الاعتماد ⇔ نجاحُ تنفيذه؛ صفرُ حالةٍ يظهر فيها الزرُّ ويُرفض الفعل. | V178: مفتوح | W178: مؤكَّدة | X178: الزرُّ يُصيَّر في equipments.php:1065 خلف $can_edit المشتقِّ من check_page_permissions($conn,'equipments') (السطر 48)، والمعالجُ approve_card.php:29 يفحص 'equipments_fleet' — وهما يُحلّان إلى موديولين مختلفين (256 و8) فيقع «زرٌّ ظاهرٌ وفعلٌ مرفوض». | Y178: P2 | Z178: نعم | AA178: نعم | AB178: 06_M14 | AC178: فجوة تنفيذ (Implementation) | AD178: Decision Closed · Implementation Open
A179: INJ-0175 | B179: INJAZ-CORE-01 | C179: PR-04 · المالُ أثرٌ لا مصدر — «ويمنع قيدًا بلا واقعةٍ تشغيلية» | D179: المالية والخزينة | E179: الذمم والتحصيل — كتّاب fin_dues العشرة | F179: http://localhost/ems/Finance/dues_fin.php | G179: ثالثًا: المصروف والدفع | H179: «يوجب أن يتولد كلُّ إيرادٍ ومصروفٍ وذمةٍ من واقعةٍ اجتازت سلسلةَ الاعتماد وبوابةَ الاستحقاق» — لكلِّ صفٍّ ماليٍّ مستندٌ مصدرٌ يُنقر إليه. | I179: موضعُ كتابةٍ واحدٌ (proc_helpers.php:612) بلا أيِّ مرجعٍ مبنيٍّ؛ وأربعةُ مواضعِ المروحة تحمل event_id وصفَّ fin_event_links يربطها بمصدرها، والإعفاءُ في dues_fin.php:73 قرارُ تصميمٍ موثَّقٌ لا سهو. — [مُصحَّح بعد التحقق] الصياغة الأولى: عشرةُ مواضعِ كتابةٍ في fin_dues، تسعةٌ منها خارج الشاشة ولا يمرّ أيٌّ منها بفحص dues_fin.php:82-95: app/Services/EffectFanout.php:175 · :1057 · :1271 · :1304 (كلُّها direction='credit' بلا source_doc_ | J179: Governance Gap | K179: P2 | L179: الذمّةُ الدائنة — وهي التي تولّد الالتزامَ بالدفع — تُنشأ من خمسة مسارات بلا حقلِ مستندٍ مصدرٍ إطلاقًا؛ فلا يمكن الانتقالُ من رقمٍ في كشف حساب المورد إلى واقعته، وينكسر PR-08 معه. | M179: الحارسُ نُفِّذ في طبقة الشاشة لا في طبقة الخدمة/القاعدة، فبقي كلُّ مسارٍ خدميٍّ خارجَه؛ والاستثناءُ الممنوحُ لـcredit جعل أكثرَ المسارات استعمالًا بلا مصدر. | N179: Finance/dues_fin.php:68-73,97; app/Services/EffectFanout.php:175-186,1057-1080,1271-1292,1304-1325; Procurement/proc_helpers.php:602-620 | P179: ١) نفّذ SELECT COUNT(*) FROM fin_dues WHERE source_doc_type IS NULL → عددٌ كبيرٌ من صفوف credit. ٢) اعتمد تايم شيت ليوم عملٍ فيتولد صفُّ fin_dues من EffectFanout.php:175 بلا source_doc_type. ٣) من شاشة الذمم اضغط الصفَّ محاولًا بلوغَ مستنده → لا رابط. | Q179: أضِف حقولَ source_doc_type/source_doc_id (أو event_id إلزاميًّا) في نداءات insert('fin_dues') الخمسةِ التي تفتقدها (EffectFanout.php:175/1057/1271/1304 و proc_helpers.php:612)، ثم شدّد قيدَ القاعدة ليشمل direction='credit' بعد ردم التاريخي. | R179: فريق الباك-إند — وحدة المالية | S179: نعم | T179: نعم | U179: SELECT COUNT(*) FROM fin_dues WHERE COALESCE(event_id,0)=0 AND source_doc_type IS NULL = صفر (أو مصنَّفًا legacy_no_ref)، وكلُّ صفٍّ في شاشة الذمم يفتح مستندَه بنقرة. | V179: مفتوح | W179: مرجَّحة | X179: dues_fin.php:73 يُعفي credit صراحةً بتعليقٍ مُبرَّر («مصدرُه حدثُ المروحة»)، والأربعةُ في EffectFanout (175/1057/1271/1304) تمرّر event_id وتكتب رابطَ fin_event_links بـself::link — فالتتبعُ قائمٌ لا مفقود. الفجوةُ الحقيقيةُ الوحيدةُ proc_helpers.php:612: ذمّةٌ دائنةٌ بلا event_id ولا source_doc_type ومرجعُها period_ref='PO-<id>' وحدَه. | Y179: P0 | Z179: نعم | AA179: نعم | AB179: 01_CORE | AC179: فجوة تنفيذ (Implementation) | AD179: Decision Closed · Implementation Open
A180: INJ-0176 | B180: INJAZ-CORE-01 | C180: PR-04 · المالُ أثرٌ لا مصدر — «يمنع توليدَ أثرٍ ماليٍّ من إدخالٍ مباشر» | D180: المالية والخزينة | E180: سجل الأحداث المالية | F180: http://localhost/ems/Finance/events_list_fin.php | G180: خارج الوثيقة — بانتظار قرار المالك | H180: «لا يقع أثرٌ ماليٌّ من إدخالٍ مباشر. وكلُّ إيرادٍ ومصروفٍ وذمةٍ يتولد من واقعةٍ تشغيليةٍ اجتازت سلسلةَ اعتمادها وبوابةَ استحقاقها». | I180: إدخالٌ ماليٌّ مباشرٌ بمرجعٍ نصيٍّ غيرِ محقَّقٍ ولا مفتاحِ عطالة، لكنه مقيَّدٌ بصلاحيةِ الإضافة ويمرُّ بسلسلةِ اعتمادٍ قبل توليدِ قيدٍ مسودةٍ يُفحص عند ترحيله بقفل الفترة. — [مُصحَّح بعد التحقق] الصياغة الأولى: معالجُ الحفظ في Finance/events_list_fin.php:151-199 ينشئ صفًّا في fin_financial_events — وهو جذرُ الأثر المالي — من حقولِ $_POST مباشرة: نوعُ الحدث ومصدرُه ومرجعٌ نصيٌّ حرٌّ (source_ref) والمبلغُ والع | J180: Governance Gap | K180: P2 | L180: بابٌ مفتوحٌ لخلق المال من العدم: يكفي مستخدمٌ بصلاحية الإضافة على الشاشة ليُنشئ حدثًا ماليًّا بمبلغٍ اختياريٍّ ومرجعٍ نصيٍّ لا يُتحقَّق منه، ثم يمرّ في دورة الاعتماد ويولّد قيدًا في الدفاتر. | M180: الشاشةُ صُمِّمت كسجلٍّ إداريٍّ للأحداث ثم صارت مسارَ إنشاءٍ كاملًا بلا اشتراطِ مصدرٍ مستنديٍّ محقَّق. | N180: Finance/events_list_fin.php:151; Finance/events_list_fin.php:160; Finance/events_list_fin.php:170; Finance/events_list_fin.php:193; Finance/events_list_fin.php:275 | P180: ١) بدور مالية له can_add افتح «سجل الأحداث المالية». ٢) أنشئ حدثًا: النوع «مصروف»، المصدر «عام»، المرجع «xyz»، المبلغ 1000000. ٣) احفظ → ينشأ الصف. ٤) مرّره في دورة الاعتماد حتى approved → يتولد قيدٌ آليّ. | Q180: في Finance/events_list_fin.php:151 اجعل source_ref مرجعًا محقَّقًا: أضِف حقلَي source_table/source_id إلزاميين مع تحقّقٍ من وجود الصف في جدول المصدر (proc_order · mnt_order · unit_record · claim)، وارفض الحفظَ 422 عند غيابه؛ وأضِف ems_period_check قبل الإدراج. | R180: فريق الباك-إند — وحدة المالية | S180: نعم | T180: نعم | U180: POST لإنشاء حدثٍ ماليٍّ بمرجعٍ نصيٍّ لا يقابله صفٌّ في جدول المصدر يُرفض 422 برمزٍ محكوم، ولا يُنشأ أي صف. | V180: مفتوح | W180: مرجَّحة | X180: الأسطرُ 151-199 صحيحةٌ حرفيًّا: الصفُّ يُنشأ من $_POST بفحصِ قوائمَ بيضاءَ ومبلغٍ موجبٍ فقط و source_ref نصٌّ حر. لكن الحفظَ يتطلب can_add على الموديول 86 (أدوارُ المالية)، والصفُّ يولد state='draft' ولا يبلغ fin_auto_journal (السطر 275) إلا بعد سلسلةِ اعتمادٍ خماسية، وقفلُ الفترة مفروضٌ عند الترحيل في Finance/journal_form_fin.php:143 — فليست «خلق مالٍ من العدم» بضغطةٍ واحدة. | Y180: P0 | Z180: نعم | AA180: نعم | AB180: 01_CORE | AC180: فجوة تنفيذ (Implementation) | AD180: Decision Closed · Implementation Open
A181: INJ-0177 | B181: INJAZ-CORE-01 | C181: PR-04 · المالُ أثرٌ لا مصدر — «ونسبةُ القيود اليدويةِ مؤشرُ صحةٍ يُقاس ويُخفَّض» | D181: المالية والخزينة | E181: القيود اليومية | F181: http://localhost/ems/Finance/journal_form_fin.php | G181: سادسًا: القيود والدفاتر | H181: «استعلم عن كل صفٍّ في جدول القيود بلا source_event_id — يجب أن يكون صفرًا (أو مصنَّفًا استثناءً موثَّقًا). جرّب POST لإنشاء قيدٍ يدويٍّ بلا واقعة — يُرفض». | I181: القيدُ اليدويُّ بلا حدثٍ يُحفظ مسودةً بسببٍ مكتوبٍ إلزامًا، ولا يُرحَّل إلا بيد المدير المالي وفي فترةٍ مفتوحة — والناقصُ مؤشرُ «نسبة القيود اليدوية» لا الحارسُ نفسُه. — [مُصحَّح بعد التحقق] الصياغة الأولى: نموذجُ القيد يعرض الحدثَ المرتبطَ باسمِ «الحدث المرتبط (اختياري)» وخيارٍ أولَ نصُّه «— بلا حدث —» (السطران 238 و240)، والمعالجُ يقرأ $event_id = intval($_POST['event_id']) ?: null (السطر 130) ويُدرج ا | J181: Governance Gap | K181: P2 | L181: أيُّ رقمٍ يمكن إدخالُه في الدفاتر بقيدٍ متوازنٍ بلا واقعةٍ تشغيلية؛ فتنكسر سلسلةُ التتبع من القائمة المالية إلى المستند، ولا مؤشرَ يقيس نسبةَ القيود اليدوية أصلًا في أي لوحة. | M181: نُفِّذت ضوابطُ التوازن والفترة والعملة والسبب، ولم يُنفَّذ اشتراطُ الواقعة، ولم يُصنَّف القيدُ اليدويُّ استثناءً موثَّقًا بسقفٍ ومعتمِدٍ أعلى. | N181: Finance/journal_form_fin.php:41,130,142-146,178,238-240 | P181: ١) بدور محاسب افتح «القيود اليومية» واضغط «إنشاء قيد». ٢) اترك «الحدث المرتبط» على «— بلا حدث —». ٣) أدخِل سطرين متوازنين وبيانًا واحفظ → يُحفظ القيد بـevent_id NULL. | Q181: في Finance/journal_form_fin.php:130 اجعل event_id إلزاميًّا افتراضيًّا: ارفض الحفظَ 422 عند غيابه إلا إذا حمل الطلبُ manual_exception_ref مربوطًا بصفٍّ في سجل الاستثناءات باعتمادِ المدير المالي؛ وأضِف بطاقةَ «نسبة القيود اليدوية» إلى Finance/cfo_daily_board_fin.php محسوبةً حيًّا. | R181: فريق الباك-إند — وحدة المالية | S181: نعم | T181: نعم | U181: حفظُ قيدٍ بلا حدثٍ مرتبطٍ وبلا مرجعِ استثناءٍ معتمدٍ يُرفض 422؛ ولوحةُ المالية تعرض نسبةَ القيود اليدوية محسوبةً من القاعدة. | V181: مفتوح | W181: مرجَّحة | X181: الأسطرُ صحيحةٌ حرفيًّا (event_id اختياري في :130 و:178 والخيارُ «— بلا حدث —» في :240)، لكن الفاحصَ أسقط الضوابطَ المحيطة: البيانُ/السببُ إلزامٌ (:146)، والقيدُ يُحفظ state='draft'، والترحيلُ محصورٌ في fin_can_perform(...,'finance_manager') (:41)، وبوابةُ الفترة تمنع المقفلة (:142-144). والمسارُ اليدويُّ منصوصٌ عليه في SPEC-01 #13 التي يستشهد بها الكود. | Y181: P0 | Z181: نعم | AA181: نعم | AB181: 01_CORE | AC181: فجوة تنفيذ (Implementation) | AD181: Decision Closed · Implementation Open
A182: INJ-0178 | B182: INJAZ-CORE-01 | C182: PR-04 · المالُ أثرٌ لا مصدر | D182: المالية والخزينة | E182: طلبات الدفع والسداد | F182: http://localhost/ems/Finance/payments_fin.php | G182: ثالثًا: المصروف والدفع | H182: «كلُّ إيرادٍ ومصروفٍ وذمةٍ يتولد من واقعةٍ تشغيليةٍ اجتازت سلسلةَ اعتمادها وبوابةَ استحقاقها». | I182: تنفيذُ الحركة (حيث يقع الأثرُ المالي) يمرُّ بـApprovalGate::assertComplete تحت العلَم EMS_U13_APPROVAL_GATE (افتراضُه monitor: يسجّل ولا يمنع، وenforce يمنع) — فالبابُ ليس مفتوحًا بلا أيِّ سلسلةِ اعتماد. — [مُصحَّح بعد التحقق] الصياغة الأولى: معالجُ الإنشاء (الأسطر 119-136) ينشئ حركةَ خزينةٍ من direction+party+amount؛ receivable_id اختياريٌّ (السطر 126) ولا حقلَ لمستندٍ مصدرٍ أو التزامٍ أو ذمّةٍ للصرف، والفحصُ الوحيد amount>0 (السطر 128). | J182: Governance Gap | K182: P2 | L182: حركةُ خزينةٍ (صرفٌ أو تحصيل) تُنشأ بلا أي مستندٍ يربطها بالتزامٍ أو ذمّة؛ وحين تُنفَّذ لاحقًا تُغيّر حالةَ ذممِ المورد جملةً (السطر 84) بلا مطابقةٍ للمبالغ. | M182: الشاشةُ عوملت كسجلِّ حركاتٍ حرٍّ لا كمنفّذٍ لأمرِ دفعٍ معتمدٍ صادرٍ من دورة الطلبات المالية. | N182: Finance/payments_fin.php:119; Finance/payments_fin.php:126; Finance/payments_fin.php:128; Finance/payments_fin.php:131; Finance/payments_fin.php:84 | P182: ١) بدور مالية له can_add افتح «طلبات الدفع والسداد». ٢) أنشئ حركةَ صرفٍ لمورد بمبلغٍ اختياريٍّ بلا اختيار ذمّة. ٣) احفظ → تُنشأ مسودةُ صرفٍ بلا أي مستندٍ مصدر. | Q182: في Finance/payments_fin.php:119 اجعل الصرفَ (disbursement) يشترط obligation_id أو due_id أو request_id موجودًا ومعتمدًا، وارفض 422 عند غيابه؛ وأضِف ems_period_check و fin_verify_action_token و ems_audit_change في المعالج. | R182: فريق الباك-إند — وحدة المالية | S182: نعم | T182: نعم | U182: حفظُ حركةِ صرفٍ بلا مستندِ التزامٍ أو ذمّةٍ معتمدةٍ يُرفض 422؛ وكلُّ صفٍّ في fin_payments يفتح مستندَه بنقرة. | V182: مفتوح | W182: مرجَّحة | X182: معالجُ الإنشاء يطابق الوصف (مسودةٌ بلا مستندٍ مصدرٍ وبفحص amount>0 وحدَه)، لكنّ البندَ أغفل حارسَ التنفيذ. | Y182: P1 | Z182: نعم | AA182: نعم | AB182: 01_CORE | AC182: فجوة تنفيذ (Implementation) | AD182: Decision Closed · Implementation Open
A183: INJ-0179 | B183: INJAZ-CORE-01 | C183: PR-04 · المالُ أثرٌ لا مصدر · §٩-١ «◆ ما لا تملكه المالية: العقدَ والسعر» | D183: المالية والخزينة | E183: التكاليف والربحية بالمركز | F183: http://localhost/ems/Finance/cost_report_fin.php | G183: متابعة وتقارير المالية | H183: المالية «لا تملك العقدَ والسعر»، و«لا يقع أثرٌ ماليٌّ من إدخالٍ مباشر». | I183: معالجُ Finance/cost_report_fin.php:34-51 ينشئ صفًّا في fin_cost_records من $_POST يتضمن total_cost و revenue (السطران 42-43) بلا أي مستندٍ مصدرٍ ولا حدثٍ ولا فحصِ فترة؛ الفحصُ الوحيد قائمةُ أنواعٍ بيضاء و total_cost>=0 (السطر 44). فالإيرادُ — وهو ما لا تملكه المالية — يُدخَل يدويًّا هنا. | J183: Governance Gap | K183: P2 | L183: أرقامُ التكلفة والإيراد التي تُبنى عليها تقاريرُ الربحية وهامشُ العقد تُدخَل يدويًّا بلا واقعةٍ ولا عقد؛ فيصير تقريرُ الربحية رأيًا لا قياسًا، ويخالف حدَّ اختصاص الإدارة. | M183: الشاشةُ بُنيت لالتقاط تكاليفَ غير مؤتمتةٍ ولم يُقيَّد الحقلُ الإيراديُّ ولا اشتُرط مستندٌ للتكلفة. | N183: Finance/cost_report_fin.php:34; Finance/cost_report_fin.php:42; Finance/cost_report_fin.php:43; Finance/cost_report_fin.php:44; Finance/cost_report_fin.php:46 | P183: ١) بدور مالية افتح «التكاليف والربحية بالمركز». ٢) أضِف سجلَّ تكلفةٍ بنوعٍ ما وقيمةِ تكلفةٍ وإيرادٍ اختياريين. ٣) احفظ → يظهر الرقمُ في تقرير الربحية بلا مصدر. | Q183: في Finance/cost_report_fin.php:34 اشترط source_event_id مرتبطًا بحدثٍ مالي أو مستندٍ تشغيليٍّ لكل سجلِّ تكلفة، واحذف حقلَ revenue من هذه الشاشة (الإيرادُ من المستخلص/الفاتورة حصرًا) واقرأه قراءةً من fin_financial_events. | R183: فريق الباك-إند — وحدة المالية | S183: نعم | T183: نعم | U183: حفظُ سجلِّ تكلفةٍ بلا حدثٍ مصدرٍ يُرفض 422؛ وحقلُ الإيراد غيرُ قابلٍ للإدخال في هذه الشاشة ويُقرأ من مصدره. | V183: مفتوح | W183: مؤكَّدة | X183: المعالجُ في السطر 34 يُدرج fin_cost_records من $_POST بحقلَي total_cost وrevenue (42-43) بلا مستندٍ مصدرٍ ولا حدثٍ ولا فحصِ فترة — والفحصُ الوحيد قائمةٌ بيضاء وtotal_cost>=0 (44). أخفضتُ الخطورةَ لأن الفعلَ محروسٌ بـcan_add ولا يُنشئ قيدًا محاسبيًّا. | Y183: P1 | Z183: نعم | AA183: نعم | AB183: 01_CORE | AC183: فجوة تنفيذ (Implementation) | AD183: Decision Closed · Implementation Open
A184: INJ-0180 | B184: INJAZ-CORE-01 | C184: PR-06 · لا رجعيةَ في المعتمَد — «لا كتابةَ ماليةً في فترةٍ مقفلة» | D184: المالية والخزينة | E184: شاشات المالية الكاتبة | F184: http://localhost/ems/Finance/payments_fin.php | G184: ثالثًا: المصروف والدفع | H184: «يوجب… انفتاحُ الفترة المحاسبية» (§٢٤-١)، والحارسُ المنفَّذ includes/period_guard.php يُرجع 423 لأي كتابةٍ ماليةٍ في فترةٍ مقفلة. | I184: الدفترُ العامُّ (fin_financial_events) محروسٌ مركزيًّا؛ والمكشوفُ الدفاترُ المساعدةُ (fin_dues · fin_payments · fin_receivables) التي تُكتب مباشرةً بلا فحصِ فترة. — [مُصحَّح بعد التحقق] الصياغة الأولى: من بين شاشات مجلد Finance الكاتبة، شاشةٌ واحدةٌ فقط تستدعي حارسَ الفترة: Finance/journal_form_fin.php (السطران 59 و143). ولا استدعاءَ في payments_fin.php ولا dues_fin.php ولا events_list_fin.php ولا c | J184: Governance Gap | K184: P2 | L184: إقفالُ الفترة يمنع القيدَ اليدويَّ وحدَه: تبقى الذممُ والمدفوعاتُ والأحداثُ الماليةُ وسجلاتُ التكلفة والمطابقةُ البنكية تُنشأ وتُعدَّل بتواريخَ داخل فترةٍ مقفلة، فيتغير الرصيدُ بعد الإقفال ويفقد الإقفالُ معناه. | M184: حارسُ الفترة أُضيف نقطيًّا عند إصلاح القيود ولم يُعمَّم على مسارات الكتابة المالية الأخرى. | N184: includes/period_guard.php:24; app/Core/EventPublisher.php:311-318; Finance/journal_form_fin.php:143; Finance/dues_fin.php:97; Finance/payments_fin.php:131 | P184: ١) أقفِل فترةَ الشهر الماضي. ٢) أنشئ حركةَ صرفٍ أو ذمّةً أو حدثًا ماليًّا بتاريخٍ داخل تلك الفترة. ٣) لاحظ نجاحَ الحفظ بلا أي منع. | Q184: أضِف require_once includes/period_guard.php و ems_period_check($conn,$company_id,$date) قبل كل insert/update ماليٍّ في الملفات التسعة المذكورة، وأرجِع 423 برسالة السبب عند الإقفال. | R184: فريق الباك-إند — وحدة المالية | S184: نعم | T184: نعم | U184: كلُّ محاولةِ كتابةٍ ماليةٍ بتاريخٍ في فترةٍ مقفلةٍ تُرفض 423 برسالةٍ تسمّي الفترةَ والسبب، من كل شاشات المالية. | V184: مفتوح | W184: مرجَّحة | X184: صحيحٌ أن شاشات Finance الكاتبةَ لا تستدعي ems_period_check (عدا journal_form_fin)، لكنّ الحارسَ مركزيٌّ في نقطة الخنق: app/Core/EventPublisher.php:311-318 يرفض أيَّ حدثٍ ماليٍّ في فترةٍ مقفلة، ومعه DepreciationService:128 وPeriodicEventService وclaim_helpers:1048. | Y184: P1 | Z184: نعم | AA184: نعم | AB184: 01_CORE | AC184: فجوة تنفيذ (Implementation) | AD184: Decision Closed · Implementation Open
A185: INJ-0181 | B185: INJAZ-CORE-01 | C185: AR-04 · مفتاحُ منع التكرار في كل أثر — «إعادةُ النداء ترجع مرجعَ الأثر الأول» | D185: المالية والخزينة | E185: شاشات المالية الكاتبة | F185: http://localhost/ems/Finance/journal_form_fin.php | G185: سادسًا: القيود والدفاتر | H185: «كلُّ فعلٍ ذي أثرٍ يحمل مفتاحًا مركَّبًا لا يتكرر… تحقق من UNIQUE index على المفتاح المركَّب». | I185: لا يحمل أيُّ معالجِ كتابةٍ في مجلد Finance مفتاحَ عطالةٍ على مستوى الطلب: إنشاءُ القيد (journal_form_fin.php:177) والذمّة (dues_fin.php:97) وحركةِ الخزينة (payments_fin.php:131) والحدثِ المالي (events_list_fin.php:193) وسجلِّ التكلفة (cost_report_fin.php:46) — كلُّها إدراجٌ مباشرٌ بلا مفتاح. ورمزُ الحماية جلسيٌّ يُقارَن ولا يُستهلك (includes/security.php:233) فلا يمنع إعادةَ الإرسال. والمفتاحُ منفَّذٌ في طبقة الأحداث فقط. | J185: Event/Integration Gap | K185: P2 | L185: نقرتان أو زرُّ رجوعٍ أو إعادةُ إرسالٍ تُنشئ قيدًا ثانيًا أو ذمّةً ثانيةً أو صرفًا ثانيًا بالمبلغ نفسِه؛ وهي أكثرُ أخطاء الأنظمة المالية شيوعًا وأصعبُها اكتشافًا بعد الإقفال. | M185: العطالةُ نُفِّذت في ناقل الأحداث (idempotency_key) ولم تُنفَّذ في طبقة الطلب لأي معالجٍ في المستودع؛ و app/Core/ProcessedOperations.php الذي يوفّرها بلا أي مستدعٍ إنتاجي. | N185: Finance/journal_form_fin.php:174; Finance/journal_form_fin.php:177; Finance/dues_fin.php:97; Finance/payments_fin.php:130; Finance/events_list_fin.php:192; includes/security.php:233; app/Core/ProcessedOperations.php:1 | P185: ١) أنشئ قيدًا متوازنًا واضغط حفظ. ٢) اضغط زرَّ الرجوع ثم أعِد الإرسال. ٣) اعدّ صفوفَ fin_journal_entries → قيدان بنفس المحتوى وبرقمين مختلفين. | Q185: أضِف حقلَ idempotency_key في نماذج المالية (مولَّدًا في الواجهة) وفهرسًا فريدًا على (company_id, idempotency_key) في fin_journal_entries و fin_dues و fin_payments و fin_financial_events و fin_cost_records، واستعمل app/Core/ProcessedOperations.php لادّعاء المفتاح قبل الكتابة وإرجاعِ مرجع الأثر الأول عند التكرار. | R185: فريق الباك-إند — وحدة المالية | S185: نعم | T185: لا | U185: إرسالُ نفس نموذج القيد/الذمّة/الصرف مرتين وبالتوازي ينتج صفًّا واحدًا، والاستجابةُ الثانيةُ تحمل رقمَ المستند الأول. | V185: مفتوح | W185: مؤكَّدة | X185: لا مفتاحَ عطالةٍ في أيِّ معالجِ كتابةٍ ماليّ (journal_form_fin.php:177 · dues_fin.php:97 · payments_fin.php:131 · events_list_fin.php:193)، وverify_csrf_token (security.php:233) مقارنةٌ جلسيةٌ لا تُستهلك، وProcessedOperations بلا مستدعٍ إنتاجيّ. خُفّضت لأن نمطَ PRG (ems_gov_flash_redirect بعد الإدراج) يحجب تكرارَ التحديث. | Y185: P1 | Z185: نعم | AA185: نعم | AB185: 01_CORE | AC185: فجوة تنفيذ (Implementation) | AD185: Decision Closed · Implementation Open
A186: INJ-0182 | B186: INJAZ-CORE-01 | C186: PR-06 · لا رجعيةَ في المعتمَد — «التصحيحُ حركةٌ جديدةٌ تشير إلى الأصل، أو حركةٌ عاكسةٌ بمرجعها» | D186: المالية والخزينة | E186: الذمم والتحصيل / طلبات الدفع | F186: http://localhost/ems/Finance/dues_fin.php | G186: ثالثًا: المصروف والدفع | H186: «المستندُ المعتمدُ لا يُعدَّل ولا يُحذف. والتصحيحُ حركةٌ جديدةٌ تشير إلى الأصل، أو حركةٌ عاكسةٌ بمرجعها إن كان الأثرُ ماليًّا قد وقع». | I186: لا مسارَ عكسٍ لأيٍّ من الذمم أو المدفوعات: الشاشتان توفران حذفًا ناعمًا فقط (dues_fin.php:44 و :52 · payments_fin.php:112)، والحذفُ الناعمُ للذمّة مشروطٌ بألا تكون paid والدفعةُ بأن تكون draft — أي أن المنفَّذَ لا يُعكس ولا يُصحَّح بحركةٍ جديدة. وأعمدةُ «عكس عن»/«معكوس بـ» تُحقن رؤوسًا بلا مصدر (gov_columns.php:38-39)، وapp/Services/Actions/ReverseService.php بلا أي مستدعٍ إنتاجي. | J186: Risk/Governance Gap | K186: P2 | L186: خطأٌ في ذمّةٍ مسوّاةٍ أو صرفٍ منفَّذٍ لا سبيلَ لتصحيحه إلا بتعديلٍ خلفيٍّ في القاعدة أو بترك الخطأ؛ فتفقد الدفاترُ خاصيةَ السجل التاريخيِّ التي يفرضها المبدأ. | M186: بوابةُ العكس العامة كُتبت ولم تُوصل بأي شاشة، واكتُفي بالحذف الناعم بديلًا عن الحركة العاكسة. | N186: Finance/dues_fin.php:43; :51; Finance/payments_fin.php:112; includes/gov_columns.php:38-39; app/Services/Actions/ReverseService.php:22 | P186: ١) نفّذ دفعةَ صرفٍ (state=executed). ٢) ابحث عن زرِّ «عكس الحركة» → لا يوجد؛ وزرُّ الحذف لا يعمل على المنفَّذ. ٣) افتح عمودَي «عكس عن»/«معكوس بـ» → «—» دائمًا. | Q186: أضِف فعلَ «حركة عاكسة» في Finance/payments_fin.php و Finance/dues_fin.php يستدعي app/Services/Actions/ReverseService.php وينشئ صفًّا جديدًا بـreverses_id يشير إلى الأصل ويُبقي الأصلَ ظاهرًا، ثم املأ عمودَي gov_columns من هذا المرجع. | R186: فريق الباك-إند — وحدة المالية | S186: نعم | T186: نعم | U186: عكسُ دفعةٍ منفَّذةٍ ينشئ صفًّا جديدًا بمرجعِ الأصل، ويظهر الصفّان معًا في الشاشة وفي سجل التدقيق، ولا يُحذف الأصل. | V186: مفتوح | W186: مؤكَّدة | X186: الشاشتان توفران حذفًا ناعمًا مشروطًا فقط (dues_fin.php:43 و:51 · payments_fin.php:112)، وapp/Services/Actions/ReverseService::resolve بلا أيِّ مستدعٍ إنتاجيّ، وأعمدةُ «عكس عن/معكوس بـ» رؤوسٌ محقونةٌ من gov_columns.php:38-39 بلا مصدر. | Y186: P1 | Z186: نعم | AA186: نعم | AB186: 01_CORE | AC186: فجوة تنفيذ (Implementation) | AD186: Decision Closed · Implementation Open
A187: INJ-0183 | B187: INJAZ-FRD-01 | C187: INJAZ-FRD-01 §٩-٣ · المرحلة ٧ — «لا مرحلةَ بلا مخرَج» · شرطُ الإغلاق بالدليل | D187: المالية والخزينة | E187: إقفال الفترة المحاسبية — بنود الإقفال | F187: http://localhost/ems/Finance/periods_fin.php | G187: سابعًا: الإقفال والموازنة | H187: «لا إقفالَ نهائيٌّ قبل إنجاز بنود الإقفال الإلزامية» كما يعلن رأسُ الملف، والبندُ المنجَزُ يُغلق بدليلٍ لا بصمت. | I187: إنجازُ بند الإقفال (الأسطر 75-80) يضع item_state='done' لأي بندٍ بمعرّفه عبر GET بلا مرفقٍ ولا مرجعِ مستندٍ ولا ملاحظةٍ ولا تحقّقٍ من أن البند يخصّ الفترةَ المعنيّة (الشرطُ الوحيد array('id'=>$it))، ثم يصير الإقفالُ ممكنًا لأن العدّاد في السطر 41 يعدّ البنودَ pending فقط. | J187: Governance Gap | K187: P2 | L187: قائمةُ الإقفال تتحول إلى نقراتٍ شكلية: تُعلَّم البنودُ منجَزةً بلا دليل، فيقع الإقفالُ النهائيُّ مستوفيًا الشكلَ خاليًا من المضمون. | M187: لم يُطلب دليلٌ لإنجاز البند ولم يُربط البندُ بمصدرِ إثباتٍ (تقريرٍ أو مطابقةٍ أو مرفق). | N187: Finance/periods_fin.php:41; :74; :77; :78 | P187: ١) بدور مالية افتح فترةً وبنودَ إقفالها. ٢) اضغط «إنجاز» على كل بندٍ إلزاميٍّ متتاليًا بلا إدخال شيء. ٣) اضغط «إقفال» → يقع الإقفال. | Q187: في Finance/periods_fin.php:75 اشترط evidence_ref (مرفق أو مرجع تقرير) وملاحظةً غيرَ فارغةٍ لإنجاز البند، وأضِف شرطَ period_id إلى where، واستدعِ ems_audit_change لكل إنجازٍ. | R187: فريق الباك-إند — وحدة المالية | S187: لا | T187: لا | U187: إنجازُ بندِ إقفالٍ بلا مرجعِ دليلٍ يُرفض 422؛ وكلُّ بندٍ منجَزٍ يعرض دليلَه ومن أنجزه ومتى. | V187: مفتوح | W187: مؤكَّدة | X187: إنجازُ بند الإقفال يقع بـGET بلا مرجعِ دليلٍ ولا ملاحظةٍ ولا شرطِ period_id في where، والعدّادُ الحاكمُ يعدّ pending فقط. | Y187: P2 | Z187: نعم | AA187: نعم | AB187: 02_FRD | AC187: فجوة تنفيذ (Implementation) | AD187: Decision Closed · Implementation Open
... A205: INJ-0201 | B205: M-14 | C205: ▐ ١١-١٢ · GOV-0358 «حوكمة إدارتي» — منظرٌ نطاقيٌّ لكل إدارة | D205: المالية والخزينة | E205: حوكمة الإدارة المالية | F205: http://localhost/ems/Finance/gov_dept_fin.php | G205: غير موجود في السايدبار | H205: «يُضاف لكل إدارةٍ مكوّنٌ نطاقيٌّ واحدٌ باسم «حوكمة إدارتي»… وحقُّ المستخدمِ فيه قراءةٌ فقط»، وتعرض مساحتُه تعارضاتِ الواجبات والتفويضاتِ والاستثناءات. | I205: الملفُّ Finance/gov_dept_fin.php موجودٌ على القرص لكنه لا يظهر في سايدبار أي دورٍ ماليٍّ (ليس ضمن الشاشات التسع والعشرين الظاهرة)، فلا يبلغه المديرُ المالي إلا بالرابط المباشر. | J205: Missing Screen | K205: P2 | L205: المديرُ الماليُّ لا يرى تعارضاتِ الواجبات في حسابات إدارته ولا التفويضاتِ السارية، وهي المساحةُ الوحيدةُ التي تمكّنه من أداء واجب التصديق الدوري؛ فتبقى مخالفاتُ SoD غيرَ مرئيةٍ لمن يملك إصلاحَها. | M205: الشاشةُ بُنيت ولم تُبذَر لها صفوفُ nav_items لأدوار المالية. | N205: database/schema/seed_reference.sql (لا صفَّ nav_items بمسار Finance/gov_dept_fin.php); Finance/fin_m10_actions.php:56 | P205: ١) ادخل بدور ١٩ «مدير الإدارة المالية». ٢) ابحث في السايدبار عن «حوكمة إدارتي» → غير موجودة. ٣) افتح http://localhost/ems/Finance/gov_dept_fin.php مباشرةً → تُفتح. | Q205: ابذر صفَّ nav_items لأدوار المالية (١٧ · ١٩) يشير إلى Finance/gov_dept_fin.php بعنوان «حوكمة الإدارة المالية» ضمن مجموعة المتابعة، وتحقّق من أن حقَّه قراءةٌ فقط. | R205: مكتب الهندسة — وحدة التنقل | S205: لا | T205: نعم | U205: بدور ١٩ يظهر رابطُ «حوكمة الإدارة المالية» ويفتح مساحةً تعرض تعارضاتِ الواجبات والتفويضات قراءةً فقط. | V205: مفتوح | W205: مؤكَّدة | X205: بحثُ nav_items لا يعطي أيَّ صفٍّ لمسار Finance/gov_dept_fin.php في أيِّ دور، ولا رابطَ وارد من شاشةٍ أخرى (الإشارتان الوحيدتان في Finance/fin_m10_actions.php سلسلتا نصٍّ لا رابط) — فالوصولُ بالرابط المباشر وحده. | Y205: P2 | Z205: نعم | AA205: نعم | AB205: 06_M14 | AC205: فجوة تنفيذ (Implementation) | AD205: Decision Closed · Implementation Open
A206: INJ-0202 | B206: M-14 | C206: SEC-025 · الصلاحياتُ والنطاق — الدورُ بلا شاشاتٍ لا يُنشأ | D206: المالية والخزينة | E206: منفذ المدفوعات البنكية / معد المطابقة البنكية | G206: غير موجود في السايدبار | H206: لكلِّ دورٍ في `roles` شاشاتُه ومنحُه وقائمتُه — «الدورُ يحدد الروابطَ التي تتبع له، والصلاحيةُ تحدد أتظهر الصفحةُ أم لا». | I206: دوران معرَّفان بلا شاشةٍ ولا منحةٍ ولا رابط؛ الأثرُ انطباعُ تغطيةٍ في مصفوفة فصل الواجبات لا خللٌ تشغيليٌّ واقع. — [مُصحَّح بعد التحقق] الصياغة الأولى: الدوران 34 «منفذ المدفوعات البنكية» و35 «معد المطابقة البنكية» موجودانِ في `roles` (`database/schema/seed_reference.sql:52-53`) ولهما **صفرُ صفوفٍ** في `modules` (لا يملكان شاشةً) و**صفرُ صفوفٍ** في ` | J206: Permission Gap | K206: P2 | L206: مستخدمٌ يُسنَد إليه أحدُ الدورين يدخل إلى نظامٍ فارغٍ تمامًا — لا شاشةَ ولا رابط؛ وفي الوقتِ نفسِه يظهر الدورانِ في مصفوفةِ فصلِ الواجباتِ ويوحيان بتغطيةٍ غيرِ موجودة (تنفيذُ الدفعِ والمطابقةُ البنكية من أخطرِ مواضعِ SoD). | M206: أُنشئ الدوران بهجرةِ إعادةِ هيكلةِ الأدوارِ الماليةِ (2026-08-09) ولم تُنشأ لهما شاشاتٌ ولا منحٌ ولا قوائم. | N206: database/schema/seed_reference.sql:52; :53; :449; :3542 | P206: ١) استعلم `SELECT COUNT(*) FROM modules WHERE owner_role_id IN (34,35)` → 0. ٢) `SELECT COUNT(*) FROM role_permissions WHERE role_id IN (34,35)` → 0. ٣) `SELECT COUNT(*) FROM nav_items WHERE role_id IN (34,35)` → 0. ٤) أسنِد الدورَ 34 لمستخدمٍ وادخل: لا شاشةَ ولا رابط. | Q206: إمّا أنشئ شاشاتِ الدورين (تنفيذُ الدفعِ البنكي · المطابقةُ البنكية) وسجِّلها في `modules` وامنحها وولِّد `nav_items`، وإمّا عطِّل الدورين (`UPDATE roles SET status = 0 WHERE id IN (34,35)`) حتى إنشائها — ولا يُترك دورٌ فارغٌ في مصفوفةِ فصلِ الواجبات. | R206: فريق الباك-إند — المالية والخزينة | S206: نعم | T206: لا | U206: كلُّ دورٍ بحالة `status=1` في `roles` يملك منحةَ قراءةٍ واحدةً على الأقل وصفَّ `nav_items` واحدًا فعّالًا — يُثبت باستعلامٍ واحدٍ يرجع صفرَ استثناءات. | V206: مفتوح | W206: مؤكَّدة | X206: تحققتُ بجردِ البذرة: الدوران 34 و35 قائمان بـstatus=1 (seed_reference.sql:52-53) وبصفرِ صفوفٍ في modules و role_permissions و nav_items — بينما كلُّ الأدوار 1..33 لها صفوفٌ في الثلاثة. لكن لا أثرَ تشغيليًّا: لا مستخدمَ مُسنَدٌ ولا فعلَ غيرَ مصرَّحٍ ينتج، والخللُ نقصُ اكتمالٍ يُغلق إمّا بإنشاء الشاشتين وإمّا بتعطيل الدورين. | Y206: P0 | Z206: نعم | AA206: نعم | AB206: 06_M14 | AC206: فجوة تنفيذ (Implementation) | AD206: Decision Closed · Implementation Open
A207: INJ-0203 | B207: INJAZ-CORE-01 | C207: PR-02 · عزلُ الكيانات بنيويّ (٤-١ المبادئُ الاثنا عشرَ الحاكمة) | D207: التمويل والملكية | E207: إنشاء عملية تمويل | F207: http://localhost/ems/Financing/financing_operation_new.php | G207: ثانيًا: عملية التمويل | H207: «عزلُ الكيانات بنيويّ» — ولا يُشتق نطاقُ الشركة من قيمةٍ ثابتةٍ في الشيفرة بل من سياق الجلسة، وبوابةُ العزل تُغلق مغلقًا عند غياب السياق. | I207: احتياطيٌّ مرمَّزٌ للشركة 4 يقع على جلسات السوبر أو الحساباتِ بلا شركة فتُنسب عملياتُهم إلى الكيان 4؛ ولا أثرَ له على المستخدمين ذوي الشركة الصالحة. — [مُصحَّح بعد التحقق] الصياغة الأولى: شاشةُ إنشاء عملية التمويل تحدّد الشركةَ بـ$co = $company_id ?: 4 (السطر 23): إن كانت شركةُ الجلسة صفرًا (سوبر أو حسابٌ بلا شركة) تُكتب العمليةُ في الشركة رقم ٤ حتمًا. والنمطُ نفسُه في Financing/financ | J207: Data Mismatch | K207: P2 | L207: عمليةُ تمويلٍ بعقدٍ وقيمةِ شراءٍ ورأسِ مالٍ تُنسب إلى شركةٍ ثابتةٍ في الشيفرة بدل شركة المستخدم؛ فتُخلط بياناتُ كيانين وتُكتب أصولُ شركةٍ في دفاتر أخرى — وهو ما يبطل العزلَ البنيويَّ من أصله. | M207: قيمةٌ افتراضيةٌ من بيئة التطوير (شركة الاختبار ٤) بقيت في شيفرة الإنتاج. | N207: Financing/financing_operation_new.php:23; Financing/financing_operation_new.php:38; Financing/financing_board.php:30; app/Core/TenantContext.php:1 | P207: ١) ادخل بحسابٍ company_id=0 (أو بحساب سوبر). ٢) افتح «إنشاء عملية تمويل» وأنشئ عملية. ٣) افحص الصف → company_id = 4. | Q207: احذف الاحتياطيَّ في Financing/financing_operation_new.php:23 و Financing/financing_board.php:30 واستبدله برفضٍ صريح: if ($company_id<=0) ems_gov_flash_redirect(...,'GOV-SCOPE-403')؛ ومرّر الشركةَ من بوابة العزل لا من متغيرٍ محلي. | R207: فريق الباك-إند — وحدة التمويل | S207: نعم | T207: نعم | U207: حسابٌ بلا شركةٍ صالحةٍ لا يستطيع فتحَ الشاشة ولا إنشاءَ عملية؛ وصفرُ صفٍّ في financing_operations بشركةٍ تخالف شركةَ منشئه. | V207: مفتوح | W207: مرجَّحة | X207: $co = $company_id ?: 4 موجودٌ حرفيًّا في financing_operation_new.php:23 وfinancing_board.php:30. لكن الاحتياطيَّ لا يعمل إلا حين company_id=0، وهي حالُ السوبر (-1) وحدَه عمليًّا لأنه الوحيدُ الذي يجتاز بوابةَ المنح في السطر 26؛ والمستخدمُ العاديُّ بشركةٍ صالحةٍ لا يتأثر — فلا انهيارَ للعزل البنيوي. | Y207: P0 | Z207: نعم | AA207: نعم | AB207: 01_CORE | AC207: فجوة تنفيذ (Implementation) | AD207: Decision Closed · Implementation Open
A208: INJ-0204 | B208: INJAZ-FRD-01 | C208: INJAZ-FRD-01 §١٠-٥ · الأثرُ العابرُ للإدارات — «الإداراتُ المتأثرة: المالية والخزينة …» | D208: التمويل والملكية | E208: الأقساط ومواعيد السداد | F208: http://localhost/ems/Financing/installments.php | G208: رابعًا: الأقساط والتكلفة | H208: «الإداراتُ المتأثرةُ بأفعالها: المالية والخزينة · إدارة الأسطول · الحوكمة والالتزام…» و«الأثرُ ينتقل بالأحداث»؛ وسلسلةُ «تمويل → مالية» تُغلق. | I208: تسجيلُ سداد قسطٍ يحدّث جدولَي التمويل فقط (installments.php:37 و:40) ولا ينشئ أي حركةِ خزينةٍ (fin_payments) ولا ذمّةً ولا قيدًا ولا حدثًا منشورًا. ومرجعُ السداد payment_ref نصٌّ حرٌّ (السطر 29) لا يشير إلى مستندِ صرفٍ حقيقي. والدالةُ الوحيدةُ التي تنشر حدثَ تمويلٍ (publishInstallmentDue بمفتاح fininst:<op>:<seq>) لا تُستدعى من أي مكان. | J208: Event/Integration Gap | K208: P2 | L208: سلسلةُ «تمويل ← مالية» مقطوعةٌ تمامًا: أقساطٌ تُسدَّد في نظام التمويل ولا يعلم بها دفترُ الخزينة ولا الدفاترُ ولا التدفقُ النقدي؛ والتمويلُ لا ينشر حدثًا واحدًا في النظام كلِّه. | M208: بُنيت شاشةُ الأقساط كسجلٍّ داخليٍّ للإدارة ولم تُوصل بناقل الأحداث ولا بمسار الخزينة. | N208: Financing/installments.php:29; Financing/installments.php:37; Financing/installments.php:44; app/Services/Financing/FinancingService.php:235; app/Services/Financing/FinancingService.php:246 | P208: ١) سدّد قسطًا بمرجعٍ نصيّ. ٢) افتح «الخزينة والصناديق» و«القيود اليومية» → لا حركةَ ولا قيد. ٣) ابحث عن حدثٍ بمفتاح fininst في جدول الأحداث → لا شيء. | Q208: اربط السدادَ بمستندِ صرفٍ حقيقي: اشترط payment_id من fin_payments بحالة executed بدل النص الحر، وانشر الحدث financing.installment.paid عبر EventPublisher بمفتاح عطالةٍ fininst:<op>:<seq>، وسجّل مستهلكًا ماليًّا ينشئ القيد. | R208: فريق الباك-إند — وحدة التمويل | S208: نعم | T208: نعم | U208: سدادُ قسطٍ يشترط مستندَ صرفٍ منفَّذًا، وينشر حدثًا واحدًا، ويظهر أثرُه في الخزينة والدفاتر خلال دورة cron واحدة. | V208: مفتوح | W208: مؤكَّدة | X208: سدادُ القسط يُحدّث financing_installments (:37) و financing_operations (:42) فقط، وpayment_ref نصٌّ حرٌّ (:29)، وpublishInstallmentDue (FinancingService.php:235) بلا مستدعٍ خارجَ tests/. خُفّضت لأن الأثرَ محصورٌ في وحدةٍ طرفيةٍ لا يمنع سلسلةً أساسية. | Y208: P1 | Z208: نعم | AA208: نعم | AB208: 02_FRD | AC208: فجوة تنفيذ (Implementation) | AD208: Decision Closed · Implementation Open
A209: INJ-0205 | B209: INJAZ-FRD-01 | C209: INJAZ-FRD-01 §١٠-٤ · CORE-01 ٤-٢/١٠ لا زرَّ بلا أثرٍ ظاهر | D209: التمويل والملكية | E209: انحرافات التمويل — الروابط الثلاثة الوهمية | F209: http://localhost/ems/Financing/deviations.php | G209: خامسًا: الانحراف والتصحيح | H209: «لكلٍّ وجهةٌ حيةٌ موجودةٌ — وصفرُ شاشةٍ «قريبًا»»، والمِرساةُ في الرابط تشير إلى عنصرٍ حيٍّ في الصفحة. | I209: ثلاثةُ روابطَ في سايدبار دور ٢٦ تحمل مِراسٍ لا وجودَ لها في Financing/deviations.php: ../Financing/deviations.php#n9g13i1 و#n9g14i1 و#n9g15i1 (بذرةُ nav_items الأسطر 4900-4902). بحثٌ عن هذه المعرّفات في الملف يعيد صفرَ نتيجة، فالنقرُ عليها يفتح الشاشةَ نفسَها بلا أي ترشيحٍ ولا تمرير. | J209: Broken Button | K209: P2 | L209: ثلاثةُ عناصرَ في قائمة الإدارة تَعِد بثلاث شاشاتٍ وتؤدي جميعُها إلى الشاشة نفسِها بلا تمييز؛ فيظن المستخدمُ أن النظامَ معطَّلٌ أو أنه أخطأ النقر. | M209: وُلِّد ظهورٌ لكل شاشةٍ معلَنةٍ في NAV-09 وأُلحقت به مِرساةٌ اصطناعيةٌ للتفرقة دون تنفيذ الأقسام المقابلة. | N209: database/schema/seed_reference.sql:4900; database/schema/seed_reference.sql:4901; database/schema/seed_reference.sql:4902; Financing/deviations.php:60; Financing/deviations.php:85 | P209: ١) بدور ٢٦ انقر «فروق السداد والاستحقاق». ٢) لاحظ فتحَ «الانحرافات الثلاث» بلا ترشيح. ٣) ابحث في مصدر الصفحة عن n9g13i1 → غير موجود. ٤) كرّر على الرابطين الآخرين. | Q209: استبدل المِراسي بمعاملِ ترشيحٍ حقيقيّ: ../Financing/deviations.php?type=payment_gap|unrecorded_exit|no_movement، وأضِف في Financing/deviations.php قراءةَ $_GET['type'] وترشيحَ الاستعلام في السطر 61 به وإظهارَ الترشيح في العنوان. | R209: فريق الباك-إند — وحدة التمويل | S209: لا | T209: نعم | U209: كلُّ رابطٍ من الثلاثة يفتح الشاشةَ مرشَّحةً على صنفه ويظهر الصنفُ في العنوان؛ وصفرُ رابطٍ بمِرساةٍ لا وجودَ لها. | V209: مفتوح | W209: مؤكَّدة | X209: المراسي الثلاثة (#n9g13i1 · #n9g14i1 · #n9g15i1) لا وجودَ لها في Financing/deviations.php، وهي حالةٌ من 72 صفَّ تنقّلٍ بمِراسٍ ميتةٍ في البذرة — فثلاثةُ عناوينَ مختلفةٍ تفتح الشاشةَ نفسَها بلا ترشيح. | Y209: P1 | Z209: نعم | AA209: نعم | AB209: 02_FRD | AC209: فجوة تنفيذ (Implementation) | AD209: Decision Closed · Implementation Open
A210: INJ-0206 | B210: INJAZ-FRD-01 | C210: PR-09 · الواقعُ يُسجَّل ولا يُفترض · PR-05 الحارسُ في الخادم | D210: التمويل والملكية | E210: الانحرافات الثلاث | F210: http://localhost/ems/Financing/deviations.php | G210: خامسًا: الانحراف والتصحيح | H210: الكتابةُ فعلٌ مقصودٌ بحارسه، ولا يقع أثرٌ في القاعدة بمجرد فتح صفحةِ عرض. | I210: Financing/deviations.php ينفّذ عمليتَي INSERT ... SELECT في financing_deviations عند كل تحميلٍ للصفحة (الأسطر 40-49 و50-58) خارج أي معالجِ POST، بـmysqli_query خامٍّ وبتضمين $company_id في نص الاستعلام، متجاوزًا بوابةَ العزل؛ وإغلاقُ الانحراف (السطر 25) بلا رمزِ حمايةٍ ولا سطرِ تدقيقٍ ولا فحصِ اعتماد الذات. | J210: Governance Gap | K210: P2 | L210: فتحُ شاشةِ عرضٍ يكتب صفوفًا في جدولٍ حوكميّ؛ فعددُ الانحرافات وتوقيتُ رصدها يعتمدان على من فتح الصفحةَ ومتى لا على الواقع، ويستحيل تفسيرُ تاريخ الرصد في مراجعة. | M210: نُفِّذ الرصدُ داخل مسار العرض بدل مهمةٍ دوريةٍ (FinancingService::deviationSweep الموجودةُ أصلًا بلا أي مستدعٍ). | N210: Financing/deviations.php:25-36; :39-49; :50-58 | P210: ١) افتح Financing/deviations.php مرةً واحدة. ٢) افحص financing_deviations → صفوفٌ جديدةٌ أُنشئت بمجرد الفتح. ٣) أغلق انحرافًا بقرارٍ → لا سطرَ تدقيق. | Q210: انقل كتلتَي الرصد (الأسطر 40-58) إلى مهمةٍ دوريةٍ تستدعي FinancingService::deviationSweep، واجعل الشاشةَ عرضًا فقط؛ وأضِف verify_csrf_token و ems_audit_change و ems_no_self_approval لفعل الإغلاق في السطر 25. | R210: فريق الباك-إند — وحدة التمويل | S210: لا | T210: لا | U210: فتحُ الشاشة لا يغيّر عددَ صفوف financing_deviations؛ والرصدُ يقع في مهمة cron ويُسجَّل وقتُه؛ وكلُّ إغلاقٍ يترك سطرَ تدقيق. | V210: مفتوح | W210: مؤكَّدة | X210: الكتلتان `INSERT ... SELECT` (:39-49 و:50-58) تُنفَّذان عند كل تحميلٍ خارجَ أيِّ معالجِ POST بـmysqli_query خامٍّ وبـ$company_id مُدرَجًا نصًّا، وإغلاقُ الانحراف (:25-36) بلا رمزٍ ولا تدقيق. | Y210: P2 | Z210: نعم | AA210: نعم | AB210: 02_FRD | AC210: فجوة تنفيذ (Implementation) | AD210: Decision Closed · Implementation Open
A211: INJ-0207 | B211: INJAZ-FRD-01 | C211: INJAZ-FRD-01 §١٠-٣ · المرحلة ٦ «سادسًا: سرية الملكية — منح رؤية بمدة وسبب · المعتمِد: الحوكمة» | D211: التمويل والملكية | E211: سرية الملكية — منح الرؤية | G211: غير موجود في السايدبار | H211: المرحلةُ السادسةُ في دورة الإدارة «سرية الملكية» مستندُها «منح رؤية بمدة وسبب» ومعتمِدُها «الحوكمة» وشاشاتُها ٢. | I211: لا مجموعةَ للمرحلة السادسة في سايدبار دور ٢٦ إطلاقًا: المجموعاتُ هي (لوحة الإدارة · أولًا · ثانيًا · ثالثًا · رابعًا · خامسًا · متابعة وتقارير · خارج الوثيقة). وشاشتا المنح الفعليتان Governance/ownership_grants.php و Governance/sensitive_fields.php مملوكتان للحوكمة ولا تظهران لدور ٢٦ ولو قراءةً، رغم أن الإدارةَ هي صاحبةُ المجال المقيَّد. | J211: Missing Screen | K211: P2 | L211: الإدارةُ التي يقوم عملُها كلُّه على «صلاحيةٍ فرديةٍ بمدةٍ وسبب» لا ترى مِنحَ الرؤية السارية على مجالها ولا مددَها ولا أسبابَها؛ فلا تستطيع طلبَ سحبِ منحةٍ ولا مراجعةَ من يطّلع على أسرارها. | M211: لم تُبذَر مجموعةُ المرحلة السادسة، ولم يُنشأ منظرٌ نطاقيٌّ للتمويل على شاشة المنح المملوكة للحوكمة. | N211: database/schema/seed_reference.sql:4899; Governance/ownership_grants.php:1; Governance/sensitive_fields.php:1; app/Core/OwnershipDomainGuard.php:113 | P211: ١) ادخل بدور ٢٦. ٢) اعدّ المجموعاتِ → لا مجموعةَ باسم «سادسًا: سرية الملكية». ٣) ابحث عن «منح الرؤية» أو «الحقول الحساسة» → غير موجودتين. | Q211: أضِف مجموعةً سادسةً لدور ٢٦ بظهورَين قراءةً + طلبِ سحبٍ على Governance/ownership_grants.php (مرشَّحًا على أكواد ownership.*) و Governance/sensitive_fields.php، مع حجب فعل المنح عن الدور. | R211: مكتب الهندسة — وحدة التنقل | S211: لا | T211: نعم | U211: بدور ٢٦ تظهر مجموعة «سادسًا: سرية الملكية» بشاشتين، والمنحُ محجوبٌ والطلبُ متاح. | V211: مفتوح | W211: مؤكَّدة | X211: مجموعاتُ الدور 26 المحسوبةُ هي (0·1·2·3·4·5·7·99) بلا مرحلةٍ سادسة، وownership_grants.php محروسةٌ بأرقام 1·19·السوبر (السطر 27) فلا يفتحها 26 ولو قراءةً — والوثيقة frd_readable.md:786 تُثبت المرحلةَ السادسة بشاشتين. | Y211: P1 | Z211: نعم | AA211: نعم | AB211: 02_FRD | AC211: فجوة تنفيذ (Implementation) | AD211: Decision Closed · Implementation Open
A212: INJ-0208 | B212: INJAZ-FRD-01 | C212: INJAZ-FRD-01 §١٠-٤ · شاشاتُها — «مخاطر التمويل والملكية (risk_dept_cap.php)» | D212: التمويل والملكية | E212: مخاطر التمويل والملكية (risk_dept_cap.php) | G212: خارج الوثيقة — بانتظار قرار المالك | H212: تعلن الوثيقةُ ضمن شاشات الإدارة الأربعَ عشرةَ شاشةَ «مخاطر التمويل والملكية» رمزُها risk_dept_cap.php بـ٢٢ عمودًا و٣ أفعال في مرحلة «مخاطرُ الإدارة». | I212: لا وجودَ لملف risk_dept_cap.php؛ مجلد Risk/ يحوي risk_dept_fin.php و risk_dept_gov.php فقط. وسايدبار دور ٢٦ يعرض بدلًا منها «مساحة مخاطر الإدارة» (Risk/dept_risk_space.php) داخل مجموعة «خارج الوثيقة — بانتظار قرار المالك». | J212: Missing Screen | K212: P2 | L212: مخاطرُ التمويل (تعثرُ السداد · فقدُ ملكية · مخالفةُ شرطٍ تعاقديّ) بلا سجلٍّ باسم الإدارة ونطاقها؛ فينكسر الخطُّ الأولُ عند أخطر إدارةٍ ماليًّا بعد الخزينة. | M212: لم تُولَّد شاشةُ مخاطر الإدارة من قائمة الشاشات واكتُفي بمكوّنٍ عامّ. | N212: Risk/ (لا risk_dept_cap.php); database/schema/seed_reference.sql (nav_items للدور 26 · مجموعة stage_no=99) | P212: ١) ادخل بدور ٢٦. ٢) ابحث عن «مخاطر التمويل والملكية» → غير موجودة. ٣) جرّب Risk/risk_dept_cap.php → 404. | Q212: أنشئ Risk/risk_dept_cap.php على غرار Risk/risk_dept_fin.php بنطاق التمويل والملكية وسجّله في modules و nav_items لدور ٢٦ في مجموعة «مخاطرُ الإدارة». | R212: فريق الباك-إند — وحدة التمويل | S212: لا | T212: نعم | U212: بدور ٢٦ تُفتح شاشةُ مخاطر التمويل وتعرض مخاطرَ الإدارة وحدَها بأعمدتها. | V212: مفتوح | W212: مؤكَّدة | X212: لا ملفَّ Risk/risk_dept_cap.php في المستودع (المجلدُ يحوي risk_dept_fin.php وrisk_dept_gov.php فقط)، وسايدبارُ الدور 26 يعرض «مساحة مخاطر الإدارة» → Risk/dept_risk_space.php داخل مجموعة «خارج الوثيقة». | Y212: P2 | Z212: نعم | AA212: نعم | AB212: 02_FRD | AC212: فجوة قرار (Decision) | AD212: Decision Open
A213: INJ-0209 | B213: INJAZ-UX-01 | C213: §٧-٣ · §٨ — منتقي الأعمدة والمناظر والتصدير في الشاشات الطويلة | D213: التمويل والملكية | E213: شبكات التمويل | F213: http://localhost/ems/Financing/installments.php | G213: رابعًا: الأقساط والتكلفة | H213: «الشاشاتُ الطويلةُ (٢٠+ عمودًا) تحتاج مناظرَ وزرَّ إظهارِ الكلِّ إلزامًا»، و«التصديرُ يدعم العرضَ الحاليَّ وجميعَ الأعمدةِ المسموحةِ معًا». | I213: إحدى عشرةَ شبكةً في مجلد Financing بلا أي أداةِ إظهارِ أعمدةٍ ولا منتقي مناظرَ ولا تصدير: installments.php · deviations.php · owners_registry.php · cost_allocation.php · financing_board.php · financiers_registry.php · fin_models.php · fin_changes.php · ownership_links.php · operation_profile.php · asset_disposal.php. وجداولُها موسومةٌ data-no-dt (deviations.php:85 · owners_registry.php:60) أي بلا فرزٍ ولا بحثٍ ولا ترقيمِ صفحاتٍ أصلًا. | J213: UX/UI Defect | K213: P2 | L213: شاشاتُ إدارةٍ كاملةٍ بجداولَ ساكنةٍ محدودةٍ بـLIMIT ثابت (100 في deviations · 200 في installments) بلا بحثٍ ولا فرزٍ ولا ترقيمٍ ولا تصدير؛ فلا يمكن العملُ عليها عمليًّا حين تكبر البيانات. | M213: بُنيت شاشاتُ التمويل بجداول HTML خام مع data-no-dt لتفادي مشكلات التصيير، فسقطت معها كلُّ خدمات الجدول. | N213: Financing/deviations.php:85; Financing/owners_registry.php:60; Financing/installments.php:54; Financing/deviations.php:62; includes/u13_screen_kit.php:319 | P213: ١) بدور ٢٦ افتح «الأقساط ومواعيد السداد». ٢) ابحث عن مربع بحثٍ أو فرزٍ أو ترقيمِ صفحات → لا شيء. ٣) لاحظ توقفَ القائمة عند ٢٠٠ صفٍّ بلا إشارة. | Q213: فعّل مكوّنَ الجدول الموحّد (CM-08) على شبكات Financing بإزالة data-no-dt وربطها بمعالجةٍ خادمية، وأضِف منتقي الأعمدة CM-10 بالنص الموحّد وزرَّ تصديرٍ عبر excel.php بخيارين. | R213: مكتب الهندسة — وحدة الواجهة | S213: لا | T213: نعم | U213: كلُّ شبكةٍ في Financing تدعم البحثَ والفرزَ والترقيم، وتعرض زرَّ «إظهار كل الأعمدة» وزرَّ تصديرٍ بخيارين. | V213: مفتوح | W213: مؤكَّدة | X213: إحدى عشرةَ شبكةً في Financing بلا زرِّ أعمدةٍ ولا منتقي مناظرَ ولا تصدير، وستٌّ منها موسومةٌ data-no-dt (بينها deviations:85 و owners_registry:60). | Y213: P2 | Z213: نعم | AA213: نعم | AB213: 03_UX | AC213: فجوة تنفيذ (Implementation) | AD213: Decision Closed · Implementation Open
